Workbook
Name \1: #REF!
Name \q: #REF!
Name \w: #REF!
Name _______us96: #REF!
Name _____us96: #REF!
Name ____BAS1: #REF!
Name ____us96: #REF!
Name ___BAS1: #REF!
Name ___res1: #REF!
Name ___res3: #REF!
Name ___res4: #REF!
Name ___us96: #REF!
Name __BAS1: #REF!
Name __DAT1: #REF!
Name __DAT10: #REF!
Name __DAT11: #REF!
Name __DAT12: #REF!
Name __DAT13: #REF!
Name __DAT14: #REF!
Name __DAT15: #REF!
Name __DAT16: #REF!
Name __DAT17: #REF!
Name __DAT18: #REF!
Name __DAT19: #REF!
Name __DAT2: #REF!
Name __DAT20: #REF!
Name __DAT3: #REF!
Name __DAT4: #REF!
Name __DAT5: #REF!
Name __DAT6: #REF!
Name __DAT7: #REF!
Name __DAT8: #REF!
Name __DAT9: #REF!
Name __res1: #REF!
Name __res2: #REF!
Name __res3: #REF!
Name __res4: #REF!
Name __us96: #REF!
Name _A: #REF!
Name _aa: #REF!
Name _ACT1: #REF!
Name _ACT10: #REF!
Name _ACT11: #REF!
Name _ACT12: #REF!
Name _ACT13: #REF!
Name _ACT14: #REF!
Name _ACT15: #REF!
Name _ACT16: #REF!
Name _ACT17: #REF!
Name _ACT18: #REF!
Name _ACT19: #REF!
Name _ACT2: #REF!
Name _ACT20: #REF!
Name _ACT21: #REF!
Name _ACT22: #REF!
Name _ACT23: #REF!
Name _ACT3: #REF!
Name _ACT4: #REF!
Name _ACT5: #REF!
Name _ACT6: #REF!

Sheet Hoja1
E1: =+SUBTOTAL(9,E3:E89) -> 4.75e+09
A2: NOMBRE SUBGRUPO | B2: CATEGORIA2 | C2: NOMBRE CATEGORIA | D2: INCLUIR | E2: PRESUPUESTO (ORIGINAL) | F2: OBS
A3: Obras Civiles | B3: 11-0102-000G | C3: MAO CD - Civil / Hormigón (G) | D3: NO | E3: 2.4934757e+08
A4: Estructura | B4: 11-0208-000G | C4: MAO CD - Estructura / Montajes (G) | D4: SI | E4: 9107425.3
A5: Mecanica | B5: 11-0308-000G | C5: MAO CD - Mecánica / Montajes (G) | D5: SI | E5: 6.482323e+08
A6: Cañería | B6: 11-0408-000G | C6: MAO CD - Cañería / Montajes (G) | D6: SI | E6: 37872374
A7: Electricidad & Instrumentacion | B7: 11-0508-000G | C7: MAO CD - Electricidad / Montajes (G) | D7: SI | E7: 4909779.4
A8: Andamios | B8: 11-1101-000G | C8: MAO CD - Andamios / Andamios (G) | D8: SI | E8: 40034534
A9: Operador | B9: 11-1201-010G | C9: MAO CD - Equipos / Equipos / Operador (G) | D9: SI | E9: 1.0954463e+08
A10: Rigger | B10: 11-1201-020G | C10: MAO CD - Equipos / Equipos / Rigger (G) | D10: SI | E10: 69826848
A11: Staff Superior | B11: 12-5101-000G | C11: MAO CI - Staff Superior / Staff Superior (G) | D11: SI | E11: 2.6331137e+08
A12: Oficina Técnica | B12: 12-5201-000G | C12: MAO CI - Oficina Técnica / Oficina Técnica (G) | D12: SI | E12: 80469295
A13: Supervisión | B13: 12-5301-000G | C13: MAO CI - Supervisión / Supervisión (G) | D13: SI | E13: 97274459
A14: Administración | B14: 12-5401-000G | C14: MAO CI - Administración / Administración (G) | D14: SI | E14: 55188181
... A89: Utilidades | B89: 72-A060-100G | C89: GAS CI - Of. Central / Utilidades / Todos (G) | D89: SI | E89: 0

Sheet Indice
D2: INDICE | H2: CC: EIMI00398 ARAUCO
C4: INFORME DE COSTOS N° 01
G9: Cliente | H9: : | I9: ARAUCO
G10: Administrador de Proyecto | H10: : | I10: CRISTIAN SEPULVEDA GARAY
G11: Centros de Costos | H11: : | I11: EIMI00398
G12: Periodo | H12: : | I12: 46053
C16: Matriz de Producción
C17: Matriz de Costos
C18: Matriz de Resultado
C19: Matriz de Proyecciones

Sheet Formato General
B1: INFORME DE RESULTADOS
B2: =MID(Indice!H2,1,100) -> CC: EIMI00398 ARAUCO | L2: ="Periodo : " & TEXT(Indice!I12,"Mmmm yyyy") -> Periodo : enero 2026
A4: FORMATO GENERAL | B4: Num | C4: Partida | E4: Presupuesto Original | F4: Aumentos o Dism. de Obras y Reajuste | G4: Presupuesto Corregido | I4: Gastos Reales del Mes | J4: Gastos Reales Acumulados | K4: Avance Según Obra Ejecutada | L4: Proyección de gasto por efectuar | N4: Resultado de la Obra
B5: A. | C5: Costos Directos
B6: A1 | C6: 01 - Obras Civiles | E6: =IF(ISBLANK(A6),"", SUMIF(CATEGORIAS[[#All],[FORMATO GENERAL]], A6, CATEGORIAS[[#All],[PRESUPUESTO (ORIGINAL)]])) | F6: =IF(ISBLANK(A6),"",G6-E6) | G6: =IF(ISBLANK(A6),"",SUMIF(CATEGORIAS[[#All],[FORMATO GENERAL]], A6, CATEGORIAS[[#All],[PRESUPUESTO FINAL PROYECTADO]])) | I6: =IF(ISBLANK(A6),"",J6-SUMIF(CATEGORIAS[[#All],[FORMATO GENERAL]], A6, CATEGORIAS[[#All],[COSTO REAL ANTERIOR]])) | J6: =IF(ISBLANK(A6),"",SUMIF(CATEGORIAS[[#All],[FORMATO GENERAL]], A6, CATEGORIAS[[#All],[COSTO REAL]])) | K6: =IF(ISBLANK(A6),"",SUMIF(CATEGORIAS[[#All],[FORMATO GENERAL]], A6, CATEGORIAS[[#All],[TOTAL PRODUCCION ACTUAL]])) | L6: =IF(ISBLANK(A6),"",SUMIF(CATEGORIAS[[#All],[FORMATO GENERAL]], A6, CATEGORIAS[[#All],[PROYECCION TOTAL DE COSTO]])) | N6: =IF(ISBLANK(A6),"",TRUNC(G6-J6-L6,2))
A7: 0A01 | C7: Mano de Obra | E7: =IF(ISBLANK(A7),"", SUMIF(CATEGORIAS[[#All],[FORMATO GENERAL]], A7, CATEGORIAS[[#All],[PRESUPUESTO (ORIGINAL)]])) -> 2.4934757e+08 | F7: =IF(ISBLANK(A7),"",G7-E7) -> -50544234 | G7: =IF(ISBLANK(A7),"",SUMIF(CATEGORIAS[[#All],[FORMATO GENERAL]], A7, CATEGORIAS[[#All],[PRESUPUESTO FINAL PROYECTADO]])) -> 1.9880333e+08 | I7: =IF(ISBLANK(A7),"",J7-SUMIF(CATEGORIAS[[#All],[FORMATO GENERAL]], A7, CATEGORIAS[[#All],[COSTO REAL ANTERIOR]])) -> 0 | J7: =IF(ISBLANK(A7),"",SUMIF(CATEGORIAS[[#All],[FORMATO GENERAL]], A7, CATEGORIAS[[#All],[COSTO REAL]])) -> 226422941 | K7: =IF(ISBLANK(A7),"",SUMIF(CATEGORIAS[[#All],[FORMATO GENERAL]], A7, CATEGORIAS[[#All],[TOTAL PRODUCCION ACTUAL]])) -> 1.9880333e+08 | L7: =IF(ISBLANK(A7),"",SUMIF(CATEGORIAS[[#All],[FORMATO GENERAL]], A7, CATEGORIAS[[#All],[PROYECCION TOTAL DE COSTO]])) -> 0 | N7: =IF(ISBLANK(A7),"",TRUNC(G7-J7-L7,2)) -> -27619608
A8: 0A02 | C8: Obras Civiles Reembolsable | E8: =IF(ISBLANK(A8),"", SUMIF(CATEGORIAS[[#All],[FORMATO GENERAL]], A8, CATEGORIAS[[#All],[PRESUPUESTO (ORIGINAL)]])) -> 5.0495371e+08 | F8: =IF(ISBLANK(A8),"",G8-E8) -> -52500881 | G8: =IF(ISBLANK(A8),"",SUMIF(CATEGORIAS[[#All],[FORMATO GENERAL]], A8, CATEGORIAS[[#All],[PRESUPUESTO FINAL PROYECTADO]])) -> 4.5245283e+08 | I8: =IF(ISBLANK(A8),"",J8-SUMIF(CATEGORIAS[[#All],[FORMATO GENERAL]], A8, CATEGORIAS[[#All],[COSTO REAL ANTERIOR]])) -> 7053441 | J8: =IF(ISBLANK(A8),"",SUMIF(CATEGORIAS[[#All],[FORMATO GENERAL]], A8, CATEGORIAS[[#All],[COSTO REAL]])) -> 548455838 | K8: =IF(ISBLANK(A8),"",SUMIF(CATEGORIAS[[#All],[FORMATO GENERAL]], A8, CATEGORIAS[[#All],[TOTAL PRODUCCION ACTUAL]])) -> 4.5245283e+08 | L8: =IF(ISBLANK(A8),"",SUMIF(CATEGORIAS[[#All],[FORMATO GENERAL]], A8, CATEGORIAS[[#All],[PROYECCION TOTAL DE COSTO]])) -> 0 | N8: =IF(ISBLANK(A8),"",TRUNC(G8-J8-L8,2)) -> -96003007
B9: A2 | C9: 02 - Estructura | E9: =IF(ISBLANK(A9),"", SUMIF(CATEGORIAS[[#All],[FORMATO GENERAL]], A9, CATEGORIAS[[#All],[PRESUPUESTO (ORIGINAL)]])) | F9: =IF(ISBLANK(A9),"",G9-E9) | G9: =IF(ISBLANK(A9),"",SUMIF(CATEGORIAS[[#All],[FORMATO GENERAL]], A9, CATEGORIAS[[#All],[PRESUPUESTO FINAL PROYECTADO]])) | I9: =IF(ISBLANK(A9),"",J9-SUMIF(CATEGORIAS[[#All],[FORMATO GENERAL]], A9, CATEGORIAS[[#All],[COSTO REAL ANTERIOR]])) | J9: =IF(ISBLANK(A9),"",SUMIF(CATEGORIAS[[#All],[FORMATO GENERAL]], A9, CATEGORIAS[[#All],[COSTO REAL]])) | K9: =IF(ISBLANK(A9),"",SUMIF(CATEGORIAS[[#All],[FORMATO GENERAL]], A9, CATEGORIAS[[#All],[TOTAL PRODUCCION ACTUAL]])) | L9: =IF(ISBLANK(A9),"",SUMIF(CATEGORIAS[[#All],[FORMATO GENERAL]], A9, CATEGORIAS[[#All],[PROYECCION TOTAL DE COSTO]])) | N9: =IF(ISBLANK(A9),"",TRUNC(G9-J9-L9,2))
A10: 0B01 | C10: Mano de Obra | E10: =IF(ISBLANK(A10),"", SUMIF(CATEGORIAS[[#All],[FORMATO GENERAL]], A10, CATEGORIAS[[#All],[PRESUPUESTO (ORIGINAL)]])) -> 9107425.3 | F10: =IF(ISBLANK(A10),"",G10-E10) -> -2901494.2 | G10: =IF(ISBLANK(A10),"",SUMIF(CATEGORIAS[[#All],[FORMATO GENERAL]], A10, CATEGORIAS[[#All],[PRESUPUESTO FINAL PROYECTADO]])) -> 6205931.1 | I10: =IF(ISBLANK(A10),"",J10-SUMIF(CATEGORIAS[[#All],[FORMATO GENERAL]], A10, CATEGORIAS[[#All],[COSTO REAL ANTERIOR]])) -> 0 | J10: =IF(ISBLANK(A10),"",SUMIF(CATEGORIAS[[#All],[FORMATO GENERAL]], A10, CATEGORIAS[[#All],[COSTO REAL]])) -> 0 | K10: =IF(ISBLANK(A10),"",SUMIF(CATEGORIAS[[#All],[FORMATO GENERAL]], A10, CATEGORIAS[[#All],[TOTAL PRODUCCION ACTUAL]])) -> 6205931.1 | L10: =IF(ISBLANK(A10),"",SUMIF(CATEGORIAS[[#All],[FORMATO GENERAL]], A10, CATEGORIAS[[#All],[PROYECCION TOTAL DE COSTO]])) -> 0 | N10: =IF(ISBLANK(A10),"",TRUNC(G10-J10-L10,2)) -> 6205931.1
A11: 0B02 | C11: Estructura Reembolsable | E11: =IF(ISBLANK(A11),"", SUMIF(CATEGORIAS[[#All],[FORMATO GENERAL]], A11, CATEGORIAS[[#All],[PRESUPUESTO (ORIGINAL)]])) -> 0 | F11: =IF(ISBLANK(A11),"",G11-E11) -> 0 | G11: =IF(ISBLANK(A11),"",SUMIF(CATEGORIAS[[#All],[FORMATO GENERAL]], A11, CATEGORIAS[[#All],[PRESUPUESTO FINAL PROYECTADO]])) -> 0 | I11: =IF(ISBLANK(A11),"",J11-SUMIF(CATEGORIAS[[#All],[FORMATO GENERAL]], A11, CATEGORIAS[[#All],[COSTO REAL ANTERIOR]])) -> 0 | J11: =IF(ISBLANK(A11),"",SUMIF(CATEGORIAS[[#All],[FORMATO GENERAL]], A11, CATEGORIAS[[#All],[COSTO REAL]])) -> 0 | K11: =IF(ISBLANK(A11),"",SUMIF(CATEGORIAS[[#All],[FORMATO GENERAL]], A11, CATEGORIAS[[#All],[TOTAL PRODUCCION ACTUAL]])) -> 0 | L11: =IF(ISBLANK(A11),"",SUMIF(CATEGORIAS[[#All],[FORMATO GENERAL]], A11, CATEGORIAS[[#All],[PROYECCION TOTAL DE COSTO]])) -> 0 | N11: =IF(ISBLANK(A11),"",TRUNC(G11-J11-L11,2)) -> 0
B12: A3 | C12: 03 - Mecanica (MO Arquitectura Puentes) | E12: =IF(ISBLANK(A12),"", SUMIF(CATEGORIAS[[#All],[FORMATO GENERAL]], A12, CATEGORIAS[[#All],[PRESUPUESTO (ORIGINAL)]])) | F12: =IF(ISBLANK(A12),"",G12-E12) | G12: =IF(ISBLANK(A12),"",SUMIF(CATEGORIAS[[#All],[FORMATO GENERAL]], A12, CATEGORIAS[[#All],[PRESUPUESTO FINAL PROYECTADO]])) | I12: =IF(ISBLANK(A12),"",J12-SUMIF(CATEGORIAS[[#All],[FORMATO GENERAL]], A12, CATEGORIAS[[#All],[COSTO REAL ANTERIOR]])) | J12: =IF(ISBLANK(A12),"",SUMIF(CATEGORIAS[[#All],[FORMATO GENERAL]], A12, CATEGORIAS[[#All],[COSTO REAL]])) | K12: =IF(ISBLANK(A12),"",SUMIF(CATEGORIAS[[#All],[FORMATO GENERAL]], A12, CATEGORIAS[[#All],[TOTAL PRODUCCION ACTUAL]])) | L12: =IF(ISBLANK(A12),"",SUMIF(CATEGORIAS[[#All],[FORMATO GENERAL]], A12, CATEGORIAS[[#All],[PROYECCION TOTAL DE COSTO]])) | N12: =IF(ISBLANK(A12),"",TRUNC(G12-J12-L12,2))
A13: 0C01 | C13: Mano de Obra | E13: =IF(ISBLANK(A13),"", SUMIF(CATEGORIAS[[#All],[FORMATO GENERAL]], A13, CATEGORIAS[[#All],[PRESUPUESTO (ORIGINAL)]])) -> 6.482323e+08 | F13: =IF(ISBLANK(A13),"",G13-E13) -> 1.9356882e+08 | G13: =IF(ISBLANK(A13),"",SUMIF(CATEGORIAS[[#All],[FORMATO GENERAL]], A13, CATEGORIAS[[#All],[PRESUPUESTO FINAL PROYECTADO]])) -> 8.4180112e+08 | I13: =IF(ISBLANK(A13),"",J13-SUMIF(CATEGORIAS[[#All],[FORMATO GENERAL]], A13, CATEGORIAS[[#All],[COSTO REAL ANTERIOR]])) -> 0 | J13: =IF(ISBLANK(A13),"",SUMIF(CATEGORIAS[[#All],[FORMATO GENERAL]], A13, CATEGORIAS[[#All],[COSTO REAL]])) -> 586461235 | K13: =IF(ISBLANK(A13),"",SUMIF(CATEGORIAS[[#All],[FORMATO GENERAL]], A13, CATEGORIAS[[#All],[TOTAL PRODUCCION ACTUAL]])) -> 8.4180112e+08 | L13: =IF(ISBLANK(A13),"",SUMIF(CATEGORIAS[[#All],[FORMATO GENERAL]], A13, CATEGORIAS[[#All],[PROYECCION TOTAL DE COSTO]])) -> 0 | N13: =IF(ISBLANK(A13),"",TRUNC(G13-J13-L13,2)) -> 2.5533988e+08
A14: 0C02 | C14: Mecanica Reembolsable | E14: =IF(ISBLANK(A14),"", SUMIF(CATEGORIAS[[#All],[FORMATO GENERAL]], A14, CATEGORIAS[[#All],[PRESUPUESTO (ORIGINAL)]])) -> 1.4433078e+08 | F14: =IF(ISBLANK(A14),"",G14-E14) -> 80364044 | G14: =IF(ISBLANK(A14),"",SUMIF(CATEGORIAS[[#All],[FORMATO GENERAL]], A14, CATEGORIAS[[#All],[PRESUPUESTO FINAL PROYECTADO]])) -> 2.2469483e+08 | I14: =IF(ISBLANK(A14),"",J14-SUMIF(CATEGORIAS[[#All],[FORMATO GENERAL]], A14, CATEGORIAS[[#All],[COSTO REAL ANTERIOR]])) -> 18039318 | J14: =IF(ISBLANK(A14),"",SUMIF(CATEGORIAS[[#All],[FORMATO GENERAL]], A14, CATEGORIAS[[#All],[COSTO REAL]])) -> 339509978 | K14: =IF(ISBLANK(A14),"",SUMIF(CATEGORIAS[[#All],[FORMATO GENERAL]], A14, CATEGORIAS[[#All],[TOTAL PRODUCCION ACTUAL]])) -> 2.2469483e+08 | L14: =IF(ISBLANK(A14),"",SUMIF(CATEGORIAS[[#All],[FORMATO GENERAL]], A14, CATEGORIAS[[#All],[PROYECCION TOTAL DE COSTO]])) -> 0 | N14: =IF(ISBLANK(A14),"",TRUNC(G14-J14-L14,2)) -> -1.1481515e+08
B15: A4 | C15: 04 - Cañeria | E15: =IF(ISBLANK(A15),"", SUMIF(CATEGORIAS[[#All],[FORMATO GENERAL]], A15, CATEGORIAS[[#All],[PRESUPUESTO (ORIGINAL)]])) | F15: =IF(ISBLANK(A15),"",G15-E15) | G15: =IF(ISBLANK(A15),"",SUMIF(CATEGORIAS[[#All],[FORMATO GENERAL]], A15, CATEGORIAS[[#All],[PRESUPUESTO FINAL PROYECTADO]])) | I15: =IF(ISBLANK(A15),"",J15-SUMIF(CATEGORIAS[[#All],[FORMATO GENERAL]], A15, CATEGORIAS[[#All],[COSTO REAL ANTERIOR]])) | J15: =IF(ISBLANK(A15),"",SUMIF(CATEGORIAS[[#All],[FORMATO GENERAL]], A15, CATEGORIAS[[#All],[COSTO REAL]])) | K15: =IF(ISBLANK(A15),"",SUMIF(CATEGORIAS[[#All],[FORMATO GENERAL]], A15, CATEGORIAS[[#All],[TOTAL PRODUCCION ACTUAL]])) | L15: =IF(ISBLANK(A15),"",SUMIF(CATEGORIAS[[#All],[FORMATO GENERAL]], A15, CATEGORIAS[[#All],[PROYECCION TOTAL DE COSTO]])) | N15: =IF(ISBLANK(A15),"",TRUNC(G15-J15-L15,2))
A16: 0D01 | C16: Mano de Obra | E16: =IF(ISBLANK(A16),"", SUMIF(CATEGORIAS[[#All],[FORMATO GENERAL]], A16, CATEGORIAS[[#All],[PRESUPUESTO (ORIGINAL)]])) -> 37872374 | F16: =IF(ISBLANK(A16),"",G16-E16) -> -19046384 | G16: =IF(ISBLANK(A16),"",SUMIF(CATEGORIAS[[#All],[FORMATO GENERAL]], A16, CATEGORIAS[[#All],[PRESUPUESTO FINAL PROYECTADO]])) -> 18825990 | I16: =IF(ISBLANK(A16),"",J16-SUMIF(CATEGORIAS[[#All],[FORMATO GENERAL]], A16, CATEGORIAS[[#All],[COSTO REAL ANTERIOR]])) -> 0 | J16: =IF(ISBLANK(A16),"",SUMIF(CATEGORIAS[[#All],[FORMATO GENERAL]], A16, CATEGORIAS[[#All],[COSTO REAL]])) -> 0 | K16: =IF(ISBLANK(A16),"",SUMIF(CATEGORIAS[[#All],[FORMATO GENERAL]], A16, CATEGORIAS[[#All],[TOTAL PRODUCCION ACTUAL]])) -> 18825990 | L16: =IF(ISBLANK(A16),"",SUMIF(CATEGORIAS[[#All],[FORMATO GENERAL]], A16, CATEGORIAS[[#All],[PROYECCION TOTAL DE COSTO]])) -> 0 | N16: =IF(ISBLANK(A16),"",TRUNC(G16-J16-L16,2)) -> 18825990
A17: 0D02 | C17: Cañeria Reembolsable | E17: =IF(ISBLANK(A17),"", SUMIF(CATEGORIAS[[#All],[FORMATO GENERAL]], A17, CATEGORIAS[[#All],[PRESUPUESTO (ORIGINAL)]])) -> 3653812.6 | F17: =IF(ISBLANK(A17),"",G17-E17) -> -2584050.3 | G17: =IF(ISBLANK(A17),"",SUMIF(CATEGORIAS[[#All],[FORMATO GENERAL]], A17, CATEGORIAS[[#All],[PRESUPUESTO FINAL PROYECTADO]])) -> 1069762.3 | I17: =IF(ISBLANK(A17),"",J17-SUMIF(CATEGORIAS[[#All],[FORMATO GENERAL]], A17, CATEGORIAS[[#All],[COSTO REAL ANTERIOR]])) -> 0 | J17: =IF(ISBLANK(A17),"",SUMIF(CATEGORIAS[[#All],[FORMATO GENERAL]], A17, CATEGORIAS[[#All],[COSTO REAL]])) -> 0 | K17: =IF(ISBLANK(A17),"",SUMIF(CATEGORIAS[[#All],[FORMATO GENERAL]], A17, CATEGORIAS[[#All],[TOTAL PRODUCCION ACTUAL]])) -> 1069762.3 | L17: =IF(ISBLANK(A17),"",SUMIF(CATEGORIAS[[#All],[FORMATO GENERAL]], A17, CATEGORIAS[[#All],[PROYECCION TOTAL DE COSTO]])) -> 0 | N17: =IF(ISBLANK(A17),"",TRUNC(G17-J17-L17,2)) -> 1069762.3
B18: A5 | C18: 05- Electricidad & Instrumentacion | E18: =IF(ISBLANK(A18),"", SUMIF(CATEGORIAS[[#All],[FORMATO GENERAL]], A18, CATEGORIAS[[#All],[PRESUPUESTO (ORIGINAL)]])) | F18: =IF(ISBLANK(A18),"",G18-E18) | G18: =IF(ISBLANK(A18),"",SUMIF(CATEGORIAS[[#All],[FORMATO GENERAL]], A18, CATEGORIAS[[#All],[PRESUPUESTO FINAL PROYECTADO]])) | I18: =IF(ISBLANK(A18),"",J18-SUMIF(CATEGORIAS[[#All],[FORMATO GENERAL]], A18, CATEGORIAS[[#All],[COSTO REAL ANTERIOR]])) | J18: =IF(ISBLANK(A18),"",SUMIF(CATEGORIAS[[#All],[FORMATO GENERAL]], A18, CATEGORIAS[[#All],[COSTO REAL]])) | K18: =IF(ISBLANK(A18),"",SUMIF(CATEGORIAS[[#All],[FORMATO GENERAL]], A18, CATEGORIAS[[#All],[TOTAL PRODUCCION ACTUAL]])) | L18: =IF(ISBLANK(A18),"",SUMIF(CATEGORIAS[[#All],[FORMATO GENERAL]], A18, CATEGORIAS[[#All],[PROYECCION TOTAL DE COSTO]])) | N18: =IF(ISBLANK(A18),"",TRUNC(G18-J18-L18,2))
A19: 0F01 | C19: Mano de Obra | E19: =IF(ISBLANK(A19),"", SUMIF(CATEGORIAS[[#All],[FORMATO GENERAL]], A19, CATEGORIAS[[#All],[PRESUPUESTO (ORIGINAL)]])) -> 4909779.4 | F19: =IF(ISBLANK(A19),"",G19-E19) -> 1.1470541e+08 | G19: =IF(ISBLANK(A19),"",SUMIF(CATEGORIAS[[#All],[FORMATO GENERAL]], A19, CATEGORIAS[[#All],[PRESUPUESTO FINAL PROYECTADO]])) -> 1.1961519e+08 | I19: =IF(ISBLANK(A19),"",J19-SUMIF(CATEGORIAS[[#All],[FORMATO GENERAL]], A19, CATEGORIAS[[#All],[COSTO REAL ANTERIOR]])) -> 0 | J19: =IF(ISBLANK(A19),"",SUMIF(CATEGORIAS[[#All],[FORMATO GENERAL]], A19, CATEGORIAS[[#All],[COSTO REAL]])) -> 41920101 | K19: =IF(ISBLANK(A19),"",SUMIF(CATEGORIAS[[#All],[FORMATO GENERAL]], A19, CATEGORIAS[[#All],[TOTAL PRODUCCION ACTUAL]])) -> 1.1961519e+08 | L19: =IF(ISBLANK(A19),"",SUMIF(CATEGORIAS[[#All],[FORMATO GENERAL]], A19, CATEGORIAS[[#All],[PROYECCION TOTAL DE COSTO]])) -> 0 | N19: =IF(ISBLANK(A19),"",TRUNC(G19-J19-L19,2)) -> 77695091
A20: 0F02 | C20: Electricidad Reembolsable | E20: =IF(ISBLANK(A20),"", SUMIF(CATEGORIAS[[#All],[FORMATO GENERAL]], A20, CATEGORIAS[[#All],[PRESUPUESTO (ORIGINAL)]])) -> 1198500 | F20: =IF(ISBLANK(A20),"",G20-E20) -> -232733.36 | G20: =IF(ISBLANK(A20),"",SUMIF(CATEGORIAS[[#All],[FORMATO GENERAL]], A20, CATEGORIAS[[#All],[PRESUPUESTO FINAL PROYECTADO]])) -> 965766.64 | I20: =IF(ISBLANK(A20),"",J20-SUMIF(CATEGORIAS[[#All],[FORMATO GENERAL]], A20, CATEGORIAS[[#All],[COSTO REAL ANTERIOR]])) -> -370962 | J20: =IF(ISBLANK(A20),"",SUMIF(CATEGORIAS[[#All],[FORMATO GENERAL]], A20, CATEGORIAS[[#All],[COSTO REAL]])) -> 3189423 | K20: =IF(ISBLANK(A20),"",SUMIF(CATEGORIAS[[#All],[FORMATO GENERAL]], A20, CATEGORIAS[[#All],[TOTAL PRODUCCION ACTUAL]])) -> 965766.64 | L20: =IF(ISBLANK(A20),"",SUMIF(CATEGORIAS[[#All],[FORMATO GENERAL]], A20, CATEGORIAS[[#All],[PROYECCION TOTAL DE COSTO]])) -> 0 | N20: =IF(ISBLANK(A20),"",TRUNC(G20-J20-L20,2)) -> -2223656.4
B21: A6 | C21: 06 - Andamios | E21: =IF(ISBLANK(A21),"", SUMIF(CATEGORIAS[[#All],[FORMATO GENERAL]], A21, CATEGORIAS[[#All],[PRESUPUESTO (ORIGINAL)]])) | F21: =IF(ISBLANK(A21),"",G21-E21) | G21: =IF(ISBLANK(A21),"",SUMIF(CATEGORIAS[[#All],[FORMATO GENERAL]], A21, CATEGORIAS[[#All],[PRESUPUESTO FINAL PROYECTADO]])) | I21: =IF(ISBLANK(A21),"",J21-SUMIF(CATEGORIAS[[#All],[FORMATO GENERAL]], A21, CATEGORIAS[[#All],[COSTO REAL ANTERIOR]])) | J21: =IF(ISBLANK(A21),"",SUMIF(CATEGORIAS[[#All],[FORMATO GENERAL]], A21, CATEGORIAS[[#All],[COSTO REAL]])) | K21: =IF(ISBLANK(A21),"",SUMIF(CATEGORIAS[[#All],[FORMATO GENERAL]], A21, CATEGORIAS[[#All],[TOTAL PRODUCCION ACTUAL]])) | L21: =IF(ISBLANK(A21),"",SUMIF(CATEGORIAS[[#All],[FORMATO GENERAL]], A21, CATEGORIAS[[#All],[PROYECCION TOTAL DE COSTO]])) | N21: =IF(ISBLANK(A21),"",TRUNC(G21-J21-L21,2))
A22: 0N01 | C22: Mano de Obra | E22: =IF(ISBLANK(A22),"", SUMIF(CATEGORIAS[[#All],[FORMATO GENERAL]], A22, CATEGORIAS[[#All],[PRESUPUESTO (ORIGINAL)]])) -> 40034534 | F22: =IF(ISBLANK(A22),"",G22-E22) -> 14598476 | G22: =IF(ISBLANK(A22),"",SUMIF(CATEGORIAS[[#All],[FORMATO GENERAL]], A22, CATEGORIAS[[#All],[PRESUPUESTO FINAL PROYECTADO]])) -> 54633010 | I22: =IF(ISBLANK(A22),"",J22-SUMIF(CATEGORIAS[[#All],[FORMATO GENERAL]], A22, CATEGORIAS[[#All],[COSTO REAL ANTERIOR]])) -> 0 | J22: =IF(ISBLANK(A22),"",SUMIF(CATEGORIAS[[#All],[FORMATO GENERAL]], A22, CATEGORIAS[[#All],[COSTO REAL]])) -> 166683412 | K22: =IF(ISBLANK(A22),"",SUMIF(CATEGORIAS[[#All],[FORMATO GENERAL]], A22, CATEGORIAS[[#All],[TOTAL PRODUCCION ACTUAL]])) -> 54633010 | L22: =IF(ISBLANK(A22),"",SUMIF(CATEGORIAS[[#All],[FORMATO GENERAL]], A22, CATEGORIAS[[#All],[PROYECCION TOTAL DE COSTO]])) -> 0 | N22: =IF(ISBLANK(A22),"",TRUNC(G22-J22-L22,2)) -> -1.120504e+08
B23: A7 | C23: 07 - Aislación | E23: =IF(ISBLANK(A23),"", SUMIF(CATEGORIAS[[#All],[FORMATO GENERAL]], A23, CATEGORIAS[[#All],[PRESUPUESTO (ORIGINAL)]])) | F23: =IF(ISBLANK(A23),"",G23-E23) | G23: =IF(ISBLANK(A23),"",SUMIF(CATEGORIAS[[#All],[FORMATO GENERAL]], A23, CATEGORIAS[[#All],[PRESUPUESTO FINAL PROYECTADO]])) | I23: =IF(ISBLANK(A23),"",J23-SUMIF(CATEGORIAS[[#All],[FORMATO GENERAL]], A23, CATEGORIAS[[#All],[COSTO REAL ANTERIOR]])) | J23: =IF(ISBLANK(A23),"",SUMIF(CATEGORIAS[[#All],[FORMATO GENERAL]], A23, CATEGORIAS[[#All],[COSTO REAL]])) | K23: =IF(ISBLANK(A23),"",SUMIF(CATEGORIAS[[#All],[FORMATO GENERAL]], A23, CATEGORIAS[[#All],[TOTAL PRODUCCION ACTUAL]])) | L23: =IF(ISBLANK(A23),"",SUMIF(CATEGORIAS[[#All],[FORMATO GENERAL]], A23, CATEGORIAS[[#All],[PROYECCION TOTAL DE COSTO]])) | N23: =IF(ISBLANK(A23),"",TRUNC(G23-J23-L23,2))
A24: 0H01 | C24: Mano de Obra | E24: =IF(ISBLANK(A24),"", SUMIF(CATEGORIAS[[#All],[FORMATO GENERAL]], A24, CATEGORIAS[[#All],[PRESUPUESTO (ORIGINAL)]])) -> 0 | F24: =IF(ISBLANK(A24),"",G24-E24) -> 0 | G24: =IF(ISBLANK(A24),"",SUMIF(CATEGORIAS[[#All],[FORMATO GENERAL]], A24, CATEGORIAS[[#All],[PRESUPUESTO FINAL PROYECTADO]])) -> 0 | I24: =IF(ISBLANK(A24),"",J24-SUMIF(CATEGORIAS[[#All],[FORMATO GENERAL]], A24, CATEGORIAS[[#All],[COSTO REAL ANTERIOR]])) -> 0 | J24: =IF(ISBLANK(A24),"",SUMIF(CATEGORIAS[[#All],[FORMATO GENERAL]], A24, CATEGORIAS[[#All],[COSTO REAL]])) -> 0 | K24: =IF(ISBLANK(A24),"",SUMIF(CATEGORIAS[[#All],[FORMATO GENERAL]], A24, CATEGORIAS[[#All],[TOTAL PRODUCCION ACTUAL]])) -> 0 | L24: =IF(ISBLANK(A24),"",SUMIF(CATEGORIAS[[#All],[FORMATO GENERAL]], A24, CATEGORIAS[[#All],[PROYECCION TOTAL DE COSTO]])) -> 0 | N24: =IF(ISBLANK(A24),"",TRUNC(G24-J24-L24,2)) -> 0
A25: 0H02 | C25: Aislación Reembolsable | E25: =IF(ISBLANK(A25),"", SUMIF(CATEGORIAS[[#All],[FORMATO GENERAL]], A25, CATEGORIAS[[#All],[PRESUPUESTO (ORIGINAL)]])) -> 0 | F25: =IF(ISBLANK(A25),"",G25-E25) -> 0 | G25: =IF(ISBLANK(A25),"",SUMIF(CATEGORIAS[[#All],[FORMATO GENERAL]], A25, CATEGORIAS[[#All],[PRESUPUESTO FINAL PROYECTADO]])) -> 0 | I25: =IF(ISBLANK(A25),"",J25-SUMIF(CATEGORIAS[[#All],[FORMATO GENERAL]], A25, CATEGORIAS[[#All],[COSTO REAL ANTERIOR]])) -> 0 | J25: =IF(ISBLANK(A25),"",SUMIF(CATEGORIAS[[#All],[FORMATO GENERAL]], A25, CATEGORIAS[[#All],[COSTO REAL]])) -> 0 | K25: =IF(ISBLANK(A25),"",SUMIF(CATEGORIAS[[#All],[FORMATO GENERAL]], A25, CATEGORIAS[[#All],[TOTAL PRODUCCION ACTUAL]])) -> 0 | L25: =IF(ISBLANK(A25),"",SUMIF(CATEGORIAS[[#All],[FORMATO GENERAL]], A25, CATEGORIAS[[#All],[PROYECCION TOTAL DE COSTO]])) -> 0 | N25: =IF(ISBLANK(A25),"",TRUNC(G25-J25-L25,2)) -> 0
B26: A8 | C26: 08 - Caldera | E26: =IF(ISBLANK(A26),"", SUMIF(CATEGORIAS[[#All],[FORMATO GENERAL]], A26, CATEGORIAS[[#All],[PRESUPUESTO (ORIGINAL)]])) | F26: =IF(ISBLANK(A26),"",G26-E26) | G26: =IF(ISBLANK(A26),"",SUMIF(CATEGORIAS[[#All],[FORMATO GENERAL]], A26, CATEGORIAS[[#All],[PRESUPUESTO FINAL PROYECTADO]])) | I26: =IF(ISBLANK(A26),"",J26-SUMIF(CATEGORIAS[[#All],[FORMATO GENERAL]], A26, CATEGORIAS[[#All],[COSTO REAL ANTERIOR]])) | J26: =IF(ISBLANK(A26),"",SUMIF(CATEGORIAS[[#All],[FORMATO GENERAL]], A26, CATEGORIAS[[#All],[COSTO REAL]])) | K26: =IF(ISBLANK(A26),"",SUMIF(CATEGORIAS[[#All],[FORMATO GENERAL]], A26, CATEGORIAS[[#All],[TOTAL PRODUCCION ACTUAL]])) | L26: =IF(ISBLANK(A26),"",SUMIF(CATEGORIAS[[#All],[FORMATO GENERAL]], A26, CATEGORIAS[[#All],[PROYECCION TOTAL DE COSTO]])) | N26: =IF(ISBLANK(A26),"",TRUNC(G26-J26-L26,2))
A27: 0I01 | C27: Mano de Obra | E27: =IF(ISBLANK(A27),"", SUMIF(CATEGORIAS[[#All],[FORMATO GENERAL]], A27, CATEGORIAS[[#All],[PRESUPUESTO (ORIGINAL)]])) -> 0 | F27: =IF(ISBLANK(A27),"",G27-E27) -> 0 | G27: =IF(ISBLANK(A27),"",SUMIF(CATEGORIAS[[#All],[FORMATO GENERAL]], A27, CATEGORIAS[[#All],[PRESUPUESTO FINAL PROYECTADO]])) -> 0 | I27: =IF(ISBLANK(A27),"",J27-SUMIF(CATEGORIAS[[#All],[FORMATO GENERAL]], A27, CATEGORIAS[[#All],[COSTO REAL ANTERIOR]])) -> 0 | J27: =IF(ISBLANK(A27),"",SUMIF(CATEGORIAS[[#All],[FORMATO GENERAL]], A27, CATEGORIAS[[#All],[COSTO REAL]])) -> 0 | K27: =IF(ISBLANK(A27),"",SUMIF(CATEGORIAS[[#All],[FORMATO GENERAL]], A27, CATEGORIAS[[#All],[TOTAL PRODUCCION ACTUAL]])) -> 0 | L27: =IF(ISBLANK(A27),"",SUMIF(CATEGORIAS[[#All],[FORMATO GENERAL]], A27, CATEGORIAS[[#All],[PROYECCION TOTAL DE COSTO]])) -> 0 | N27: =IF(ISBLANK(A27),"",TRUNC(G27-J27-L27,2)) -> 0
A28: 0I02 | C28: Caldera Reembolsable | E28: =IF(ISBLANK(A28),"", SUMIF(CATEGORIAS[[#All],[FORMATO GENERAL]], A28, CATEGORIAS[[#All],[PRESUPUESTO (ORIGINAL)]])) -> 0 | F28: =IF(ISBLANK(A28),"",G28-E28) -> 0 | G28: =IF(ISBLANK(A28),"",SUMIF(CATEGORIAS[[#All],[FORMATO GENERAL]], A28, CATEGORIAS[[#All],[PRESUPUESTO FINAL PROYECTADO]])) -> 0 | I28: =IF(ISBLANK(A28),"",J28-SUMIF(CATEGORIAS[[#All],[FORMATO GENERAL]], A28, CATEGORIAS[[#All],[COSTO REAL ANTERIOR]])) -> 0 | J28: =IF(ISBLANK(A28),"",SUMIF(CATEGORIAS[[#All],[FORMATO GENERAL]], A28, CATEGORIAS[[#All],[COSTO REAL]])) -> 0 | K28: =IF(ISBLANK(A28),"",SUMIF(CATEGORIAS[[#All],[FORMATO GENERAL]], A28, CATEGORIAS[[#All],[TOTAL PRODUCCION ACTUAL]])) -> 0 | L28: =IF(ISBLANK(A28),"",SUMIF(CATEGORIAS[[#All],[FORMATO GENERAL]], A28, CATEGORIAS[[#All],[PROYECCION TOTAL DE COSTO]])) -> 0 | N28: =IF(ISBLANK(A28),"",TRUNC(G28-J28-L28,2)) -> 0
B29: A9 | C29: 09 - Ducto | E29: =IF(ISBLANK(A29),"", SUMIF(CATEGORIAS[[#All],[FORMATO GENERAL]], A29, CATEGORIAS[[#All],[PRESUPUESTO (ORIGINAL)]])) | F29: =IF(ISBLANK(A29),"",G29-E29) | G29: =IF(ISBLANK(A29),"",SUMIF(CATEGORIAS[[#All],[FORMATO GENERAL]], A29, CATEGORIAS[[#All],[PRESUPUESTO FINAL PROYECTADO]])) | I29: =IF(ISBLANK(A29),"",J29-SUMIF(CATEGORIAS[[#All],[FORMATO GENERAL]], A29, CATEGORIAS[[#All],[COSTO REAL ANTERIOR]])) | J29: =IF(ISBLANK(A29),"",SUMIF(CATEGORIAS[[#All],[FORMATO GENERAL]], A29, CATEGORIAS[[#All],[COSTO REAL]])) | K29: =IF(ISBLANK(A29),"",SUMIF(CATEGORIAS[[#All],[FORMATO GENERAL]], A29, CATEGORIAS[[#All],[TOTAL PRODUCCION ACTUAL]])) | L29: =IF(ISBLANK(A29),"",SUMIF(CATEGORIAS[[#All],[FORMATO GENERAL]], A29, CATEGORIAS[[#All],[PROYECCION TOTAL DE COSTO]])) | N29: =IF(ISBLANK(A29),"",TRUNC(G29-J29-L29,2))
A30: 0J01 | C30: Mano de Obra | E30: =IF(ISBLANK(A30),"", SUMIF(CATEGORIAS[[#All],[FORMATO GENERAL]], A30, CATEGORIAS[[#All],[PRESUPUESTO (ORIGINAL)]])) -> 0 | F30: =IF(ISBLANK(A30),"",G30-E30) -> 0 | G30: =IF(ISBLANK(A30),"",SUMIF(CATEGORIAS[[#All],[FORMATO GENERAL]], A30, CATEGORIAS[[#All],[PRESUPUESTO FINAL PROYECTADO]])) -> 0 | I30: =IF(ISBLANK(A30),"",J30-SUMIF(CATEGORIAS[[#All],[FORMATO GENERAL]], A30, CATEGORIAS[[#All],[COSTO REAL ANTERIOR]])) -> 0 | J30: =IF(ISBLANK(A30),"",SUMIF(CATEGORIAS[[#All],[FORMATO GENERAL]], A30, CATEGORIAS[[#All],[COSTO REAL]])) -> 0 | K30: =IF(ISBLANK(A30),"",SUMIF(CATEGORIAS[[#All],[FORMATO GENERAL]], A30, CATEGORIAS[[#All],[TOTAL PRODUCCION ACTUAL]])) -> 0 | L30: =IF(ISBLANK(A30),"",SUMIF(CATEGORIAS[[#All],[FORMATO GENERAL]], A30, CATEGORIAS[[#All],[PROYECCION TOTAL DE COSTO]])) -> 0 | N30: =IF(ISBLANK(A30),"",TRUNC(G30-J30-L30,2)) -> 0
A31: 0J02 | C31: Ducto Reembolsable | E31: =IF(ISBLANK(A31),"", SUMIF(CATEGORIAS[[#All],[FORMATO GENERAL]], A31, CATEGORIAS[[#All],[PRESUPUESTO (ORIGINAL)]])) -> 0 | F31: =IF(ISBLANK(A31),"",G31-E31) -> 0 | G31: =IF(ISBLANK(A31),"",SUMIF(CATEGORIAS[[#All],[FORMATO GENERAL]], A31, CATEGORIAS[[#All],[PRESUPUESTO FINAL PROYECTADO]])) -> 0 | I31: =IF(ISBLANK(A31),"",J31-SUMIF(CATEGORIAS[[#All],[FORMATO GENERAL]], A31, CATEGORIAS[[#All],[COSTO REAL ANTERIOR]])) -> 0 | J31: =IF(ISBLANK(A31),"",SUMIF(CATEGORIAS[[#All],[FORMATO GENERAL]], A31, CATEGORIAS[[#All],[COSTO REAL]])) -> 0 | K31: =IF(ISBLANK(A31),"",SUMIF(CATEGORIAS[[#All],[FORMATO GENERAL]], A31, CATEGORIAS[[#All],[TOTAL PRODUCCION ACTUAL]])) -> 0 | L31: =IF(ISBLANK(A31),"",SUMIF(CATEGORIAS[[#All],[FORMATO GENERAL]], A31, CATEGORIAS[[#All],[PROYECCION TOTAL DE COSTO]])) -> 0 | N31: =IF(ISBLANK(A31),"",TRUNC(G31-J31-L31,2)) -> 0
B32: A10 | C32: 10 - Comisionamiento - PEM | E32: =IF(ISBLANK(A32),"", SUMIF(CATEGORIAS[[#All],[FORMATO GENERAL]], A32, CATEGORIAS[[#All],[PRESUPUESTO (ORIGINAL)]])) | F32: =IF(ISBLANK(A32),"",G32-E32) | G32: =IF(ISBLANK(A32),"",SUMIF(CATEGORIAS[[#All],[FORMATO GENERAL]], A32, CATEGORIAS[[#All],[PRESUPUESTO FINAL PROYECTADO]])) | I32: =IF(ISBLANK(A32),"",J32-SUMIF(CATEGORIAS[[#All],[FORMATO GENERAL]], A32, CATEGORIAS[[#All],[COSTO REAL ANTERIOR]])) | J32: =IF(ISBLANK(A32),"",SUMIF(CATEGORIAS[[#All],[FORMATO GENERAL]], A32, CATEGORIAS[[#All],[COSTO REAL]])) | K32: =IF(ISBLANK(A32),"",SUMIF(CATEGORIAS[[#All],[FORMATO GENERAL]], A32, CATEGORIAS[[#All],[TOTAL PRODUCCION ACTUAL]])) | L32: =IF(ISBLANK(A32),"",SUMIF(CATEGORIAS[[#All],[FORMATO GENERAL]], A32, CATEGORIAS[[#All],[PROYECCION TOTAL DE COSTO]])) | N32: =IF(ISBLANK(A32),"",TRUNC(G32-J32-L32,2))
A33: 0G01 | C33: Mano de Obra | E33: =IF(ISBLANK(A33),"", SUMIF(CATEGORIAS[[#All],[FORMATO GENERAL]], A33, CATEGORIAS[[#All],[PRESUPUESTO (ORIGINAL)]])) -> 0 | F33: =IF(ISBLANK(A33),"",G33-E33) -> 0 | G33: =IF(ISBLANK(A33),"",SUMIF(CATEGORIAS[[#All],[FORMATO GENERAL]], A33, CATEGORIAS[[#All],[PRESUPUESTO FINAL PROYECTADO]])) -> 0 | I33: =IF(ISBLANK(A33),"",J33-SUMIF(CATEGORIAS[[#All],[FORMATO GENERAL]], A33, CATEGORIAS[[#All],[COSTO REAL ANTERIOR]])) -> 0 | J33: =IF(ISBLANK(A33),"",SUMIF(CATEGORIAS[[#All],[FORMATO GENERAL]], A33, CATEGORIAS[[#All],[COSTO REAL]])) -> 0 | K33: =IF(ISBLANK(A33),"",SUMIF(CATEGORIAS[[#All],[FORMATO GENERAL]], A33, CATEGORIAS[[#All],[TOTAL PRODUCCION ACTUAL]])) -> 0 | L33: =IF(ISBLANK(A33),"",SUMIF(CATEGORIAS[[#All],[FORMATO GENERAL]], A33, CATEGORIAS[[#All],[PROYECCION TOTAL DE COSTO]])) -> 0 | N33: =IF(ISBLANK(A33),"",TRUNC(G33-J33-L33,2)) -> 0
B34: A11 | C34: 11 - Arquitectura | E34: =IF(ISBLANK(A34),"", SUMIF(CATEGORIAS[[#All],[FORMATO GENERAL]], A34, CATEGORIAS[[#All],[PRESUPUESTO (ORIGINAL)]])) | F34: =IF(ISBLANK(A34),"",G34-E34) | G34: =IF(ISBLANK(A34),"",SUMIF(CATEGORIAS[[#All],[FORMATO GENERAL]], A34, CATEGORIAS[[#All],[PRESUPUESTO FINAL PROYECTADO]])) | I34: =IF(ISBLANK(A34),"",J34-SUMIF(CATEGORIAS[[#All],[FORMATO GENERAL]], A34, CATEGORIAS[[#All],[COSTO REAL ANTERIOR]])) | J34: =IF(ISBLANK(A34),"",SUMIF(CATEGORIAS[[#All],[FORMATO GENERAL]], A34, CATEGORIAS[[#All],[COSTO REAL]])) | K34: =IF(ISBLANK(A34),"",SUMIF(CATEGORIAS[[#All],[FORMATO GENERAL]], A34, CATEGORIAS[[#All],[TOTAL PRODUCCION ACTUAL]])) | L34: =IF(ISBLANK(A34),"",SUMIF(CATEGORIAS[[#All],[FORMATO GENERAL]], A34, CATEGORIAS[[#All],[PROYECCION TOTAL DE COSTO]])) | N34: =IF(ISBLANK(A34),"",TRUNC(G34-J34-L34,2))
A35: 0K01 | C35: Mano de Obra | E35: =IF(ISBLANK(A35),"", SUMIF(CATEGORIAS[[#All],[FORMATO GENERAL]], A35, CATEGORIAS[[#All],[PRESUPUESTO (ORIGINAL)]])) -> 0 | F35: =IF(ISBLANK(A35),"",G35-E35) -> 0 | G35: =IF(ISBLANK(A35),"",SUMIF(CATEGORIAS[[#All],[FORMATO GENERAL]], A35, CATEGORIAS[[#All],[PRESUPUESTO FINAL PROYECTADO]])) -> 0 | I35: =IF(ISBLANK(A35),"",J35-SUMIF(CATEGORIAS[[#All],[FORMATO GENERAL]], A35, CATEGORIAS[[#All],[COSTO REAL ANTERIOR]])) -> 0 | J35: =IF(ISBLANK(A35),"",SUMIF(CATEGORIAS[[#All],[FORMATO GENERAL]], A35, CATEGORIAS[[#All],[COSTO REAL]])) -> 0 | K35: =IF(ISBLANK(A35),"",SUMIF(CATEGORIAS[[#All],[FORMATO GENERAL]], A35, CATEGORIAS[[#All],[TOTAL PRODUCCION ACTUAL]])) -> 0 | L35: =IF(ISBLANK(A35),"",SUMIF(CATEGORIAS[[#All],[FORMATO GENERAL]], A35, CATEGORIAS[[#All],[PROYECCION TOTAL DE COSTO]])) -> 0 | N35: =IF(ISBLANK(A35),"",TRUNC(G35-J35-L35,2)) -> 0
A36: 0K02 | C36: Arquitectura Reembolsable | E36: =IF(ISBLANK(A36),"", SUMIF(CATEGORIAS[[#All],[FORMATO GENERAL]], A36, CATEGORIAS[[#All],[PRESUPUESTO (ORIGINAL)]])) -> 0 | F36: =IF(ISBLANK(A36),"",G36-E36) -> 0 | G36: =IF(ISBLANK(A36),"",SUMIF(CATEGORIAS[[#All],[FORMATO GENERAL]], A36, CATEGORIAS[[#All],[PRESUPUESTO FINAL PROYECTADO]])) -> 0 | I36: =IF(ISBLANK(A36),"",J36-SUMIF(CATEGORIAS[[#All],[FORMATO GENERAL]], A36, CATEGORIAS[[#All],[COSTO REAL ANTERIOR]])) -> 0 | J36: =IF(ISBLANK(A36),"",SUMIF(CATEGORIAS[[#All],[FORMATO GENERAL]], A36, CATEGORIAS[[#All],[COSTO REAL]])) -> 0 | K36: =IF(ISBLANK(A36),"",SUMIF(CATEGORIAS[[#All],[FORMATO GENERAL]], A36, CATEGORIAS[[#All],[TOTAL PRODUCCION ACTUAL]])) -> 0 | L36: =IF(ISBLANK(A36),"",SUMIF(CATEGORIAS[[#All],[FORMATO GENERAL]], A36, CATEGORIAS[[#All],[PROYECCION TOTAL DE COSTO]])) -> 0 | N36: =IF(ISBLANK(A36),"",TRUNC(G36-J36-L36,2)) -> 0
B37: A12 | C37: 12 - Estanque | E37: =IF(ISBLANK(A37),"", SUMIF(CATEGORIAS[[#All],[FORMATO GENERAL]], A37, CATEGORIAS[[#All],[PRESUPUESTO (ORIGINAL)]])) | F37: =IF(ISBLANK(A37),"",G37-E37) | G37: =IF(ISBLANK(A37),"",SUMIF(CATEGORIAS[[#All],[FORMATO GENERAL]], A37, CATEGORIAS[[#All],[PRESUPUESTO FINAL PROYECTADO]])) | I37: =IF(ISBLANK(A37),"",J37-SUMIF(CATEGORIAS[[#All],[FORMATO GENERAL]], A37, CATEGORIAS[[#All],[COSTO REAL ANTERIOR]])) | J37: =IF(ISBLANK(A37),"",SUMIF(CATEGORIAS[[#All],[FORMATO GENERAL]], A37, CATEGORIAS[[#All],[COSTO REAL]])) | K37: =IF(ISBLANK(A37),"",SUMIF(CATEGORIAS[[#All],[FORMATO GENERAL]], A37, CATEGORIAS[[#All],[TOTAL PRODUCCION ACTUAL]])) | L37: =IF(ISBLANK(A37),"",SUMIF(CATEGORIAS[[#All],[FORMATO GENERAL]], A37, CATEGORIAS[[#All],[PROYECCION TOTAL DE COSTO]])) | N37: =IF(ISBLANK(A37),"",TRUNC(G37-J37-L37,2))
A38: 0M01 | C38: Mano de Obra | E38: =IF(ISBLANK(A38),"", SUMIF(CATEGORIAS[[#All],[FORMATO GENERAL]], A38, CATEGORIAS[[#All],[PRESUPUESTO (ORIGINAL)]])) -> 0 | F38: =IF(ISBLANK(A38),"",G38-E38) -> 0 | G38: =IF(ISBLANK(A38),"",SUMIF(CATEGORIAS[[#All],[FORMATO GENERAL]], A38, CATEGORIAS[[#All],[PRESUPUESTO FINAL PROYECTADO]])) -> 0 | I38: =IF(ISBLANK(A38),"",J38-SUMIF(CATEGORIAS[[#All],[FORMATO GENERAL]], A38, CATEGORIAS[[#All],[COSTO REAL ANTERIOR]])) -> 0 | J38: =IF(ISBLANK(A38),"",SUMIF(CATEGORIAS[[#All],[FORMATO GENERAL]], A38, CATEGORIAS[[#All],[COSTO REAL]])) -> 0 | K38: =IF(ISBLANK(A38),"",SUMIF(CATEGORIAS[[#All],[FORMATO GENERAL]], A38, CATEGORIAS[[#All],[TOTAL PRODUCCION ACTUAL]])) -> 0 | L38: =IF(ISBLANK(A38),"",SUMIF(CATEGORIAS[[#All],[FORMATO GENERAL]], A38, CATEGORIAS[[#All],[PROYECCION TOTAL DE COSTO]])) -> 0 | N38: =IF(ISBLANK(A38),"",TRUNC(G38-J38-L38,2)) -> 0
A39: 0M02 | C39: Estanque Reembolsable | E39: =IF(ISBLANK(A39),"", SUMIF(CATEGORIAS[[#All],[FORMATO GENERAL]], A39, CATEGORIAS[[#All],[PRESUPUESTO (ORIGINAL)]])) -> 0 | F39: =IF(ISBLANK(A39),"",G39-E39) -> 0 | G39: =IF(ISBLANK(A39),"",SUMIF(CATEGORIAS[[#All],[FORMATO GENERAL]], A39, CATEGORIAS[[#All],[PRESUPUESTO FINAL PROYECTADO]])) -> 0 | I39: =IF(ISBLANK(A39),"",J39-SUMIF(CATEGORIAS[[#All],[FORMATO GENERAL]], A39, CATEGORIAS[[#All],[COSTO REAL ANTERIOR]])) -> 0 | J39: =IF(ISBLANK(A39),"",SUMIF(CATEGORIAS[[#All],[FORMATO GENERAL]], A39, CATEGORIAS[[#All],[COSTO REAL]])) -> 0 | K39: =IF(ISBLANK(A39),"",SUMIF(CATEGORIAS[[#All],[FORMATO GENERAL]], A39, CATEGORIAS[[#All],[TOTAL PRODUCCION ACTUAL]])) -> 0 | L39: =IF(ISBLANK(A39),"",SUMIF(CATEGORIAS[[#All],[FORMATO GENERAL]], A39, CATEGORIAS[[#All],[PROYECCION TOTAL DE COSTO]])) -> 0 | N39: =IF(ISBLANK(A39),"",TRUNC(G39-J39-L39,2)) -> 0
B40: A13 | C40: Costo Proporcional HH | E40: =IF(ISBLANK(A40),"", SUMIF(CATEGORIAS[[#All],[FORMATO GENERAL]], A40, CATEGORIAS[[#All],[PRESUPUESTO (ORIGINAL)]])) | F40: =IF(ISBLANK(A40),"",G40-E40) | G40: =IF(ISBLANK(A40),"",SUMIF(CATEGORIAS[[#All],[FORMATO GENERAL]], A40, CATEGORIAS[[#All],[PRESUPUESTO FINAL PROYECTADO]])) | I40: =IF(ISBLANK(A40),"",J40-SUMIF(CATEGORIAS[[#All],[FORMATO GENERAL]], A40, CATEGORIAS[[#All],[COSTO REAL ANTERIOR]])) | J40: =IF(ISBLANK(A40),"",SUMIF(CATEGORIAS[[#All],[FORMATO GENERAL]], A40, CATEGORIAS[[#All],[COSTO REAL]])) | K40: =IF(ISBLANK(A40),"",SUMIF(CATEGORIAS[[#All],[FORMATO GENERAL]], A40, CATEGORIAS[[#All],[TOTAL PRODUCCION ACTUAL]])) | L40: =IF(ISBLANK(A40),"",SUMIF(CATEGORIAS[[#All],[FORMATO GENERAL]], A40, CATEGORIAS[[#All],[PROYECCION TOTAL DE COSTO]])) | N40: =IF(ISBLANK(A40),"",TRUNC(G40-J40-L40,2))
A41: 0Y01 | C41: Movilización | E41: =IF(ISBLANK(A41),"", SUMIF(CATEGORIAS[[#All],[FORMATO GENERAL]], A41, CATEGORIAS[[#All],[PRESUPUESTO (ORIGINAL)]])) -> 1.3325478e+08 | F41: =IF(ISBLANK(A41),"",G41-E41) -> 5084246.4 | G41: =IF(ISBLANK(A41),"",SUMIF(CATEGORIAS[[#All],[FORMATO GENERAL]], A41, CATEGORIAS[[#All],[PRESUPUESTO FINAL PROYECTADO]])) -> 1.3833903e+08 | I41: =IF(ISBLANK(A41),"",J41-SUMIF(CATEGORIAS[[#All],[FORMATO GENERAL]], A41, CATEGORIAS[[#All],[COSTO REAL ANTERIOR]])) -> 0 | J41: =IF(ISBLANK(A41),"",SUMIF(CATEGORIAS[[#All],[FORMATO GENERAL]], A41, CATEGORIAS[[#All],[COSTO REAL]])) -> 1.9913927e+08 | K41: =IF(ISBLANK(A41),"",SUMIF(CATEGORIAS[[#All],[FORMATO GENERAL]], A41, CATEGORIAS[[#All],[TOTAL PRODUCCION ACTUAL]])) -> 1.3833903e+08 | L41: =IF(ISBLANK(A41),"",SUMIF(CATEGORIAS[[#All],[FORMATO GENERAL]], A41, CATEGORIAS[[#All],[PROYECCION TOTAL DE COSTO]])) -> 0 | N41: =IF(ISBLANK(A41),"",TRUNC(G41-J41-L41,2)) -> -60800244
A42: 0Y02 | C42: Alimentación | E42: =IF(ISBLANK(A42),"", SUMIF(CATEGORIAS[[#All],[FORMATO GENERAL]], A42, CATEGORIAS[[#All],[PRESUPUESTO (ORIGINAL)]])) -> 55445823 | F42: =IF(ISBLANK(A42),"",G42-E42) -> 8479996.7 | G42: =IF(ISBLANK(A42),"",SUMIF(CATEGORIAS[[#All],[FORMATO GENERAL]], A42, CATEGORIAS[[#All],[PRESUPUESTO FINAL PROYECTADO]])) -> 63925819 | I42: =IF(ISBLANK(A42),"",J42-SUMIF(CATEGORIAS[[#All],[FORMATO GENERAL]], A42, CATEGORIAS[[#All],[COSTO REAL ANTERIOR]])) -> 0 | J42: =IF(ISBLANK(A42),"",SUMIF(CATEGORIAS[[#All],[FORMATO GENERAL]], A42, CATEGORIAS[[#All],[COSTO REAL]])) -> 55284127 | K42: =IF(ISBLANK(A42),"",SUMIF(CATEGORIAS[[#All],[FORMATO GENERAL]], A42, CATEGORIAS[[#All],[TOTAL PRODUCCION ACTUAL]])) -> 63925819 | L42: =IF(ISBLANK(A42),"",SUMIF(CATEGORIAS[[#All],[FORMATO GENERAL]], A42, CATEGORIAS[[#All],[PROYECCION TOTAL DE COSTO]])) -> 0 | N42: =IF(ISBLANK(A42),"",TRUNC(G42-J42-L42,2)) -> 8641691.9
A43: 0Y03 | C43: Cursos y Examenes | E43: =IF(ISBLANK(A43),"", SUMIF(CATEGORIAS[[#All],[FORMATO GENERAL]], A43, CATEGORIAS[[#All],[PRESUPUESTO (ORIGINAL)]])) -> 0 | F43: =IF(ISBLANK(A43),"",G43-E43) -> 0 | G43: =IF(ISBLANK(A43),"",SUMIF(CATEGORIAS[[#All],[FORMATO GENERAL]], A43, CATEGORIAS[[#All],[PRESUPUESTO FINAL PROYECTADO]])) -> 0 | I43: =IF(ISBLANK(A43),"",J43-SUMIF(CATEGORIAS[[#All],[FORMATO GENERAL]], A43, CATEGORIAS[[#All],[COSTO REAL ANTERIOR]])) -> 0 | J43: =IF(ISBLANK(A43),"",SUMIF(CATEGORIAS[[#All],[FORMATO GENERAL]], A43, CATEGORIAS[[#All],[COSTO REAL]])) -> 0 | K43: =IF(ISBLANK(A43),"",SUMIF(CATEGORIAS[[#All],[FORMATO GENERAL]], A43, CATEGORIAS[[#All],[TOTAL PRODUCCION ACTUAL]])) -> 0 | L43: =IF(ISBLANK(A43),"",SUMIF(CATEGORIAS[[#All],[FORMATO GENERAL]], A43, CATEGORIAS[[#All],[PROYECCION TOTAL DE COSTO]])) -> 0 | N43: =IF(ISBLANK(A43),"",TRUNC(G43-J43-L43,2)) -> 0
A44: 0Y04 | C44: Elem. de Seguridad | E44: =IF(ISBLANK(A44),"", SUMIF(CATEGORIAS[[#All],[FORMATO GENERAL]], A44, CATEGORIAS[[#All],[PRESUPUESTO (ORIGINAL)]])) -> 49460193 | F44: =IF(ISBLANK(A44),"",G44-E44) -> 9118898.4 | G44: =IF(ISBLANK(A44),"",SUMIF(CATEGORIAS[[#All],[FORMATO GENERAL]], A44, CATEGORIAS[[#All],[PRESUPUESTO FINAL PROYECTADO]])) -> 58579092 | I44: =IF(ISBLANK(A44),"",J44-SUMIF(CATEGORIAS[[#All],[FORMATO GENERAL]], A44, CATEGORIAS[[#All],[COSTO REAL ANTERIOR]])) -> -7606773 | J44: =IF(ISBLANK(A44),"",SUMIF(CATEGORIAS[[#All],[FORMATO GENERAL]], A44, CATEGORIAS[[#All],[COSTO REAL]])) -> 65116448 | K44: =IF(ISBLANK(A44),"",SUMIF(CATEGORIAS[[#All],[FORMATO GENERAL]], A44, CATEGORIAS[[#All],[TOTAL PRODUCCION ACTUAL]])) -> 58579092 | L44: =IF(ISBLANK(A44),"",SUMIF(CATEGORIAS[[#All],[FORMATO GENERAL]], A44, CATEGORIAS[[#All],[PROYECCION TOTAL DE COSTO]])) -> 0 | N44: =IF(ISBLANK(A44),"",TRUNC(G44-J44-L44,2)) -> -6537356.3
A45: 0Y05 | C45: Mat. de Consumo | E45: =IF(ISBLANK(A45),"", SUMIF(CATEGORIAS[[#All],[FORMATO GENERAL]], A45, CATEGORIAS[[#All],[PRESUPUESTO (ORIGINAL)]])) -> 12103995 | F45: =IF(ISBLANK(A45),"",G45-E45) -> 1517057.5 | G45: =IF(ISBLANK(A45),"",SUMIF(CATEGORIAS[[#All],[FORMATO GENERAL]], A45, CATEGORIAS[[#All],[PRESUPUESTO FINAL PROYECTADO]])) -> 13621052 | I45: =IF(ISBLANK(A45),"",J45-SUMIF(CATEGORIAS[[#All],[FORMATO GENERAL]], A45, CATEGORIAS[[#All],[COSTO REAL ANTERIOR]])) -> -5064484 | J45: =IF(ISBLANK(A45),"",SUMIF(CATEGORIAS[[#All],[FORMATO GENERAL]], A45, CATEGORIAS[[#All],[COSTO REAL]])) -> 19527807 | K45: =IF(ISBLANK(A45),"",SUMIF(CATEGORIAS[[#All],[FORMATO GENERAL]], A45, CATEGORIAS[[#All],[TOTAL PRODUCCION ACTUAL]])) -> 13621052 | L45: =IF(ISBLANK(A45),"",SUMIF(CATEGORIAS[[#All],[FORMATO GENERAL]], A45, CATEGORIAS[[#All],[PROYECCION TOTAL DE COSTO]])) -> 0 | N45: =IF(ISBLANK(A45),"",TRUNC(G45-J45-L45,2)) -> -5906755
A46: 0Y06 | C46: Herramienta Menor | E46: =IF(ISBLANK(A46),"", SUMIF(CATEGORIAS[[#All],[FORMATO GENERAL]], A46, CATEGORIAS[[#All],[PRESUPUESTO (ORIGINAL)]])) -> 8347787 | F46: =IF(ISBLANK(A46),"",G46-E46) -> 10169316 | G46: =IF(ISBLANK(A46),"",SUMIF(CATEGORIAS[[#All],[FORMATO GENERAL]], A46, CATEGORIAS[[#All],[PRESUPUESTO FINAL PROYECTADO]])) -> 18517103 | I46: =IF(ISBLANK(A46),"",J46-SUMIF(CATEGORIAS[[#All],[FORMATO GENERAL]], A46, CATEGORIAS[[#All],[COSTO REAL ANTERIOR]])) -> 25082986 | J46: =IF(ISBLANK(A46),"",SUMIF(CATEGORIAS[[#All],[FORMATO GENERAL]], A46, CATEGORIAS[[#All],[COSTO REAL]])) -> 76380238 | K46: =IF(ISBLANK(A46),"",SUMIF(CATEGORIAS[[#All],[FORMATO GENERAL]], A46, CATEGORIAS[[#All],[TOTAL PRODUCCION ACTUAL]])) -> 18517103 | L46: =IF(ISBLANK(A46),"",SUMIF(CATEGORIAS[[#All],[FORMATO GENERAL]], A46, CATEGORIAS[[#All],[PROYECCION TOTAL DE COSTO]])) -> 0 | N46: =IF(ISBLANK(A46),"",TRUNC(G46-J46-L46,2)) -> -57863135
A47: 0Y07 | C47: Artículos de Oficina | E47: =IF(ISBLANK(A47),"", SUMIF(CATEGORIAS[[#All],[FORMATO GENERAL]], A47, CATEGORIAS[[#All],[PRESUPUESTO (ORIGINAL)]])) -> 0 | F47: =IF(ISBLANK(A47),"",G47-E47) -> 0 | G47: =IF(ISBLANK(A47),"",SUMIF(CATEGORIAS[[#All],[FORMATO GENERAL]], A47, CATEGORIAS[[#All],[PRESUPUESTO FINAL PROYECTADO]])) -> 0 | I47: =IF(ISBLANK(A47),"",J47-SUMIF(CATEGORIAS[[#All],[FORMATO GENERAL]], A47, CATEGORIAS[[#All],[COSTO REAL ANTERIOR]])) -> 0 | J47: =IF(ISBLANK(A47),"",SUMIF(CATEGORIAS[[#All],[FORMATO GENERAL]], A47, CATEGORIAS[[#All],[COSTO REAL]])) -> 0 | K47: =IF(ISBLANK(A47),"",SUMIF(CATEGORIAS[[#All],[FORMATO GENERAL]], A47, CATEGORIAS[[#All],[TOTAL PRODUCCION ACTUAL]])) -> 0 | L47: =IF(ISBLANK(A47),"",SUMIF(CATEGORIAS[[#All],[FORMATO GENERAL]], A47, CATEGORIAS[[#All],[PROYECCION TOTAL DE COSTO]])) -> 0 | N47: =IF(ISBLANK(A47),"",TRUNC(G47-J47-L47,2)) -> 0
A48: 0Y08 | C48: Movilización Interna | E48: =IF(ISBLANK(A48),"", SUMIF(CATEGORIAS[[#All],[FORMATO GENERAL]], A48, CATEGORIAS[[#All],[PRESUPUESTO (ORIGINAL)]])) -> 1.8004888e+08 | F48: =IF(ISBLANK(A48),"",G48-E48) -> 22146845 | G48: =IF(ISBLANK(A48),"",SUMIF(CATEGORIAS[[#All],[FORMATO GENERAL]], A48, CATEGORIAS[[#All],[PRESUPUESTO FINAL PROYECTADO]])) -> 2.0219572e+08 | I48: =IF(ISBLANK(A48),"",J48-SUMIF(CATEGORIAS[[#All],[FORMATO GENERAL]], A48, CATEGORIAS[[#All],[COSTO REAL ANTERIOR]])) -> 50400 | J48: =IF(ISBLANK(A48),"",SUMIF(CATEGORIAS[[#All],[FORMATO GENERAL]], A48, CATEGORIAS[[#All],[COSTO REAL]])) -> 211932874 | K48: =IF(ISBLANK(A48),"",SUMIF(CATEGORIAS[[#All],[FORMATO GENERAL]], A48, CATEGORIAS[[#All],[TOTAL PRODUCCION ACTUAL]])) -> 2.0219572e+08 | L48: =IF(ISBLANK(A48),"",SUMIF(CATEGORIAS[[#All],[FORMATO GENERAL]], A48, CATEGORIAS[[#All],[PROYECCION TOTAL DE COSTO]])) -> 0 | N48: =IF(ISBLANK(A48),"",TRUNC(G48-J48-L48,2)) -> -9737152
C49: Otros Directos | E49: =IF(ISBLANK(A49),"", SUMIF(CATEGORIAS[[#All],[FORMATO GENERAL]], A49, CATEGORIAS[[#All],[PRESUPUESTO (ORIGINAL)]])) | F49: =IF(ISBLANK(A49),"",G49-E49) | G49: =IF(ISBLANK(A49),"",SUMIF(CATEGORIAS[[#All],[FORMATO GENERAL]], A49, CATEGORIAS[[#All],[PRESUPUESTO FINAL PROYECTADO]])) | I49: =IF(ISBLANK(A49),"",J49-SUMIF(CATEGORIAS[[#All],[FORMATO GENERAL]], A49, CATEGORIAS[[#All],[COSTO REAL ANTERIOR]])) | J49: =IF(ISBLANK(A49),"",SUMIF(CATEGORIAS[[#All],[FORMATO GENERAL]], A49, CATEGORIAS[[#All],[COSTO REAL]])) | K49: =IF(ISBLANK(A49),"",SUMIF(CATEGORIAS[[#All],[FORMATO GENERAL]], A49, CATEGORIAS[[#All],[TOTAL PRODUCCION ACTUAL]])) | L49: =IF(ISBLANK(A49),"",SUMIF(CATEGORIAS[[#All],[FORMATO GENERAL]], A49, CATEGORIAS[[#All],[PROYECCION TOTAL DE COSTO]])) | N49: =IF(ISBLANK(A49),"",TRUNC(G49-J49-L49,2))
A50: 0Z01 | B50: A14 | C50: Equipos | E50: =IF(ISBLANK(A50),"", SUMIF(CATEGORIAS[[#All],[FORMATO GENERAL]], A50, CATEGORIAS[[#All],[PRESUPUESTO (ORIGINAL)]])) -> 8.2520614e+08 | F50: =IF(ISBLANK(A50),"",G50-E50) -> 1.8054081e+08 | G50: =IF(ISBLANK(A50),"",SUMIF(CATEGORIAS[[#All],[FORMATO GENERAL]], A50, CATEGORIAS[[#All],[PRESUPUESTO FINAL PROYECTADO]])) -> 1.005747e+09 | I50: =IF(ISBLANK(A50),"",J50-SUMIF(CATEGORIAS[[#All],[FORMATO GENERAL]], A50, CATEGORIAS[[#All],[COSTO REAL ANTERIOR]])) -> -5501231 | J50: =IF(ISBLANK(A50),"",SUMIF(CATEGORIAS[[#All],[FORMATO GENERAL]], A50, CATEGORIAS[[#All],[COSTO REAL]])) -> 7.186262e+08 | K50: =IF(ISBLANK(A50),"",SUMIF(CATEGORIAS[[#All],[FORMATO GENERAL]], A50, CATEGORIAS[[#All],[TOTAL PRODUCCION ACTUAL]])) -> 1.005747e+09 | L50: =IF(ISBLANK(A50),"",SUMIF(CATEGORIAS[[#All],[FORMATO GENERAL]], A50, CATEGORIAS[[#All],[PROYECCION TOTAL DE COSTO]])) -> 0 | N50: =IF(ISBLANK(A50),"",TRUNC(G50-J50-L50,2)) -> 2.8712075e+08
A51: 0Z02 | B51: A15 | C51: Subcontratos | E51: =IF(ISBLANK(A51),"", SUMIF(CATEGORIAS[[#All],[FORMATO GENERAL]], A51, CATEGORIAS[[#All],[PRESUPUESTO (ORIGINAL)]])) -> 1.1022147e+08 | F51: =IF(ISBLANK(A51),"",G51-E51) -> 1.2845934e+08 | G51: =IF(ISBLANK(A51),"",SUMIF(CATEGORIAS[[#All],[FORMATO GENERAL]], A51, CATEGORIAS[[#All],[PRESUPUESTO FINAL PROYECTADO]])) -> 2.3868082e+08 | I51: =IF(ISBLANK(A51),"",J51-SUMIF(CATEGORIAS[[#All],[FORMATO GENERAL]], A51, CATEGORIAS[[#All],[COSTO REAL ANTERIOR]])) -> 3335540 | J51: =IF(ISBLANK(A51),"",SUMIF(CATEGORIAS[[#All],[FORMATO GENERAL]], A51, CATEGORIAS[[#All],[COSTO REAL]])) -> 1.8795792e+08 | K51: =IF(ISBLANK(A51),"",SUMIF(CATEGORIAS[[#All],[FORMATO GENERAL]], A51, CATEGORIAS[[#All],[TOTAL PRODUCCION ACTUAL]])) -> 2.3868082e+08 | L51: =IF(ISBLANK(A51),"",SUMIF(CATEGORIAS[[#All],[FORMATO GENERAL]], A51, CATEGORIAS[[#All],[PROYECCION TOTAL DE COSTO]])) -> 0 | N51: =IF(ISBLANK(A51),"",TRUNC(G51-J51-L51,2)) -> 50722900
A52: 0Z03 | B52: A16 | C52: Instalación de Faenas | E52: =IF(ISBLANK(A52),"", SUMIF(CATEGORIAS[[#All],[FORMATO GENERAL]], A52, CATEGORIAS[[#All],[PRESUPUESTO (ORIGINAL)]])) -> 1.3575453e+08 | F52: =IF(ISBLANK(A52),"",G52-E52) -> 61083739 | G52: =IF(ISBLANK(A52),"",SUMIF(CATEGORIAS[[#All],[FORMATO GENERAL]], A52, CATEGORIAS[[#All],[PRESUPUESTO FINAL PROYECTADO]])) -> 1.9683827e+08 | I52: =IF(ISBLANK(A52),"",J52-SUMIF(CATEGORIAS[[#All],[FORMATO GENERAL]], A52, CATEGORIAS[[#All],[COSTO REAL ANTERIOR]])) -> -35662648 | J52: =IF(ISBLANK(A52),"",SUMIF(CATEGORIAS[[#All],[FORMATO GENERAL]], A52, CATEGORIAS[[#All],[COSTO REAL]])) -> 104873927 | K52: =IF(ISBLANK(A52),"",SUMIF(CATEGORIAS[[#All],[FORMATO GENERAL]], A52, CATEGORIAS[[#All],[TOTAL PRODUCCION ACTUAL]])) -> 1.9683827e+08 | L52: =IF(ISBLANK(A52),"",SUMIF(CATEGORIAS[[#All],[FORMATO GENERAL]], A52, CATEGORIAS[[#All],[PROYECCION TOTAL DE COSTO]])) -> 0 | N52: =IF(ISBLANK(A52),"",TRUNC(G52-J52-L52,2)) -> 91964344
C54: Subtotal Costos Directos | E54: =SUM(E6:E52) -> 3.1534844e+09 | F54: =SUM(F6:F52) -> 7.0202723e+08 | G54: =SUM(G6:G52) -> 3.8555116e+09 | I54: =SUM(I6:I52) -> -644413.18 | J54: =SUM(J6:J52) -> 3.5514817e+09 | K54: =SUM(K6:K52) -> 3.8555116e+09 | L54: =SUM(L6:L52) -> 0 | N54: =SUM(N6:N52) -> 3.0402988e+08
A56: B. | B56: B. | C56: Costos Indirectos
B57: B1 | C57: Mano de Obra Indirecta | E57: =IF(ISBLANK(A57),"", SUMIF(CATEGORIAS[[#All],[FORMATO GENERAL]], A57, CATEGORIAS[[#All],[PRESUPUESTO (ORIGINAL)]])) | F57: =IF(ISBLANK(A57),"",G57-E57) | G57: =IF(ISBLANK(A57),"",SUMIF(CATEGORIAS[[#All],[FORMATO GENERAL]], A57, CATEGORIAS[[#All],[PRESUPUESTO FINAL PROYECTADO]])) | I57: =IF(ISBLANK(A57),"",J57-SUMIF(CATEGORIAS[[#All],[FORMATO GENERAL]], A57, CATEGORIAS[[#All],[COSTO REAL ANTERIOR]])) | J57: =IF(ISBLANK(A57),"",SUMIF(CATEGORIAS[[#All],[FORMATO GENERAL]], A57, CATEGORIAS[[#All],[COSTO REAL]])) | K57: =IF(ISBLANK(A57),"",SUMIF(CATEGORIAS[[#All],[FORMATO GENERAL]], A57, CATEGORIAS[[#All],[TOTAL PRODUCCION ACTUAL]])) | L57: =IF(ISBLANK(A57),"",SUMIF(CATEGORIAS[[#All],[FORMATO GENERAL]], A57, CATEGORIAS[[#All],[PROYECCION TOTAL DE COSTO]])) | N57: =IF(ISBLANK(A57),"",TRUNC(G57-J57-L57,2))
A58: 1F01 | C58: Staff Superior | E58: =IF(ISBLANK(A58),"", SUMIF(CATEGORIAS[[#All],[FORMATO GENERAL]], A58, CATEGORIAS[[#All],[PRESUPUESTO (ORIGINAL)]])) -> 2.6331137e+08 | F58: =IF(ISBLANK(A58),"",G58-E58) -> 1.2651094e+08 | G58: =IF(ISBLANK(A58),"",SUMIF(CATEGORIAS[[#All],[FORMATO GENERAL]], A58, CATEGORIAS[[#All],[PRESUPUESTO FINAL PROYECTADO]])) -> 3.8982231e+08 | I58: =IF(ISBLANK(A58),"",J58-SUMIF(CATEGORIAS[[#All],[FORMATO GENERAL]], A58, CATEGORIAS[[#All],[COSTO REAL ANTERIOR]])) -> 24997457 | J58: =IF(ISBLANK(A58),"",SUMIF(CATEGORIAS[[#All],[FORMATO GENERAL]], A58, CATEGORIAS[[#All],[COSTO REAL]])) -> 3.5409637e+08 | K58: =IF(ISBLANK(A58),"",SUMIF(CATEGORIAS[[#All],[FORMATO GENERAL]], A58, CATEGORIAS[[#All],[TOTAL PRODUCCION ACTUAL]])) -> 3.8982231e+08 | L58: =IF(ISBLANK(A58),"",SUMIF(CATEGORIAS[[#All],[FORMATO GENERAL]], A58, CATEGORIAS[[#All],[PROYECCION TOTAL DE COSTO]])) -> 1652803.5 | N58: =IF(ISBLANK(A58),"",TRUNC(G58-J58-L58,2)) -> 34073137
A59: 1F02 | C59: Oficina Técnica | E59: =IF(ISBLANK(A59),"", SUMIF(CATEGORIAS[[#All],[FORMATO GENERAL]], A59, CATEGORIAS[[#All],[PRESUPUESTO (ORIGINAL)]])) -> 80469295 | F59: =IF(ISBLANK(A59),"",G59-E59) -> 43596690 | G59: =IF(ISBLANK(A59),"",SUMIF(CATEGORIAS[[#All],[FORMATO GENERAL]], A59, CATEGORIAS[[#All],[PRESUPUESTO FINAL PROYECTADO]])) -> 1.2406598e+08 | I59: =IF(ISBLANK(A59),"",J59-SUMIF(CATEGORIAS[[#All],[FORMATO GENERAL]], A59, CATEGORIAS[[#All],[COSTO REAL ANTERIOR]])) -> 0 | J59: =IF(ISBLANK(A59),"",SUMIF(CATEGORIAS[[#All],[FORMATO GENERAL]], A59, CATEGORIAS[[#All],[COSTO REAL]])) -> 1.2277887e+08 | K59: =IF(ISBLANK(A59),"",SUMIF(CATEGORIAS[[#All],[FORMATO GENERAL]], A59, CATEGORIAS[[#All],[TOTAL PRODUCCION ACTUAL]])) -> 1.2406598e+08 | L59: =IF(ISBLANK(A59),"",SUMIF(CATEGORIAS[[#All],[FORMATO GENERAL]], A59, CATEGORIAS[[#All],[PROYECCION TOTAL DE COSTO]])) -> 0 | N59: =IF(ISBLANK(A59),"",TRUNC(G59-J59-L59,2)) -> 1287118.1
A60: 1F03 | C60: Supervisión | E60: =IF(ISBLANK(A60),"", SUMIF(CATEGORIAS[[#All],[FORMATO GENERAL]], A60, CATEGORIAS[[#All],[PRESUPUESTO (ORIGINAL)]])) -> 97274459 | F60: =IF(ISBLANK(A60),"",G60-E60) -> 74377434 | G60: =IF(ISBLANK(A60),"",SUMIF(CATEGORIAS[[#All],[FORMATO GENERAL]], A60, CATEGORIAS[[#All],[PRESUPUESTO FINAL PROYECTADO]])) -> 1.7165189e+08 | I60: =IF(ISBLANK(A60),"",J60-SUMIF(CATEGORIAS[[#All],[FORMATO GENERAL]], A60, CATEGORIAS[[#All],[COSTO REAL ANTERIOR]])) -> 0 | J60: =IF(ISBLANK(A60),"",SUMIF(CATEGORIAS[[#All],[FORMATO GENERAL]], A60, CATEGORIAS[[#All],[COSTO REAL]])) -> 121259605 | K60: =IF(ISBLANK(A60),"",SUMIF(CATEGORIAS[[#All],[FORMATO GENERAL]], A60, CATEGORIAS[[#All],[TOTAL PRODUCCION ACTUAL]])) -> 1.7165189e+08 | L60: =IF(ISBLANK(A60),"",SUMIF(CATEGORIAS[[#All],[FORMATO GENERAL]], A60, CATEGORIAS[[#All],[PROYECCION TOTAL DE COSTO]])) -> 0 | N60: =IF(ISBLANK(A60),"",TRUNC(G60-J60-L60,2)) -> 50392288
A61: 1F04 | C61: Seguridad / Medio Ambiente | E61: =IF(ISBLANK(A61),"", SUMIF(CATEGORIAS[[#All],[FORMATO GENERAL]], A61, CATEGORIAS[[#All],[PRESUPUESTO (ORIGINAL)]])) -> 97189487 | F61: =IF(ISBLANK(A61),"",G61-E61) -> 49662844 | G61: =IF(ISBLANK(A61),"",SUMIF(CATEGORIAS[[#All],[FORMATO GENERAL]], A61, CATEGORIAS[[#All],[PRESUPUESTO FINAL PROYECTADO]])) -> 1.4685233e+08 | I61: =IF(ISBLANK(A61),"",J61-SUMIF(CATEGORIAS[[#All],[FORMATO GENERAL]], A61, CATEGORIAS[[#All],[COSTO REAL ANTERIOR]])) -> 0 | J61: =IF(ISBLANK(A61),"",SUMIF(CATEGORIAS[[#All],[FORMATO GENERAL]], A61, CATEGORIAS[[#All],[COSTO REAL]])) -> 84690890 | K61: =IF(ISBLANK(A61),"",SUMIF(CATEGORIAS[[#All],[FORMATO GENERAL]], A61, CATEGORIAS[[#All],[TOTAL PRODUCCION ACTUAL]])) -> 1.4685233e+08 | L61: =IF(ISBLANK(A61),"",SUMIF(CATEGORIAS[[#All],[FORMATO GENERAL]], A61, CATEGORIAS[[#All],[PROYECCION TOTAL DE COSTO]])) -> 0 | N61: =IF(ISBLANK(A61),"",TRUNC(G61-J61-L61,2)) -> 62161440
A62: 1F05 | C62: Control de Calidad | E62: =IF(ISBLANK(A62),"", SUMIF(CATEGORIAS[[#All],[FORMATO GENERAL]], A62, CATEGORIAS[[#All],[PRESUPUESTO (ORIGINAL)]])) -> 39901820 | F62: =IF(ISBLANK(A62),"",G62-E62) -> 21371381 | G62: =IF(ISBLANK(A62),"",SUMIF(CATEGORIAS[[#All],[FORMATO GENERAL]], A62, CATEGORIAS[[#All],[PRESUPUESTO FINAL PROYECTADO]])) -> 61273201 | I62: =IF(ISBLANK(A62),"",J62-SUMIF(CATEGORIAS[[#All],[FORMATO GENERAL]], A62, CATEGORIAS[[#All],[COSTO REAL ANTERIOR]])) -> 0 | J62: =IF(ISBLANK(A62),"",SUMIF(CATEGORIAS[[#All],[FORMATO GENERAL]], A62, CATEGORIAS[[#All],[COSTO REAL]])) -> 44849347 | K62: =IF(ISBLANK(A62),"",SUMIF(CATEGORIAS[[#All],[FORMATO GENERAL]], A62, CATEGORIAS[[#All],[TOTAL PRODUCCION ACTUAL]])) -> 61273201 | L62: =IF(ISBLANK(A62),"",SUMIF(CATEGORIAS[[#All],[FORMATO GENERAL]], A62, CATEGORIAS[[#All],[PROYECCION TOTAL DE COSTO]])) -> 0 | N62: =IF(ISBLANK(A62),"",TRUNC(G62-J62-L62,2)) -> 16423854
A63: 1F06 | C63: Administración | E63: =IF(ISBLANK(A63),"", SUMIF(CATEGORIAS[[#All],[FORMATO GENERAL]], A63, CATEGORIAS[[#All],[PRESUPUESTO (ORIGINAL)]])) -> 55188181 | F63: =IF(ISBLANK(A63),"",G63-E63) -> 36286670 | G63: =IF(ISBLANK(A63),"",SUMIF(CATEGORIAS[[#All],[FORMATO GENERAL]], A63, CATEGORIAS[[#All],[PRESUPUESTO FINAL PROYECTADO]])) -> 91474851 | I63: =IF(ISBLANK(A63),"",J63-SUMIF(CATEGORIAS[[#All],[FORMATO GENERAL]], A63, CATEGORIAS[[#All],[COSTO REAL ANTERIOR]])) -> 0 | J63: =IF(ISBLANK(A63),"",SUMIF(CATEGORIAS[[#All],[FORMATO GENERAL]], A63, CATEGORIAS[[#All],[COSTO REAL]])) -> 89355743 | K63: =IF(ISBLANK(A63),"",SUMIF(CATEGORIAS[[#All],[FORMATO GENERAL]], A63, CATEGORIAS[[#All],[TOTAL PRODUCCION ACTUAL]])) -> 91474851 | L63: =IF(ISBLANK(A63),"",SUMIF(CATEGORIAS[[#All],[FORMATO GENERAL]], A63, CATEGORIAS[[#All],[PROYECCION TOTAL DE COSTO]])) -> 0 | N63: =IF(ISBLANK(A63),"",TRUNC(G63-J63-L63,2)) -> 2119107.6
A64: 1F07 | C64: Servicios | E64: =IF(ISBLANK(A64),"", SUMIF(CATEGORIAS[[#All],[FORMATO GENERAL]], A64, CATEGORIAS[[#All],[PRESUPUESTO (ORIGINAL)]])) -> 67752175 | F64: =IF(ISBLANK(A64),"",G64-E64) -> 31934012 | G64: =IF(ISBLANK(A64),"",SUMIF(CATEGORIAS[[#All],[FORMATO GENERAL]], A64, CATEGORIAS[[#All],[PRESUPUESTO FINAL PROYECTADO]])) -> 99686187 | I64: =IF(ISBLANK(A64),"",J64-SUMIF(CATEGORIAS[[#All],[FORMATO GENERAL]], A64, CATEGORIAS[[#All],[COSTO REAL ANTERIOR]])) -> 6940424 | J64: =IF(ISBLANK(A64),"",SUMIF(CATEGORIAS[[#All],[FORMATO GENERAL]], A64, CATEGORIAS[[#All],[COSTO REAL]])) -> 145760303 | K64: =IF(ISBLANK(A64),"",SUMIF(CATEGORIAS[[#All],[FORMATO GENERAL]], A64, CATEGORIAS[[#All],[TOTAL PRODUCCION ACTUAL]])) -> 99686187 | L64: =IF(ISBLANK(A64),"",SUMIF(CATEGORIAS[[#All],[FORMATO GENERAL]], A64, CATEGORIAS[[#All],[PROYECCION TOTAL DE COSTO]])) -> 0 | N64: =IF(ISBLANK(A64),"",TRUNC(G64-J64-L64,2)) -> -46074116
A65: 1F08 | C65: Topografía | E65: =IF(ISBLANK(A65),"", SUMIF(CATEGORIAS[[#All],[FORMATO GENERAL]], A65, CATEGORIAS[[#All],[PRESUPUESTO (ORIGINAL)]])) -> 44741710 | F65: =IF(ISBLANK(A65),"",G65-E65) -> 20197248 | G65: =IF(ISBLANK(A65),"",SUMIF(CATEGORIAS[[#All],[FORMATO GENERAL]], A65, CATEGORIAS[[#All],[PRESUPUESTO FINAL PROYECTADO]])) -> 64938958 | I65: =IF(ISBLANK(A65),"",J65-SUMIF(CATEGORIAS[[#All],[FORMATO GENERAL]], A65, CATEGORIAS[[#All],[COSTO REAL ANTERIOR]])) -> 0 | J65: =IF(ISBLANK(A65),"",SUMIF(CATEGORIAS[[#All],[FORMATO GENERAL]], A65, CATEGORIAS[[#All],[COSTO REAL]])) -> 80582133 | K65: =IF(ISBLANK(A65),"",SUMIF(CATEGORIAS[[#All],[FORMATO GENERAL]], A65, CATEGORIAS[[#All],[TOTAL PRODUCCION ACTUAL]])) -> 64938958 | L65: =IF(ISBLANK(A65),"",SUMIF(CATEGORIAS[[#All],[FORMATO GENERAL]], A65, CATEGORIAS[[#All],[PROYECCION TOTAL DE COSTO]])) -> 0 | N65: =IF(ISBLANK(A65),"",TRUNC(G65-J65-L65,2)) -> -15643175
A66: 1F09 | C66: Movilización | E66: =IF(ISBLANK(A66),"", SUMIF(CATEGORIAS[[#All],[FORMATO GENERAL]], A66, CATEGORIAS[[#All],[PRESUPUESTO (ORIGINAL)]])) -> 17775000 | F66: =IF(ISBLANK(A66),"",G66-E66) -> 9437056.5 | G66: =IF(ISBLANK(A66),"",SUMIF(CATEGORIAS[[#All],[FORMATO GENERAL]], A66, CATEGORIAS[[#All],[PRESUPUESTO FINAL PROYECTADO]])) -> 27212056 | I66: =IF(ISBLANK(A66),"",J66-SUMIF(CATEGORIAS[[#All],[FORMATO GENERAL]], A66, CATEGORIAS[[#All],[COSTO REAL ANTERIOR]])) -> 518650 | J66: =IF(ISBLANK(A66),"",SUMIF(CATEGORIAS[[#All],[FORMATO GENERAL]], A66, CATEGORIAS[[#All],[COSTO REAL]])) -> 79403794 | K66: =IF(ISBLANK(A66),"",SUMIF(CATEGORIAS[[#All],[FORMATO GENERAL]], A66, CATEGORIAS[[#All],[TOTAL PRODUCCION ACTUAL]])) -> 27212056 | L66: =IF(ISBLANK(A66),"",SUMIF(CATEGORIAS[[#All],[FORMATO GENERAL]], A66, CATEGORIAS[[#All],[PROYECCION TOTAL DE COSTO]])) -> 0 | N66: =IF(ISBLANK(A66),"",TRUNC(G66-J66-L66,2)) -> -52191738
A67: 1F10 | C67: Pensión y Alimentación | E67: =IF(ISBLANK(A67),"", SUMIF(CATEGORIAS[[#All],[FORMATO GENERAL]], A67, CATEGORIAS[[#All],[PRESUPUESTO (ORIGINAL)]])) -> 85743100 | F67: =IF(ISBLANK(A67),"",G67-E67) -> 44596855 | G67: =IF(ISBLANK(A67),"",SUMIF(CATEGORIAS[[#All],[FORMATO GENERAL]], A67, CATEGORIAS[[#All],[PRESUPUESTO FINAL PROYECTADO]])) -> 1.3033996e+08 | I67: =IF(ISBLANK(A67),"",J67-SUMIF(CATEGORIAS[[#All],[FORMATO GENERAL]], A67, CATEGORIAS[[#All],[COSTO REAL ANTERIOR]])) -> 939133 | J67: =IF(ISBLANK(A67),"",SUMIF(CATEGORIAS[[#All],[FORMATO GENERAL]], A67, CATEGORIAS[[#All],[COSTO REAL]])) -> 1.6623875e+08 | K67: =IF(ISBLANK(A67),"",SUMIF(CATEGORIAS[[#All],[FORMATO GENERAL]], A67, CATEGORIAS[[#All],[TOTAL PRODUCCION ACTUAL]])) -> 1.3033996e+08 | L67: =IF(ISBLANK(A67),"",SUMIF(CATEGORIAS[[#All],[FORMATO GENERAL]], A67, CATEGORIAS[[#All],[PROYECCION TOTAL DE COSTO]])) -> 249500 | N67: =IF(ISBLANK(A67),"",TRUNC(G67-J67-L67,2)) -> -36148299
C69: Otros Indirectos | E69: =IF(ISBLANK(A69),"", SUMIF(CATEGORIAS[[#All],[FORMATO GENERAL]], A69, CATEGORIAS[[#All],[PRESUPUESTO (ORIGINAL)]])) | F69: =IF(ISBLANK(A69),"",G69-E69) | G69: =IF(ISBLANK(A69),"",SUMIF(CATEGORIAS[[#All],[FORMATO GENERAL]], A69, CATEGORIAS[[#All],[PRESUPUESTO FINAL PROYECTADO]])) | I69: =IF(ISBLANK(A69),"",J69-SUMIF(CATEGORIAS[[#All],[FORMATO GENERAL]], A69, CATEGORIAS[[#All],[COSTO REAL ANTERIOR]])) | J69: =IF(ISBLANK(A69),"",SUMIF(CATEGORIAS[[#All],[FORMATO GENERAL]], A69, CATEGORIAS[[#All],[COSTO REAL]])) | K69: =IF(ISBLANK(A69),"",SUMIF(CATEGORIAS[[#All],[FORMATO GENERAL]], A69, CATEGORIAS[[#All],[TOTAL PRODUCCION ACTUAL]])) | L69: =IF(ISBLANK(A69),"",SUMIF(CATEGORIAS[[#All],[FORMATO GENERAL]], A69, CATEGORIAS[[#All],[PROYECCION TOTAL DE COSTO]])) | N69: =IF(ISBLANK(A69),"",TRUNC(G69-J69-L69,2))
A70: 1Z01 | B70: B2 | C70: Equipos Indirectos | E70: =IF(ISBLANK(A70),"", SUMIF(CATEGORIAS[[#All],[FORMATO GENERAL]], A70, CATEGORIAS[[#All],[PRESUPUESTO (ORIGINAL)]])) -> 1.1279563e+08 | F70: =IF(ISBLANK(A70),"",G70-E70) -> 48654423 | G70: =IF(ISBLANK(A70),"",SUMIF(CATEGORIAS[[#All],[FORMATO GENERAL]], A70, CATEGORIAS[[#All],[PRESUPUESTO FINAL PROYECTADO]])) -> 1.6145005e+08 | I70: =IF(ISBLANK(A70),"",J70-SUMIF(CATEGORIAS[[#All],[FORMATO GENERAL]], A70, CATEGORIAS[[#All],[COSTO REAL ANTERIOR]])) -> 2813505 | J70: =IF(ISBLANK(A70),"",SUMIF(CATEGORIAS[[#All],[FORMATO GENERAL]], A70, CATEGORIAS[[#All],[COSTO REAL]])) -> 1.3140729e+08 | K70: =IF(ISBLANK(A70),"",SUMIF(CATEGORIAS[[#All],[FORMATO GENERAL]], A70, CATEGORIAS[[#All],[TOTAL PRODUCCION ACTUAL]])) -> 1.6145005e+08 | L70: =IF(ISBLANK(A70),"",SUMIF(CATEGORIAS[[#All],[FORMATO GENERAL]], A70, CATEGORIAS[[#All],[PROYECCION TOTAL DE COSTO]])) -> 482537.5 | N70: =IF(ISBLANK(A70),"",TRUNC(G70-J70-L70,2)) -> 29560219
A71: 1Z02 | B71: B3 | C71: Gastos Generales | E71: =IF(ISBLANK(A71),"", SUMIF(CATEGORIAS[[#All],[FORMATO GENERAL]], A71, CATEGORIAS[[#All],[PRESUPUESTO (ORIGINAL)]])) -> 1.9454474e+08 | F71: =IF(ISBLANK(A71),"",G71-E71) -> 53203877 | G71: =IF(ISBLANK(A71),"",SUMIF(CATEGORIAS[[#All],[FORMATO GENERAL]], A71, CATEGORIAS[[#All],[PRESUPUESTO FINAL PROYECTADO]])) -> 2.4774862e+08 | I71: =IF(ISBLANK(A71),"",J71-SUMIF(CATEGORIAS[[#All],[FORMATO GENERAL]], A71, CATEGORIAS[[#All],[COSTO REAL ANTERIOR]])) -> 6894916 | J71: =IF(ISBLANK(A71),"",SUMIF(CATEGORIAS[[#All],[FORMATO GENERAL]], A71, CATEGORIAS[[#All],[COSTO REAL]])) -> 174581266 | K71: =IF(ISBLANK(A71),"",SUMIF(CATEGORIAS[[#All],[FORMATO GENERAL]], A71, CATEGORIAS[[#All],[TOTAL PRODUCCION ACTUAL]])) -> 2.4774862e+08 | L71: =IF(ISBLANK(A71),"",SUMIF(CATEGORIAS[[#All],[FORMATO GENERAL]], A71, CATEGORIAS[[#All],[PROYECCION TOTAL DE COSTO]])) -> 2000000 | N71: =IF(ISBLANK(A71),"",TRUNC(G71-J71-L71,2)) -> 71167352
A72: 1Z03 | B72: B4 | C72: Gastos Financieros | E72: =IF(ISBLANK(A72),"", SUMIF(CATEGORIAS[[#All],[FORMATO GENERAL]], A72, CATEGORIAS[[#All],[PRESUPUESTO (ORIGINAL)]])) -> 8312500 | F72: =IF(ISBLANK(A72),"",G72-E72) -> 293085.07 | G72: =IF(ISBLANK(A72),"",SUMIF(CATEGORIAS[[#All],[FORMATO GENERAL]], A72, CATEGORIAS[[#All],[PRESUPUESTO FINAL PROYECTADO]])) -> 8605585.1 | I72: =IF(ISBLANK(A72),"",J72-SUMIF(CATEGORIAS[[#All],[FORMATO GENERAL]], A72, CATEGORIAS[[#All],[COSTO REAL ANTERIOR]])) -> 40631 | J72: =IF(ISBLANK(A72),"",SUMIF(CATEGORIAS[[#All],[FORMATO GENERAL]], A72, CATEGORIAS[[#All],[COSTO REAL]])) -> 42897990 | K72: =IF(ISBLANK(A72),"",SUMIF(CATEGORIAS[[#All],[FORMATO GENERAL]], A72, CATEGORIAS[[#All],[TOTAL PRODUCCION ACTUAL]])) -> 8605585.1 | L72: =IF(ISBLANK(A72),"",SUMIF(CATEGORIAS[[#All],[FORMATO GENERAL]], A72, CATEGORIAS[[#All],[PROYECCION TOTAL DE COSTO]])) -> 0 | N72: =IF(ISBLANK(A72),"",TRUNC(G72-J72-L72,2)) -> -34292405
A73: 1Z04 | B73: B5 | C73: Seguros y Boletas de Garantia | E73: =IF(ISBLANK(A73),"", SUMIF(CATEGORIAS[[#All],[FORMATO GENERAL]], A73, CATEGORIAS[[#All],[PRESUPUESTO (ORIGINAL)]])) -> 51516138 | F73: =IF(ISBLANK(A73),"",G73-E73) -> 1816374.3 | G73: =IF(ISBLANK(A73),"",SUMIF(CATEGORIAS[[#All],[FORMATO GENERAL]], A73, CATEGORIAS[[#All],[PRESUPUESTO FINAL PROYECTADO]])) -> 53332512 | I73: =IF(ISBLANK(A73),"",J73-SUMIF(CATEGORIAS[[#All],[FORMATO GENERAL]], A73, CATEGORIAS[[#All],[COSTO REAL ANTERIOR]])) -> -844408 | J73: =IF(ISBLANK(A73),"",SUMIF(CATEGORIAS[[#All],[FORMATO GENERAL]], A73, CATEGORIAS[[#All],[COSTO REAL]])) -> 54456193 | K73: =IF(ISBLANK(A73),"",SUMIF(CATEGORIAS[[#All],[FORMATO GENERAL]], A73, CATEGORIAS[[#All],[TOTAL PRODUCCION ACTUAL]])) -> 53332512 | L73: =IF(ISBLANK(A73),"",SUMIF(CATEGORIAS[[#All],[FORMATO GENERAL]], A73, CATEGORIAS[[#All],[PROYECCION TOTAL DE COSTO]])) -> 0 | N73: =IF(ISBLANK(A73),"",TRUNC(G73-J73-L73,2)) -> -1123681.1
A74: 1Z05 | B74: B6 | C74: Perdida de Reajuste | E74: =IF(ISBLANK(A74),"", SUMIF(CATEGORIAS[[#All],[FORMATO GENERAL]], A74, CATEGORIAS[[#All],[PRESUPUESTO (ORIGINAL)]])) -> 0 | F74: =IF(ISBLANK(A74),"",G74-E74) -> 0 | G74: =IF(ISBLANK(A74),"",SUMIF(CATEGORIAS[[#All],[FORMATO GENERAL]], A74, CATEGORIAS[[#All],[PRESUPUESTO FINAL PROYECTADO]])) -> 0 | I74: =IF(ISBLANK(A74),"",J74-SUMIF(CATEGORIAS[[#All],[FORMATO GENERAL]], A74, CATEGORIAS[[#All],[COSTO REAL ANTERIOR]])) -> 0 | J74: =IF(ISBLANK(A74),"",SUMIF(CATEGORIAS[[#All],[FORMATO GENERAL]], A74, CATEGORIAS[[#All],[COSTO REAL]])) -> 0 | K74: =IF(ISBLANK(A74),"",SUMIF(CATEGORIAS[[#All],[FORMATO GENERAL]], A74, CATEGORIAS[[#All],[TOTAL PRODUCCION ACTUAL]])) -> 0 | L74: =IF(ISBLANK(A74),"",SUMIF(CATEGORIAS[[#All],[FORMATO GENERAL]], A74, CATEGORIAS[[#All],[PROYECCION TOTAL DE COSTO]])) -> 0 | N74: =IF(ISBLANK(A74),"",TRUNC(G74-J74-L74,2)) -> 0
C76: Subtotal Costos Indirectos | E76: =SUM(E57:E75) -> 1.2165156e+09 | F76: =SUM(F57:F75) -> 5.6193889e+08 | G76: =SUM(G57:G75) -> 1.7784545e+09 | I76: =SUM(I57:I75) -> 42300308 | J76: =SUM(J57:J75) -> 1.6923586e+09 | K76: =SUM(K57:K75) -> 1.7784545e+09 | L76: =SUM(L57:L75) -> 4384841 | N76: =SUM(N57:N75) -> 81711102
A78: 2A00 | B78: C. | C78: Margen Esperado | E78: =IF(ISBLANK(A78),"",SUMIF('Analisis por Categorias'!A:A,A78,'Analisis por Categorias'!G:G)) -> 3.8e+08 | F78: =IF(ISBLANK(A78),"",G78-E78) -> 0 | G78: =IF(ISBLANK(A78),"",SUMIF('Analisis por Categorias'!A:A,A78,'Analisis por Categorias'!L:L)) -> 3.8e+08 | I78: 0 | J78: 0 | K78: =IF(ISBLANK(A78),"",SUMIF('Analisis por Categorias'!$A:$A,A78,'Analisis por Categorias'!O:O)) -> 3.8e+08 | L78: 0 | N78: =IF(ISBLANK(A78),"",G78-J78-L78) -> 3.8e+08
A79: 1K01 | C79: Oficina Central | E79: =IF(ISBLANK(A79),"", SUMIF(CATEGORIAS[[#All],[SUBGRUPO]], A79, CATEGORIAS[[#All],[PRESUPUESTO (ORIGINAL)]])) -> 1.9e+08 | G79: =IF(ISBLANK(A79),"", SUMIF(CATEGORIAS[[#All],[SUBGRUPO]], A79, CATEGORIAS[[#All],[PRESUPUESTO FINAL PROYECTADO]])) -> 1.9e+08 | I79: 0 | J79: 0 | K79: =IF(ISBLANK(A79),"",SUMIF(CATEGORIAS[[#All],[SUBGRUPO]], A79, CATEGORIAS[[#All],[TOTAL PRODUCCION ACTUAL]])) -> 1.9e+08 | L79: 0 | N79: =IF(ISBLANK(A79),"",G79-J79-L79) -> 1.9e+08
A80: 1K02 | C80: Imprevistos | E80: =IF(ISBLANK(A80),"", SUMIF(CATEGORIAS[[#All],[SUBGRUPO]], A80, CATEGORIAS[[#All],[PRESUPUESTO (ORIGINAL)]])) -> 47500000 | G80: =IF(ISBLANK(A80),"", SUMIF(CATEGORIAS[[#All],[SUBGRUPO]], A80, CATEGORIAS[[#All],[PRESUPUESTO FINAL PROYECTADO]])) -> 47500000 | I80: 0 | J80: 0 | K80: =IF(ISBLANK(A80),"",SUMIF(CATEGORIAS[[#All],[SUBGRUPO]], A80, CATEGORIAS[[#All],[TOTAL PRODUCCION ACTUAL]])) -> 47500000 | L80: 0 | N80: =IF(ISBLANK(A80),"",G80-J80-L80) -> 47500000
A81: 1K03 | C81: Utilidad | E81: =IF(ISBLANK(A81),"", SUMIF(CATEGORIAS[[#All],[SUBGRUPO]], A81, CATEGORIAS[[#All],[PRESUPUESTO (ORIGINAL)]])) -> 1.425e+08 | G81: =IF(ISBLANK(A81),"", SUMIF(CATEGORIAS[[#All],[SUBGRUPO]], A81, CATEGORIAS[[#All],[PRESUPUESTO FINAL PROYECTADO]])) -> 1.425e+08 | I81: 0 | J81: 0 | K81: =IF(ISBLANK(A81),"",SUMIF(CATEGORIAS[[#All],[SUBGRUPO]], A81, CATEGORIAS[[#All],[TOTAL PRODUCCION ACTUAL]])) -> 1.425e+08 | L81: 0 | N81: =IF(ISBLANK(A81),"",G81-J81-L81) -> 1.425e+08
B83: D. | C83: TOTAL | E83: =E54+E76+E78 -> 4.75e+09 | F83: =F54+F76+F78 -> 1.2639661e+09 | G83: =G54+G76+G78 -> 6.0139661e+09 | I83: =I54+I76+I78 -> 41655895 | J83: =J54+J76+J78 -> 5.2438403e+09 | K83: =K54+K76+K78 -> 6.0139661e+09 | L83: =L54+L76+L78 -> 4384841 | N83: =N54+N76+N78+N82 -> 7.6574098e+08
B84: E. | C84: Oficina Central (4%) | N84: =-4%*G83 -> -2.4055864e+08
B85: F. | C85: TOTAL | N85: =+N83+N84 -> 5.2518234e+08
C87: Fecha de Inicio Contractual
C88: Fecha de Termino Contractual | E88: 45930
L94: Administrador Obra

Sheet Analisis por Categorias
E1: ERROR DE PRODUCCION - ADICIONALES | G1: 4 | H1: 5 | I1: 6 | L1: 7 | M1: 8 | O1: =+L2-O2 -> -0.0018701553 | P1: 11 | Q1: 12 | R1: 13 | S1: 14 | T1: 15 | U1: 16 | V1: 17 | W1: 18 | X1: 19 | Y1: 20 | Z1: 21 | AA1: 22 | AB1: 23 | AC1: 24 | AD1: 25 | AE1: 26
E2: ERROR DE PRODUCCION - ADICIONALES | G2: =SUBTOTAL(9,CATEGORIAS[PRESUPUESTO (ORIGINAL)]) -> 4.75e+09 | H2: =SUBTOTAL(9,CATEGORIAS[POM]) -> 4.3139404e+09 | I2: =SUBTOTAL(9,CATEGORIAS[ADICIONALES]) -> 1.5613215e+09 | J2: =+SUBTOTAL(9,CATEGORIAS[REAJUSTE PAGADO]) -> 1.3870427e+08 | K2: =+SUBTOTAL(9,CATEGORIAS[REAJUSTE PROYECTADO]) -> 0 | L2: =SUBTOTAL(9,CATEGORIAS[PRESUPUESTO FINAL PROYECTADO]) -> 6.0139661e+09 | M2: =SUBTOTAL(9,CATEGORIAS[PRODUCCION PARTIDAS ORIGINALES ACTUAL]) -> 4.4518842e+09 | N2: =SUBTOTAL(9,CATEGORIAS[PRODUCCION ADICIONALES ACTUAL]) -> 1.5620819e+09 | O2: =SUBTOTAL(9,CATEGORIAS[TOTAL PRODUCCION ACTUAL]) -> 6.0139661e+09 | P2: =SUBTOTAL(9,CATEGORIAS[PRODUCCION ANTERIOR]) -> 4.4518724e+09 | Q2: =SUBTOTAL(9,CATEGORIAS[PRODUCCION ADICIONALES ANTERIOR]) -> 1.5413014e+09 | R2: =SUBTOTAL(9,CATEGORIAS[TOTAL PRODUCCION ANTERIOR]) -> 5.9931738e+09 | S2: =SUBTOTAL(9,CATEGORIAS[COSTO ACUMULADO AX]) -> 5.5981128e+09 | T2: =SUM(CATEGORIAS[CAMBIO DE CATEGORIA]) -> 3.7252903e-09 | U2: =SUBTOTAL(9,CATEGORIAS[PROVISIONES]) -> 25727542 | V2: =SUBTOTAL(9,CATEGORIAS[COSTO REAL]) -> 5.6238403e+09 | W2: =SUBTOTAL(9,CATEGORIAS[COSTO ACUMULADO ANTERIOR]) -> 5.4162668e+09 | X2: =SUBTOTAL(9,CATEGORIAS[CAMBIO DE CATEGORIA ANTERIOR]) -> 3.7252903e-09 | Y2: =SUBTOTAL(9,CATEGORIAS[PROVISIONES ANTERIOR]) -> 1.659176e+08 | Z2: =SUBTOTAL(9,CATEGORIAS[COSTO REAL ANTERIOR]) -> 5.5821844e+09 | AA2: =SUBTOTAL(9,CATEGORIAS[PROYECCION DE INGRESO DEL SALDO]) -> 0.0051058717 | AB2: =SUBTOTAL(9,CATEGORIAS[INVENTARIO]) -> 0 | AC2: =SUBTOTAL(9,CATEGORIAS[PEDIDOS DE COMPRA NO RECIBIDOS]) -> 0 | AD2: =SUBTOTAL(9,CATEGORIAS[PROYECCION DE COSTO DEL SALDO]) -> 4384841 | AE2: =SUBTOTAL(9,CATEGORIAS[PROYECCION TOTAL DE COSTO]) -> 4384841
E3: ERROR DE COSTO - CAMBIO CATEGORIA - PROVISION | H3: 3931246334 | L3: 5.9931738e+09 | M3: PRODUCCION | S3: COSTOS | AA3: PROYECCION
E4: ERROR DE PROYECCION - INVENTARIO | H4: =+H2-H3 -> 3.8269406e+08 | J4: 1.3860928e+08 | M4: ACUMULADA | P4: ACUMULADA ANTERIOR | S4: ACUMULADO | W4: ACUMULADO ANTERIOR | AA4: PRODUCCION | AB4: COSTOS
G5: CARGA MANUAL | H5: CARGA MANUAL | I5: CARGA MANUAL | L5: FORMULA | M5: CARGA MANUAL | N5: CARGA MANUAL | O5: FORMULA | P5: CARGA MANUAL | Q5: CARGA MANUAL | R5: FORMULA | S5: DESDE AX | T5: CARGA MANUAL | U5: CARGA MANUAL | V5: FORMULA | W5: CARGA MANUAL | X5: CARGA MANUAL | Y5: CARGA MANUAL | Z5: FORMULA | AA5: FORMULA | AB5: DESDE AX | AC5: DESDE AX | AD5: CARGA MANUAL | AE5: FORMULA
A6: FORMATO GENERAL | B6: SUBGRUPO | C6: NOMBRE SUBGRUPO | D6: CATEGORIA2 | E6: NOMBRE CATEGORIA | F6: INCLUIR | G6: PRESUPUESTO (ORIGINAL) | H6: POM | I6: ADICIONALES | J6: REAJUSTE PAGADO | K6: REAJUSTE PROYECTADO | L6: PRESUPUESTO FINAL PROYECTADO | M6: PRODUCCION PARTIDAS ORIGINALES ACTUAL | N6: PRODUCCION ADICIONALES ACTUAL | O6: TOTAL PRODUCCION ACTUAL | P6: PRODUCCION ANTERIOR | Q6: PRODUCCION ADICIONALES ANTERIOR | R6: TOTAL PRODUCCION ANTERIOR | S6: COSTO ACUMULADO AX | T6: CAMBIO DE CATEGORIA | U6: PROVISIONES | V6: COSTO REAL | W6: COSTO ACUMULADO ANTERIOR | X6: CAMBIO DE CATEGORIA ANTERIOR | Y6: PROVISIONES ANTERIOR | Z6: COSTO REAL ANTERIOR | AA6: PROYECCION DE INGRESO DEL SALDO | AB6: INVENTARIO | AC6: PEDIDOS DE COMPRA NO RECIBIDOS | AD6: PROYECCION DE COSTO DEL SALDO | AE6: PROYECCION TOTAL DE COSTO | AF6: ITEM | AG6: Columna1
D7: 10-0000-000G | E7: MAO / Por Distribuir (G) | F7: NO | G7: 0 | H7: 0 | I7: 0 | J7: 0 | K7: 0 | L7: =CATEGORIAS[[#This Row],[ADICIONALES]]+CATEGORIAS[[#This Row],[POM]]+CATEGORIAS[[#This Row],[REAJUSTE PAGADO]]+CATEGORIAS[[#This Row],[REAJUSTE PROYECTADO]] -> 0 | M7: 0 | N7: 0 | O7: =+CATEGORIAS[[#This Row],[PRODUCCION PARTIDAS ORIGINALES ACTUAL]]+CATEGORIAS[[#This Row],[PRODUCCION ADICIONALES ACTUAL]] -> 0 | P7: 0 | Q7: 0 | R7: =+CATEGORIAS[[#This Row],[PRODUCCION ANTERIOR]]+CATEGORIAS[[#This Row],[PRODUCCION ADICIONALES ANTERIOR]] -> 0 | S7: 0 | U7: 0 | V7: =SUM(CATEGORIAS[[#This Row],[COSTO ACUMULADO AX]:[PROVISIONES]]) -> 0 | W7: 0 | Y7: 0 | Z7: =SUM(CATEGORIAS[[#This Row],[COSTO ACUMULADO ANTERIOR]:[PROVISIONES ANTERIOR]]) -> 0 | AA7: =ABS(+CATEGORIAS[[#This Row],[PRESUPUESTO FINAL PROYECTADO]]-CATEGORIAS[[#This Row],[TOTAL PRODUCCION ACTUAL]]) -> 0 | AD7: 0 | AE7: =SUM(CATEGORIAS[[#This Row],[INVENTARIO]:[PROYECCION DE COSTO DEL SALDO]]) -> 0 | AG7: =+CATEGORIAS[[#This Row],[PRESUPUESTO FINAL PROYECTADO]]-CATEGORIAS[[#This Row],[COSTO REAL]]-CATEGORIAS[[#This Row],[PROYECCION TOTAL DE COSTO]] -> 0
D8: 11-0101-000G | E8: MAO CD - Civil / Movimiento de tierra (G) | F8: NO | G8: 0 | H8: 0 | I8: 0 | J8: 0 | K8: 0 | L8: =CATEGORIAS[[#This Row],[ADICIONALES]]+CATEGORIAS[[#This Row],[POM]]+CATEGORIAS[[#This Row],[REAJUSTE PAGADO]]+CATEGORIAS[[#This Row],[REAJUSTE PROYECTADO]] -> 0 | M8: 0 | N8: 0 | O8: =+CATEGORIAS[[#This Row],[PRODUCCION PARTIDAS ORIGINALES ACTUAL]]+CATEGORIAS[[#This Row],[PRODUCCION ADICIONALES ACTUAL]] -> 0 | P8: 0 | Q8: 0 | R8: =+CATEGORIAS[[#This Row],[PRODUCCION ANTERIOR]]+CATEGORIAS[[#This Row],[PRODUCCION ADICIONALES ANTERIOR]] -> 0 | S8: 0 | U8: 0 | V8: =SUM(CATEGORIAS[[#This Row],[COSTO ACUMULADO AX]:[PROVISIONES]]) -> 0 | W8: 0 | Y8: 0 | Z8: =SUM(CATEGORIAS[[#This Row],[COSTO ACUMULADO ANTERIOR]:[PROVISIONES ANTERIOR]]) -> 0 | AA8: =ABS(+CATEGORIAS[[#This Row],[PRESUPUESTO FINAL PROYECTADO]]-CATEGORIAS[[#This Row],[TOTAL PRODUCCION ACTUAL]]) -> 0 | AD8: 0 | AE8: =SUM(CATEGORIAS[[#This Row],[INVENTARIO]:[PROYECCION DE COSTO DEL SALDO]]) -> 0 | AG8: =+CATEGORIAS[[#This Row],[PRESUPUESTO FINAL PROYECTADO]]-CATEGORIAS[[#This Row],[COSTO REAL]]-CATEGORIAS[[#This Row],[PROYECCION TOTAL DE COSTO]] -> 0
A9: 0A01 | B9: 0A01 | C9: Obras Civiles | D9: 11-0102-000G | E9: MAO CD - Civil / Hormigón (G) | F9: NO | G9: 2.4934757e+08 | H9: 1.4836277e+08 | I9: 45209537 | J9: 5231027.1 | K9: 0 | L9: =CATEGORIAS[[#This Row],[ADICIONALES]]+CATEGORIAS[[#This Row],[POM]]+CATEGORIAS[[#This Row],[REAJUSTE PAGADO]]+CATEGORIAS[[#This Row],[REAJUSTE PROYECTADO]] -> 1.9880333e+08 | M9: 1.5356467e+08 | N9: 45238661 | O9: =+CATEGORIAS[[#This Row],[PRODUCCION PARTIDAS ORIGINALES ACTUAL]]+CATEGORIAS[[#This Row],[PRODUCCION ADICIONALES ACTUAL]] -> 1.9880333e+08 | P9: 1.5356467e+08 | Q9: 45209537 | R9: =+CATEGORIAS[[#This Row],[PRODUCCION ANTERIOR]]+CATEGORIAS[[#This Row],[PRODUCCION ADICIONALES ANTERIOR]] -> 1.9877421e+08 | S9: 242028406 | T9: -15605465 | U9: 0 | V9: =SUM(CATEGORIAS[[#This Row],[COSTO ACUMULADO AX]:[PROVISIONES]]) -> 226422941 | W9: 242028406 | X9: -15605465 | Y9: 0 | Z9: =SUM(CATEGORIAS[[#This Row],[COSTO ACUMULADO ANTERIOR]:[PROVISIONES ANTERIOR]]) -> 226422941 | AA9: =ABS(+CATEGORIAS[[#This Row],[PRESUPUESTO FINAL PROYECTADO]]-CATEGORIAS[[#This Row],[TOTAL PRODUCCION ACTUAL]]) -> 0 | AD9: 0 | AE9: =SUM(CATEGORIAS[[#This Row],[INVENTARIO]:[PROYECCION DE COSTO DEL SALDO]]) -> 0 | AG9: =+CATEGORIAS[[#This Row],[PRESUPUESTO FINAL PROYECTADO]]-CATEGORIAS[[#This Row],[COSTO REAL]]-CATEGORIAS[[#This Row],[PROYECCION TOTAL DE COSTO]] -> -27619608
D10: 11-0103-000G | E10: MAO CD - Civil / Moldaje (G) | F10: NO | G10: 0 | H10: 0 | I10: 0 | J10: 0 | K10: 0 | L10: =CATEGORIAS[[#This Row],[ADICIONALES]]+CATEGORIAS[[#This Row],[POM]]+CATEGORIAS[[#This Row],[REAJUSTE PAGADO]]+CATEGORIAS[[#This Row],[REAJUSTE PROYECTADO]] -> 0 | M10: 0 | N10: 0 | O10: =+CATEGORIAS[[#This Row],[PRODUCCION PARTIDAS ORIGINALES ACTUAL]]+CATEGORIAS[[#This Row],[PRODUCCION ADICIONALES ACTUAL]] -> 0 | P10: 0 | Q10: 0 | R10: =+CATEGORIAS[[#This Row],[PRODUCCION ANTERIOR]]+CATEGORIAS[[#This Row],[PRODUCCION ADICIONALES ANTERIOR]] -> 0 | S10: 0 | U10: 0 | V10: =SUM(CATEGORIAS[[#This Row],[COSTO ACUMULADO AX]:[PROVISIONES]]) -> 0 | W10: 0 | Y10: 0 | Z10: =SUM(CATEGORIAS[[#This Row],[COSTO ACUMULADO ANTERIOR]:[PROVISIONES ANTERIOR]]) -> 0 | AA10: =ABS(+CATEGORIAS[[#This Row],[PRESUPUESTO FINAL PROYECTADO]]-CATEGORIAS[[#This Row],[TOTAL PRODUCCION ACTUAL]]) -> 0 | AD10: 0 | AE10: =SUM(CATEGORIAS[[#This Row],[INVENTARIO]:[PROYECCION DE COSTO DEL SALDO]]) -> 0 | AG10: =+CATEGORIAS[[#This Row],[PRESUPUESTO FINAL PROYECTADO]]-CATEGORIAS[[#This Row],[COSTO REAL]]-CATEGORIAS[[#This Row],[PROYECCION TOTAL DE COSTO]] -> 0
D11: 11-0104-000G | E11: MAO CD - Civil / Enfierradura (G) | F11: NO | G11: 0 | H11: 0 | I11: 0 | J11: 0 | K11: 0 | L11: =CATEGORIAS[[#This Row],[ADICIONALES]]+CATEGORIAS[[#This Row],[POM]]+CATEGORIAS[[#This Row],[REAJUSTE PAGADO]]+CATEGORIAS[[#This Row],[REAJUSTE PROYECTADO]] -> 0 | M11: 0 | N11: 0 | O11: =+CATEGORIAS[[#This Row],[PRODUCCION PARTIDAS ORIGINALES ACTUAL]]+CATEGORIAS[[#This Row],[PRODUCCION ADICIONALES ACTUAL]] -> 0 | P11: 0 | Q11: 0 | R11: =+CATEGORIAS[[#This Row],[PRODUCCION ANTERIOR]]+CATEGORIAS[[#This Row],[PRODUCCION ADICIONALES ANTERIOR]] -> 0 | S11: 0 | U11: 0 | V11: =SUM(CATEGORIAS[[#This Row],[COSTO ACUMULADO AX]:[PROVISIONES]]) -> 0 | W11: 0 | Y11: 0 | Z11: =SUM(CATEGORIAS[[#This Row],[COSTO ACUMULADO ANTERIOR]:[PROVISIONES ANTERIOR]]) -> 0 | AA11: =ABS(+CATEGORIAS[[#This Row],[PRESUPUESTO FINAL PROYECTADO]]-CATEGORIAS[[#This Row],[TOTAL PRODUCCION ACTUAL]]) -> 0 | AD11: 0 | AE11: =SUM(CATEGORIAS[[#This Row],[INVENTARIO]:[PROYECCION DE COSTO DEL SALDO]]) -> 0 | AG11: =+CATEGORIAS[[#This Row],[PRESUPUESTO FINAL PROYECTADO]]-CATEGORIAS[[#This Row],[COSTO REAL]]-CATEGORIAS[[#This Row],[PROYECCION TOTAL DE COSTO]] -> 0
D12: 11-0105-000G | E12: MAO CD - Civil / Arquitectura (G) | F12: NO | G12: 0 | H12: 0 | I12: 0 | J12: 0 | K12: 0 | L12: =CATEGORIAS[[#This Row],[ADICIONALES]]+CATEGORIAS[[#This Row],[POM]]+CATEGORIAS[[#This Row],[REAJUSTE PAGADO]]+CATEGORIAS[[#This Row],[REAJUSTE PROYECTADO]] -> 0 | M12: 0 | N12: 0 | O12: =+CATEGORIAS[[#This Row],[PRODUCCION PARTIDAS ORIGINALES ACTUAL]]+CATEGORIAS[[#This Row],[PRODUCCION ADICIONALES ACTUAL]] -> 0 | P12: 0 | Q12: 0 | R12: =+CATEGORIAS[[#This Row],[PRODUCCION ANTERIOR]]+CATEGORIAS[[#This Row],[PRODUCCION ADICIONALES ANTERIOR]] -> 0 | S12: 0 | U12: 0 | V12: =SUM(CATEGORIAS[[#This Row],[COSTO ACUMULADO AX]:[PROVISIONES]]) -> 0 | W12: 0 | Y12: 0 | Z12: =SUM(CATEGORIAS[[#This Row],[COSTO ACUMULADO ANTERIOR]:[PROVISIONES ANTERIOR]]) -> 0 | AA12: =ABS(+CATEGORIAS[[#This Row],[PRESUPUESTO FINAL PROYECTADO]]-CATEGORIAS[[#This Row],[TOTAL PRODUCCION ACTUAL]]) -> 0 | AD12: 0 | AE12: =SUM(CATEGORIAS[[#This Row],[INVENTARIO]:[PROYECCION DE COSTO DEL SALDO]]) -> 0 | AG12: =+CATEGORIAS[[#This Row],[PRESUPUESTO FINAL PROYECTADO]]-CATEGORIAS[[#This Row],[COSTO REAL]]-CATEGORIAS[[#This Row],[PROYECCION TOTAL DE COSTO]] -> 0
D13: 11-0199-000G | E13: MAO CD - Civil / Otros (G) | F13: SI | G13: 0 | H13: 0 | I13: 0 | J13: 0 | K13: 0 | L13: =CATEGORIAS[[#This Row],[ADICIONALES]]+CATEGORIAS[[#This Row],[POM]]+CATEGORIAS[[#This Row],[REAJUSTE PAGADO]]+CATEGORIAS[[#This Row],[REAJUSTE PROYECTADO]] -> 0 | M13: 0 | N13: 0 | O13: =+CATEGORIAS[[#This Row],[PRODUCCION PARTIDAS ORIGINALES ACTUAL]]+CATEGORIAS[[#This Row],[PRODUCCION ADICIONALES ACTUAL]] -> 0 | P13: 0 | Q13: 0 | R13: =+CATEGORIAS[[#This Row],[PRODUCCION ANTERIOR]]+CATEGORIAS[[#This Row],[PRODUCCION ADICIONALES ANTERIOR]] -> 0 | S13: 0 | U13: 0 | V13: =SUM(CATEGORIAS[[#This Row],[COSTO ACUMULADO AX]:[PROVISIONES]]) -> 0 | W13: 0 | Y13: 0 | Z13: =SUM(CATEGORIAS[[#This Row],[COSTO ACUMULADO ANTERIOR]:[PROVISIONES ANTERIOR]]) -> 0 | AA13: =ABS(+CATEGORIAS[[#This Row],[PRESUPUESTO FINAL PROYECTADO]]-CATEGORIAS[[#This Row],[TOTAL PRODUCCION ACTUAL]]) -> 0 | AD13: 0 | AE13: =SUM(CATEGORIAS[[#This Row],[INVENTARIO]:[PROYECCION DE COSTO DEL SALDO]]) -> 0 | AG13: =+CATEGORIAS[[#This Row],[PRESUPUESTO FINAL PROYECTADO]]-CATEGORIAS[[#This Row],[COSTO REAL]]-CATEGORIAS[[#This Row],[PROYECCION TOTAL DE COSTO]] -> 0
D14: 11-0207-000G | E14: MAO CD - Estructura / Soldadura (G) | F14: NO | G14: 0 | H14: 0 | I14: 0 | J14: 0 | K14: 0 | L14: =CATEGORIAS[[#This Row],[ADICIONALES]]+CATEGORIAS[[#This Row],[POM]]+CATEGORIAS[[#This Row],[REAJUSTE PAGADO]]+CATEGORIAS[[#This Row],[REAJUSTE PROYECTADO]] -> 0 | M14: 0 | N14: 0 | O14: =+CATEGORIAS[[#This Row],[PRODUCCION PARTIDAS ORIGINALES ACTUAL]]+CATEGORIAS[[#This Row],[PRODUCCION ADICIONALES ACTUAL]] -> 0 | P14: 0 | Q14: 0 | R14: =+CATEGORIAS[[#This Row],[PRODUCCION ANTERIOR]]+CATEGORIAS[[#This Row],[PRODUCCION ADICIONALES ANTERIOR]] -> 0 | S14: 0 | U14: 0 | V14: =SUM(CATEGORIAS[[#This Row],[COSTO ACUMULADO AX]:[PROVISIONES]]) -> 0 | W14: 0 | Y14: 0 | Z14: =SUM(CATEGORIAS[[#This Row],[COSTO ACUMULADO ANTERIOR]:[PROVISIONES ANTERIOR]]) -> 0 | AA14: =ABS(+CATEGORIAS[[#This Row],[PRESUPUESTO FINAL PROYECTADO]]-CATEGORIAS[[#This Row],[TOTAL PRODUCCION ACTUAL]]) -> 0 | AD14: 0 | AE14: =SUM(CATEGORIAS[[#This Row],[INVENTARIO]:[PROYECCION DE COSTO DEL SALDO]]) -> 0 | AG14: =+CATEGORIAS[[#This Row],[PRESUPUESTO FINAL PROYECTADO]]-CATEGORIAS[[#This Row],[COSTO REAL]]-CATEGORIAS[[#This Row],[PROYECCION TOTAL DE COSTO]] -> 0
A15: 0B01 | B15: 0A02 | C15: Estructura | D15: 11-0208-000G | E15: MAO CD - Estructura / Montajes (G) | F15: SI | G15: 9107425.3 | H15: 5994572.4 | I15: 0 | J15: 211358.76 | K15: 0 | L15: =CATEGORIAS[[#This Row],[ADICIONALES]]+CATEGORIAS[[#This Row],[POM]]+CATEGORIAS[[#This Row],[REAJUSTE PAGADO]]+CATEGORIAS[[#This Row],[REAJUSTE PROYECTADO]] -> 6205931.1 | M15: 6204754.4 | N15: 1176.7382 | O15: =+CATEGORIAS[[#This Row],[PRODUCCION PARTIDAS ORIGINALES ACTUAL]]+CATEGORIAS[[#This Row],[PRODUCCION ADICIONALES ACTUAL]] -> 6205931.1 | P15: 6204754.4 | Q15: 0 | R15: =+CATEGORIAS[[#This Row],[PRODUCCION ANTERIOR]]+CATEGORIAS[[#This Row],[PRODUCCION ADICIONALES ANTERIOR]] -> 6204754.4 | S15: 0 | U15: 0 | V15: =SUM(CATEGORIAS[[#This Row],[COSTO ACUMULADO AX]:[PROVISIONES]]) -> 0 | W15: 0 | Y15: 0 | Z15: =SUM(CATEGORIAS[[#This Row],[COSTO ACUMULADO ANTERIOR]:[PROVISIONES ANTERIOR]]) -> 0 | AA15: =ABS(+CATEGORIAS[[#This Row],[PRESUPUESTO FINAL PROYECTADO]]-CATEGORIAS[[#This Row],[TOTAL PRODUCCION ACTUAL]]) -> 0 | AD15: 0 | AE15: =SUM(CATEGORIAS[[#This Row],[INVENTARIO]:[PROYECCION DE COSTO DEL SALDO]]) -> 0 | AG15: =+CATEGORIAS[[#This Row],[PRESUPUESTO FINAL PROYECTADO]]-CATEGORIAS[[#This Row],[COSTO REAL]]-CATEGORIAS[[#This Row],[PROYECCION TOTAL DE COSTO]] -> 6205931.1
D16: 11-0231-201G | E16: Remuneraciones / Otros Gastos / Prov. Vacaciones | F16: NO | G16: 0 | H16: 0 | I16: 0 | J16: 0 | K16: 0 | L16: =CATEGORIAS[[#This Row],[ADICIONALES]]+CATEGORIAS[[#This Row],[POM]]+CATEGORIAS[[#This Row],[REAJUSTE PAGADO]]+CATEGORIAS[[#This Row],[REAJUSTE PROYECTADO]] -> 0 | M16: 0 | N16: 0 | O16: =+CATEGORIAS[[#This Row],[PRODUCCION PARTIDAS ORIGINALES ACTUAL]]+CATEGORIAS[[#This Row],[PRODUCCION ADICIONALES ACTUAL]] -> 0 | P16: 0 | Q16: 0 | R16: =+CATEGORIAS[[#This Row],[PRODUCCION ANTERIOR]]+CATEGORIAS[[#This Row],[PRODUCCION ADICIONALES ANTERIOR]] -> 0 | S16: 0 | U16: 0 | V16: =SUM(CATEGORIAS[[#This Row],[COSTO ACUMULADO AX]:[PROVISIONES]]) -> 0 | W16: 0 | Y16: 0 | Z16: =SUM(CATEGORIAS[[#This Row],[COSTO ACUMULADO ANTERIOR]:[PROVISIONES ANTERIOR]]) -> 0 | AA16: =ABS(+CATEGORIAS[[#This Row],[PRESUPUESTO FINAL PROYECTADO]]-CATEGORIAS[[#This Row],[TOTAL PRODUCCION ACTUAL]]) -> 0 | AD16: 0 | AE16: =SUM(CATEGORIAS[[#This Row],[INVENTARIO]:[PROYECCION DE COSTO DEL SALDO]]) -> 0 | AG16: =+CATEGORIAS[[#This Row],[PRESUPUESTO FINAL PROYECTADO]]-CATEGORIAS[[#This Row],[COSTO REAL]]-CATEGORIAS[[#This Row],[PROYECCION TOTAL DE COSTO]] -> 0
D17: 11-0307-000G | E17: MAO CD - Mecánica / Soldadura (G) | F17: NO | G17: 0 | H17: 0 | I17: 0 | J17: 0 | K17: 0 | L17: =CATEGORIAS[[#This Row],[ADICIONALES]]+CATEGORIAS[[#This Row],[POM]]+CATEGORIAS[[#This Row],[REAJUSTE PAGADO]]+CATEGORIAS[[#This Row],[REAJUSTE PROYECTADO]] -> 0 | M17: 0 | N17: 0 | O17: =+CATEGORIAS[[#This Row],[PRODUCCION PARTIDAS ORIGINALES ACTUAL]]+CATEGORIAS[[#This Row],[PRODUCCION ADICIONALES ACTUAL]] -> 0 | P17: 0 | Q17: 0 | R17: =+CATEGORIAS[[#This Row],[PRODUCCION ANTERIOR]]+CATEGORIAS[[#This Row],[PRODUCCION ADICIONALES ANTERIOR]] -> 0 | S17: 0 | U17: 0 | V17: =SUM(CATEGORIAS[[#This Row],[COSTO ACUMULADO AX]:[PROVISIONES]]) -> 0 | W17: 0 | Y17: 0 | Z17: =SUM(CATEGORIAS[[#This Row],[COSTO ACUMULADO ANTERIOR]:[PROVISIONES ANTERIOR]]) -> 0 | AA17: =ABS(+CATEGORIAS[[#This Row],[PRESUPUESTO FINAL PROYECTADO]]-CATEGORIAS[[#This Row],[TOTAL PRODUCCION ACTUAL]]) -> 0 | AD17: 0 | AE17: =SUM(CATEGORIAS[[#This Row],[INVENTARIO]:[PROYECCION DE COSTO DEL SALDO]]) -> 0 | AG17: =+CATEGORIAS[[#This Row],[PRESUPUESTO FINAL PROYECTADO]]-CATEGORIAS[[#This Row],[COSTO REAL]]-CATEGORIAS[[#This Row],[PROYECCION TOTAL DE COSTO]] -> 0
A18: 0C01 | B18: 0A03 | C18: Mecanica | D18: 11-0308-000G | E18: MAO CD - Mecánica / Montajes (G) | F18: SI | G18: 6.482323e+08 | H18: 6.6364583e+08 | I18: 1.5475623e+08 | J18: 23399060 | K18: 0 | L18: =CATEGORIAS[[#This Row],[ADICIONALES]]+CATEGORIAS[[#This Row],[POM]]+CATEGORIAS[[#This Row],[REAJUSTE PAGADO]]+CATEGORIAS[[#This Row],[REAJUSTE PROYECTADO]] -> 8.4180112e+08 | M18: 6.8691462e+08 | N18: 1.548865e+08 | O18: =+CATEGORIAS[[#This Row],[PRODUCCION PARTIDAS ORIGINALES ACTUAL]]+CATEGORIAS[[#This Row],[PRODUCCION ADICIONALES ACTUAL]] -> 8.4180112e+08 | P18: 6.8691462e+08 | Q18: 1.5687251e+08 | R18: =+CATEGORIAS[[#This Row],[PRODUCCION ANTERIOR]]+CATEGORIAS[[#This Row],[PRODUCCION ADICIONALES ANTERIOR]] -> 8.4378713e+08 | S18: 590365191 | T18: -3903956 | U18: 0 | V18: =SUM(CATEGORIAS[[#This Row],[COSTO ACUMULADO AX]:[PROVISIONES]]) -> 586461235 | W18: 590365191 | X18: -3903956 | Y18: 0 | Z18: =SUM(CATEGORIAS[[#This Row],[COSTO ACUMULADO ANTERIOR]:[PROVISIONES ANTERIOR]]) -> 586461235 | AA18: =ABS(+CATEGORIAS[[#This Row],[PRESUPUESTO FINAL PROYECTADO]]-CATEGORIAS[[#This Row],[TOTAL PRODUCCION ACTUAL]]) -> 4.7683716e-07 | AD18: 0 | AE18: =SUM(CATEGORIAS[[#This Row],[INVENTARIO]:[PROYECCION DE COSTO DEL SALDO]]) -> 0 | AG18: =+CATEGORIAS[[#This Row],[PRESUPUESTO FINAL PROYECTADO]]-CATEGORIAS[[#This Row],[COSTO REAL]]-CATEGORIAS[[#This Row],[PROYECCION TOTAL DE COSTO]] -> 2.5533988e+08
D19: 11-0321-619A | E19: Remuneraciones / Remuneraciones / Otros Dsctos. al Personal | F19: NO | G19: 0 | H19: 0 | I19: 0 | J19: 0 | K19: 0 | L19: =CATEGORIAS[[#This Row],[ADICIONALES]]+CATEGORIAS[[#This Row],[POM]]+CATEGORIAS[[#This Row],[REAJUSTE PAGADO]]+CATEGORIAS[[#This Row],[REAJUSTE PROYECTADO]] -> 0 | M19: 0 | N19: 0 | O19: =+CATEGORIAS[[#This Row],[PRODUCCION PARTIDAS ORIGINALES ACTUAL]]+CATEGORIAS[[#This Row],[PRODUCCION ADICIONALES ACTUAL]] -> 0 | P19: 0 | Q19: 0 | R19: =+CATEGORIAS[[#This Row],[PRODUCCION ANTERIOR]]+CATEGORIAS[[#This Row],[PRODUCCION ADICIONALES ANTERIOR]] -> 0 | S19: 0 | U19: 0 | V19: =SUM(CATEGORIAS[[#This Row],[COSTO ACUMULADO AX]:[PROVISIONES]]) -> 0 | W19: 0 | Y19: 0 | Z19: =SUM(CATEGORIAS[[#This Row],[COSTO ACUMULADO ANTERIOR]:[PROVISIONES ANTERIOR]]) -> 0 | AA19: =ABS(+CATEGORIAS[[#This Row],[PRESUPUESTO FINAL PROYECTADO]]-CATEGORIAS[[#This Row],[TOTAL PRODUCCION ACTUAL]]) -> 0 | AD19: 0 | AE19: =SUM(CATEGORIAS[[#This Row],[INVENTARIO]:[PROYECCION DE COSTO DEL SALDO]]) -> 0 | AG19: =+CATEGORIAS[[#This Row],[PRESUPUESTO FINAL PROYECTADO]]-CATEGORIAS[[#This Row],[COSTO REAL]]-CATEGORIAS[[#This Row],[PROYECCION TOTAL DE COSTO]] -> 0
D20: 11-0321-619G | E20: Remuneraciones / Remuneraciones / Otros Dsctos. al Personal | F20: NO | G20: 0 | H20: 0 | I20: 0 | J20: 0 | K20: 0 | L20: =CATEGORIAS[[#This Row],[ADICIONALES]]+CATEGORIAS[[#This Row],[POM]]+CATEGORIAS[[#This Row],[REAJUSTE PAGADO]]+CATEGORIAS[[#This Row],[REAJUSTE PROYECTADO]] -> 0 | M20: 0 | N20: 0 | O20: =+CATEGORIAS[[#This Row],[PRODUCCION PARTIDAS ORIGINALES ACTUAL]]+CATEGORIAS[[#This Row],[PRODUCCION ADICIONALES ACTUAL]] -> 0 | P20: 0 | Q20: 0 | R20: =+CATEGORIAS[[#This Row],[PRODUCCION ANTERIOR]]+CATEGORIAS[[#This Row],[PRODUCCION ADICIONALES ANTERIOR]] -> 0 | S20: 0 | U20: 0 | V20: =SUM(CATEGORIAS[[#This Row],[COSTO ACUMULADO AX]:[PROVISIONES]]) -> 0 | W20: 0 | Y20: 0 | Z20: =SUM(CATEGORIAS[[#This Row],[COSTO ACUMULADO ANTERIOR]:[PROVISIONES ANTERIOR]]) -> 0 | AA20: =ABS(+CATEGORIAS[[#This Row],[PRESUPUESTO FINAL PROYECTADO]]-CATEGORIAS[[#This Row],[TOTAL PRODUCCION ACTUAL]]) -> 0 | AD20: 0 | AE20: =SUM(CATEGORIAS[[#This Row],[INVENTARIO]:[PROYECCION DE COSTO DEL SALDO]]) -> 0 | AG20: =+CATEGORIAS[[#This Row],[PRESUPUESTO FINAL PROYECTADO]]-CATEGORIAS[[#This Row],[COSTO REAL]]-CATEGORIAS[[#This Row],[PROYECCION TOTAL DE COSTO]] -> 0
D21: 11-0331-201G | E21: Remuneraciones / Remuneraciones / Remuneraciones | F21: NO | G21: 0 | H21: 0 | I21: 0 | J21: 0 | K21: 0 | L21: =CATEGORIAS[[#This Row],[ADICIONALES]]+CATEGORIAS[[#This Row],[POM]]+CATEGORIAS[[#This Row],[REAJUSTE PAGADO]]+CATEGORIAS[[#This Row],[REAJUSTE PROYECTADO]] -> 0 | M21: 0 | N21: 0 | O21: =+CATEGORIAS[[#This Row],[PRODUCCION PARTIDAS ORIGINALES ACTUAL]]+CATEGORIAS[[#This Row],[PRODUCCION ADICIONALES ACTUAL]] -> 0 | P21: 0 | Q21: 0 | R21: =+CATEGORIAS[[#This Row],[PRODUCCION ANTERIOR]]+CATEGORIAS[[#This Row],[PRODUCCION ADICIONALES ANTERIOR]] -> 0 | S21: 0 | U21: 0 | V21: =SUM(CATEGORIAS[[#This Row],[COSTO ACUMULADO AX]:[PROVISIONES]]) -> 0 | W21: 0 | Y21: 0 | Z21: =SUM(CATEGORIAS[[#This Row],[COSTO ACUMULADO ANTERIOR]:[PROVISIONES ANTERIOR]]) -> 0 | AA21: =ABS(+CATEGORIAS[[#This Row],[PRESUPUESTO FINAL PROYECTADO]]-CATEGORIAS[[#This Row],[TOTAL PRODUCCION ACTUAL]]) -> 0 | AD21: 0 | AE21: =SUM(CATEGORIAS[[#This Row],[INVENTARIO]:[PROYECCION DE COSTO DEL SALDO]]) -> 0 | AG21: =+CATEGORIAS[[#This Row],[PRESUPUESTO FINAL PROYECTADO]]-CATEGORIAS[[#This Row],[COSTO REAL]]-CATEGORIAS[[#This Row],[PROYECCION TOTAL DE COSTO]] -> 0
D22: 11-0407-000G | E22: MAO CD - Cañería / Soldadura (G) | F22: NO | G22: 0 | H22: 0 | I22: 0 | J22: 0 | K22: 0 | L22: =CATEGORIAS[[#This Row],[ADICIONALES]]+CATEGORIAS[[#This Row],[POM]]+CATEGORIAS[[#This Row],[REAJUSTE PAGADO]]+CATEGORIAS[[#This Row],[REAJUSTE PROYECTADO]] -> 0 | M22: 0 | N22: 0 | O22: =+CATEGORIAS[[#This Row],[PRODUCCION PARTIDAS ORIGINALES ACTUAL]]+CATEGORIAS[[#This Row],[PRODUCCION ADICIONALES ACTUAL]] -> 0 | P22: 0 | Q22: 0 | R22: =+CATEGORIAS[[#This Row],[PRODUCCION ANTERIOR]]+CATEGORIAS[[#This Row],[PRODUCCION ADICIONALES ANTERIOR]] -> 0 | S22: 0 | U22: 0 | V22: =SUM(CATEGORIAS[[#This Row],[COSTO ACUMULADO AX]:[PROVISIONES]]) -> 0 | W22: 0 | Y22: 0 | Z22: =SUM(CATEGORIAS[[#This Row],[COSTO ACUMULADO ANTERIOR]:[PROVISIONES ANTERIOR]]) -> 0 | AA22: =ABS(+CATEGORIAS[[#This Row],[PRESUPUESTO FINAL PROYECTADO]]-CATEGORIAS[[#This Row],[TOTAL PRODUCCION ACTUAL]]) -> 0 | AD22: 0 | AE22: =SUM(CATEGORIAS[[#This Row],[INVENTARIO]:[PROYECCION DE COSTO DEL SALDO]]) -> 0 | AG22: =+CATEGORIAS[[#This Row],[PRESUPUESTO FINAL PROYECTADO]]-CATEGORIAS[[#This Row],[COSTO REAL]]-CATEGORIAS[[#This Row],[PROYECCION TOTAL DE COSTO]] -> 0
A23: 0D01 | B23: 0A04 | C23: Cañería | D23: 11-0408-000G | E23: MAO CD - Cañería / Montajes (G) | F23: SI | G23: 37872374 | H23: 9336138.6 | I23: 9160674.7 | J23: 329176.89 | K23: 0 | L23: =CATEGORIAS[[#This Row],[ADICIONALES]]+CATEGORIAS[[#This Row],[POM]]+CATEGORIAS[[#This Row],[REAJUSTE PAGADO]]+CATEGORIAS[[#This Row],[REAJUSTE PROYECTADO]] -> 18825990 | M23: 9663482.8 | N23: 9162507.4 | O23: =+CATEGORIAS[[#This Row],[PRODUCCION PARTIDAS ORIGINALES ACTUAL]]+CATEGORIAS[[#This Row],[PRODUCCION ADICIONALES ACTUAL]] -> 18825990 | P23: 9663482.8 | Q23: 9160674.7 | R23: =+CATEGORIAS[[#This Row],[PRODUCCION ANTERIOR]]+CATEGORIAS[[#This Row],[PRODUCCION ADICIONALES ANTERIOR]] -> 18824158 | S23: 0 | U23: 0 | V23: =SUM(CATEGORIAS[[#This Row],[COSTO ACUMULADO AX]:[PROVISIONES]]) -> 0 | W23: 0 | Y23: 0 | Z23: =SUM(CATEGORIAS[[#This Row],[COSTO ACUMULADO ANTERIOR]:[PROVISIONES ANTERIOR]]) -> 0 | AA23: =ABS(+CATEGORIAS[[#This Row],[PRESUPUESTO FINAL PROYECTADO]]-CATEGORIAS[[#This Row],[TOTAL PRODUCCION ACTUAL]]) -> 0 | AE23: =SUM(CATEGORIAS[[#This Row],[INVENTARIO]:[PROYECCION DE COSTO DEL SALDO]]) -> 0 | AG23: =+CATEGORIAS[[#This Row],[PRESUPUESTO FINAL PROYECTADO]]-CATEGORIAS[[#This Row],[COSTO REAL]]-CATEGORIAS[[#This Row],[PROYECCION TOTAL DE COSTO]] -> 18825990
D24: 11-0507-000G | E24: MAO CD - Electricidad / Soldadura (G) | F24: NO | G24: 0 | H24: 0 | I24: 0 | J24: 0 | K24: 0 | L24: =CATEGORIAS[[#This Row],[ADICIONALES]]+CATEGORIAS[[#This Row],[POM]]+CATEGORIAS[[#This Row],[REAJUSTE PAGADO]]+CATEGORIAS[[#This Row],[REAJUSTE PROYECTADO]] -> 0 | M24: 0 | N24: 0 | O24: =+CATEGORIAS[[#This Row],[PRODUCCION PARTIDAS ORIGINALES ACTUAL]]+CATEGORIAS[[#This Row],[PRODUCCION ADICIONALES ACTUAL]] -> 0 | P24: 0 | Q24: 0 | R24: =+CATEGORIAS[[#This Row],[PRODUCCION ANTERIOR]]+CATEGORIAS[[#This Row],[PRODUCCION ADICIONALES ANTERIOR]] -> 0 | S24: 0 | U24: 0 | V24: =SUM(CATEGORIAS[[#This Row],[COSTO ACUMULADO AX]:[PROVISIONES]]) -> 0 | W24: 0 | Y24: 0 | Z24: =SUM(CATEGORIAS[[#This Row],[COSTO ACUMULADO ANTERIOR]:[PROVISIONES ANTERIOR]]) -> 0 | AA24: =ABS(+CATEGORIAS[[#This Row],[PRESUPUESTO FINAL PROYECTADO]]-CATEGORIAS[[#This Row],[TOTAL PRODUCCION ACTUAL]]) -> 0 | AD24: 0 | AE24: =SUM(CATEGORIAS[[#This Row],[INVENTARIO]:[PROYECCION DE COSTO DEL SALDO]]) -> 0 | AG24: =+CATEGORIAS[[#This Row],[PRESUPUESTO FINAL PROYECTADO]]-CATEGORIAS[[#This Row],[COSTO REAL]]-CATEGORIAS[[#This Row],[PROYECCION TOTAL DE COSTO]] -> 0
A25: 0F01 | B25: 0A05 | C25: Electricidad & Instrumentacion | D25: 11-0508-000G | E25: MAO CD - Electricidad / Montajes (G) | F25: SI | G25: 4909779.4 | H25: 3800857.2 | I25: 1.1568032e+08 | J25: 134011.97 | K25: 0 | L25: =CATEGORIAS[[#This Row],[ADICIONALES]]+CATEGORIAS[[#This Row],[POM]]+CATEGORIAS[[#This Row],[REAJUSTE PAGADO]]+CATEGORIAS[[#This Row],[REAJUSTE PROYECTADO]] -> 1.1961519e+08 | M25: 3934123.1 | N25: 1.1568107e+08 | O25: =+CATEGORIAS[[#This Row],[PRODUCCION PARTIDAS ORIGINALES ACTUAL]]+CATEGORIAS[[#This Row],[PRODUCCION ADICIONALES ACTUAL]] -> 1.1961519e+08 | P25: 3934123.1 | Q25: 1.1568032e+08 | R25: =+CATEGORIAS[[#This Row],[PRODUCCION ANTERIOR]]+CATEGORIAS[[#This Row],[PRODUCCION ADICIONALES ANTERIOR]] -> 1.1961445e+08 | S25: 41920101 | U25: 0 | V25: =SUM(CATEGORIAS[[#This Row],[COSTO ACUMULADO AX]:[PROVISIONES]]) -> 41920101 | W25: 41920101 | Y25: 0 | Z25: =SUM(CATEGORIAS[[#This Row],[COSTO ACUMULADO ANTERIOR]:[PROVISIONES ANTERIOR]]) -> 41920101 | AA25: =ABS(+CATEGORIAS[[#This Row],[PRESUPUESTO FINAL PROYECTADO]]-CATEGORIAS[[#This Row],[TOTAL PRODUCCION ACTUAL]]) -> 0 | AD25: 0 | AE25: =SUM(CATEGORIAS[[#This Row],[INVENTARIO]:[PROYECCION DE COSTO DEL SALDO]]) -> 0 | AG25: =+CATEGORIAS[[#This Row],[PRESUPUESTO FINAL PROYECTADO]]-CATEGORIAS[[#This Row],[COSTO REAL]]-CATEGORIAS[[#This Row],[PROYECCION TOTAL DE COSTO]] -> 77695091
D26: 11-0607-000G | E26: MAO CD - Instrumentación / Soldadura (G) | F26: NO | G26: 0 | H26: 0 | I26: 0 | J26: 0 | K26: 0 | L26: =CATEGORIAS[[#This Row],[ADICIONALES]]+CATEGORIAS[[#This Row],[POM]]+CATEGORIAS[[#This Row],[REAJUSTE PAGADO]]+CATEGORIAS[[#This Row],[REAJUSTE PROYECTADO]] -> 0 | M26: 0 | N26: 0 | O26: =+CATEGORIAS[[#This Row],[PRODUCCION PARTIDAS ORIGINALES ACTUAL]]+CATEGORIAS[[#This Row],[PRODUCCION ADICIONALES ACTUAL]] -> 0 | P26: 0 | Q26: 0 | R26: =+CATEGORIAS[[#This Row],[PRODUCCION ANTERIOR]]+CATEGORIAS[[#This Row],[PRODUCCION ADICIONALES ANTERIOR]] -> 0 | S26: 0 | U26: 0 | V26: =SUM(CATEGORIAS[[#This Row],[COSTO ACUMULADO AX]:[PROVISIONES]]) -> 0 | W26: 0 | Y26: 0 | Z26: =SUM(CATEGORIAS[[#This Row],[COSTO ACUMULADO ANTERIOR]:[PROVISIONES ANTERIOR]]) -> 0 | AA26: =ABS(+CATEGORIAS[[#This Row],[PRESUPUESTO FINAL PROYECTADO]]-CATEGORIAS[[#This Row],[TOTAL PRODUCCION ACTUAL]]) -> 0 | AD26: 0 | AE26: =SUM(CATEGORIAS[[#This Row],[INVENTARIO]:[PROYECCION DE COSTO DEL SALDO]]) -> 0 | AG26: =+CATEGORIAS[[#This Row],[PRESUPUESTO FINAL PROYECTADO]]-CATEGORIAS[[#This Row],[COSTO REAL]]-CATEGORIAS[[#This Row],[PROYECCION TOTAL DE COSTO]] -> 0
D27: 11-0608-000G | E27: MAO CD - Instrumentación / Montajes (G) | F27: NO | G27: 0 | H27: 0 | I27: 0 | J27: 0 | K27: 0 | L27: =CATEGORIAS[[#This Row],[ADICIONALES]]+CATEGORIAS[[#This Row],[POM]]+CATEGORIAS[[#This Row],[REAJUSTE PAGADO]]+CATEGORIAS[[#This Row],[REAJUSTE PROYECTADO]] -> 0 | M27: 0 | N27: 0 | O27: =+CATEGORIAS[[#This Row],[PRODUCCION PARTIDAS ORIGINALES ACTUAL]]+CATEGORIAS[[#This Row],[PRODUCCION ADICIONALES ACTUAL]] -> 0 | P27: 0 | Q27: 0 | R27: =+CATEGORIAS[[#This Row],[PRODUCCION ANTERIOR]]+CATEGORIAS[[#This Row],[PRODUCCION ADICIONALES ANTERIOR]] -> 0 | S27: 0 | U27: 0 | V27: =SUM(CATEGORIAS[[#This Row],[COSTO ACUMULADO AX]:[PROVISIONES]]) -> 0 | W27: 0 | Y27: 0 | Z27: =SUM(CATEGORIAS[[#This Row],[COSTO ACUMULADO ANTERIOR]:[PROVISIONES ANTERIOR]]) -> 0 | AA27: =ABS(+CATEGORIAS[[#This Row],[PRESUPUESTO FINAL PROYECTADO]]-CATEGORIAS[[#This Row],[TOTAL PRODUCCION ACTUAL]]) -> 0 | AD27: 0 | AE27: =SUM(CATEGORIAS[[#This Row],[INVENTARIO]:[PROYECCION DE COSTO DEL SALDO]]) -> 0 | AG27: =+CATEGORIAS[[#This Row],[PRESUPUESTO FINAL PROYECTADO]]-CATEGORIAS[[#This Row],[COSTO REAL]]-CATEGORIAS[[#This Row],[PROYECCION TOTAL DE COSTO]] -> 0
D28: 11-0701-000G | E28: MAO CD - Aislación / Aislación (G) | F28: SI | G28: 0 | H28: 0 | I28: 0 | J28: 0 | K28: 0 | L28: =CATEGORIAS[[#This Row],[ADICIONALES]]+CATEGORIAS[[#This Row],[POM]]+CATEGORIAS[[#This Row],[REAJUSTE PAGADO]]+CATEGORIAS[[#This Row],[REAJUSTE PROYECTADO]] -> 0 | M28: 0 | N28: 0 | O28: =+CATEGORIAS[[#This Row],[PRODUCCION PARTIDAS ORIGINALES ACTUAL]]+CATEGORIAS[[#This Row],[PRODUCCION ADICIONALES ACTUAL]] -> 0 | P28: 0 | Q28: 0 | R28: =+CATEGORIAS[[#This Row],[PRODUCCION ANTERIOR]]+CATEGORIAS[[#This Row],[PRODUCCION ADICIONALES ANTERIOR]] -> 0 | S28: 0 | U28: 0 | V28: =SUM(CATEGORIAS[[#This Row],[COSTO ACUMULADO AX]:[PROVISIONES]]) -> 0 | W28: 0 | Y28: 0 | Z28: =SUM(CATEGORIAS[[#This Row],[COSTO ACUMULADO ANTERIOR]:[PROVISIONES ANTERIOR]]) -> 0 | AA28: =ABS(+CATEGORIAS[[#This Row],[PRESUPUESTO FINAL PROYECTADO]]-CATEGORIAS[[#This Row],[TOTAL PRODUCCION ACTUAL]]) -> 0 | AD28: 0 | AE28: =SUM(CATEGORIAS[[#This Row],[INVENTARIO]:[PROYECCION DE COSTO DEL SALDO]]) -> 0 | AG28: =+CATEGORIAS[[#This Row],[PRESUPUESTO FINAL PROYECTADO]]-CATEGORIAS[[#This Row],[COSTO REAL]]-CATEGORIAS[[#This Row],[PROYECCION TOTAL DE COSTO]] -> 0
D29: 11-0807-000G | E29: MAO CD - Caldera / Soldadura (G) | F29: NO | G29: 0 | H29: 0 | I29: 0 | J29: 0 | K29: 0 | L29: =CATEGORIAS[[#This Row],[ADICIONALES]]+CATEGORIAS[[#This Row],[POM]]+CATEGORIAS[[#This Row],[REAJUSTE PAGADO]]+CATEGORIAS[[#This Row],[REAJUSTE PROYECTADO]] -> 0 | M29: 0 | N29: 0 | O29: =+CATEGORIAS[[#This Row],[PRODUCCION PARTIDAS ORIGINALES ACTUAL]]+CATEGORIAS[[#This Row],[PRODUCCION ADICIONALES ACTUAL]] -> 0 | P29: 0 | Q29: 0 | R29: =+CATEGORIAS[[#This Row],[PRODUCCION ANTERIOR]]+CATEGORIAS[[#This Row],[PRODUCCION ADICIONALES ANTERIOR]] -> 0 | S29: 0 | U29: 0 | V29: =SUM(CATEGORIAS[[#This Row],[COSTO ACUMULADO AX]:[PROVISIONES]]) -> 0 | W29: 0 | Y29: 0 | Z29: =SUM(CATEGORIAS[[#This Row],[COSTO ACUMULADO ANTERIOR]:[PROVISIONES ANTERIOR]]) -> 0 | AA29: =ABS(+CATEGORIAS[[#This Row],[PRESUPUESTO FINAL PROYECTADO]]-CATEGORIAS[[#This Row],[TOTAL PRODUCCION ACTUAL]]) -> 0 | AD29: 0 | AE29: =SUM(CATEGORIAS[[#This Row],[INVENTARIO]:[PROYECCION DE COSTO DEL SALDO]]) -> 0 | AG29: =+CATEGORIAS[[#This Row],[PRESUPUESTO FINAL PROYECTADO]]-CATEGORIAS[[#This Row],[COSTO REAL]]-CATEGORIAS[[#This Row],[PROYECCION TOTAL DE COSTO]] -> 0
D30: 11-0808-000G | E30: MAO CD - Caldera / Montajes (G) | F30: NO | G30: 0 | H30: 0 | I30: 0 | J30: 0 | K30: 0 | L30: =CATEGORIAS[[#This Row],[ADICIONALES]]+CATEGORIAS[[#This Row],[POM]]+CATEGORIAS[[#This Row],[REAJUSTE PAGADO]]+CATEGORIAS[[#This Row],[REAJUSTE PROYECTADO]] -> 0 | M30: 0 | N30: 0 | O30: =+CATEGORIAS[[#This Row],[PRODUCCION PARTIDAS ORIGINALES ACTUAL]]+CATEGORIAS[[#This Row],[PRODUCCION ADICIONALES ACTUAL]] -> 0 | P30: 0 | Q30: 0 | R30: =+CATEGORIAS[[#This Row],[PRODUCCION ANTERIOR]]+CATEGORIAS[[#This Row],[PRODUCCION ADICIONALES ANTERIOR]] -> 0 | S30: 0 | U30: 0 | V30: =SUM(CATEGORIAS[[#This Row],[COSTO ACUMULADO AX]:[PROVISIONES]]) -> 0 | W30: 0 | Y30: 0 | Z30: =SUM(CATEGORIAS[[#This Row],[COSTO ACUMULADO ANTERIOR]:[PROVISIONES ANTERIOR]]) -> 0 | AA30: =ABS(+CATEGORIAS[[#This Row],[PRESUPUESTO FINAL PROYECTADO]]-CATEGORIAS[[#This Row],[TOTAL PRODUCCION ACTUAL]]) -> 0 | AD30: 0 | AE30: =SUM(CATEGORIAS[[#This Row],[INVENTARIO]:[PROYECCION DE COSTO DEL SALDO]]) -> 0 | AG30: =+CATEGORIAS[[#This Row],[PRESUPUESTO FINAL PROYECTADO]]-CATEGORIAS[[#This Row],[COSTO REAL]]-CATEGORIAS[[#This Row],[PROYECCION TOTAL DE COSTO]] -> 0
D31: 11-0907-000G | E31: MAO CD - Ductos / Soldadura (G) | F31: NO | G31: 0 | H31: 0 | I31: 0 | J31: 0 | K31: 0 | L31: =CATEGORIAS[[#This Row],[ADICIONALES]]+CATEGORIAS[[#This Row],[POM]]+CATEGORIAS[[#This Row],[REAJUSTE PAGADO]]+CATEGORIAS[[#This Row],[REAJUSTE PROYECTADO]] -> 0 | M31: 0 | N31: 0 | O31: =+CATEGORIAS[[#This Row],[PRODUCCION PARTIDAS ORIGINALES ACTUAL]]+CATEGORIAS[[#This Row],[PRODUCCION ADICIONALES ACTUAL]] -> 0 | P31: 0 | Q31: 0 | R31: =+CATEGORIAS[[#This Row],[PRODUCCION ANTERIOR]]+CATEGORIAS[[#This Row],[PRODUCCION ADICIONALES ANTERIOR]] -> 0 | S31: 0 | U31: 0 | V31: =SUM(CATEGORIAS[[#This Row],[COSTO ACUMULADO AX]:[PROVISIONES]]) -> 0 | W31: 0 | Y31: 0 | Z31: =SUM(CATEGORIAS[[#This Row],[COSTO ACUMULADO ANTERIOR]:[PROVISIONES ANTERIOR]]) -> 0 | AA31: =ABS(+CATEGORIAS[[#This Row],[PRESUPUESTO FINAL PROYECTADO]]-CATEGORIAS[[#This Row],[TOTAL PRODUCCION ACTUAL]]) -> 0 | AD31: 0 | AE31: =SUM(CATEGORIAS[[#This Row],[INVENTARIO]:[PROYECCION DE COSTO DEL SALDO]]) -> 0 | AG31: =+CATEGORIAS[[#This Row],[PRESUPUESTO FINAL PROYECTADO]]-CATEGORIAS[[#This Row],[COSTO REAL]]-CATEGORIAS[[#This Row],[PROYECCION TOTAL DE COSTO]] -> 0
D32: 11-0908-000G | E32: MAO CD - Ductos / Montajes (G) | F32: NO | G32: 0 | H32: 0 | I32: 0 | J32: 0 | K32: 0 | L32: =CATEGORIAS[[#This Row],[ADICIONALES]]+CATEGORIAS[[#This Row],[POM]]+CATEGORIAS[[#This Row],[REAJUSTE PAGADO]]+CATEGORIAS[[#This Row],[REAJUSTE PROYECTADO]] -> 0 | M32: 0 | N32: 0 | O32: =+CATEGORIAS[[#This Row],[PRODUCCION PARTIDAS ORIGINALES ACTUAL]]+CATEGORIAS[[#This Row],[PRODUCCION ADICIONALES ACTUAL]] -> 0 | P32: 0 | Q32: 0 | R32: =+CATEGORIAS[[#This Row],[PRODUCCION ANTERIOR]]+CATEGORIAS[[#This Row],[PRODUCCION ADICIONALES ANTERIOR]] -> 0 | S32: 0 | U32: 0 | V32: =SUM(CATEGORIAS[[#This Row],[COSTO ACUMULADO AX]:[PROVISIONES]]) -> 0 | W32: 0 | Y32: 0 | Z32: =SUM(CATEGORIAS[[#This Row],[COSTO ACUMULADO ANTERIOR]:[PROVISIONES ANTERIOR]]) -> 0 | AA32: =ABS(+CATEGORIAS[[#This Row],[PRESUPUESTO FINAL PROYECTADO]]-CATEGORIAS[[#This Row],[TOTAL PRODUCCION ACTUAL]]) -> 0 | AD32: 0 | AE32: =SUM(CATEGORIAS[[#This Row],[INVENTARIO]:[PROYECCION DE COSTO DEL SALDO]]) -> 0 | AG32: =+CATEGORIAS[[#This Row],[PRESUPUESTO FINAL PROYECTADO]]-CATEGORIAS[[#This Row],[COSTO REAL]]-CATEGORIAS[[#This Row],[PROYECCION TOTAL DE COSTO]] -> 0
D33: 11-1001-000G | E33: MAO CD - Comisionamiento / Comisionamiento (G) | F33: NO | G33: 0 | H33: 0 | I33: 0 | J33: 0 | K33: 0 | L33: =CATEGORIAS[[#This Row],[ADICIONALES]]+CATEGORIAS[[#This Row],[POM]]+CATEGORIAS[[#This Row],[REAJUSTE PAGADO]]+CATEGORIAS[[#This Row],[REAJUSTE PROYECTADO]] -> 0 | M33: 0 | N33: 0 | O33: =+CATEGORIAS[[#This Row],[PRODUCCION PARTIDAS ORIGINALES ACTUAL]]+CATEGORIAS[[#This Row],[PRODUCCION ADICIONALES ACTUAL]] -> 0 | P33: 0 | Q33: 0 | R33: =+CATEGORIAS[[#This Row],[PRODUCCION ANTERIOR]]+CATEGORIAS[[#This Row],[PRODUCCION ADICIONALES ANTERIOR]] -> 0 | S33: 0 | U33: 0 | V33: =SUM(CATEGORIAS[[#This Row],[COSTO ACUMULADO AX]:[PROVISIONES]]) -> 0 | W33: 0 | Y33: 0 | Z33: =SUM(CATEGORIAS[[#This Row],[COSTO ACUMULADO ANTERIOR]:[PROVISIONES ANTERIOR]]) -> 0 | AA33: =ABS(+CATEGORIAS[[#This Row],[PRESUPUESTO FINAL PROYECTADO]]-CATEGORIAS[[#This Row],[TOTAL PRODUCCION ACTUAL]]) -> 0 | AD33: 0 | AE33: =SUM(CATEGORIAS[[#This Row],[INVENTARIO]:[PROYECCION DE COSTO DEL SALDO]]) -> 0 | AG33: =+CATEGORIAS[[#This Row],[PRESUPUESTO FINAL PROYECTADO]]-CATEGORIAS[[#This Row],[COSTO REAL]]-CATEGORIAS[[#This Row],[PROYECCION TOTAL DE COSTO]] -> 0
A34: 0N01 | B34: 0A08 | C34: Andamios | D34: 11-1101-000G | E34: MAO CD - Andamios / Andamios (G) | F34: SI | G34: 40034534 | H34: 36291829 | I34: 17061591 | J34: 1279590.2 | K34: 0 | L34: =CATEGORIAS[[#This Row],[ADICIONALES]]+CATEGORIAS[[#This Row],[POM]]+CATEGORIAS[[#This Row],[REAJUSTE PAGADO]]+CATEGORIAS[[#This Row],[REAJUSTE PROYECTADO]] -> 54633010 | M34: 37564295 | N34: 17068715 | O34: =+CATEGORIAS[[#This Row],[PRODUCCION PARTIDAS ORIGINALES ACTUAL]]+CATEGORIAS[[#This Row],[PRODUCCION ADICIONALES ACTUAL]] -> 54633010 | P34: 37564295 | Q34: 17061591 | R34: =+CATEGORIAS[[#This Row],[PRODUCCION ANTERIOR]]+CATEGORIAS[[#This Row],[PRODUCCION ADICIONALES ANTERIOR]] -> 54625886 | S34: 166683412 | U34: 0 | V34: =SUM(CATEGORIAS[[#This Row],[COSTO ACUMULADO AX]:[PROVISIONES]]) -> 166683412 | W34: 166683412 | Y34: 0 | Z34: =SUM(CATEGORIAS[[#This Row],[COSTO ACUMULADO ANTERIOR]:[PROVISIONES ANTERIOR]]) -> 166683412 | AA34: =ABS(+CATEGORIAS[[#This Row],[PRESUPUESTO FINAL PROYECTADO]]-CATEGORIAS[[#This Row],[TOTAL PRODUCCION ACTUAL]]) -> 0 | AD34: 0 | AE34: =SUM(CATEGORIAS[[#This Row],[INVENTARIO]:[PROYECCION DE COSTO DEL SALDO]]) -> 0 | AG34: =+CATEGORIAS[[#This Row],[PRESUPUESTO FINAL PROYECTADO]]-CATEGORIAS[[#This Row],[COSTO REAL]]-CATEGORIAS[[#This Row],[PROYECCION TOTAL DE COSTO]] -> -1.120504e+08
D35: 11-1201-000G | E35: MAO CD - Pintura / Pintura (G) | F35: NO | G35: 0 | H35: 0 | I35: 0 | J35: 0 | K35: 0 | L35: =CATEGORIAS[[#This Row],[ADICIONALES]]+CATEGORIAS[[#This Row],[POM]]+CATEGORIAS[[#This Row],[REAJUSTE PAGADO]]+CATEGORIAS[[#This Row],[REAJUSTE PROYECTADO]] -> 0 | M35: 0 | N35: 0 | O35: =+CATEGORIAS[[#This Row],[PRODUCCION PARTIDAS ORIGINALES ACTUAL]]+CATEGORIAS[[#This Row],[PRODUCCION ADICIONALES ACTUAL]] -> 0 | P35: 0 | Q35: 0 | R35: =+CATEGORIAS[[#This Row],[PRODUCCION ANTERIOR]]+CATEGORIAS[[#This Row],[PRODUCCION ADICIONALES ANTERIOR]] -> 0 | S35: 0 | U35: 0 | V35: =SUM(CATEGORIAS[[#This Row],[COSTO ACUMULADO AX]:[PROVISIONES]]) -> 0 | W35: 0 | Y35: 0 | Z35: =SUM(CATEGORIAS[[#This Row],[COSTO ACUMULADO ANTERIOR]:[PROVISIONES ANTERIOR]]) -> 0 | AA35: =ABS(+CATEGORIAS[[#This Row],[PRESUPUESTO FINAL PROYECTADO]]-CATEGORIAS[[#This Row],[TOTAL PRODUCCION ACTUAL]]) -> 0 | AD35: 0 | AE35: =SUM(CATEGORIAS[[#This Row],[INVENTARIO]:[PROYECCION DE COSTO DEL SALDO]]) -> 0 | AG35: =+CATEGORIAS[[#This Row],[PRESUPUESTO FINAL PROYECTADO]]-CATEGORIAS[[#This Row],[COSTO REAL]]-CATEGORIAS[[#This Row],[PROYECCION TOTAL DE COSTO]] -> 0
A36: 0Z01 | B36: 0D07 | C36: Operador | D36: 11-1201-010G | E36: MAO CD - Equipos / Equipos / Operador (G) | F36: SI | G36: 1.0954463e+08 | H36: 1.0954463e+08 | I36: 31540254 | J36: 3862363.4 | K36: 0 | L36: =CATEGORIAS[[#This Row],[ADICIONALES]]+CATEGORIAS[[#This Row],[POM]]+CATEGORIAS[[#This Row],[REAJUSTE PAGADO]]+CATEGORIAS[[#This Row],[REAJUSTE PROYECTADO]] -> 1.4494725e+08 | M36: 1.1338549e+08 | N36: 31561758 | O36: =+CATEGORIAS[[#This Row],[PRODUCCION PARTIDAS ORIGINALES ACTUAL]]+CATEGORIAS[[#This Row],[PRODUCCION ADICIONALES ACTUAL]] -> 1.4494725e+08 | P36: 1.1338549e+08 | Q36: 31540254 | R36: =+CATEGORIAS[[#This Row],[PRODUCCION ANTERIOR]]+CATEGORIAS[[#This Row],[PRODUCCION ADICIONALES ANTERIOR]] -> 1.4492574e+08 | S36: 78474322 | U36: 0 | V36: =SUM(CATEGORIAS[[#This Row],[COSTO ACUMULADO AX]:[PROVISIONES]]) -> 78474322 | W36: 78474322 | Y36: 0 | Z36: =SUM(CATEGORIAS[[#This Row],[COSTO ACUMULADO ANTERIOR]:[PROVISIONES ANTERIOR]]) -> 78474322 | AA36: =ABS(+CATEGORIAS[[#This Row],[PRESUPUESTO FINAL PROYECTADO]]-CATEGORIAS[[#This Row],[TOTAL PRODUCCION ACTUAL]]) -> 0 | AD36: 0 | AE36: =SUM(CATEGORIAS[[#This Row],[INVENTARIO]:[PROYECCION DE COSTO DEL SALDO]]) -> 0 | AG36: =+CATEGORIAS[[#This Row],[PRESUPUESTO FINAL PROYECTADO]]-CATEGORIAS[[#This Row],[COSTO REAL]]-CATEGORIAS[[#This Row],[PROYECCION TOTAL DE COSTO]] -> 66472926
A37: 0Z01 | B37: 0D08 | C37: Rigger | D37: 11-1201-020G | E37: MAO CD - Equipos / Equipos / Rigger (G) | F37: SI | G37: 69826848 | H37: 69826848 | I37: 20104651 | J37: 2461979.8 | K37: 0 | L37: =CATEGORIAS[[#This Row],[ADICIONALES]]+CATEGORIAS[[#This Row],[POM]]+CATEGORIAS[[#This Row],[REAJUSTE PAGADO]]+CATEGORIAS[[#This Row],[REAJUSTE PROYECTADO]] -> 92393479 | M37: 72275121 | N37: 20118358 | O37: =+CATEGORIAS[[#This Row],[PRODUCCION PARTIDAS ORIGINALES ACTUAL]]+CATEGORIAS[[#This Row],[PRODUCCION ADICIONALES ACTUAL]] -> 92393479 | P37: 72275121 | Q37: 20104651 | R37: =+CATEGORIAS[[#This Row],[PRODUCCION ANTERIOR]]+CATEGORIAS[[#This Row],[PRODUCCION ADICIONALES ANTERIOR]] -> 92379772 | S37: 40245262 | U37: 0 | V37: =SUM(CATEGORIAS[[#This Row],[COSTO ACUMULADO AX]:[PROVISIONES]]) -> 40245262 | W37: 40245262 | Y37: 0 | Z37: =SUM(CATEGORIAS[[#This Row],[COSTO ACUMULADO ANTERIOR]:[PROVISIONES ANTERIOR]]) -> 40245262 | AA37: =ABS(+CATEGORIAS[[#This Row],[PRESUPUESTO FINAL PROYECTADO]]-CATEGORIAS[[#This Row],[TOTAL PRODUCCION ACTUAL]]) -> 0 | AD37: 0 | AE37: =SUM(CATEGORIAS[[#This Row],[INVENTARIO]:[PROYECCION DE COSTO DEL SALDO]]) -> 0 | AG37: =+CATEGORIAS[[#This Row],[PRESUPUESTO FINAL PROYECTADO]]-CATEGORIAS[[#This Row],[COSTO REAL]]-CATEGORIAS[[#This Row],[PROYECCION TOTAL DE COSTO]] -> 52148217
D38: 11-1201-030G | E38: MAO CD - Equipos / Equipos / Operador dpto Equipos (G) | F38: NO | G38: 0 | H38: 0 | I38: 0 | J38: 0 | K38: 0 | L38: =CATEGORIAS[[#This Row],[ADICIONALES]]+CATEGORIAS[[#This Row],[POM]]+CATEGORIAS[[#This Row],[REAJUSTE PAGADO]]+CATEGORIAS[[#This Row],[REAJUSTE PROYECTADO]] -> 0 | M38: 0 | N38: 0 | O38: =+CATEGORIAS[[#This Row],[PRODUCCION PARTIDAS ORIGINALES ACTUAL]]+CATEGORIAS[[#This Row],[PRODUCCION ADICIONALES ACTUAL]] -> 0 | P38: 0 | Q38: 0 | R38: =+CATEGORIAS[[#This Row],[PRODUCCION ANTERIOR]]+CATEGORIAS[[#This Row],[PRODUCCION ADICIONALES ANTERIOR]] -> 0 | S38: 0 | U38: 0 | V38: =SUM(CATEGORIAS[[#This Row],[COSTO ACUMULADO AX]:[PROVISIONES]]) -> 0 | W38: 0 | Y38: 0 | Z38: =SUM(CATEGORIAS[[#This Row],[COSTO ACUMULADO ANTERIOR]:[PROVISIONES ANTERIOR]]) -> 0 | AA38: =ABS(+CATEGORIAS[[#This Row],[PRESUPUESTO FINAL PROYECTADO]]-CATEGORIAS[[#This Row],[TOTAL PRODUCCION ACTUAL]]) -> 0 | AD38: 0 | AE38: =SUM(CATEGORIAS[[#This Row],[INVENTARIO]:[PROYECCION DE COSTO DEL SALDO]]) -> 0 | AG38: =+CATEGORIAS[[#This Row],[PRESUPUESTO FINAL PROYECTADO]]-CATEGORIAS[[#This Row],[COSTO REAL]]-CATEGORIAS[[#This Row],[PROYECCION TOTAL DE COSTO]] -> 0
D39: 11-1201-040G | E39: MAO CD - Equipos / Equipos / Rigger dpto Equipos(G) | F39: NO | G39: 0 | H39: 0 | I39: 0 | J39: 0 | K39: 0 | L39: =CATEGORIAS[[#This Row],[ADICIONALES]]+CATEGORIAS[[#This Row],[POM]]+CATEGORIAS[[#This Row],[REAJUSTE PAGADO]]+CATEGORIAS[[#This Row],[REAJUSTE PROYECTADO]] -> 0 | M39: 0 | N39: 0 | O39: =+CATEGORIAS[[#This Row],[PRODUCCION PARTIDAS ORIGINALES ACTUAL]]+CATEGORIAS[[#This Row],[PRODUCCION ADICIONALES ACTUAL]] -> 0 | P39: 0 | Q39: 0 | R39: =+CATEGORIAS[[#This Row],[PRODUCCION ANTERIOR]]+CATEGORIAS[[#This Row],[PRODUCCION ADICIONALES ANTERIOR]] -> 0 | S39: 0 | U39: 0 | V39: =SUM(CATEGORIAS[[#This Row],[COSTO ACUMULADO AX]:[PROVISIONES]]) -> 0 | W39: 0 | Y39: 0 | Z39: =SUM(CATEGORIAS[[#This Row],[COSTO ACUMULADO ANTERIOR]:[PROVISIONES ANTERIOR]]) -> 0 | AA39: =ABS(+CATEGORIAS[[#This Row],[PRESUPUESTO FINAL PROYECTADO]]-CATEGORIAS[[#This Row],[TOTAL PRODUCCION ACTUAL]]) -> 0 | AD39: 0 | AE39: =SUM(CATEGORIAS[[#This Row],[INVENTARIO]:[PROYECCION DE COSTO DEL SALDO]]) -> 0 | AG39: =+CATEGORIAS[[#This Row],[PRESUPUESTO FINAL PROYECTADO]]-CATEGORIAS[[#This Row],[COSTO REAL]]-CATEGORIAS[[#This Row],[PROYECCION TOTAL DE COSTO]] -> 0
D40: 11-1307-000G | E40: MAO CD - Estanque / Soldadura (G) | F40: NO | G40: 0 | H40: 0 | I40: 0 | J40: 0 | K40: 0 | L40: =CATEGORIAS[[#This Row],[ADICIONALES]]+CATEGORIAS[[#This Row],[POM]]+CATEGORIAS[[#This Row],[REAJUSTE PAGADO]]+CATEGORIAS[[#This Row],[REAJUSTE PROYECTADO]] -> 0 | M40: 0 | N40: 0 | O40: =+CATEGORIAS[[#This Row],[PRODUCCION PARTIDAS ORIGINALES ACTUAL]]+CATEGORIAS[[#This Row],[PRODUCCION ADICIONALES ACTUAL]] -> 0 | P40: 0 | Q40: 0 | R40: =+CATEGORIAS[[#This Row],[PRODUCCION ANTERIOR]]+CATEGORIAS[[#This Row],[PRODUCCION ADICIONALES ANTERIOR]] -> 0 | S40: 0 | U40: 0 | V40: =SUM(CATEGORIAS[[#This Row],[COSTO ACUMULADO AX]:[PROVISIONES]]) -> 0 | W40: 0 | Y40: 0 | Z40: =SUM(CATEGORIAS[[#This Row],[COSTO ACUMULADO ANTERIOR]:[PROVISIONES ANTERIOR]]) -> 0 | AA40: =ABS(+CATEGORIAS[[#This Row],[PRESUPUESTO FINAL PROYECTADO]]-CATEGORIAS[[#This Row],[TOTAL PRODUCCION ACTUAL]]) -> 0 | AD40: 0 | AE40: =SUM(CATEGORIAS[[#This Row],[INVENTARIO]:[PROYECCION DE COSTO DEL SALDO]]) -> 0 | AG40: =+CATEGORIAS[[#This Row],[PRESUPUESTO FINAL PROYECTADO]]-CATEGORIAS[[#This Row],[COSTO REAL]]-CATEGORIAS[[#This Row],[PROYECCION TOTAL DE COSTO]] -> 0
D41: 11-1308-000G | E41: MAO CD - Estanque / Montajes (G) | F41: NO | G41: 0 | H41: 0 | I41: 0 | J41: 0 | K41: 0 | L41: =CATEGORIAS[[#This Row],[ADICIONALES]]+CATEGORIAS[[#This Row],[POM]]+CATEGORIAS[[#This Row],[REAJUSTE PAGADO]]+CATEGORIAS[[#This Row],[REAJUSTE PROYECTADO]] -> 0 | M41: 0 | N41: 0 | O41: =+CATEGORIAS[[#This Row],[PRODUCCION PARTIDAS ORIGINALES ACTUAL]]+CATEGORIAS[[#This Row],[PRODUCCION ADICIONALES ACTUAL]] -> 0 | P41: 0 | Q41: 0 | R41: =+CATEGORIAS[[#This Row],[PRODUCCION ANTERIOR]]+CATEGORIAS[[#This Row],[PRODUCCION ADICIONALES ANTERIOR]] -> 0 | S41: 0 | U41: 0 | V41: =SUM(CATEGORIAS[[#This Row],[COSTO ACUMULADO AX]:[PROVISIONES]]) -> 0 | W41: 0 | Y41: 0 | Z41: =SUM(CATEGORIAS[[#This Row],[COSTO ACUMULADO ANTERIOR]:[PROVISIONES ANTERIOR]]) -> 0 | AA41: =ABS(+CATEGORIAS[[#This Row],[PRESUPUESTO FINAL PROYECTADO]]-CATEGORIAS[[#This Row],[TOTAL PRODUCCION ACTUAL]]) -> 0 | AD41: 0 | AE41: =SUM(CATEGORIAS[[#This Row],[INVENTARIO]:[PROYECCION DE COSTO DEL SALDO]]) -> 0 | AG41: =+CATEGORIAS[[#This Row],[PRESUPUESTO FINAL PROYECTADO]]-CATEGORIAS[[#This Row],[COSTO REAL]]-CATEGORIAS[[#This Row],[PROYECCION TOTAL DE COSTO]] -> 0
D42: 11-7101-000G | E42: MAO CD - Multas (G) | F42: NO | G42: 0 | H42: 0 | I42: 0 | J42: 0 | K42: 0 | L42: =CATEGORIAS[[#This Row],[ADICIONALES]]+CATEGORIAS[[#This Row],[POM]]+CATEGORIAS[[#This Row],[REAJUSTE PAGADO]]+CATEGORIAS[[#This Row],[REAJUSTE PROYECTADO]] -> 0 | M42: 0 | N42: 0 | O42: =+CATEGORIAS[[#This Row],[PRODUCCION PARTIDAS ORIGINALES ACTUAL]]+CATEGORIAS[[#This Row],[PRODUCCION ADICIONALES ACTUAL]] -> 0 | P42: 0 | Q42: 0 | R42: =+CATEGORIAS[[#This Row],[PRODUCCION ANTERIOR]]+CATEGORIAS[[#This Row],[PRODUCCION ADICIONALES ANTERIOR]] -> 0 | S42: 0 | U42: 0 | V42: =SUM(CATEGORIAS[[#This Row],[COSTO ACUMULADO AX]:[PROVISIONES]]) -> 0 | W42: 0 | Y42: 0 | Z42: =SUM(CATEGORIAS[[#This Row],[COSTO ACUMULADO ANTERIOR]:[PROVISIONES ANTERIOR]]) -> 0 | AA42: =ABS(+CATEGORIAS[[#This Row],[PRESUPUESTO FINAL PROYECTADO]]-CATEGORIAS[[#This Row],[TOTAL PRODUCCION ACTUAL]]) -> 0 | AD42: 0 | AE42: =SUM(CATEGORIAS[[#This Row],[INVENTARIO]:[PROYECCION DE COSTO DEL SALDO]]) -> 0 | AG42: =+CATEGORIAS[[#This Row],[PRESUPUESTO FINAL PROYECTADO]]-CATEGORIAS[[#This Row],[COSTO REAL]]-CATEGORIAS[[#This Row],[PROYECCION TOTAL DE COSTO]] -> 0
A43: 1F01 | B43: 1F01 | C43: Staff Superior | D43: 12-5101-000G | E43: MAO CI - Staff Superior / Staff Superior (G) | F43: SI | G43: 2.6331137e+08 | H43: 2.6331137e+08 | I43: 1.1722702e+08 | J43: 9283925.7 | K43: 0 | L43: =CATEGORIAS[[#This Row],[ADICIONALES]]+CATEGORIAS[[#This Row],[POM]]+CATEGORIAS[[#This Row],[REAJUSTE PAGADO]]+CATEGORIAS[[#This Row],[REAJUSTE PROYECTADO]] -> 3.8982231e+08 | M43: 2.7254361e+08 | N43: 1.1727871e+08 | O43: =+CATEGORIAS[[#This Row],[PRODUCCION PARTIDAS ORIGINALES ACTUAL]]+CATEGORIAS[[#This Row],[PRODUCCION ADICIONALES ACTUAL]] -> 3.8982231e+08 | P43: 2.7254361e+08 | Q43: 1.1722702e+08 | R43: =+CATEGORIAS[[#This Row],[PRODUCCION ANTERIOR]]+CATEGORIAS[[#This Row],[PRODUCCION ADICIONALES ANTERIOR]] -> 3.8977063e+08 | S43: 3.5409637e+08 | U43: 0 | V43: =SUM(CATEGORIAS[[#This Row],[COSTO ACUMULADO AX]:[PROVISIONES]]) -> 3.5409637e+08 | W43: 3.2909892e+08 | Y43: 0 | Z43: =SUM(CATEGORIAS[[#This Row],[COSTO ACUMULADO ANTERIOR]:[PROVISIONES ANTERIOR]]) -> 3.2909892e+08 | AA43: =ABS(+CATEGORIAS[[#This Row],[PRESUPUESTO FINAL PROYECTADO]]-CATEGORIAS[[#This Row],[TOTAL PRODUCCION ACTUAL]]) -> 0 | AD43: 1652803.5 | AE43: =SUM(CATEGORIAS[[#This Row],[INVENTARIO]:[PROYECCION DE COSTO DEL SALDO]]) -> 1652803.5 | AG43: =+CATEGORIAS[[#This Row],[PRESUPUESTO FINAL PROYECTADO]]-CATEGORIAS[[#This Row],[COSTO REAL]]-CATEGORIAS[[#This Row],[PROYECCION TOTAL DE COSTO]] -> 34073137
A44: 1F02 | B44: 1F02 | C44: Oficina Técnica | D44: 12-5201-000G | E44: MAO CI - Oficina Técnica / Oficina Técnica (G) | F44: SI | G44: 80469295 | H44: 80469295 | I44: 40759475 | J44: 2837214.9 | K44: 0 | L44: =CATEGORIAS[[#This Row],[ADICIONALES]]+CATEGORIAS[[#This Row],[POM]]+CATEGORIAS[[#This Row],[REAJUSTE PAGADO]]+CATEGORIAS[[#This Row],[REAJUSTE PROYECTADO]] -> 1.2406598e+08 | M44: 83290714 | N44: 40775271 | O44: =+CATEGORIAS[[#This Row],[PRODUCCION PARTIDAS ORIGINALES ACTUAL]]+CATEGORIAS[[#This Row],[PRODUCCION ADICIONALES ACTUAL]] -> 1.2406598e+08 | P44: 83290714 | Q44: 40759475 | R44: =+CATEGORIAS[[#This Row],[PRODUCCION ANTERIOR]]+CATEGORIAS[[#This Row],[PRODUCCION ADICIONALES ANTERIOR]] -> 1.2405019e+08 | S44: 1.2277887e+08 | U44: 0 | V44: =SUM(CATEGORIAS[[#This Row],[COSTO ACUMULADO AX]:[PROVISIONES]]) -> 1.2277887e+08 | W44: 1.2277887e+08 | Y44: 0 | Z44: =SUM(CATEGORIAS[[#This Row],[COSTO ACUMULADO ANTERIOR]:[PROVISIONES ANTERIOR]]) -> 1.2277887e+08 | AA44: =ABS(+CATEGORIAS[[#This Row],[PRESUPUESTO FINAL PROYECTADO]]-CATEGORIAS[[#This Row],[TOTAL PRODUCCION ACTUAL]]) -> 1.4901161e-08 | AD44: 0 | AE44: =SUM(CATEGORIAS[[#This Row],[INVENTARIO]:[PROYECCION DE COSTO DEL SALDO]]) -> 0 | AG44: =+CATEGORIAS[[#This Row],[PRESUPUESTO FINAL PROYECTADO]]-CATEGORIAS[[#This Row],[COSTO REAL]]-CATEGORIAS[[#This Row],[PROYECCION TOTAL DE COSTO]] -> 1287118.1
A45: 1F03 | B45: 1F03 | C45: Supervisión | D45: 12-5301-000G | E45: MAO CI - Supervisión / Supervisión (G) | F45: SI | G45: 97274459 | H45: 97274459 | I45: 70947696 | J45: 3429737.4 | K45: 0 | L45: =CATEGORIAS[[#This Row],[ADICIONALES]]+CATEGORIAS[[#This Row],[POM]]+CATEGORIAS[[#This Row],[REAJUSTE PAGADO]]+CATEGORIAS[[#This Row],[REAJUSTE PROYECTADO]] -> 1.7165189e+08 | M45: 1.006851e+08 | N45: 70966791 | O45: =+CATEGORIAS[[#This Row],[PRODUCCION PARTIDAS ORIGINALES ACTUAL]]+CATEGORIAS[[#This Row],[PRODUCCION ADICIONALES ACTUAL]] -> 1.7165189e+08 | P45: 1.006851e+08 | Q45: 70947696 | R45: =+CATEGORIAS[[#This Row],[PRODUCCION ANTERIOR]]+CATEGORIAS[[#This Row],[PRODUCCION ADICIONALES ANTERIOR]] -> 1.716328e+08 | S45: 121259605 | U45: 0 | V45: =SUM(CATEGORIAS[[#This Row],[COSTO ACUMULADO AX]:[PROVISIONES]]) -> 121259605 | W45: 121259605 | Y45: 0 | Z45: =SUM(CATEGORIAS[[#This Row],[COSTO ACUMULADO ANTERIOR]:[PROVISIONES ANTERIOR]]) -> 121259605 | AA45: =ABS(+CATEGORIAS[[#This Row],[PRESUPUESTO FINAL PROYECTADO]]-CATEGORIAS[[#This Row],[TOTAL PRODUCCION ACTUAL]]) -> 2.9802322e-08 | AD45: 0 | AE45: =SUM(CATEGORIAS[[#This Row],[INVENTARIO]:[PROYECCION DE COSTO DEL SALDO]]) -> 0 | AG45: =+CATEGORIAS[[#This Row],[PRESUPUESTO FINAL PROYECTADO]]-CATEGORIAS[[#This Row],[COSTO REAL]]-CATEGORIAS[[#This Row],[PROYECCION TOTAL DE COSTO]] -> 50392288
A46: 1F06 | B46: 1F06 | C46: Administración | D46: 12-5401-000G | E46: MAO CI - Administración / Administración (G) | F46: SI | G46: 55188181 | H46: 55188181 | I46: 34340825 | J46: 1945844.5 | K46: 0 | L46: =CATEGORIAS[[#This Row],[ADICIONALES]]+CATEGORIAS[[#This Row],[POM]]+CATEGORIAS[[#This Row],[REAJUSTE PAGADO]]+CATEGORIAS[[#This Row],[REAJUSTE PROYECTADO]] -> 91474851 | M46: 57123192 | N46: 34351659 | O46: =+CATEGORIAS[[#This Row],[PRODUCCION PARTIDAS ORIGINALES ACTUAL]]+CATEGORIAS[[#This Row],[PRODUCCION ADICIONALES ACTUAL]] -> 91474851 | P46: 57123192 | Q46: 34340825 | R46: =+CATEGORIAS[[#This Row],[PRODUCCION ANTERIOR]]+CATEGORIAS[[#This Row],[PRODUCCION ADICIONALES ANTERIOR]] -> 91464017 | S46: 89355743 | U46: 0 | V46: =SUM(CATEGORIAS[[#This Row],[COSTO ACUMULADO AX]:[PROVISIONES]]) -> 89355743 | W46: 89355743 | Y46: 0 | Z46: =SUM(CATEGORIAS[[#This Row],[COSTO ACUMULADO ANTERIOR]:[PROVISIONES ANTERIOR]]) -> 89355743 | AA46: =ABS(+CATEGORIAS[[#This Row],[PRESUPUESTO FINAL PROYECTADO]]-CATEGORIAS[[#This Row],[TOTAL PRODUCCION ACTUAL]]) -> 0 | AD46: 0 | AE46: =SUM(CATEGORIAS[[#This Row],[INVENTARIO]:[PROYECCION DE COSTO DEL SALDO]]) -> 0 | AG46: =+CATEGORIAS[[#This Row],[PRESUPUESTO FINAL PROYECTADO]]-CATEGORIAS[[#This Row],[COSTO REAL]]-CATEGORIAS[[#This Row],[PROYECCION TOTAL DE COSTO]] -> 2119107.6
A47: 1F04 | B47: 1F04 | C47: Prevención De Riesgos | D47: 12-5501-000G | E47: MAO CI - Prevención De Riesgos / Prevención De Riesgos (G) | F47: SI | G47: 97189487 | H47: 97189487 | I47: 46236102 | J47: 3426741.4 | K47: 0 | L47: =CATEGORIAS[[#This Row],[ADICIONALES]]+CATEGORIAS[[#This Row],[POM]]+CATEGORIAS[[#This Row],[REAJUSTE PAGADO]]+CATEGORIAS[[#This Row],[REAJUSTE PROYECTADO]] -> 1.4685233e+08 | M47: 1.0059715e+08 | N47: 46255180 | O47: =+CATEGORIAS[[#This Row],[PRODUCCION PARTIDAS ORIGINALES ACTUAL]]+CATEGORIAS[[#This Row],[PRODUCCION ADICIONALES ACTUAL]] -> 1.4685233e+08 | P47: 1.0059715e+08 | Q47: 46236102 | R47: =+CATEGORIAS[[#This Row],[PRODUCCION ANTERIOR]]+CATEGORIAS[[#This Row],[PRODUCCION ADICIONALES ANTERIOR]] -> 1.4683325e+08 | S47: 84690890 | U47: 0 | V47: =SUM(CATEGORIAS[[#This Row],[COSTO ACUMULADO AX]:[PROVISIONES]]) -> 84690890 | W47: 84690890 | Y47: 0 | Z47: =SUM(CATEGORIAS[[#This Row],[COSTO ACUMULADO ANTERIOR]:[PROVISIONES ANTERIOR]]) -> 84690890 | AA47: =ABS(+CATEGORIAS[[#This Row],[PRESUPUESTO FINAL PROYECTADO]]-CATEGORIAS[[#This Row],[TOTAL PRODUCCION ACTUAL]]) -> 0 | AD47: 0 | AE47: =SUM(CATEGORIAS[[#This Row],[INVENTARIO]:[PROYECCION DE COSTO DEL SALDO]]) -> 0 | AG47: =+CATEGORIAS[[#This Row],[PRESUPUESTO FINAL PROYECTADO]]-CATEGORIAS[[#This Row],[COSTO REAL]]-CATEGORIAS[[#This Row],[PROYECCION TOTAL DE COSTO]] -> 62161440
A48: 1F05 | B48: 1F05 | C48: Calidad | D48: 12-5601-000G | E48: MAO CI - Control De Calidad / Control De Calidad (G) | F48: SI | G48: 39901820 | H48: 39901820 | I48: 19964509 | J48: 1406872.5 | K48: 0 | L48: =CATEGORIAS[[#This Row],[ADICIONALES]]+CATEGORIAS[[#This Row],[POM]]+CATEGORIAS[[#This Row],[REAJUSTE PAGADO]]+CATEGORIAS[[#This Row],[REAJUSTE PROYECTADO]] -> 61273201 | M48: 41300860 | N48: 19972342 | O48: =+CATEGORIAS[[#This Row],[PRODUCCION PARTIDAS ORIGINALES ACTUAL]]+CATEGORIAS[[#This Row],[PRODUCCION ADICIONALES ACTUAL]] -> 61273201 | P48: 41300860 | Q48: 19964509 | R48: =+CATEGORIAS[[#This Row],[PRODUCCION ANTERIOR]]+CATEGORIAS[[#This Row],[PRODUCCION ADICIONALES ANTERIOR]] -> 61265368 | S48: 44849347 | U48: 0 | V48: =SUM(CATEGORIAS[[#This Row],[COSTO ACUMULADO AX]:[PROVISIONES]]) -> 44849347 | W48: 44849347 | Y48: 0 | Z48: =SUM(CATEGORIAS[[#This Row],[COSTO ACUMULADO ANTERIOR]:[PROVISIONES ANTERIOR]]) -> 44849347 | AA48: =ABS(+CATEGORIAS[[#This Row],[PRESUPUESTO FINAL PROYECTADO]]-CATEGORIAS[[#This Row],[TOTAL PRODUCCION ACTUAL]]) -> 7.4505806e-09 | AD48: 0 | AE48: =SUM(CATEGORIAS[[#This Row],[INVENTARIO]:[PROYECCION DE COSTO DEL SALDO]]) -> 0 | AG48: =+CATEGORIAS[[#This Row],[PRESUPUESTO FINAL PROYECTADO]]-CATEGORIAS[[#This Row],[COSTO REAL]]-CATEGORIAS[[#This Row],[PROYECCION TOTAL DE COSTO]] -> 16423854
A49: 1F07 | B49: 1F07 | C49: Servicios | D49: 12-5701-000G | E49: MAO CI - Servicios / Servicios (G) | F49: SI | G49: 67752175 | H49: 67752175 | I49: 29545182 | J49: 2388830.2 | K49: 0 | L49: =CATEGORIAS[[#This Row],[ADICIONALES]]+CATEGORIAS[[#This Row],[POM]]+CATEGORIAS[[#This Row],[REAJUSTE PAGADO]]+CATEGORIAS[[#This Row],[REAJUSTE PROYECTADO]] -> 99686187 | M49: 70127705 | N49: 29558482 | O49: =+CATEGORIAS[[#This Row],[PRODUCCION PARTIDAS ORIGINALES ACTUAL]]+CATEGORIAS[[#This Row],[PRODUCCION ADICIONALES ACTUAL]] -> 99686187 | P49: 70127705 | Q49: 29545182 | R49: =+CATEGORIAS[[#This Row],[PRODUCCION ANTERIOR]]+CATEGORIAS[[#This Row],[PRODUCCION ADICIONALES ANTERIOR]] -> 99672887 | S49: 145760303 | U49: 0 | V49: =SUM(CATEGORIAS[[#This Row],[COSTO ACUMULADO AX]:[PROVISIONES]]) -> 145760303 | W49: 136346467 | Y49: 2473412 | Z49: =SUM(CATEGORIAS[[#This Row],[COSTO ACUMULADO ANTERIOR]:[PROVISIONES ANTERIOR]]) -> 138819879 | AA49: =ABS(+CATEGORIAS[[#This Row],[PRESUPUESTO FINAL PROYECTADO]]-CATEGORIAS[[#This Row],[TOTAL PRODUCCION ACTUAL]]) -> 0 | AD49: 0 | AE49: =SUM(CATEGORIAS[[#This Row],[INVENTARIO]:[PROYECCION DE COSTO DEL SALDO]]) -> 0 | AG49: =+CATEGORIAS[[#This Row],[PRESUPUESTO FINAL PROYECTADO]]-CATEGORIAS[[#This Row],[COSTO REAL]]-CATEGORIAS[[#This Row],[PROYECCION TOTAL DE COSTO]] -> -46074116
A50: 1F08 | B50: 1F08 | C50: Topografía | D50: 12-5902-000G | E50: MAO CI - Servicios / Topografía (G) | F50: SI | G50: 44741710 | H50: 44741710 | I50: 18619729 | J50: 1577519.1 | K50: 0 | L50: =CATEGORIAS[[#This Row],[ADICIONALES]]+CATEGORIAS[[#This Row],[POM]]+CATEGORIAS[[#This Row],[REAJUSTE PAGADO]]+CATEGORIAS[[#This Row],[REAJUSTE PROYECTADO]] -> 64938958 | M50: 46310447 | N50: 18628512 | O50: =+CATEGORIAS[[#This Row],[PRODUCCION PARTIDAS ORIGINALES ACTUAL]]+CATEGORIAS[[#This Row],[PRODUCCION ADICIONALES ACTUAL]] -> 64938958 | P50: 46310447 | Q50: 18619729 | R50: =+CATEGORIAS[[#This Row],[PRODUCCION ANTERIOR]]+CATEGORIAS[[#This Row],[PRODUCCION ADICIONALES ANTERIOR]] -> 64930176 | S50: 80582133 | U50: 0 | V50: =SUM(CATEGORIAS[[#This Row],[COSTO ACUMULADO AX]:[PROVISIONES]]) -> 80582133 | W50: 80582133 | Y50: 0 | Z50: =SUM(CATEGORIAS[[#This Row],[COSTO ACUMULADO ANTERIOR]:[PROVISIONES ANTERIOR]]) -> 80582133 | AA50: =ABS(+CATEGORIAS[[#This Row],[PRESUPUESTO FINAL PROYECTADO]]-CATEGORIAS[[#This Row],[TOTAL PRODUCCION ACTUAL]]) -> 0 | AD50: 0 | AE50: =SUM(CATEGORIAS[[#This Row],[INVENTARIO]:[PROYECCION DE COSTO DEL SALDO]]) -> 0 | AG50: =+CATEGORIAS[[#This Row],[PRESUPUESTO FINAL PROYECTADO]]-CATEGORIAS[[#This Row],[COSTO REAL]]-CATEGORIAS[[#This Row],[PROYECCION TOTAL DE COSTO]] -> -15643175
D51: 12-6001-000G | E51: MAO CI - Prov. Pers. Planta / PROVAC (G) | F51: NO | G51: 0 | H51: 0 | I51: 0 | J51: 0 | K51: 0 | L51: =CATEGORIAS[[#This Row],[ADICIONALES]]+CATEGORIAS[[#This Row],[POM]]+CATEGORIAS[[#This Row],[REAJUSTE PAGADO]]+CATEGORIAS[[#This Row],[REAJUSTE PROYECTADO]] -> 0 | M51: 0 | N51: 0 | O51: =+CATEGORIAS[[#This Row],[PRODUCCION PARTIDAS ORIGINALES ACTUAL]]+CATEGORIAS[[#This Row],[PRODUCCION ADICIONALES ACTUAL]] -> 0 | P51: 0 | Q51: 0 | R51: =+CATEGORIAS[[#This Row],[PRODUCCION ANTERIOR]]+CATEGORIAS[[#This Row],[PRODUCCION ADICIONALES ANTERIOR]] -> 0 | S51: 0 | U51: 0 | V51: =SUM(CATEGORIAS[[#This Row],[COSTO ACUMULADO AX]:[PROVISIONES]]) -> 0 | W51: 0 | Y51: 0 | Z51: =SUM(CATEGORIAS[[#This Row],[COSTO ACUMULADO ANTERIOR]:[PROVISIONES ANTERIOR]]) -> 0 | AA51: =ABS(+CATEGORIAS[[#This Row],[PRESUPUESTO FINAL PROYECTADO]]-CATEGORIAS[[#This Row],[TOTAL PRODUCCION ACTUAL]]) -> 0 | AD51: 0 | AE51: =SUM(CATEGORIAS[[#This Row],[INVENTARIO]:[PROYECCION DE COSTO DEL SALDO]]) -> 0 | AG51: =+CATEGORIAS[[#This Row],[PRESUPUESTO FINAL PROYECTADO]]-CATEGORIAS[[#This Row],[COSTO REAL]]-CATEGORIAS[[#This Row],[PROYECCION TOTAL DE COSTO]] -> 0
D52: 12-6002-000G | E52: MAO CI - Prov. Pers. Planta / PIAS (G) | F52: NO | G52: 0 | H52: 0 | I52: 0 | J52: 0 | K52: 0 | L52: =CATEGORIAS[[#This Row],[ADICIONALES]]+CATEGORIAS[[#This Row],[POM]]+CATEGORIAS[[#This Row],[REAJUSTE PAGADO]]+CATEGORIAS[[#This Row],[REAJUSTE PROYECTADO]] -> 0 | M52: 0 | N52: 0 | O52: =+CATEGORIAS[[#This Row],[PRODUCCION PARTIDAS ORIGINALES ACTUAL]]+CATEGORIAS[[#This Row],[PRODUCCION ADICIONALES ACTUAL]] -> 0 | P52: 0 | Q52: 0 | R52: =+CATEGORIAS[[#This Row],[PRODUCCION ANTERIOR]]+CATEGORIAS[[#This Row],[PRODUCCION ADICIONALES ANTERIOR]] -> 0 | S52: 0 | U52: 0 | V52: =SUM(CATEGORIAS[[#This Row],[COSTO ACUMULADO AX]:[PROVISIONES]]) -> 0 | W52: 0 | Y52: 0 | Z52: =SUM(CATEGORIAS[[#This Row],[COSTO ACUMULADO ANTERIOR]:[PROVISIONES ANTERIOR]]) -> 0 | AA52: =ABS(+CATEGORIAS[[#This Row],[PRESUPUESTO FINAL PROYECTADO]]-CATEGORIAS[[#This Row],[TOTAL PRODUCCION ACTUAL]]) -> 0 | AD52: 0 | AE52: =SUM(CATEGORIAS[[#This Row],[INVENTARIO]:[PROYECCION DE COSTO DEL SALDO]]) -> 0 | AG52: =+CATEGORIAS[[#This Row],[PRESUPUESTO FINAL PROYECTADO]]-CATEGORIAS[[#This Row],[COSTO REAL]]-CATEGORIAS[[#This Row],[PROYECCION TOTAL DE COSTO]] -> 0
D53: 12-7101-000G | E53: MAO CI - Multas (G) | F53: NO | G53: 0 | H53: 0 | I53: 0 | J53: 0 | K53: 0 | L53: =CATEGORIAS[[#This Row],[ADICIONALES]]+CATEGORIAS[[#This Row],[POM]]+CATEGORIAS[[#This Row],[REAJUSTE PAGADO]]+CATEGORIAS[[#This Row],[REAJUSTE PROYECTADO]] -> 0 | M53: 0 | N53: 0 | O53: =+CATEGORIAS[[#This Row],[PRODUCCION PARTIDAS ORIGINALES ACTUAL]]+CATEGORIAS[[#This Row],[PRODUCCION ADICIONALES ACTUAL]] -> 0 | P53: 0 | Q53: 0 | R53: =+CATEGORIAS[[#This Row],[PRODUCCION ANTERIOR]]+CATEGORIAS[[#This Row],[PRODUCCION ADICIONALES ANTERIOR]] -> 0 | S53: 0 | U53: 0 | V53: =SUM(CATEGORIAS[[#This Row],[COSTO ACUMULADO AX]:[PROVISIONES]]) -> 0 | W53: 0 | Y53: 0 | Z53: =SUM(CATEGORIAS[[#This Row],[COSTO ACUMULADO ANTERIOR]:[PROVISIONES ANTERIOR]]) -> 0 | AA53: =ABS(+CATEGORIAS[[#This Row],[PRESUPUESTO FINAL PROYECTADO]]-CATEGORIAS[[#This Row],[TOTAL PRODUCCION ACTUAL]]) -> 0 | AD53: 0 | AE53: =SUM(CATEGORIAS[[#This Row],[INVENTARIO]:[PROYECCION DE COSTO DEL SALDO]]) -> 0 | AG53: =+CATEGORIAS[[#This Row],[PRESUPUESTO FINAL PROYECTADO]]-CATEGORIAS[[#This Row],[COSTO REAL]]-CATEGORIAS[[#This Row],[PROYECCION TOTAL DE COSTO]] -> 0
D54: 12-9999-990G | E54: MO / Personal Inclusion / (G) | F54: NO | G54: 0 | H54: 0 | I54: 0 | J54: 0 | K54: 0 | L54: =CATEGORIAS[[#This Row],[ADICIONALES]]+CATEGORIAS[[#This Row],[POM]]+CATEGORIAS[[#This Row],[REAJUSTE PAGADO]]+CATEGORIAS[[#This Row],[REAJUSTE PROYECTADO]] -> 0 | M54: 0 | N54: 0 | O54: =+CATEGORIAS[[#This Row],[PRODUCCION PARTIDAS ORIGINALES ACTUAL]]+CATEGORIAS[[#This Row],[PRODUCCION ADICIONALES ACTUAL]] -> 0 | P54: 0 | Q54: 0 | R54: =+CATEGORIAS[[#This Row],[PRODUCCION ANTERIOR]]+CATEGORIAS[[#This Row],[PRODUCCION ADICIONALES ANTERIOR]] -> 0 | S54: 0 | U54: 0 | V54: =SUM(CATEGORIAS[[#This Row],[COSTO ACUMULADO AX]:[PROVISIONES]]) -> 0 | W54: 0 | Y54: 0 | Z54: =SUM(CATEGORIAS[[#This Row],[COSTO ACUMULADO ANTERIOR]:[PROVISIONES ANTERIOR]]) -> 0 | AA54: =ABS(+CATEGORIAS[[#This Row],[PRESUPUESTO FINAL PROYECTADO]]-CATEGORIAS[[#This Row],[TOTAL PRODUCCION ACTUAL]]) -> 0 | AD54: 0 | AE54: =SUM(CATEGORIAS[[#This Row],[INVENTARIO]:[PROYECCION DE COSTO DEL SALDO]]) -> 0 | AG54: =+CATEGORIAS[[#This Row],[PRESUPUESTO FINAL PROYECTADO]]-CATEGORIAS[[#This Row],[COSTO REAL]]-CATEGORIAS[[#This Row],[PROYECCION TOTAL DE COSTO]] -> 0
A55: 0A02 | B55: 0B01 | C55: Civil | D55: 21-0102-010A | E55: MAT CD - Civil / Hormigón / Hormigón (A) | F55: SI | G55: 2.2987048e+08 | H55: 2.0513554e+08 | I55: 0 | J55: 7232741.6 | K55: 0 | L55: =CATEGORIAS[[#This Row],[ADICIONALES]]+CATEGORIAS[[#This Row],[POM]]+CATEGORIAS[[#This Row],[REAJUSTE PAGADO]]+CATEGORIAS[[#This Row],[REAJUSTE PROYECTADO]] -> 2.1236828e+08 | M55: 2.1232801e+08 | N55: 40268.231 | O55: =+CATEGORIAS[[#This Row],[PRODUCCION PARTIDAS ORIGINALES ACTUAL]]+CATEGORIAS[[#This Row],[PRODUCCION ADICIONALES ACTUAL]] -> 2.1236828e+08 | P55: 2.1232801e+08 | Q55: 0 | R55: =+CATEGORIAS[[#This Row],[PRODUCCION ANTERIOR]]+CATEGORIAS[[#This Row],[PRODUCCION ADICIONALES ANTERIOR]] -> 2.1232801e+08 | S55: 237696926 | U55: 0 | V55: =SUM(CATEGORIAS[[#This Row],[COSTO ACUMULADO AX]:[PROVISIONES]]) -> 237696926 | W55: 231456519 | Y55: 0 | Z55: =SUM(CATEGORIAS[[#This Row],[COSTO ACUMULADO ANTERIOR]:[PROVISIONES ANTERIOR]]) -> 231456519 | AA55: =ABS(+CATEGORIAS[[#This Row],[PRESUPUESTO FINAL PROYECTADO]]-CATEGORIAS[[#This Row],[TOTAL PRODUCCION ACTUAL]]) -> 0 | AD55: 0 | AE55: =SUM(CATEGORIAS[[#This Row],[INVENTARIO]:[PROYECCION DE COSTO DEL SALDO]]) -> 0 | AG55: =+CATEGORIAS[[#This Row],[PRESUPUESTO FINAL PROYECTADO]]-CATEGORIAS[[#This Row],[COSTO REAL]]-CATEGORIAS[[#This Row],[PROYECCION TOTAL DE COSTO]] -> -25328647
D56: 21-0102-010G | E56: MAT CD - Civil / Hormigón / Hormigón (G) | F56: NO | G56: 0 | H56: 0 | I56: 0 | J56: 0 | K56: 0 | L56: =CATEGORIAS[[#This Row],[ADICIONALES]]+CATEGORIAS[[#This Row],[POM]]+CATEGORIAS[[#This Row],[REAJUSTE PAGADO]]+CATEGORIAS[[#This Row],[REAJUSTE PROYECTADO]] -> 0 | M56: 0 | N56: 0 | O56: =+CATEGORIAS[[#This Row],[PRODUCCION PARTIDAS ORIGINALES ACTUAL]]+CATEGORIAS[[#This Row],[PRODUCCION ADICIONALES ACTUAL]] -> 0 | P56: 0 | Q56: 0 | R56: =+CATEGORIAS[[#This Row],[PRODUCCION ANTERIOR]]+CATEGORIAS[[#This Row],[PRODUCCION ADICIONALES ANTERIOR]] -> 0 | S56: 0 | U56: 0 | V56: =SUM(CATEGORIAS[[#This Row],[COSTO ACUMULADO AX]:[PROVISIONES]]) -> 0 | W56: 0 | Y56: 0 | Z56: =SUM(CATEGORIAS[[#This Row],[COSTO ACUMULADO ANTERIOR]:[PROVISIONES ANTERIOR]]) -> 0 | AA56: =ABS(+CATEGORIAS[[#This Row],[PRESUPUESTO FINAL PROYECTADO]]-CATEGORIAS[[#This Row],[TOTAL PRODUCCION ACTUAL]]) -> 0 | AD56: 0 | AE56: =SUM(CATEGORIAS[[#This Row],[INVENTARIO]:[PROYECCION DE COSTO DEL SALDO]]) -> 0 | AG56: =+CATEGORIAS[[#This Row],[PRESUPUESTO FINAL PROYECTADO]]-CATEGORIAS[[#This Row],[COSTO REAL]]-CATEGORIAS[[#This Row],[PROYECCION TOTAL DE COSTO]] -> 0
D57: 21-0102-020A | E57: MAT CD - Civil / Hormigón / Hormigón Prefabricado (A) | F57: NO | G57: 0 | H57: 0 | I57: 0 | J57: 0 | K57: 0 | L57: =CATEGORIAS[[#This Row],[ADICIONALES]]+CATEGORIAS[[#This Row],[POM]]+CATEGORIAS[[#This Row],[REAJUSTE PAGADO]]+CATEGORIAS[[#This Row],[REAJUSTE PROYECTADO]] -> 0 | M57: 0 | N57: 0 | O57: =+CATEGORIAS[[#This Row],[PRODUCCION PARTIDAS ORIGINALES ACTUAL]]+CATEGORIAS[[#This Row],[PRODUCCION ADICIONALES ACTUAL]] -> 0 | P57: 0 | Q57: 0 | R57: =+CATEGORIAS[[#This Row],[PRODUCCION ANTERIOR]]+CATEGORIAS[[#This Row],[PRODUCCION ADICIONALES ANTERIOR]] -> 0 | S57: 0 | U57: 0 | V57: =SUM(CATEGORIAS[[#This Row],[COSTO ACUMULADO AX]:[PROVISIONES]]) -> 0 | W57: 0 | Y57: 0 | Z57: =SUM(CATEGORIAS[[#This Row],[COSTO ACUMULADO ANTERIOR]:[PROVISIONES ANTERIOR]]) -> 0 | AA57: =ABS(+CATEGORIAS[[#This Row],[PRESUPUESTO FINAL PROYECTADO]]-CATEGORIAS[[#This Row],[TOTAL PRODUCCION ACTUAL]]) -> 0 | AD57: 0 | AE57: =SUM(CATEGORIAS[[#This Row],[INVENTARIO]:[PROYECCION DE COSTO DEL SALDO]]) -> 0 | AG57: =+CATEGORIAS[[#This Row],[PRESUPUESTO FINAL PROYECTADO]]-CATEGORIAS[[#This Row],[COSTO REAL]]-CATEGORIAS[[#This Row],[PROYECCION TOTAL DE COSTO]] -> 0
D58: 21-0102-020G | E58: MAT CD - Civil / Hormigón / Hormigón Prefabricado (G) | F58: NO | G58: 0 | H58: 0 | I58: 0 | J58: 0 | K58: 0 | L58: =CATEGORIAS[[#This Row],[ADICIONALES]]+CATEGORIAS[[#This Row],[POM]]+CATEGORIAS[[#This Row],[REAJUSTE PAGADO]]+CATEGORIAS[[#This Row],[REAJUSTE PROYECTADO]] -> 0 | M58: 0 | N58: 0 | O58: =+CATEGORIAS[[#This Row],[PRODUCCION PARTIDAS ORIGINALES ACTUAL]]+CATEGORIAS[[#This Row],[PRODUCCION ADICIONALES ACTUAL]] -> 0 | P58: 0 | Q58: 0 | R58: =+CATEGORIAS[[#This Row],[PRODUCCION ANTERIOR]]+CATEGORIAS[[#This Row],[PRODUCCION ADICIONALES ANTERIOR]] -> 0 | S58: 0 | U58: 0 | V58: =SUM(CATEGORIAS[[#This Row],[COSTO ACUMULADO AX]:[PROVISIONES]]) -> 0 | W58: 0 | Y58: 0 | Z58: =SUM(CATEGORIAS[[#This Row],[COSTO ACUMULADO ANTERIOR]:[PROVISIONES ANTERIOR]]) -> 0 | AA58: =ABS(+CATEGORIAS[[#This Row],[PRESUPUESTO FINAL PROYECTADO]]-CATEGORIAS[[#This Row],[TOTAL PRODUCCION ACTUAL]]) -> 0 | AD58: 0 | AE58: =SUM(CATEGORIAS[[#This Row],[INVENTARIO]:[PROYECCION DE COSTO DEL SALDO]]) -> 0 | AG58: =+CATEGORIAS[[#This Row],[PRESUPUESTO FINAL PROYECTADO]]-CATEGORIAS[[#This Row],[COSTO REAL]]-CATEGORIAS[[#This Row],[PROYECCION TOTAL DE COSTO]] -> 0
D59: 21-0102-030A | E59: MAT CD - Civil / Hormigón / Flete prefabricado (A) | F59: NO | G59: 0 | H59: 0 | I59: 0 | J59: 0 | K59: 0 | L59: =CATEGORIAS[[#This Row],[ADICIONALES]]+CATEGORIAS[[#This Row],[POM]]+CATEGORIAS[[#This Row],[REAJUSTE PAGADO]]+CATEGORIAS[[#This Row],[REAJUSTE PROYECTADO]] -> 0 | M59: 0 | N59: 0 | O59: =+CATEGORIAS[[#This Row],[PRODUCCION PARTIDAS ORIGINALES ACTUAL]]+CATEGORIAS[[#This Row],[PRODUCCION ADICIONALES ACTUAL]] -> 0 | P59: 0 | Q59: 0 | R59: =+CATEGORIAS[[#This Row],[PRODUCCION ANTERIOR]]+CATEGORIAS[[#This Row],[PRODUCCION ADICIONALES ANTERIOR]] -> 0 | S59: 0 | U59: 0 | V59: =SUM(CATEGORIAS[[#This Row],[COSTO ACUMULADO AX]:[PROVISIONES]]) -> 0 | W59: 0 | Y59: 0 | Z59: =SUM(CATEGORIAS[[#This Row],[COSTO ACUMULADO ANTERIOR]:[PROVISIONES ANTERIOR]]) -> 0 | AA59: =ABS(+CATEGORIAS[[#This Row],[PRESUPUESTO FINAL PROYECTADO]]-CATEGORIAS[[#This Row],[TOTAL PRODUCCION ACTUAL]]) -> 0 | AD59: 0 | AE59: =SUM(CATEGORIAS[[#This Row],[INVENTARIO]:[PROYECCION DE COSTO DEL SALDO]]) -> 0 | AG59: =+CATEGORIAS[[#This Row],[PRESUPUESTO FINAL PROYECTADO]]-CATEGORIAS[[#This Row],[COSTO REAL]]-CATEGORIAS[[#This Row],[PROYECCION TOTAL DE COSTO]] -> 0
D60: 21-0102-030G | E60: MAT CD - Civil / Hormigón / Flete prefabricado (G) | F60: NO | G60: 0 | H60: 0 | I60: 0 | J60: 0 | K60: 0 | L60: =CATEGORIAS[[#This Row],[ADICIONALES]]+CATEGORIAS[[#This Row],[POM]]+CATEGORIAS[[#This Row],[REAJUSTE PAGADO]]+CATEGORIAS[[#This Row],[REAJUSTE PROYECTADO]] -> 0 | M60: 0 | N60: 0 | O60: =+CATEGORIAS[[#This Row],[PRODUCCION PARTIDAS ORIGINALES ACTUAL]]+CATEGORIAS[[#This Row],[PRODUCCION ADICIONALES ACTUAL]] -> 0 | P60: 0 | Q60: 0 | R60: =+CATEGORIAS[[#This Row],[PRODUCCION ANTERIOR]]+CATEGORIAS[[#This Row],[PRODUCCION ADICIONALES ANTERIOR]] -> 0 | S60: 0 | U60: 0 | V60: =SUM(CATEGORIAS[[#This Row],[COSTO ACUMULADO AX]:[PROVISIONES]]) -> 0 | W60: 0 | Y60: 0 | Z60: =SUM(CATEGORIAS[[#This Row],[COSTO ACUMULADO ANTERIOR]:[PROVISIONES ANTERIOR]]) -> 0 | AA60: =ABS(+CATEGORIAS[[#This Row],[PRESUPUESTO FINAL PROYECTADO]]-CATEGORIAS[[#This Row],[TOTAL PRODUCCION ACTUAL]]) -> 0 | AD60: 0 | AE60: =SUM(CATEGORIAS[[#This Row],[INVENTARIO]:[PROYECCION DE COSTO DEL SALDO]]) -> 0 | AG60: =+CATEGORIAS[[#This Row],[PRESUPUESTO FINAL PROYECTADO]]-CATEGORIAS[[#This Row],[COSTO REAL]]-CATEGORIAS[[#This Row],[PROYECCION TOTAL DE COSTO]] -> 0
D61: 21-0103-010A | E61: MAT CD - Civil / Moldaje / Moldajes (A) | F61: NO | G61: 0 | H61: 0 | I61: 0 | J61: 0 | K61: 0 | L61: =CATEGORIAS[[#This Row],[ADICIONALES]]+CATEGORIAS[[#This Row],[POM]]+CATEGORIAS[[#This Row],[REAJUSTE PAGADO]]+CATEGORIAS[[#This Row],[REAJUSTE PROYECTADO]] -> 0 | M61: 0 | N61: 0 | O61: =+CATEGORIAS[[#This Row],[PRODUCCION PARTIDAS ORIGINALES ACTUAL]]+CATEGORIAS[[#This Row],[PRODUCCION ADICIONALES ACTUAL]] -> 0 | P61: 0 | Q61: 0 | R61: =+CATEGORIAS[[#This Row],[PRODUCCION ANTERIOR]]+CATEGORIAS[[#This Row],[PRODUCCION ADICIONALES ANTERIOR]] -> 0 | S61: 0 | U61: 0 | V61: =SUM(CATEGORIAS[[#This Row],[COSTO ACUMULADO AX]:[PROVISIONES]]) -> 0 | W61: 0 | Y61: 0 | Z61: =SUM(CATEGORIAS[[#This Row],[COSTO ACUMULADO ANTERIOR]:[PROVISIONES ANTERIOR]]) -> 0 | AA61: =ABS(+CATEGORIAS[[#This Row],[PRESUPUESTO FINAL PROYECTADO]]-CATEGORIAS[[#This Row],[TOTAL PRODUCCION ACTUAL]]) -> 0 | AD61: 0 | AE61: =SUM(CATEGORIAS[[#This Row],[INVENTARIO]:[PROYECCION DE COSTO DEL SALDO]]) -> 0 | AG61: =+CATEGORIAS[[#This Row],[PRESUPUESTO FINAL PROYECTADO]]-CATEGORIAS[[#This Row],[COSTO REAL]]-CATEGORIAS[[#This Row],[PROYECCION TOTAL DE COSTO]] -> 0
D62: 21-0103-010G | E62: MAT CD - Civil / Moldaje / Moldajes (G) | F62: NO | G62: 0 | H62: 0 | I62: 0 | J62: 0 | K62: 0 | L62: =CATEGORIAS[[#This Row],[ADICIONALES]]+CATEGORIAS[[#This Row],[POM]]+CATEGORIAS[[#This Row],[REAJUSTE PAGADO]]+CATEGORIAS[[#This Row],[REAJUSTE PROYECTADO]] -> 0 | M62: 0 | N62: 0 | O62: =+CATEGORIAS[[#This Row],[PRODUCCION PARTIDAS ORIGINALES ACTUAL]]+CATEGORIAS[[#This Row],[PRODUCCION ADICIONALES ACTUAL]] -> 0 | P62: 0 | Q62: 0 | R62: =+CATEGORIAS[[#This Row],[PRODUCCION ANTERIOR]]+CATEGORIAS[[#This Row],[PRODUCCION ADICIONALES ANTERIOR]] -> 0 | S62: 0 | U62: 0 | V62: =SUM(CATEGORIAS[[#This Row],[COSTO ACUMULADO AX]:[PROVISIONES]]) -> 0 | W62: 0 | Y62: 0 | Z62: =SUM(CATEGORIAS[[#This Row],[COSTO ACUMULADO ANTERIOR]:[PROVISIONES ANTERIOR]]) -> 0 | AA62: =ABS(+CATEGORIAS[[#This Row],[PRESUPUESTO FINAL PROYECTADO]]-CATEGORIAS[[#This Row],[TOTAL PRODUCCION ACTUAL]]) -> 0 | AD62: 0 | AE62: =SUM(CATEGORIAS[[#This Row],[INVENTARIO]:[PROYECCION DE COSTO DEL SALDO]]) -> 0 | AG62: =+CATEGORIAS[[#This Row],[PRESUPUESTO FINAL PROYECTADO]]-CATEGORIAS[[#This Row],[COSTO REAL]]-CATEGORIAS[[#This Row],[PROYECCION TOTAL DE COSTO]] -> 0
A63: 0A02 | B63: 0B01 | C63: Civil | D63: 21-0104-010A | E63: MAT CD - Civil / Enfierradura / Varios (A) | F63: SI | G63: 1.9005512e+08 | H63: 1.2589758e+08 | I63: 0 | J63: 4438941.4 | K63: 0 | L63: =CATEGORIAS[[#This Row],[ADICIONALES]]+CATEGORIAS[[#This Row],[POM]]+CATEGORIAS[[#This Row],[REAJUSTE PAGADO]]+CATEGORIAS[[#This Row],[REAJUSTE PROYECTADO]] -> 1.3033652e+08 | M63: 1.303118e+08 | N63: 24713.771 | O63: =+CATEGORIAS[[#This Row],[PRODUCCION PARTIDAS ORIGINALES ACTUAL]]+CATEGORIAS[[#This Row],[PRODUCCION ADICIONALES ACTUAL]] -> 1.3033652e+08 | P63: 1.303118e+08 | Q63: 0 | R63: =+CATEGORIAS[[#This Row],[PRODUCCION ANTERIOR]]+CATEGORIAS[[#This Row],[PRODUCCION ADICIONALES ANTERIOR]] -> 1.303118e+08 | S63: 137402684 | U63: 0 | V63: =SUM(CATEGORIAS[[#This Row],[COSTO ACUMULADO AX]:[PROVISIONES]]) -> 137402684 | W63: 137338244 | Y63: 0 | Z63: =SUM(CATEGORIAS[[#This Row],[COSTO ACUMULADO ANTERIOR]:[PROVISIONES ANTERIOR]]) -> 137338244 | AA63: =ABS(+CATEGORIAS[[#This Row],[PRESUPUESTO FINAL PROYECTADO]]-CATEGORIAS[[#This Row],[TOTAL PRODUCCION ACTUAL]]) -> 0 | AD63: 0 | AE63: =SUM(CATEGORIAS[[#This Row],[INVENTARIO]:[PROYECCION DE COSTO DEL SALDO]]) -> 0 | AG63: =+CATEGORIAS[[#This Row],[PRESUPUESTO FINAL PROYECTADO]]-CATEGORIAS[[#This Row],[COSTO REAL]]-CATEGORIAS[[#This Row],[PROYECCION TOTAL DE COSTO]] -> -7066167.2
D64: 21-0104-010G | E64: MAT CD - Civil / Enfierradura / Varios (G) | F64: NO | G64: 0 | H64: 0 | I64: 0 | J64: 0 | K64: 0 | L64: =CATEGORIAS[[#This Row],[ADICIONALES]]+CATEGORIAS[[#This Row],[POM]]+CATEGORIAS[[#This Row],[REAJUSTE PAGADO]]+CATEGORIAS[[#This Row],[REAJUSTE PROYECTADO]] -> 0 | M64: 0 | N64: 0 | O64: =+CATEGORIAS[[#This Row],[PRODUCCION PARTIDAS ORIGINALES ACTUAL]]+CATEGORIAS[[#This Row],[PRODUCCION ADICIONALES ACTUAL]] -> 0 | P64: 0 | Q64: 0 | R64: =+CATEGORIAS[[#This Row],[PRODUCCION ANTERIOR]]+CATEGORIAS[[#This Row],[PRODUCCION ADICIONALES ANTERIOR]] -> 0 | S64: 0 | U64: 0 | V64: =SUM(CATEGORIAS[[#This Row],[COSTO ACUMULADO AX]:[PROVISIONES]]) -> 0 | W64: 0 | Y64: 0 | Z64: =SUM(CATEGORIAS[[#This Row],[COSTO ACUMULADO ANTERIOR]:[PROVISIONES ANTERIOR]]) -> 0 | AA64: =ABS(+CATEGORIAS[[#This Row],[PRESUPUESTO FINAL PROYECTADO]]-CATEGORIAS[[#This Row],[TOTAL PRODUCCION ACTUAL]]) -> 0 | AD64: 0 | AE64: =SUM(CATEGORIAS[[#This Row],[INVENTARIO]:[PROYECCION DE COSTO DEL SALDO]]) -> 0 | AG64: =+CATEGORIAS[[#This Row],[PRESUPUESTO FINAL PROYECTADO]]-CATEGORIAS[[#This Row],[COSTO REAL]]-CATEGORIAS[[#This Row],[PROYECCION TOTAL DE COSTO]] -> 0
D65: 21-0105-010A | E65: MAT CD - Civil / Arquitectura / Suministro Mat. Arq (A) | F65: NO | G65: 0 | H65: 0 | I65: 0 | J65: 0 | K65: 0 | L65: =CATEGORIAS[[#This Row],[ADICIONALES]]+CATEGORIAS[[#This Row],[POM]]+CATEGORIAS[[#This Row],[REAJUSTE PAGADO]]+CATEGORIAS[[#This Row],[REAJUSTE PROYECTADO]] -> 0 | M65: 0 | N65: 0 | O65: =+CATEGORIAS[[#This Row],[PRODUCCION PARTIDAS ORIGINALES ACTUAL]]+CATEGORIAS[[#This Row],[PRODUCCION ADICIONALES ACTUAL]] -> 0 | P65: 0 | Q65: 0 | R65: =+CATEGORIAS[[#This Row],[PRODUCCION ANTERIOR]]+CATEGORIAS[[#This Row],[PRODUCCION ADICIONALES ANTERIOR]] -> 0 | S65: 0 | U65: 0 | V65: =SUM(CATEGORIAS[[#This Row],[COSTO ACUMULADO AX]:[PROVISIONES]]) -> 0 | W65: 0 | Y65: 0 | Z65: =SUM(CATEGORIAS[[#This Row],[COSTO ACUMULADO ANTERIOR]:[PROVISIONES ANTERIOR]]) -> 0 | AA65: =ABS(+CATEGORIAS[[#This Row],[PRESUPUESTO FINAL PROYECTADO]]-CATEGORIAS[[#This Row],[TOTAL PRODUCCION ACTUAL]]) -> 0 | AD65: 0 | AE65: =SUM(CATEGORIAS[[#This Row],[INVENTARIO]:[PROYECCION DE COSTO DEL SALDO]]) -> 0 | AG65: =+CATEGORIAS[[#This Row],[PRESUPUESTO FINAL PROYECTADO]]-CATEGORIAS[[#This Row],[COSTO REAL]]-CATEGORIAS[[#This Row],[PROYECCION TOTAL DE COSTO]] -> 0
D66: 21-0105-010G | E66: MAT CD - Civil / Arquitectura / Suministro Mat. Arq (G) | F66: NO | G66: 0 | H66: 0 | I66: 0 | J66: 0 | K66: 0 | L66: =CATEGORIAS[[#This Row],[ADICIONALES]]+CATEGORIAS[[#This Row],[POM]]+CATEGORIAS[[#This Row],[REAJUSTE PAGADO]]+CATEGORIAS[[#This Row],[REAJUSTE PROYECTADO]] -> 0 | M66: 0 | N66: 0 | O66: =+CATEGORIAS[[#This Row],[PRODUCCION PARTIDAS ORIGINALES ACTUAL]]+CATEGORIAS[[#This Row],[PRODUCCION ADICIONALES ACTUAL]] -> 0 | P66: 0 | Q66: 0 | R66: =+CATEGORIAS[[#This Row],[PRODUCCION ANTERIOR]]+CATEGORIAS[[#This Row],[PRODUCCION ADICIONALES ANTERIOR]] -> 0 | S66: 0 | U66: 0 | V66: =SUM(CATEGORIAS[[#This Row],[COSTO ACUMULADO AX]:[PROVISIONES]]) -> 0 | W66: 0 | Y66: 0 | Z66: =SUM(CATEGORIAS[[#This Row],[COSTO ACUMULADO ANTERIOR]:[PROVISIONES ANTERIOR]]) -> 0 | AA66: =ABS(+CATEGORIAS[[#This Row],[PRESUPUESTO FINAL PROYECTADO]]-CATEGORIAS[[#This Row],[TOTAL PRODUCCION ACTUAL]]) -> 0 | AD66: 0 | AE66: =SUM(CATEGORIAS[[#This Row],[INVENTARIO]:[PROYECCION DE COSTO DEL SALDO]]) -> 0 | AG66: =+CATEGORIAS[[#This Row],[PRESUPUESTO FINAL PROYECTADO]]-CATEGORIAS[[#This Row],[COSTO REAL]]-CATEGORIAS[[#This Row],[PROYECCION TOTAL DE COSTO]] -> 0
D67: 21-0105-990A | E67: MAT CD - Civil / Arquitectura / Otros (A) | F67: NO | G67: 0 | H67: 0 | I67: 0 | J67: 0 | K67: 0 | L67: =CATEGORIAS[[#This Row],[ADICIONALES]]+CATEGORIAS[[#This Row],[POM]]+CATEGORIAS[[#This Row],[REAJUSTE PAGADO]]+CATEGORIAS[[#This Row],[REAJUSTE PROYECTADO]] -> 0 | M67: 0 | N67: 0 | O67: =+CATEGORIAS[[#This Row],[PRODUCCION PARTIDAS ORIGINALES ACTUAL]]+CATEGORIAS[[#This Row],[PRODUCCION ADICIONALES ACTUAL]] -> 0 | P67: 0 | Q67: 0 | R67: =+CATEGORIAS[[#This Row],[PRODUCCION ANTERIOR]]+CATEGORIAS[[#This Row],[PRODUCCION ADICIONALES ANTERIOR]] -> 0 | S67: 0 | U67: 0 | V67: =SUM(CATEGORIAS[[#This Row],[COSTO ACUMULADO AX]:[PROVISIONES]]) -> 0 | W67: 0 | Y67: 0 | Z67: =SUM(CATEGORIAS[[#This Row],[COSTO ACUMULADO ANTERIOR]:[PROVISIONES ANTERIOR]]) -> 0 | AA67: =ABS(+CATEGORIAS[[#This Row],[PRESUPUESTO FINAL PROYECTADO]]-CATEGORIAS[[#This Row],[TOTAL PRODUCCION ACTUAL]]) -> 0 | AD67: 0 | AE67: =SUM(CATEGORIAS[[#This Row],[INVENTARIO]:[PROYECCION DE COSTO DEL SALDO]]) -> 0 | AG67: =+CATEGORIAS[[#This Row],[PRESUPUESTO FINAL PROYECTADO]]-CATEGORIAS[[#This Row],[COSTO REAL]]-CATEGORIAS[[#This Row],[PROYECCION TOTAL DE COSTO]] -> 0
D68: 21-0105-990G | E68: MAT CD - Civil / Arquitectura / Otros (G) | F68: NO | G68: 0 | H68: 0 | I68: 0 | J68: 0 | K68: 0 | L68: =CATEGORIAS[[#This Row],[ADICIONALES]]+CATEGORIAS[[#This Row],[POM]]+CATEGORIAS[[#This Row],[REAJUSTE PAGADO]]+CATEGORIAS[[#This Row],[REAJUSTE PROYECTADO]] -> 0 | M68: 0 | N68: 0 | O68: =+CATEGORIAS[[#This Row],[PRODUCCION PARTIDAS ORIGINALES ACTUAL]]+CATEGORIAS[[#This Row],[PRODUCCION ADICIONALES ACTUAL]] -> 0 | P68: 0 | Q68: 0 | R68: =+CATEGORIAS[[#This Row],[PRODUCCION ANTERIOR]]+CATEGORIAS[[#This Row],[PRODUCCION ADICIONALES ANTERIOR]] -> 0 | S68: 0 | U68: 0 | V68: =SUM(CATEGORIAS[[#This Row],[COSTO ACUMULADO AX]:[PROVISIONES]]) -> 0 | W68: 0 | Y68: 0 | Z68: =SUM(CATEGORIAS[[#This Row],[COSTO ACUMULADO ANTERIOR]:[PROVISIONES ANTERIOR]]) -> 0 | AA68: =ABS(+CATEGORIAS[[#This Row],[PRESUPUESTO FINAL PROYECTADO]]-CATEGORIAS[[#This Row],[TOTAL PRODUCCION ACTUAL]]) -> 0 | AD68: 0 | AE68: =SUM(CATEGORIAS[[#This Row],[INVENTARIO]:[PROYECCION DE COSTO DEL SALDO]]) -> 0 | AG68: =+CATEGORIAS[[#This Row],[PRESUPUESTO FINAL PROYECTADO]]-CATEGORIAS[[#This Row],[COSTO REAL]]-CATEGORIAS[[#This Row],[PROYECCION TOTAL DE COSTO]] -> 0
A69: 0A02 | B69: 0B01 | C69: Civil | D69: 21-0111-010A | E69: MAT CD - Civil / Pernos e Insertos / Pernos e Insertos (A) | F69: SI | G69: 16081600 | H69: 44540332 | I69: 0 | J69: 1570418.8 | K69: 0 | L69: =CATEGORIAS[[#This Row],[ADICIONALES]]+CATEGORIAS[[#This Row],[POM]]+CATEGORIAS[[#This Row],[REAJUSTE PAGADO]]+CATEGORIAS[[#This Row],[REAJUSTE PROYECTADO]] -> 46110751 | M69: 46102008 | N69: 8743.2944 | O69: =+CATEGORIAS[[#This Row],[PRODUCCION PARTIDAS ORIGINALES ACTUAL]]+CATEGORIAS[[#This Row],[PRODUCCION ADICIONALES ACTUAL]] -> 46110751 | P69: 46102008 | Q69: 0 | R69: =+CATEGORIAS[[#This Row],[PRODUCCION ANTERIOR]]+CATEGORIAS[[#This Row],[PRODUCCION ADICIONALES ANTERIOR]] -> 46102008 | S69: 122477342 | U69: 0 | V69: =SUM(CATEGORIAS[[#This Row],[COSTO ACUMULADO AX]:[PROVISIONES]]) -> 122477342 | W69: 122477342 | Y69: 0 | Z69: =SUM(CATEGORIAS[[#This Row],[COSTO ACUMULADO ANTERIOR]:[PROVISIONES ANTERIOR]]) -> 122477342 | AA69: =ABS(+CATEGORIAS[[#This Row],[PRESUPUESTO FINAL PROYECTADO]]-CATEGORIAS[[#This Row],[TOTAL PRODUCCION ACTUAL]]) -> 0 | AD69: 0 | AE69: =SUM(CATEGORIAS[[#This Row],[INVENTARIO]:[PROYECCION DE COSTO DEL SALDO]]) -> 0 | AG69: =+CATEGORIAS[[#This Row],[PRESUPUESTO FINAL PROYECTADO]]-CATEGORIAS[[#This Row],[COSTO REAL]]-CATEGORIAS[[#This Row],[PROYECCION TOTAL DE COSTO]] -> -76366591
D70: 21-0111-010G | E70: MAT CD - Civil / Pernos e Insertos / Pernos e Insertos (G) | F70: NO | G70: 0 | H70: 0 | I70: 0 | J70: 0 | K70: 0 | L70: =CATEGORIAS[[#This Row],[ADICIONALES]]+CATEGORIAS[[#This Row],[POM]]+CATEGORIAS[[#This Row],[REAJUSTE PAGADO]]+CATEGORIAS[[#This Row],[REAJUSTE PROYECTADO]] -> 0 | M70: 0 | N70: 0 | O70: =+CATEGORIAS[[#This Row],[PRODUCCION PARTIDAS ORIGINALES ACTUAL]]+CATEGORIAS[[#This Row],[PRODUCCION ADICIONALES ACTUAL]] -> 0 | P70: 0 | Q70: 0 | R70: =+CATEGORIAS[[#This Row],[PRODUCCION ANTERIOR]]+CATEGORIAS[[#This Row],[PRODUCCION ADICIONALES ANTERIOR]] -> 0 | S70: 0 | U70: 0 | V70: =SUM(CATEGORIAS[[#This Row],[COSTO ACUMULADO AX]:[PROVISIONES]]) -> 0 | W70: 0 | Y70: 0 | Z70: =SUM(CATEGORIAS[[#This Row],[COSTO ACUMULADO ANTERIOR]:[PROVISIONES ANTERIOR]]) -> 0 | AA70: =ABS(+CATEGORIAS[[#This Row],[PRESUPUESTO FINAL PROYECTADO]]-CATEGORIAS[[#This Row],[TOTAL PRODUCCION ACTUAL]]) -> 0 | AD70: 0 | AE70: =SUM(CATEGORIAS[[#This Row],[INVENTARIO]:[PROYECCION DE COSTO DEL SALDO]]) -> 0 | AG70: =+CATEGORIAS[[#This Row],[PRESUPUESTO FINAL PROYECTADO]]-CATEGORIAS[[#This Row],[COSTO REAL]]-CATEGORIAS[[#This Row],[PROYECCION TOTAL DE COSTO]] -> 0
A71: 0A02 | B71: 0B01 | C71: Civil | D71: 21-0199-010A | E71: MAT CD - Civil / Otros / Materiales varios (A) | F71: SI | G71: 68946513 | H71: 46314997 | I71: 15689297 | J71: 1632990.6 | K71: 0 | L71: =CATEGORIAS[[#This Row],[ADICIONALES]]+CATEGORIAS[[#This Row],[POM]]+CATEGORIAS[[#This Row],[REAJUSTE PAGADO]]+CATEGORIAS[[#This Row],[REAJUSTE PROYECTADO]] -> 63637285 | M71: 47938896 | N71: 15698389 | O71: =+CATEGORIAS[[#This Row],[PRODUCCION PARTIDAS ORIGINALES ACTUAL]]+CATEGORIAS[[#This Row],[PRODUCCION ADICIONALES ACTUAL]] -> 63637285 | P71: 47938896 | Q71: 15689297 | R71: =+CATEGORIAS[[#This Row],[PRODUCCION ANTERIOR]]+CATEGORIAS[[#This Row],[PRODUCCION ADICIONALES ANTERIOR]] -> 63628193 | S71: 50878886 | U71: 0 | V71: =SUM(CATEGORIAS[[#This Row],[COSTO ACUMULADO AX]:[PROVISIONES]]) -> 50878886 | W71: 49286337 | Y71: 843955 | Z71: =SUM(CATEGORIAS[[#This Row],[COSTO ACUMULADO ANTERIOR]:[PROVISIONES ANTERIOR]]) -> 50130292 | AA71: =ABS(+CATEGORIAS[[#This Row],[PRESUPUESTO FINAL PROYECTADO]]-CATEGORIAS[[#This Row],[TOTAL PRODUCCION ACTUAL]]) -> 0 | AD71: 0 | AE71: =SUM(CATEGORIAS[[#This Row],[INVENTARIO]:[PROYECCION DE COSTO DEL SALDO]]) -> 0 | AG71: =+CATEGORIAS[[#This Row],[PRESUPUESTO FINAL PROYECTADO]]-CATEGORIAS[[#This Row],[COSTO REAL]]-CATEGORIAS[[#This Row],[PROYECCION TOTAL DE COSTO]] -> 12758399
D72: 21-0199-010G | E72: MAT CD - Civil / Otros / Materiales varios (G) | F72: NO | G72: 0 | H72: 0 | I72: 0 | J72: 0 | K72: 0 | L72: =CATEGORIAS[[#This Row],[ADICIONALES]]+CATEGORIAS[[#This Row],[POM]]+CATEGORIAS[[#This Row],[REAJUSTE PAGADO]]+CATEGORIAS[[#This Row],[REAJUSTE PROYECTADO]] -> 0 | M72: 0 | N72: 0 | O72: =+CATEGORIAS[[#This Row],[PRODUCCION PARTIDAS ORIGINALES ACTUAL]]+CATEGORIAS[[#This Row],[PRODUCCION ADICIONALES ACTUAL]] -> 0 | P72: 0 | Q72: 0 | R72: =+CATEGORIAS[[#This Row],[PRODUCCION ANTERIOR]]+CATEGORIAS[[#This Row],[PRODUCCION ADICIONALES ANTERIOR]] -> 0 | S72: 0 | U72: 0 | V72: =SUM(CATEGORIAS[[#This Row],[COSTO ACUMULADO AX]:[PROVISIONES]]) -> 0 | W72: 0 | Y72: 0 | Z72: =SUM(CATEGORIAS[[#This Row],[COSTO ACUMULADO ANTERIOR]:[PROVISIONES ANTERIOR]]) -> 0 | AA72: =ABS(+CATEGORIAS[[#This Row],[PRESUPUESTO FINAL PROYECTADO]]-CATEGORIAS[[#This Row],[TOTAL PRODUCCION ACTUAL]]) -> 0 | AD72: 0 | AE72: =SUM(CATEGORIAS[[#This Row],[INVENTARIO]:[PROYECCION DE COSTO DEL SALDO]]) -> 0 | AG72: =+CATEGORIAS[[#This Row],[PRESUPUESTO FINAL PROYECTADO]]-CATEGORIAS[[#This Row],[COSTO REAL]]-CATEGORIAS[[#This Row],[PROYECCION TOTAL DE COSTO]] -> 0
D73: 21-0212-010A | E73: MAT CD - Estructura / Suministro Estructura / Todos (A) | F73: NO | G73: 0 | H73: 0 | I73: 0 | J73: 0 | K73: 0 | L73: =CATEGORIAS[[#This Row],[ADICIONALES]]+CATEGORIAS[[#This Row],[POM]]+CATEGORIAS[[#This Row],[REAJUSTE PAGADO]]+CATEGORIAS[[#This Row],[REAJUSTE PROYECTADO]] -> 0 | M73: 0 | N73: 0 | O73: =+CATEGORIAS[[#This Row],[PRODUCCION PARTIDAS ORIGINALES ACTUAL]]+CATEGORIAS[[#This Row],[PRODUCCION ADICIONALES ACTUAL]] -> 0 | P73: 0 | Q73: 0 | R73: =+CATEGORIAS[[#This Row],[PRODUCCION ANTERIOR]]+CATEGORIAS[[#This Row],[PRODUCCION ADICIONALES ANTERIOR]] -> 0 | S73: 0 | U73: 0 | V73: =SUM(CATEGORIAS[[#This Row],[COSTO ACUMULADO AX]:[PROVISIONES]]) -> 0 | W73: 0 | Y73: 0 | Z73: =SUM(CATEGORIAS[[#This Row],[COSTO ACUMULADO ANTERIOR]:[PROVISIONES ANTERIOR]]) -> 0 | AA73: =ABS(+CATEGORIAS[[#This Row],[PRESUPUESTO FINAL PROYECTADO]]-CATEGORIAS[[#This Row],[TOTAL PRODUCCION ACTUAL]]) -> 0 | AD73: 0 | AE73: =SUM(CATEGORIAS[[#This Row],[INVENTARIO]:[PROYECCION DE COSTO DEL SALDO]]) -> 0 | AG73: =+CATEGORIAS[[#This Row],[PRESUPUESTO FINAL PROYECTADO]]-CATEGORIAS[[#This Row],[COSTO REAL]]-CATEGORIAS[[#This Row],[PROYECCION TOTAL DE COSTO]] -> 0
D74: 21-0212-010G | E74: MAT CD - Estructura / Suministro Estructura / Todos (G) | F74: NO | G74: 0 | H74: 0 | I74: 0 | J74: 0 | K74: 0 | L74: =CATEGORIAS[[#This Row],[ADICIONALES]]+CATEGORIAS[[#This Row],[POM]]+CATEGORIAS[[#This Row],[REAJUSTE PAGADO]]+CATEGORIAS[[#This Row],[REAJUSTE PROYECTADO]] -> 0 | M74: 0 | N74: 0 | O74: =+CATEGORIAS[[#This Row],[PRODUCCION PARTIDAS ORIGINALES ACTUAL]]+CATEGORIAS[[#This Row],[PRODUCCION ADICIONALES ACTUAL]] -> 0 | P74: 0 | Q74: 0 | R74: =+CATEGORIAS[[#This Row],[PRODUCCION ANTERIOR]]+CATEGORIAS[[#This Row],[PRODUCCION ADICIONALES ANTERIOR]] -> 0 | S74: 0 | U74: 0 | V74: =SUM(CATEGORIAS[[#This Row],[COSTO ACUMULADO AX]:[PROVISIONES]]) -> 0 | W74: 0 | Y74: 0 | Z74: =SUM(CATEGORIAS[[#This Row],[COSTO ACUMULADO ANTERIOR]:[PROVISIONES ANTERIOR]]) -> 0 | AA74: =ABS(+CATEGORIAS[[#This Row],[PRESUPUESTO FINAL PROYECTADO]]-CATEGORIAS[[#This Row],[TOTAL PRODUCCION ACTUAL]]) -> 0 | AD74: 0 | AE74: =SUM(CATEGORIAS[[#This Row],[INVENTARIO]:[PROYECCION DE COSTO DEL SALDO]]) -> 0 | AG74: =+CATEGORIAS[[#This Row],[PRESUPUESTO FINAL PROYECTADO]]-CATEGORIAS[[#This Row],[COSTO REAL]]-CATEGORIAS[[#This Row],[PROYECCION TOTAL DE COSTO]] -> 0
D75: 21-0213-010A | E75: MAT CD - Estructura / Pernos / Todos (A) | F75: SI | G75: 0 | H75: 0 | I75: 0 | J75: 0 | K75: 0 | L75: =CATEGORIAS[[#This Row],[ADICIONALES]]+CATEGORIAS[[#This Row],[POM]]+CATEGORIAS[[#This Row],[REAJUSTE PAGADO]]+CATEGORIAS[[#This Row],[REAJUSTE PROYECTADO]] -> 0 | M75: 0 | N75: 0 | O75: =+CATEGORIAS[[#This Row],[PRODUCCION PARTIDAS ORIGINALES ACTUAL]]+CATEGORIAS[[#This Row],[PRODUCCION ADICIONALES ACTUAL]] -> 0 | P75: 0 | Q75: 0 | R75: =+CATEGORIAS[[#This Row],[PRODUCCION ANTERIOR]]+CATEGORIAS[[#This Row],[PRODUCCION ADICIONALES ANTERIOR]] -> 0 | S75: 0 | U75: 0 | V75: =SUM(CATEGORIAS[[#This Row],[COSTO ACUMULADO AX]:[PROVISIONES]]) -> 0 | W75: 0 | Y75: 0 | Z75: =SUM(CATEGORIAS[[#This Row],[COSTO ACUMULADO ANTERIOR]:[PROVISIONES ANTERIOR]]) -> 0 | AA75: =ABS(+CATEGORIAS[[#This Row],[PRESUPUESTO FINAL PROYECTADO]]-CATEGORIAS[[#This Row],[TOTAL PRODUCCION ACTUAL]]) -> 0 | AD75: 0 | AE75: =SUM(CATEGORIAS[[#This Row],[INVENTARIO]:[PROYECCION DE COSTO DEL SALDO]]) -> 0 | AG75: =+CATEGORIAS[[#This Row],[PRESUPUESTO FINAL PROYECTADO]]-CATEGORIAS[[#This Row],[COSTO REAL]]-CATEGORIAS[[#This Row],[PROYECCION TOTAL DE COSTO]] -> 0
D76: 21-0213-010G | E76: MAT CD - Estructura / Pernos / Todos (G) | F76: NO | G76: 0 | H76: 0 | I76: 0 | J76: 0 | K76: 0 | L76: =CATEGORIAS[[#This Row],[ADICIONALES]]+CATEGORIAS[[#This Row],[POM]]+CATEGORIAS[[#This Row],[REAJUSTE PAGADO]]+CATEGORIAS[[#This Row],[REAJUSTE PROYECTADO]] -> 0 | M76: 0 | N76: 0 | O76: =+CATEGORIAS[[#This Row],[PRODUCCION PARTIDAS ORIGINALES ACTUAL]]+CATEGORIAS[[#This Row],[PRODUCCION ADICIONALES ACTUAL]] -> 0 | P76: 0 | Q76: 0 | R76: =+CATEGORIAS[[#This Row],[PRODUCCION ANTERIOR]]+CATEGORIAS[[#This Row],[PRODUCCION ADICIONALES ANTERIOR]] -> 0 | S76: 0 | U76: 0 | V76: =SUM(CATEGORIAS[[#This Row],[COSTO ACUMULADO AX]:[PROVISIONES]]) -> 0 | W76: 0 | Y76: 0 | Z76: =SUM(CATEGORIAS[[#This Row],[COSTO ACUMULADO ANTERIOR]:[PROVISIONES ANTERIOR]]) -> 0 | AA76: =ABS(+CATEGORIAS[[#This Row],[PRESUPUESTO FINAL PROYECTADO]]-CATEGORIAS[[#This Row],[TOTAL PRODUCCION ACTUAL]]) -> 0 | AD76: 0 | AE76: =SUM(CATEGORIAS[[#This Row],[INVENTARIO]:[PROYECCION DE COSTO DEL SALDO]]) -> 0 | AG76: =+CATEGORIAS[[#This Row],[PRESUPUESTO FINAL PROYECTADO]]-CATEGORIAS[[#This Row],[COSTO REAL]]-CATEGORIAS[[#This Row],[PROYECCION TOTAL DE COSTO]] -> 0
D77: 21-0214-010A | E77: MAT CD - Estructura / Soldaduras y Gases / Todos (A) | F77: NO | G77: 0 | H77: 0 | I77: 0 | J77: 0 | K77: 0 | L77: =CATEGORIAS[[#This Row],[ADICIONALES]]+CATEGORIAS[[#This Row],[POM]]+CATEGORIAS[[#This Row],[REAJUSTE PAGADO]]+CATEGORIAS[[#This Row],[REAJUSTE PROYECTADO]] -> 0 | M77: 0 | N77: 0 | O77: =+CATEGORIAS[[#This Row],[PRODUCCION PARTIDAS ORIGINALES ACTUAL]]+CATEGORIAS[[#This Row],[PRODUCCION ADICIONALES ACTUAL]] -> 0 | P77: 0 | Q77: 0 | R77: =+CATEGORIAS[[#This Row],[PRODUCCION ANTERIOR]]+CATEGORIAS[[#This Row],[PRODUCCION ADICIONALES ANTERIOR]] -> 0 | S77: 0 | U77: 0 | V77: =SUM(CATEGORIAS[[#This Row],[COSTO ACUMULADO AX]:[PROVISIONES]]) -> 0 | W77: 0 | Y77: 0 | Z77: =SUM(CATEGORIAS[[#This Row],[COSTO ACUMULADO ANTERIOR]:[PROVISIONES ANTERIOR]]) -> 0 | AA77: =ABS(+CATEGORIAS[[#This Row],[PRESUPUESTO FINAL PROYECTADO]]-CATEGORIAS[[#This Row],[TOTAL PRODUCCION ACTUAL]]) -> 0 | AD77: 0 | AE77: =SUM(CATEGORIAS[[#This Row],[INVENTARIO]:[PROYECCION DE COSTO DEL SALDO]]) -> 0 | AG77: =+CATEGORIAS[[#This Row],[PRESUPUESTO FINAL PROYECTADO]]-CATEGORIAS[[#This Row],[COSTO REAL]]-CATEGORIAS[[#This Row],[PROYECCION TOTAL DE COSTO]] -> 0
D78: 21-0214-010G | E78: MAT CD - Estructura / Soldaduras y Gases / Todos (G) | F78: NO | G78: 0 | H78: 0 | I78: 0 | J78: 0 | K78: 0 | L78: =CATEGORIAS[[#This Row],[ADICIONALES]]+CATEGORIAS[[#This Row],[POM]]+CATEGORIAS[[#This Row],[REAJUSTE PAGADO]]+CATEGORIAS[[#This Row],[REAJUSTE PROYECTADO]] -> 0 | M78: 0 | N78: 0 | O78: =+CATEGORIAS[[#This Row],[PRODUCCION PARTIDAS ORIGINALES ACTUAL]]+CATEGORIAS[[#This Row],[PRODUCCION ADICIONALES ACTUAL]] -> 0 | P78: 0 | Q78: 0 | R78: =+CATEGORIAS[[#This Row],[PRODUCCION ANTERIOR]]+CATEGORIAS[[#This Row],[PRODUCCION ADICIONALES ANTERIOR]] -> 0 | S78: 0 | U78: 0 | V78: =SUM(CATEGORIAS[[#This Row],[COSTO ACUMULADO AX]:[PROVISIONES]]) -> 0 | W78: 0 | Y78: 0 | Z78: =SUM(CATEGORIAS[[#This Row],[COSTO ACUMULADO ANTERIOR]:[PROVISIONES ANTERIOR]]) -> 0 | AA78: =ABS(+CATEGORIAS[[#This Row],[PRESUPUESTO FINAL PROYECTADO]]-CATEGORIAS[[#This Row],[TOTAL PRODUCCION ACTUAL]]) -> 0 | AD78: 0 | AE78: =SUM(CATEGORIAS[[#This Row],[INVENTARIO]:[PROYECCION DE COSTO DEL SALDO]]) -> 0 | AG78: =+CATEGORIAS[[#This Row],[PRESUPUESTO FINAL PROYECTADO]]-CATEGORIAS[[#This Row],[COSTO REAL]]-CATEGORIAS[[#This Row],[PROYECCION TOTAL DE COSTO]] -> 0
D79: 21-0215-010A | E79: MAT CD - Estructura / Suministro Revestimiento / Todos (A) | F79: NO | G79: 0 | H79: 0 | I79: 0 | J79: 0 | K79: 0 | L79: =CATEGORIAS[[#This Row],[ADICIONALES]]+CATEGORIAS[[#This Row],[POM]]+CATEGORIAS[[#This Row],[REAJUSTE PAGADO]]+CATEGORIAS[[#This Row],[REAJUSTE PROYECTADO]] -> 0 | M79: 0 | N79: 0 | O79: =+CATEGORIAS[[#This Row],[PRODUCCION PARTIDAS ORIGINALES ACTUAL]]+CATEGORIAS[[#This Row],[PRODUCCION ADICIONALES ACTUAL]] -> 0 | P79: 0 | Q79: 0 | R79: =+CATEGORIAS[[#This Row],[PRODUCCION ANTERIOR]]+CATEGORIAS[[#This Row],[PRODUCCION ADICIONALES ANTERIOR]] -> 0 | S79: 0 | U79: 0 | V79: =SUM(CATEGORIAS[[#This Row],[COSTO ACUMULADO AX]:[PROVISIONES]]) -> 0 | W79: 0 | Y79: 0 | Z79: =SUM(CATEGORIAS[[#This Row],[COSTO ACUMULADO ANTERIOR]:[PROVISIONES ANTERIOR]]) -> 0 | AA79: =ABS(+CATEGORIAS[[#This Row],[PRESUPUESTO FINAL PROYECTADO]]-CATEGORIAS[[#This Row],[TOTAL PRODUCCION ACTUAL]]) -> 0 | AD79: 0 | AE79: =SUM(CATEGORIAS[[#This Row],[INVENTARIO]:[PROYECCION DE COSTO DEL SALDO]]) -> 0 | AG79: =+CATEGORIAS[[#This Row],[PRESUPUESTO FINAL PROYECTADO]]-CATEGORIAS[[#This Row],[COSTO REAL]]-CATEGORIAS[[#This Row],[PROYECCION TOTAL DE COSTO]] -> 0
D80: 21-0215-010G | E80: MAT CD - Estructura / Suministro Revestimiento / Todos (G) | F80: NO | G80: 0 | H80: 0 | I80: 0 | J80: 0 | K80: 0 | L80: =CATEGORIAS[[#This Row],[ADICIONALES]]+CATEGORIAS[[#This Row],[POM]]+CATEGORIAS[[#This Row],[REAJUSTE PAGADO]]+CATEGORIAS[[#This Row],[REAJUSTE PROYECTADO]] -> 0 | M80: 0 | N80: 0 | O80: =+CATEGORIAS[[#This Row],[PRODUCCION PARTIDAS ORIGINALES ACTUAL]]+CATEGORIAS[[#This Row],[PRODUCCION ADICIONALES ACTUAL]] -> 0 | P80: 0 | Q80: 0 | R80: =+CATEGORIAS[[#This Row],[PRODUCCION ANTERIOR]]+CATEGORIAS[[#This Row],[PRODUCCION ADICIONALES ANTERIOR]] -> 0 | S80: 0 | U80: 0 | V80: =SUM(CATEGORIAS[[#This Row],[COSTO ACUMULADO AX]:[PROVISIONES]]) -> 0 | W80: 0 | Y80: 0 | Z80: =SUM(CATEGORIAS[[#This Row],[COSTO ACUMULADO ANTERIOR]:[PROVISIONES ANTERIOR]]) -> 0 | AA80: =ABS(+CATEGORIAS[[#This Row],[PRESUPUESTO FINAL PROYECTADO]]-CATEGORIAS[[#This Row],[TOTAL PRODUCCION ACTUAL]]) -> 0 | AD80: 0 | AE80: =SUM(CATEGORIAS[[#This Row],[INVENTARIO]:[PROYECCION DE COSTO DEL SALDO]]) -> 0 | AG80: =+CATEGORIAS[[#This Row],[PRESUPUESTO FINAL PROYECTADO]]-CATEGORIAS[[#This Row],[COSTO REAL]]-CATEGORIAS[[#This Row],[PROYECCION TOTAL DE COSTO]] -> 0
D81: 21-0299-010A | E81: MAT CD - Estructura / Otros / Todos (A) | F81: SI | G81: 0 | H81: 0 | I81: 0 | J81: 0 | K81: 0 | L81: =CATEGORIAS[[#This Row],[ADICIONALES]]+CATEGORIAS[[#This Row],[POM]]+CATEGORIAS[[#This Row],[REAJUSTE PAGADO]]+CATEGORIAS[[#This Row],[REAJUSTE PROYECTADO]] -> 0 | M81: 0 | N81: 0 | O81: =+CATEGORIAS[[#This Row],[PRODUCCION PARTIDAS ORIGINALES ACTUAL]]+CATEGORIAS[[#This Row],[PRODUCCION ADICIONALES ACTUAL]] -> 0 | P81: 0 | Q81: 0 | R81: =+CATEGORIAS[[#This Row],[PRODUCCION ANTERIOR]]+CATEGORIAS[[#This Row],[PRODUCCION ADICIONALES ANTERIOR]] -> 0 | S81: 0 | U81: 0 | V81: =SUM(CATEGORIAS[[#This Row],[COSTO ACUMULADO AX]:[PROVISIONES]]) -> 0 | W81: 0 | Y81: 0 | Z81: =SUM(CATEGORIAS[[#This Row],[COSTO ACUMULADO ANTERIOR]:[PROVISIONES ANTERIOR]]) -> 0 | AA81: =ABS(+CATEGORIAS[[#This Row],[PRESUPUESTO FINAL PROYECTADO]]-CATEGORIAS[[#This Row],[TOTAL PRODUCCION ACTUAL]]) -> 0 | AD81: 0 | AE81: =SUM(CATEGORIAS[[#This Row],[INVENTARIO]:[PROYECCION DE COSTO DEL SALDO]]) -> 0 | AG81: =+CATEGORIAS[[#This Row],[PRESUPUESTO FINAL PROYECTADO]]-CATEGORIAS[[#This Row],[COSTO REAL]]-CATEGORIAS[[#This Row],[PROYECCION TOTAL DE COSTO]] -> 0
D82: 21-0299-010G | E82: MAT CD - Estructura / Otros / Todos (G) | F82: NO | G82: 0 | H82: 0 | I82: 0 | J82: 0 | K82: 0 | L82: =CATEGORIAS[[#This Row],[ADICIONALES]]+CATEGORIAS[[#This Row],[POM]]+CATEGORIAS[[#This Row],[REAJUSTE PAGADO]]+CATEGORIAS[[#This Row],[REAJUSTE PROYECTADO]] -> 0 | M82: 0 | N82: 0 | O82: =+CATEGORIAS[[#This Row],[PRODUCCION PARTIDAS ORIGINALES ACTUAL]]+CATEGORIAS[[#This Row],[PRODUCCION ADICIONALES ACTUAL]] -> 0 | P82: 0 | Q82: 0 | R82: =+CATEGORIAS[[#This Row],[PRODUCCION ANTERIOR]]+CATEGORIAS[[#This Row],[PRODUCCION ADICIONALES ANTERIOR]] -> 0 | S82: 0 | U82: 0 | V82: =SUM(CATEGORIAS[[#This Row],[COSTO ACUMULADO AX]:[PROVISIONES]]) -> 0 | W82: 0 | Y82: 0 | Z82: =SUM(CATEGORIAS[[#This Row],[COSTO ACUMULADO ANTERIOR]:[PROVISIONES ANTERIOR]]) -> 0 | AA82: =ABS(+CATEGORIAS[[#This Row],[PRESUPUESTO FINAL PROYECTADO]]-CATEGORIAS[[#This Row],[TOTAL PRODUCCION ACTUAL]]) -> 0 | AD82: 0 | AE82: =SUM(CATEGORIAS[[#This Row],[INVENTARIO]:[PROYECCION DE COSTO DEL SALDO]]) -> 0 | AG82: =+CATEGORIAS[[#This Row],[PRESUPUESTO FINAL PROYECTADO]]-CATEGORIAS[[#This Row],[COSTO REAL]]-CATEGORIAS[[#This Row],[PROYECCION TOTAL DE COSTO]] -> 0
A83: 0C02 | B83: 0B04 | C83: Mecánica | D83: 21-0314-010A | E83: MAT CD - Mecánica / Soldadura y Gases / Todos (A) | F83: SI | G83: 56641077 | H83: 56342403 | I83: 0 | J83: 1986540.4 | K83: 0 | L83: =CATEGORIAS[[#This Row],[ADICIONALES]]+CATEGORIAS[[#This Row],[POM]]+CATEGORIAS[[#This Row],[REAJUSTE PAGADO]]+CATEGORIAS[[#This Row],[REAJUSTE PROYECTADO]] -> 58328943 | M83: 58317883 | N83: 11060.048 | O83: =+CATEGORIAS[[#This Row],[PRODUCCION PARTIDAS ORIGINALES ACTUAL]]+CATEGORIAS[[#This Row],[PRODUCCION ADICIONALES ACTUAL]] -> 58328943 | P83: 58317883 | Q83: 0 | R83: =+CATEGORIAS[[#This Row],[PRODUCCION ANTERIOR]]+CATEGORIAS[[#This Row],[PRODUCCION ADICIONALES ANTERIOR]] -> 58317883 | S83: 206746466 | U83: 1073940 | V83: =SUM(CATEGORIAS[[#This Row],[COSTO ACUMULADO AX]:[PROVISIONES]]) -> 207820406 | W83: 199595878 | Y83: 1073940 | Z83: =SUM(CATEGORIAS[[#This Row],[COSTO ACUMULADO ANTERIOR]:[PROVISIONES ANTERIOR]]) -> 200669818 | AA83: =ABS(+CATEGORIAS[[#This Row],[PRESUPUESTO FINAL PROYECTADO]]-CATEGORIAS[[#This Row],[TOTAL PRODUCCION ACTUAL]]) -> 0 | AD83: 0 | AE83: =SUM(CATEGORIAS[[#This Row],[INVENTARIO]:[PROYECCION DE COSTO DEL SALDO]]) -> 0 | AG83: =+CATEGORIAS[[#This Row],[PRESUPUESTO FINAL PROYECTADO]]-CATEGORIAS[[#This Row],[COSTO REAL]]-CATEGORIAS[[#This Row],[PROYECCION TOTAL DE COSTO]] -> -1.4949146e+08
D84: 21-0314-010G | E84: MAT CD - Mecánica / Soldadura y Gases / Todos (G) | F84: NO | G84: 0 | H84: 0 | I84: 0 | J84: 0 | K84: 0 | L84: =CATEGORIAS[[#This Row],[ADICIONALES]]+CATEGORIAS[[#This Row],[POM]]+CATEGORIAS[[#This Row],[REAJUSTE PAGADO]]+CATEGORIAS[[#This Row],[REAJUSTE PROYECTADO]] -> 0 | M84: 0 | N84: 0 | O84: =+CATEGORIAS[[#This Row],[PRODUCCION PARTIDAS ORIGINALES ACTUAL]]+CATEGORIAS[[#This Row],[PRODUCCION ADICIONALES ACTUAL]] -> 0 | P84: 0 | Q84: 0 | R84: =+CATEGORIAS[[#This Row],[PRODUCCION ANTERIOR]]+CATEGORIAS[[#This Row],[PRODUCCION ADICIONALES ANTERIOR]] -> 0 | S84: 0 | U84: 0 | V84: =SUM(CATEGORIAS[[#This Row],[COSTO ACUMULADO AX]:[PROVISIONES]]) -> 0 | W84: 0 | Y84: 0 | Z84: =SUM(CATEGORIAS[[#This Row],[COSTO ACUMULADO ANTERIOR]:[PROVISIONES ANTERIOR]]) -> 0 | AA84: =ABS(+CATEGORIAS[[#This Row],[PRESUPUESTO FINAL PROYECTADO]]-CATEGORIAS[[#This Row],[TOTAL PRODUCCION ACTUAL]]) -> 0 | AD84: 0 | AE84: =SUM(CATEGORIAS[[#This Row],[INVENTARIO]:[PROYECCION DE COSTO DEL SALDO]]) -> 0 | AG84: =+CATEGORIAS[[#This Row],[PRESUPUESTO FINAL PROYECTADO]]-CATEGORIAS[[#This Row],[COSTO REAL]]-CATEGORIAS[[#This Row],[PROYECCION TOTAL DE COSTO]] -> 0
D85: 21-0317-010A | E85: MAT CD - Mecánica / Suministro Equipos / Todos (A) | F85: NO | G85: 0 | H85: 0 | I85: 0 | J85: 0 | K85: 0 | L85: =CATEGORIAS[[#This Row],[ADICIONALES]]+CATEGORIAS[[#This Row],[POM]]+CATEGORIAS[[#This Row],[REAJUSTE PAGADO]]+CATEGORIAS[[#This Row],[REAJUSTE PROYECTADO]] -> 0 | M85: 0 | N85: 0 | O85: =+CATEGORIAS[[#This Row],[PRODUCCION PARTIDAS ORIGINALES ACTUAL]]+CATEGORIAS[[#This Row],[PRODUCCION ADICIONALES ACTUAL]] -> 0 | P85: 0 | Q85: 0 | R85: =+CATEGORIAS[[#This Row],[PRODUCCION ANTERIOR]]+CATEGORIAS[[#This Row],[PRODUCCION ADICIONALES ANTERIOR]] -> 0 | S85: 0 | U85: 0 | V85: =SUM(CATEGORIAS[[#This Row],[COSTO ACUMULADO AX]:[PROVISIONES]]) -> 0 | W85: 0 | Y85: 0 | Z85: =SUM(CATEGORIAS[[#This Row],[COSTO ACUMULADO ANTERIOR]:[PROVISIONES ANTERIOR]]) -> 0 | AA85: =ABS(+CATEGORIAS[[#This Row],[PRESUPUESTO FINAL PROYECTADO]]-CATEGORIAS[[#This Row],[TOTAL PRODUCCION ACTUAL]]) -> 0 | AD85: 0 | AE85: =SUM(CATEGORIAS[[#This Row],[INVENTARIO]:[PROYECCION DE COSTO DEL SALDO]]) -> 0 | AG85: =+CATEGORIAS[[#This Row],[PRESUPUESTO FINAL PROYECTADO]]-CATEGORIAS[[#This Row],[COSTO REAL]]-CATEGORIAS[[#This Row],[PROYECCION TOTAL DE COSTO]] -> 0
D86: 21-0317-010G | E86: MAT CD - Mecánica / Suministro Equipos / Todos (G) | F86: NO | G86: 0 | H86: 0 | I86: 0 | J86: 0 | K86: 0 | L86: =CATEGORIAS[[#This Row],[ADICIONALES]]+CATEGORIAS[[#This Row],[POM]]+CATEGORIAS[[#This Row],[REAJUSTE PAGADO]]+CATEGORIAS[[#This Row],[REAJUSTE PROYECTADO]] -> 0 | M86: 0 | N86: 0 | O86: =+CATEGORIAS[[#This Row],[PRODUCCION PARTIDAS ORIGINALES ACTUAL]]+CATEGORIAS[[#This Row],[PRODUCCION ADICIONALES ACTUAL]] -> 0 | P86: 0 | Q86: 0 | R86: =+CATEGORIAS[[#This Row],[PRODUCCION ANTERIOR]]+CATEGORIAS[[#This Row],[PRODUCCION ADICIONALES ANTERIOR]] -> 0 | S86: 0 | U86: 0 | V86: =SUM(CATEGORIAS[[#This Row],[COSTO ACUMULADO AX]:[PROVISIONES]]) -> 0 | W86: 0 | Y86: 0 | Z86: =SUM(CATEGORIAS[[#This Row],[COSTO ACUMULADO ANTERIOR]:[PROVISIONES ANTERIOR]]) -> 0 | AA86: =ABS(+CATEGORIAS[[#This Row],[PRESUPUESTO FINAL PROYECTADO]]-CATEGORIAS[[#This Row],[TOTAL PRODUCCION ACTUAL]]) -> 0 | AD86: 0 | AE86: =SUM(CATEGORIAS[[#This Row],[INVENTARIO]:[PROYECCION DE COSTO DEL SALDO]]) -> 0 | AG86: =+CATEGORIAS[[#This Row],[PRESUPUESTO FINAL PROYECTADO]]-CATEGORIAS[[#This Row],[COSTO REAL]]-CATEGORIAS[[#This Row],[PROYECCION TOTAL DE COSTO]] -> 0
D87: 21-0318-010A | E87: MAT CD - Mecánica / Soportes / Todos (A) | F87: NO | G87: 0 | H87: 0 | I87: 0 | J87: 0 | K87: 0 | L87: =CATEGORIAS[[#This Row],[ADICIONALES]]+CATEGORIAS[[#This Row],[POM]]+CATEGORIAS[[#This Row],[REAJUSTE PAGADO]]+CATEGORIAS[[#This Row],[REAJUSTE PROYECTADO]] -> 0 | M87: 0 | N87: 0 | O87: =+CATEGORIAS[[#This Row],[PRODUCCION PARTIDAS ORIGINALES ACTUAL]]+CATEGORIAS[[#This Row],[PRODUCCION ADICIONALES ACTUAL]] -> 0 | P87: 0 | Q87: 0 | R87: =+CATEGORIAS[[#This Row],[PRODUCCION ANTERIOR]]+CATEGORIAS[[#This Row],[PRODUCCION ADICIONALES ANTERIOR]] -> 0 | S87: 0 | U87: 0 | V87: =SUM(CATEGORIAS[[#This Row],[COSTO ACUMULADO AX]:[PROVISIONES]]) -> 0 | W87: 0 | Y87: 0 | Z87: =SUM(CATEGORIAS[[#This Row],[COSTO ACUMULADO ANTERIOR]:[PROVISIONES ANTERIOR]]) -> 0 | AA87: =ABS(+CATEGORIAS[[#This Row],[PRESUPUESTO FINAL PROYECTADO]]-CATEGORIAS[[#This Row],[TOTAL PRODUCCION ACTUAL]]) -> 0 | AD87: 0 | AE87: =SUM(CATEGORIAS[[#This Row],[INVENTARIO]:[PROYECCION DE COSTO DEL SALDO]]) -> 0 | AG87: =+CATEGORIAS[[#This Row],[PRESUPUESTO FINAL PROYECTADO]]-CATEGORIAS[[#This Row],[COSTO REAL]]-CATEGORIAS[[#This Row],[PROYECCION TOTAL DE COSTO]] -> 0
D88: 21-0318-010G | E88: MAT CD - Mecánica / Soportes / Todos (G) | F88: NO | G88: 0 | H88: 0 | I88: 0 | J88: 0 | K88: 0 | L88: =CATEGORIAS[[#This Row],[ADICIONALES]]+CATEGORIAS[[#This Row],[POM]]+CATEGORIAS[[#This Row],[REAJUSTE PAGADO]]+CATEGORIAS[[#This Row],[REAJUSTE PROYECTADO]] -> 0 | M88: 0 | N88: 0 | O88: =+CATEGORIAS[[#This Row],[PRODUCCION PARTIDAS ORIGINALES ACTUAL]]+CATEGORIAS[[#This Row],[PRODUCCION ADICIONALES ACTUAL]] -> 0 | P88: 0 | Q88: 0 | R88: =+CATEGORIAS[[#This Row],[PRODUCCION ANTERIOR]]+CATEGORIAS[[#This Row],[PRODUCCION ADICIONALES ANTERIOR]] -> 0 | S88: 0 | U88: 0 | V88: =SUM(CATEGORIAS[[#This Row],[COSTO ACUMULADO AX]:[PROVISIONES]]) -> 0 | W88: 0 | Y88: 0 | Z88: =SUM(CATEGORIAS[[#This Row],[COSTO ACUMULADO ANTERIOR]:[PROVISIONES ANTERIOR]]) -> 0 | AA88: =ABS(+CATEGORIAS[[#This Row],[PRESUPUESTO FINAL PROYECTADO]]-CATEGORIAS[[#This Row],[TOTAL PRODUCCION ACTUAL]]) -> 0 | AD88: 0 | AE88: =SUM(CATEGORIAS[[#This Row],[INVENTARIO]:[PROYECCION DE COSTO DEL SALDO]]) -> 0 | AG88: =+CATEGORIAS[[#This Row],[PRESUPUESTO FINAL PROYECTADO]]-CATEGORIAS[[#This Row],[COSTO REAL]]-CATEGORIAS[[#This Row],[PROYECCION TOTAL DE COSTO]] -> 0
D89: 21-0319-010A | E89: MAT CD - Mecánica / Pernos y Empaquetaduras / Todos (A) | F89: SI | G89: 0 | H89: 0 | I89: 0 | J89: 0 | K89: 0 | L89: =CATEGORIAS[[#This Row],[ADICIONALES]]+CATEGORIAS[[#This Row],[POM]]+CATEGORIAS[[#This Row],[REAJUSTE PAGADO]]+CATEGORIAS[[#This Row],[REAJUSTE PROYECTADO]] -> 0 | M89: 0 | N89: 0 | O89: =+CATEGORIAS[[#This Row],[PRODUCCION PARTIDAS ORIGINALES ACTUAL]]+CATEGORIAS[[#This Row],[PRODUCCION ADICIONALES ACTUAL]] -> 0 | P89: 0 | Q89: 0 | R89: =+CATEGORIAS[[#This Row],[PRODUCCION ANTERIOR]]+CATEGORIAS[[#This Row],[PRODUCCION ADICIONALES ANTERIOR]] -> 0 | S89: 0 | U89: 0 | V89: =SUM(CATEGORIAS[[#This Row],[COSTO ACUMULADO AX]:[PROVISIONES]]) -> 0 | W89: 0 | Y89: 0 | Z89: =SUM(CATEGORIAS[[#This Row],[COSTO ACUMULADO ANTERIOR]:[PROVISIONES ANTERIOR]]) -> 0 | AA89: =ABS(+CATEGORIAS[[#This Row],[PRESUPUESTO FINAL PROYECTADO]]-CATEGORIAS[[#This Row],[TOTAL PRODUCCION ACTUAL]]) -> 0 | AD89: 0 | AE89: =SUM(CATEGORIAS[[#This Row],[INVENTARIO]:[PROYECCION DE COSTO DEL SALDO]]) -> 0 | AG89: =+CATEGORIAS[[#This Row],[PRESUPUESTO FINAL PROYECTADO]]-CATEGORIAS[[#This Row],[COSTO REAL]]-CATEGORIAS[[#This Row],[PROYECCION TOTAL DE COSTO]] -> 0
D90: 21-0319-010G | E90: MAT CD - Mecánica / Pernos y Empaquetaduras / Todos (G) | F90: NO | G90: 0 | H90: 0 | I90: 0 | J90: 0 | K90: 0 | L90: =CATEGORIAS[[#This Row],[ADICIONALES]]+CATEGORIAS[[#This Row],[POM]]+CATEGORIAS[[#This Row],[REAJUSTE PAGADO]]+CATEGORIAS[[#This Row],[REAJUSTE PROYECTADO]] -> 0 | M90: 0 | N90: 0 | O90: =+CATEGORIAS[[#This Row],[PRODUCCION PARTIDAS ORIGINALES ACTUAL]]+CATEGORIAS[[#This Row],[PRODUCCION ADICIONALES ACTUAL]] -> 0 | P90: 0 | Q90: 0 | R90: =+CATEGORIAS[[#This Row],[PRODUCCION ANTERIOR]]+CATEGORIAS[[#This Row],[PRODUCCION ADICIONALES ANTERIOR]] -> 0 | S90: 0 | U90: 0 | V90: =SUM(CATEGORIAS[[#This Row],[COSTO ACUMULADO AX]:[PROVISIONES]]) -> 0 | W90: 0 | Y90: 0 | Z90: =SUM(CATEGORIAS[[#This Row],[COSTO ACUMULADO ANTERIOR]:[PROVISIONES ANTERIOR]]) -> 0 | AA90: =ABS(+CATEGORIAS[[#This Row],[PRESUPUESTO FINAL PROYECTADO]]-CATEGORIAS[[#This Row],[TOTAL PRODUCCION ACTUAL]]) -> 0 | AD90: 0 | AE90: =SUM(CATEGORIAS[[#This Row],[INVENTARIO]:[PROYECCION DE COSTO DEL SALDO]]) -> 0 | AG90: =+CATEGORIAS[[#This Row],[PRESUPUESTO FINAL PROYECTADO]]-CATEGORIAS[[#This Row],[COSTO REAL]]-CATEGORIAS[[#This Row],[PROYECCION TOTAL DE COSTO]] -> 0
A91: 0C02 | B91: 0B04 | C91: Mecánica | D91: 21-0399-010A | E91: MAT CD - Mecánica / Materiales varios / Todos (A) | F91: SI | G91: 87689706 | H91: 82306843 | I91: 81157037 | J91: 2902003.9 | K91: 0 | L91: =CATEGORIAS[[#This Row],[ADICIONALES]]+CATEGORIAS[[#This Row],[POM]]+CATEGORIAS[[#This Row],[REAJUSTE PAGADO]]+CATEGORIAS[[#This Row],[REAJUSTE PROYECTADO]] -> 1.6636588e+08 | M91: 85192690 | N91: 81173194 | O91: =+CATEGORIAS[[#This Row],[PRODUCCION PARTIDAS ORIGINALES ACTUAL]]+CATEGORIAS[[#This Row],[PRODUCCION ADICIONALES ACTUAL]] -> 1.6636588e+08 | P91: 85192690 | Q91: 81157037 | R91: =+CATEGORIAS[[#This Row],[PRODUCCION ANTERIOR]]+CATEGORIAS[[#This Row],[PRODUCCION ADICIONALES ANTERIOR]] -> 1.6634973e+08 | S91: 131689572 | U91: 0 | V91: =SUM(CATEGORIAS[[#This Row],[COSTO ACUMULADO AX]:[PROVISIONES]]) -> 131689572 | W91: 116259634 | Y91: 4541208 | Z91: =SUM(CATEGORIAS[[#This Row],[COSTO ACUMULADO ANTERIOR]:[PROVISIONES ANTERIOR]]) -> 120800842 | AA91: =ABS(+CATEGORIAS[[#This Row],[PRESUPUESTO FINAL PROYECTADO]]-CATEGORIAS[[#This Row],[TOTAL PRODUCCION ACTUAL]]) -> 0 | AD91: 0 | AE91: =SUM(CATEGORIAS[[#This Row],[INVENTARIO]:[PROYECCION DE COSTO DEL SALDO]]) -> 0 | AG91: =+CATEGORIAS[[#This Row],[PRESUPUESTO FINAL PROYECTADO]]-CATEGORIAS[[#This Row],[COSTO REAL]]-CATEGORIAS[[#This Row],[PROYECCION TOTAL DE COSTO]] -> 34676312
D92: 21-0399-010G | E92: MAT CD - Mecánica / Materiales varios / Todos (G) | F92: NO | G92: 0 | H92: 0 | I92: 0 | J92: 0 | K92: 0 | L92: =CATEGORIAS[[#This Row],[ADICIONALES]]+CATEGORIAS[[#This Row],[POM]]+CATEGORIAS[[#This Row],[REAJUSTE PAGADO]]+CATEGORIAS[[#This Row],[REAJUSTE PROYECTADO]] -> 0 | M92: 0 | N92: 0 | O92: =+CATEGORIAS[[#This Row],[PRODUCCION PARTIDAS ORIGINALES ACTUAL]]+CATEGORIAS[[#This Row],[PRODUCCION ADICIONALES ACTUAL]] -> 0 | P92: 0 | Q92: 0 | R92: =+CATEGORIAS[[#This Row],[PRODUCCION ANTERIOR]]+CATEGORIAS[[#This Row],[PRODUCCION ADICIONALES ANTERIOR]] -> 0 | S92: 0 | U92: 0 | V92: =SUM(CATEGORIAS[[#This Row],[COSTO ACUMULADO AX]:[PROVISIONES]]) -> 0 | W92: 0 | Y92: 0 | Z92: =SUM(CATEGORIAS[[#This Row],[COSTO ACUMULADO ANTERIOR]:[PROVISIONES ANTERIOR]]) -> 0 | AA92: =ABS(+CATEGORIAS[[#This Row],[PRESUPUESTO FINAL PROYECTADO]]-CATEGORIAS[[#This Row],[TOTAL PRODUCCION ACTUAL]]) -> 0 | AD92: 0 | AE92: =SUM(CATEGORIAS[[#This Row],[INVENTARIO]:[PROYECCION DE COSTO DEL SALDO]]) -> 0 | AG92: =+CATEGORIAS[[#This Row],[PRESUPUESTO FINAL PROYECTADO]]-CATEGORIAS[[#This Row],[COSTO REAL]]-CATEGORIAS[[#This Row],[PROYECCION TOTAL DE COSTO]] -> 0
D93: 21-0414-010A | E93: MAT CD - Cañería / Soldadura y Gases / Todos (A) | F93: SI | G93: 0 | H93: 0 | I93: 0 | J93: 0 | K93: 0 | L93: =CATEGORIAS[[#This Row],[ADICIONALES]]+CATEGORIAS[[#This Row],[POM]]+CATEGORIAS[[#This Row],[REAJUSTE PAGADO]]+CATEGORIAS[[#This Row],[REAJUSTE PROYECTADO]] -> 0 | M93: 0 | N93: 0 | O93: =+CATEGORIAS[[#This Row],[PRODUCCION PARTIDAS ORIGINALES ACTUAL]]+CATEGORIAS[[#This Row],[PRODUCCION ADICIONALES ACTUAL]] -> 0 | P93: 0 | Q93: 0 | R93: =+CATEGORIAS[[#This Row],[PRODUCCION ANTERIOR]]+CATEGORIAS[[#This Row],[PRODUCCION ADICIONALES ANTERIOR]] -> 0 | S93: 0 | U93: 0 | V93: =SUM(CATEGORIAS[[#This Row],[COSTO ACUMULADO AX]:[PROVISIONES]]) -> 0 | W93: 0 | Y93: 0 | Z93: =SUM(CATEGORIAS[[#This Row],[COSTO ACUMULADO ANTERIOR]:[PROVISIONES ANTERIOR]]) -> 0 | AA93: =ABS(+CATEGORIAS[[#This Row],[PRESUPUESTO FINAL PROYECTADO]]-CATEGORIAS[[#This Row],[TOTAL PRODUCCION ACTUAL]]) -> 0 | AD93: 0 | AE93: =SUM(CATEGORIAS[[#This Row],[INVENTARIO]:[PROYECCION DE COSTO DEL SALDO]]) -> 0 | AG93: =+CATEGORIAS[[#This Row],[PRESUPUESTO FINAL PROYECTADO]]-CATEGORIAS[[#This Row],[COSTO REAL]]-CATEGORIAS[[#This Row],[PROYECCION TOTAL DE COSTO]] -> 0
D94: 21-0414-010G | E94: MAT CD - Cañería / Soldadura y Gases / Todos (G) | F94: NO | G94: 0 | H94: 0 | I94: 0 | J94: 0 | K94: 0 | L94: =CATEGORIAS[[#This Row],[ADICIONALES]]+CATEGORIAS[[#This Row],[POM]]+CATEGORIAS[[#This Row],[REAJUSTE PAGADO]]+CATEGORIAS[[#This Row],[REAJUSTE PROYECTADO]] -> 0 | M94: 0 | N94: 0 | O94: =+CATEGORIAS[[#This Row],[PRODUCCION PARTIDAS ORIGINALES ACTUAL]]+CATEGORIAS[[#This Row],[PRODUCCION ADICIONALES ACTUAL]] -> 0 | P94: 0 | Q94: 0 | R94: =+CATEGORIAS[[#This Row],[PRODUCCION ANTERIOR]]+CATEGORIAS[[#This Row],[PRODUCCION ADICIONALES ANTERIOR]] -> 0 | S94: 0 | U94: 0 | V94: =SUM(CATEGORIAS[[#This Row],[COSTO ACUMULADO AX]:[PROVISIONES]]) -> 0 | W94: 0 | Y94: 0 | Z94: =SUM(CATEGORIAS[[#This Row],[COSTO ACUMULADO ANTERIOR]:[PROVISIONES ANTERIOR]]) -> 0 | AA94: =ABS(+CATEGORIAS[[#This Row],[PRESUPUESTO FINAL PROYECTADO]]-CATEGORIAS[[#This Row],[TOTAL PRODUCCION ACTUAL]]) -> 0 | AD94: 0 | AE94: =SUM(CATEGORIAS[[#This Row],[INVENTARIO]:[PROYECCION DE COSTO DEL SALDO]]) -> 0 | AG94: =+CATEGORIAS[[#This Row],[PRESUPUESTO FINAL PROYECTADO]]-CATEGORIAS[[#This Row],[COSTO REAL]]-CATEGORIAS[[#This Row],[PROYECCION TOTAL DE COSTO]] -> 0
D95: 21-0418-010A | E95: MAT CD - Cañería / Soportes / Todos (A) | F95: SI | G95: 0 | H95: 0 | I95: 0 | J95: 0 | K95: 0 | L95: =CATEGORIAS[[#This Row],[ADICIONALES]]+CATEGORIAS[[#This Row],[POM]]+CATEGORIAS[[#This Row],[REAJUSTE PAGADO]]+CATEGORIAS[[#This Row],[REAJUSTE PROYECTADO]] -> 0 | M95: 0 | N95: 0 | O95: =+CATEGORIAS[[#This Row],[PRODUCCION PARTIDAS ORIGINALES ACTUAL]]+CATEGORIAS[[#This Row],[PRODUCCION ADICIONALES ACTUAL]] -> 0 | P95: 0 | Q95: 0 | R95: =+CATEGORIAS[[#This Row],[PRODUCCION ANTERIOR]]+CATEGORIAS[[#This Row],[PRODUCCION ADICIONALES ANTERIOR]] -> 0 | S95: 0 | U95: 0 | V95: =SUM(CATEGORIAS[[#This Row],[COSTO ACUMULADO AX]:[PROVISIONES]]) -> 0 | W95: 0 | Y95: 0 | Z95: =SUM(CATEGORIAS[[#This Row],[COSTO ACUMULADO ANTERIOR]:[PROVISIONES ANTERIOR]]) -> 0 | AA95: =ABS(+CATEGORIAS[[#This Row],[PRESUPUESTO FINAL PROYECTADO]]-CATEGORIAS[[#This Row],[TOTAL PRODUCCION ACTUAL]]) -> 0 | AD95: 0 | AE95: =SUM(CATEGORIAS[[#This Row],[INVENTARIO]:[PROYECCION DE COSTO DEL SALDO]]) -> 0 | AG95: =+CATEGORIAS[[#This Row],[PRESUPUESTO FINAL PROYECTADO]]-CATEGORIAS[[#This Row],[COSTO REAL]]-CATEGORIAS[[#This Row],[PROYECCION TOTAL DE COSTO]] -> 0
D96: 21-0418-010G | E96: MAT CD - Cañería / Soportes / Todos (G) | F96: NO | G96: 0 | H96: 0 | I96: 0 | J96: 0 | K96: 0 | L96: =CATEGORIAS[[#This Row],[ADICIONALES]]+CATEGORIAS[[#This Row],[POM]]+CATEGORIAS[[#This Row],[REAJUSTE PAGADO]]+CATEGORIAS[[#This Row],[REAJUSTE PROYECTADO]] -> 0 | M96: 0 | N96: 0 | O96: =+CATEGORIAS[[#This Row],[PRODUCCION PARTIDAS ORIGINALES ACTUAL]]+CATEGORIAS[[#This Row],[PRODUCCION ADICIONALES ACTUAL]] -> 0 | P96: 0 | Q96: 0 | R96: =+CATEGORIAS[[#This Row],[PRODUCCION ANTERIOR]]+CATEGORIAS[[#This Row],[PRODUCCION ADICIONALES ANTERIOR]] -> 0 | S96: 0 | U96: 0 | V96: =SUM(CATEGORIAS[[#This Row],[COSTO ACUMULADO AX]:[PROVISIONES]]) -> 0 | W96: 0 | Y96: 0 | Z96: =SUM(CATEGORIAS[[#This Row],[COSTO ACUMULADO ANTERIOR]:[PROVISIONES ANTERIOR]]) -> 0 | AA96: =ABS(+CATEGORIAS[[#This Row],[PRESUPUESTO FINAL PROYECTADO]]-CATEGORIAS[[#This Row],[TOTAL PRODUCCION ACTUAL]]) -> 0 | AD96: 0 | AE96: =SUM(CATEGORIAS[[#This Row],[INVENTARIO]:[PROYECCION DE COSTO DEL SALDO]]) -> 0 | AG96: =+CATEGORIAS[[#This Row],[PRESUPUESTO FINAL PROYECTADO]]-CATEGORIAS[[#This Row],[COSTO REAL]]-CATEGORIAS[[#This Row],[PROYECCION TOTAL DE COSTO]] -> 0
D97: 21-0419-010A | E97: MAT CD - Cañería / Pernos y Empaquetaduras / Todos (A) | F97: SI | G97: 0 | H97: 0 | I97: 0 | J97: 0 | K97: 0 | L97: =CATEGORIAS[[#This Row],[ADICIONALES]]+CATEGORIAS[[#This Row],[POM]]+CATEGORIAS[[#This Row],[REAJUSTE PAGADO]]+CATEGORIAS[[#This Row],[REAJUSTE PROYECTADO]] -> 0 | M97: 0 | N97: 0 | O97: =+CATEGORIAS[[#This Row],[PRODUCCION PARTIDAS ORIGINALES ACTUAL]]+CATEGORIAS[[#This Row],[PRODUCCION ADICIONALES ACTUAL]] -> 0 | P97: 0 | Q97: 0 | R97: =+CATEGORIAS[[#This Row],[PRODUCCION ANTERIOR]]+CATEGORIAS[[#This Row],[PRODUCCION ADICIONALES ANTERIOR]] -> 0 | S97: 0 | U97: 0 | V97: =SUM(CATEGORIAS[[#This Row],[COSTO ACUMULADO AX]:[PROVISIONES]]) -> 0 | W97: 0 | Y97: 0 | Z97: =SUM(CATEGORIAS[[#This Row],[COSTO ACUMULADO ANTERIOR]:[PROVISIONES ANTERIOR]]) -> 0 | AA97: =ABS(+CATEGORIAS[[#This Row],[PRESUPUESTO FINAL PROYECTADO]]-CATEGORIAS[[#This Row],[TOTAL PRODUCCION ACTUAL]]) -> 0 | AD97: 0 | AE97: =SUM(CATEGORIAS[[#This Row],[INVENTARIO]:[PROYECCION DE COSTO DEL SALDO]]) -> 0 | AG97: =+CATEGORIAS[[#This Row],[PRESUPUESTO FINAL PROYECTADO]]-CATEGORIAS[[#This Row],[COSTO REAL]]-CATEGORIAS[[#This Row],[PROYECCION TOTAL DE COSTO]] -> 0
D98: 21-0419-010G | E98: MAT CD - Cañería / Pernos y Empaquetaduras / Todos (G) | F98: NO | G98: 0 | H98: 0 | I98: 0 | J98: 0 | K98: 0 | L98: =CATEGORIAS[[#This Row],[ADICIONALES]]+CATEGORIAS[[#This Row],[POM]]+CATEGORIAS[[#This Row],[REAJUSTE PAGADO]]+CATEGORIAS[[#This Row],[REAJUSTE PROYECTADO]] -> 0 | M98: 0 | N98: 0 | O98: =+CATEGORIAS[[#This Row],[PRODUCCION PARTIDAS ORIGINALES ACTUAL]]+CATEGORIAS[[#This Row],[PRODUCCION ADICIONALES ACTUAL]] -> 0 | P98: 0 | Q98: 0 | R98: =+CATEGORIAS[[#This Row],[PRODUCCION ANTERIOR]]+CATEGORIAS[[#This Row],[PRODUCCION ADICIONALES ANTERIOR]] -> 0 | S98: 0 | U98: 0 | V98: =SUM(CATEGORIAS[[#This Row],[COSTO ACUMULADO AX]:[PROVISIONES]]) -> 0 | W98: 0 | Y98: 0 | Z98: =SUM(CATEGORIAS[[#This Row],[COSTO ACUMULADO ANTERIOR]:[PROVISIONES ANTERIOR]]) -> 0 | AA98: =ABS(+CATEGORIAS[[#This Row],[PRESUPUESTO FINAL PROYECTADO]]-CATEGORIAS[[#This Row],[TOTAL PRODUCCION ACTUAL]]) -> 0 | AD98: 0 | AE98: =SUM(CATEGORIAS[[#This Row],[INVENTARIO]:[PROYECCION DE COSTO DEL SALDO]]) -> 0 | AG98: =+CATEGORIAS[[#This Row],[PRESUPUESTO FINAL PROYECTADO]]-CATEGORIAS[[#This Row],[COSTO REAL]]-CATEGORIAS[[#This Row],[PROYECCION TOTAL DE COSTO]] -> 0
D99: 21-0420-010A | E99: MAT CD - Cañería / Sumini. Cañería Fitt. y Válvs / Todos (A) | F99: SI | G99: 0 | H99: 0 | I99: 0 | J99: 0 | K99: 0 | L99: =CATEGORIAS[[#This Row],[ADICIONALES]]+CATEGORIAS[[#This Row],[POM]]+CATEGORIAS[[#This Row],[REAJUSTE PAGADO]]+CATEGORIAS[[#This Row],[REAJUSTE PROYECTADO]] -> 0 | M99: 0 | N99: 0 | O99: =+CATEGORIAS[[#This Row],[PRODUCCION PARTIDAS ORIGINALES ACTUAL]]+CATEGORIAS[[#This Row],[PRODUCCION ADICIONALES ACTUAL]] -> 0 | P99: 0 | Q99: 0 | R99: =+CATEGORIAS[[#This Row],[PRODUCCION ANTERIOR]]+CATEGORIAS[[#This Row],[PRODUCCION ADICIONALES ANTERIOR]] -> 0 | S99: 0 | U99: 0 | V99: =SUM(CATEGORIAS[[#This Row],[COSTO ACUMULADO AX]:[PROVISIONES]]) -> 0 | W99: 0 | Y99: 0 | Z99: =SUM(CATEGORIAS[[#This Row],[COSTO ACUMULADO ANTERIOR]:[PROVISIONES ANTERIOR]]) -> 0 | AA99: =ABS(+CATEGORIAS[[#This Row],[PRESUPUESTO FINAL PROYECTADO]]-CATEGORIAS[[#This Row],[TOTAL PRODUCCION ACTUAL]]) -> 0 | AD99: 0 | AE99: =SUM(CATEGORIAS[[#This Row],[INVENTARIO]:[PROYECCION DE COSTO DEL SALDO]]) -> 0 | AG99: =+CATEGORIAS[[#This Row],[PRESUPUESTO FINAL PROYECTADO]]-CATEGORIAS[[#This Row],[COSTO REAL]]-CATEGORIAS[[#This Row],[PROYECCION TOTAL DE COSTO]] -> 0
D100: 21-0420-010G | E100: MAT CD - Cañería / Sumini. Cañería Fitt. y Válvs / Todos (G) | F100: NO | G100: 0 | H100: 0 | I100: 0 | J100: 0 | K100: 0 | L100: =CATEGORIAS[[#This Row],[ADICIONALES]]+CATEGORIAS[[#This Row],[POM]]+CATEGORIAS[[#This Row],[REAJUSTE PAGADO]]+CATEGORIAS[[#This Row],[REAJUSTE PROYECTADO]] -> 0 | M100: 0 | N100: 0 | O100: =+CATEGORIAS[[#This Row],[PRODUCCION PARTIDAS ORIGINALES ACTUAL]]+CATEGORIAS[[#This Row],[PRODUCCION ADICIONALES ACTUAL]] -> 0 | P100: 0 | Q100: 0 | R100: =+CATEGORIAS[[#This Row],[PRODUCCION ANTERIOR]]+CATEGORIAS[[#This Row],[PRODUCCION ADICIONALES ANTERIOR]] -> 0 | S100: 0 | U100: 0 | V100: =SUM(CATEGORIAS[[#This Row],[COSTO ACUMULADO AX]:[PROVISIONES]]) -> 0 | W100: 0 | Y100: 0 | Z100: =SUM(CATEGORIAS[[#This Row],[COSTO ACUMULADO ANTERIOR]:[PROVISIONES ANTERIOR]]) -> 0 | AA100: =ABS(+CATEGORIAS[[#This Row],[PRESUPUESTO FINAL PROYECTADO]]-CATEGORIAS[[#This Row],[TOTAL PRODUCCION ACTUAL]]) -> 0 | AD100: 0 | AE100: =SUM(CATEGORIAS[[#This Row],[INVENTARIO]:[PROYECCION DE COSTO DEL SALDO]]) -> 0 | AG100: =+CATEGORIAS[[#This Row],[PRESUPUESTO FINAL PROYECTADO]]-CATEGORIAS[[#This Row],[COSTO REAL]]-CATEGORIAS[[#This Row],[PROYECCION TOTAL DE COSTO]] -> 0
...

Sheet Matriz de Produccion
G1: MATRIZ DE PRODUCCION | O1: =Indice!H2 -> CC: EIMI00398 ARAUCO
B2: =Indice!C4 -> INFORME DE COSTOS N° 01 | G2: ="Periodo : " & TEXT(Indice!I12,"MMMM yyyy") -> Periodo : enero 2026 | O2: FO.EIM-OFT-001-04 | Q2: Rev. 3
G4: ACUMULADO | K4: ANTERIOR | O4: PERIODO
B5: PARTIDA / CATEGORIA | D5: PRESUPUESTO | E5: POM | G5: PRODUCCION | H5: ADICIONALES | I5: TOTAL PRODUCCION ACUMULADA | K5: PRODUCCION | L5: ADICIONALES | M5: TOTAL PRODUCCION ANTERIOR | O5: PRODUCCION | P5: ADICIONALES | Q5: TOTAL PRODUCCION PERIODO
B7: COSTOS DIRECTOS | D7: =SUM(D119:D123) -> 3.0177299e+09 | E7: =SUM(E119:E123) -> 3.6586734e+09 | G7: =SUM(G119:G123) -> 2.684601e+09 | H7: =SUM(H119:H123) -> 9.7407232e+08 | I7: =SUM(I119:I123) -> 3.6586734e+09 | K7: =SUM(K119:K123) -> 2.684601e+09 | L7: =SUM(L119:L123) -> 9.5353134e+08 | M7: =SUM(M119:M123) -> 3.6381324e+09 | O7: =SUM(O119:O123) -> 0 | P7: =SUM(P119:P123) -> 20540982 | Q7: =SUM(Q119:Q123) -> 20540982 | R7: =SUM(D7:Q7) -> 2.1311097e+10
R8: =SUM(D8:Q8) -> 0
A9: 0A00 | B9: A - MANO DE OBRA DIRECTA | D9: =SUM(D10:D17) -> 9.8950398e+08 | E9: =SUM(E10:E17) -> 1.2398846e+09 | G9: =SUM(G10:G17) -> 8.9784595e+08 | H9: =SUM(H10:H17) -> 3.4203863e+08 | I9: =SUM(I10:I17) -> 1.2398846e+09 | K9: =SUM(K10:K17) -> 8.9784595e+08 | L9: =SUM(L10:L17) -> 3.4398463e+08 | M9: =SUM(M10:M17) -> 1.2418306e+09 | O9: =SUM(O10:O17) -> 0 | P9: =SUM(P10:P17) -> -1946003.6 | Q9: =SUM(Q10:Q17) -> -1946003.6 | R9: =SUM(D9:Q9) -> 7.1889269e+09
A10: 0A01 | B10: Obras Civiles | D10: =SUMIF(CATEGORIAS[[#All],[SUBGRUPO]],A10,CATEGORIAS[[#All],[PRESUPUESTO (ORIGINAL)]]) -> 2.4934757e+08 | E10: =+SUMIF(CATEGORIAS[[#All],[SUBGRUPO]],A10,CATEGORIAS[[#All],[PRODUCCION PARTIDAS ORIGINALES ACTUAL]]) +SUMIF(CATEGORIAS[[#All],[SUBGRUPO]],A10,CATEGORIAS[[#All],[PRODUCCION ADICIONALES ACTUAL]]) +SUMIF(CATEGORIAS[[#All],[SUBGRUPO]],A10,CATEGORIAS[[#All],[PROYECCION DE INGRESO DEL SALDO]]) -> 1.9880333e+08 | G10: =+SUMIF(CATEGORIAS[[#All],[SUBGRUPO]],A10,CATEGORIAS[[#All],[PRODUCCION PARTIDAS ORIGINALES ACTUAL]]) -> 1.5356467e+08 | H10: =+SUMIF(CATEGORIAS[[#All],[SUBGRUPO]],A10,CATEGORIAS[[#All],[PRODUCCION ADICIONALES ACTUAL]]) -> 45238661 | I10: =G10+H10 -> 1.9880333e+08 | K10: =+SUMIF(CATEGORIAS[[#All],[SUBGRUPO]],A10,CATEGORIAS[[#All],[PRODUCCION ANTERIOR]]) -> 1.5356467e+08 | L10: =+SUMIF(CATEGORIAS[[#All],[SUBGRUPO]],A10,CATEGORIAS[[#All],[PRODUCCION ADICIONALES ANTERIOR]]) -> 45209537 | M10: =K10+L10 -> 1.9877421e+08 | O10: =G10-K10 -> 0 | P10: =H10-L10 -> 29123.702 | Q10: =I10-M10 -> 29123.702 | R10: =SUM(D10:Q10) -> 1.2433642e+09
A11: 0A02 | B11: Estructura | D11: =SUMIF(CATEGORIAS[[#All],[SUBGRUPO]],A11,CATEGORIAS[[#All],[PRESUPUESTO (ORIGINAL)]]) -> 9107425.3 | E11: =+SUMIF(CATEGORIAS[[#All],[SUBGRUPO]],A11,CATEGORIAS[[#All],[PRODUCCION PARTIDAS ORIGINALES ACTUAL]]) +SUMIF(CATEGORIAS[[#All],[SUBGRUPO]],A11,CATEGORIAS[[#All],[PRODUCCION ADICIONALES ACTUAL]]) +SUMIF(CATEGORIAS[[#All],[SUBGRUPO]],A11,CATEGORIAS[[#All],[PROYECCION DE INGRESO DEL SALDO]]) -> 6205931.1 | G11: =+SUMIF(CATEGORIAS[[#All],[SUBGRUPO]],A11,CATEGORIAS[[#All],[PRODUCCION PARTIDAS ORIGINALES ACTUAL]]) -> 6204754.4 | H11: =+SUMIF(CATEGORIAS[[#All],[SUBGRUPO]],A11,CATEGORIAS[[#All],[PRODUCCION ADICIONALES ACTUAL]]) -> 1176.7382 | I11: =G11+H11 -> 6205931.1 | K11: =+SUMIF(CATEGORIAS[[#All],[SUBGRUPO]],A11,CATEGORIAS[[#All],[PRODUCCION ANTERIOR]]) -> 6204754.4 | L11: =+SUMIF(CATEGORIAS[[#All],[SUBGRUPO]],A11,CATEGORIAS[[#All],[PRODUCCION ADICIONALES ANTERIOR]]) -> 0 | M11: =K11+L11 -> 6204754.4 | O11: =G11-K11 -> 0 | P11: =H11-L11 -> 1176.7382 | Q11: =I11-M11 -> 1176.7382 | R11: =SUM(D11:Q11) -> 40137081
A12: 0A03 | B12: =VLOOKUP(A12,'Analisis por Categorias'!B:C,2,FALSE) -> Mecanica | D12: =SUMIF(CATEGORIAS[[#All],[SUBGRUPO]],A12,CATEGORIAS[[#All],[PRESUPUESTO (ORIGINAL)]]) -> 6.482323e+08 | E12: =+SUMIF(CATEGORIAS[[#All],[SUBGRUPO]],A12,CATEGORIAS[[#All],[PRODUCCION PARTIDAS ORIGINALES ACTUAL]]) +SUMIF(CATEGORIAS[[#All],[SUBGRUPO]],A12,CATEGORIAS[[#All],[PRODUCCION ADICIONALES ACTUAL]]) +SUMIF(CATEGORIAS[[#All],[SUBGRUPO]],A12,CATEGORIAS[[#All],[PROYECCION DE INGRESO DEL SALDO]]) -> 8.4180112e+08 | G12: =+SUMIF(CATEGORIAS[[#All],[SUBGRUPO]],A12,CATEGORIAS[[#All],[PRODUCCION PARTIDAS ORIGINALES ACTUAL]]) -> 6.8691462e+08 | H12: =+SUMIF(CATEGORIAS[[#All],[SUBGRUPO]],A12,CATEGORIAS[[#All],[PRODUCCION ADICIONALES ACTUAL]]) -> 1.548865e+08 | I12: =G12+H12 -> 8.4180112e+08 | K12: =+SUMIF(CATEGORIAS[[#All],[SUBGRUPO]],A12,CATEGORIAS[[#All],[PRODUCCION ANTERIOR]]) -> 6.8691462e+08 | L12: =+SUMIF(CATEGORIAS[[#All],[SUBGRUPO]],A12,CATEGORIAS[[#All],[PRODUCCION ADICIONALES ANTERIOR]]) -> 1.5687251e+08 | M12: =K12+L12 -> 8.4378713e+08 | O12: =G12-K12 -> 0 | P12: =H12-L12 -> -1986006.9 | Q12: =I12-M12 -> -1986006.9 | R12: =SUM(D12:Q12) -> 4.8572379e+09
A13: 0A04 | B13: =VLOOKUP(A13,'Analisis por Categorias'!B:C,2,FALSE) -> Cañería | D13: =SUMIF(CATEGORIAS[[#All],[SUBGRUPO]],A13,CATEGORIAS[[#All],[PRESUPUESTO (ORIGINAL)]]) -> 37872374 | E13: =+SUMIF(CATEGORIAS[[#All],[SUBGRUPO]],A13,CATEGORIAS[[#All],[PRODUCCION PARTIDAS ORIGINALES ACTUAL]]) +SUMIF(CATEGORIAS[[#All],[SUBGRUPO]],A13,CATEGORIAS[[#All],[PRODUCCION ADICIONALES ACTUAL]]) +SUMIF(CATEGORIAS[[#All],[SUBGRUPO]],A13,CATEGORIAS[[#All],[PROYECCION DE INGRESO DEL SALDO]]) -> 18825990 | G13: =+SUMIF(CATEGORIAS[[#All],[SUBGRUPO]],A13,CATEGORIAS[[#All],[PRODUCCION PARTIDAS ORIGINALES ACTUAL]]) -> 9663482.8 | H13: =+SUMIF(CATEGORIAS[[#All],[SUBGRUPO]],A13,CATEGORIAS[[#All],[PRODUCCION ADICIONALES ACTUAL]]) -> 9162507.4 | I13: =G13+H13 -> 18825990 | K13: =+SUMIF(CATEGORIAS[[#All],[SUBGRUPO]],A13,CATEGORIAS[[#All],[PRODUCCION ANTERIOR]]) -> 9663482.8 | L13: =+SUMIF(CATEGORIAS[[#All],[SUBGRUPO]],A13,CATEGORIAS[[#All],[PRODUCCION ADICIONALES ANTERIOR]]) -> 9160674.7 | M13: =K13+L13 -> 18824158 | O13: =G13-K13 -> 0 | P13: =H13-L13 -> 1832.6897 | Q13: =I13-M13 -> 1832.6897 | R13: =SUM(D13:Q13) -> 1.3200233e+08
A14: 0A05 | B14: =VLOOKUP(A14,'Analisis por Categorias'!B:C,2,FALSE) -> Electricidad & Instrumentacion | D14: =SUMIF(CATEGORIAS[[#All],[SUBGRUPO]],A14,CATEGORIAS[[#All],[PRESUPUESTO (ORIGINAL)]]) -> 4909779.4 | E14: =+SUMIF(CATEGORIAS[[#All],[SUBGRUPO]],A14,CATEGORIAS[[#All],[PRODUCCION PARTIDAS ORIGINALES ACTUAL]]) +SUMIF(CATEGORIAS[[#All],[SUBGRUPO]],A14,CATEGORIAS[[#All],[PRODUCCION ADICIONALES ACTUAL]]) +SUMIF(CATEGORIAS[[#All],[SUBGRUPO]],A14,CATEGORIAS[[#All],[PROYECCION DE INGRESO DEL SALDO]]) -> 1.1961519e+08 | G14: =+SUMIF(CATEGORIAS[[#All],[SUBGRUPO]],A14,CATEGORIAS[[#All],[PRODUCCION PARTIDAS ORIGINALES ACTUAL]]) -> 3934123.1 | H14: =+SUMIF(CATEGORIAS[[#All],[SUBGRUPO]],A14,CATEGORIAS[[#All],[PRODUCCION ADICIONALES ACTUAL]]) -> 1.1568107e+08 | I14: =G14+H14 -> 1.1961519e+08 | K14: =+SUMIF(CATEGORIAS[[#All],[SUBGRUPO]],A14,CATEGORIAS[[#All],[PRODUCCION ANTERIOR]]) -> 3934123.1 | L14: =+SUMIF(CATEGORIAS[[#All],[SUBGRUPO]],A14,CATEGORIAS[[#All],[PRODUCCION ADICIONALES ANTERIOR]]) -> 1.1568032e+08 | M14: =K14+L14 -> 1.1961445e+08 | O14: =G14-K14 -> 0 | P14: =H14-L14 -> 746.11059 | Q14: =I14-M14 -> 746.11059 | R14: =SUM(D14:Q14) -> 6.0298574e+08
A15: 0A06 | B15: =VLOOKUP(A15,'Analisis por Categorias'!B:C,2,FALSE) -> #N/A | D15: =SUMIF(CATEGORIAS[[#All],[SUBGRUPO]],A15,CATEGORIAS[[#All],[PRESUPUESTO (ORIGINAL)]]) -> 0 | E15: =+SUMIF(CATEGORIAS[[#All],[SUBGRUPO]],A15,CATEGORIAS[[#All],[PRODUCCION PARTIDAS ORIGINALES ACTUAL]]) +SUMIF(CATEGORIAS[[#All],[SUBGRUPO]],A15,CATEGORIAS[[#All],[PRODUCCION ADICIONALES ACTUAL]]) +SUMIF(CATEGORIAS[[#All],[SUBGRUPO]],A15,CATEGORIAS[[#All],[PROYECCION DE INGRESO DEL SALDO]]) -> 0 | G15: =+SUMIF(CATEGORIAS[[#All],[SUBGRUPO]],A15,CATEGORIAS[[#All],[PRODUCCION PARTIDAS ORIGINALES ACTUAL]]) -> 0 | H15: =+SUMIF(CATEGORIAS[[#All],[SUBGRUPO]],A15,CATEGORIAS[[#All],[PRODUCCION ADICIONALES ACTUAL]]) -> 0 | I15: =G15+H15 -> 0 | K15: =+SUMIF(CATEGORIAS[[#All],[SUBGRUPO]],A15,CATEGORIAS[[#All],[PRODUCCION ANTERIOR]]) -> 0 | L15: =+SUMIF(CATEGORIAS[[#All],[SUBGRUPO]],A15,CATEGORIAS[[#All],[PRODUCCION ADICIONALES ANTERIOR]]) -> 0 | M15: =K15+L15 -> 0 | O15: =G15-K15 -> 0 | P15: =H15-L15 -> 0 | Q15: =I15-M15 -> 0 | R15: =SUM(D15:Q15) -> 0
A16: 0A07 | B16: =VLOOKUP(A16,'Analisis por Categorias'!B:C,2,FALSE) -> #N/A | D16: =SUMIF(CATEGORIAS[[#All],[SUBGRUPO]],A16,CATEGORIAS[[#All],[PRESUPUESTO (ORIGINAL)]]) -> 0 | E16: =+SUMIF(CATEGORIAS[[#All],[SUBGRUPO]],A16,CATEGORIAS[[#All],[PRODUCCION PARTIDAS ORIGINALES ACTUAL]]) +SUMIF(CATEGORIAS[[#All],[SUBGRUPO]],A16,CATEGORIAS[[#All],[PRODUCCION ADICIONALES ACTUAL]]) +SUMIF(CATEGORIAS[[#All],[SUBGRUPO]],A16,CATEGORIAS[[#All],[PROYECCION DE INGRESO DEL SALDO]]) -> 0 | G16: =+SUMIF(CATEGORIAS[[#All],[SUBGRUPO]],A16,CATEGORIAS[[#All],[PRODUCCION PARTIDAS ORIGINALES ACTUAL]]) -> 0 | H16: =+SUMIF(CATEGORIAS[[#All],[SUBGRUPO]],A16,CATEGORIAS[[#All],[PRODUCCION ADICIONALES ACTUAL]]) -> 0 | I16: =G16+H16 -> 0 | K16: =+SUMIF(CATEGORIAS[[#All],[SUBGRUPO]],A16,CATEGORIAS[[#All],[PRODUCCION ANTERIOR]]) -> 0 | L16: =+SUMIF(CATEGORIAS[[#All],[SUBGRUPO]],A16,CATEGORIAS[[#All],[PRODUCCION ADICIONALES ANTERIOR]]) -> 0 | M16: =K16+L16 -> 0 | O16: =G16-K16 -> 0 | P16: =H16-L16 -> 0 | Q16: =I16-M16 -> 0 | R16: =SUM(D16:Q16) -> 0
A17: 0A08 | B17: Andamios | D17: =SUMIF(CATEGORIAS[[#All],[SUBGRUPO]],A17,CATEGORIAS[[#All],[PRESUPUESTO (ORIGINAL)]]) -> 40034534 | E17: =+SUMIF(CATEGORIAS[[#All],[SUBGRUPO]],A17,CATEGORIAS[[#All],[PRODUCCION PARTIDAS ORIGINALES ACTUAL]]) +SUMIF(CATEGORIAS[[#All],[SUBGRUPO]],A17,CATEGORIAS[[#All],[PRODUCCION ADICIONALES ACTUAL]]) +SUMIF(CATEGORIAS[[#All],[SUBGRUPO]],A17,CATEGORIAS[[#All],[PROYECCION DE INGRESO DEL SALDO]]) -> 54633010 | G17: =+SUMIF(CATEGORIAS[[#All],[SUBGRUPO]],A17,CATEGORIAS[[#All],[PRODUCCION PARTIDAS ORIGINALES ACTUAL]]) -> 37564295 | H17: =+SUMIF(CATEGORIAS[[#All],[SUBGRUPO]],A17,CATEGORIAS[[#All],[PRODUCCION ADICIONALES ACTUAL]]) -> 17068715 | I17: =G17+H17 -> 54633010 | K17: =+SUMIF(CATEGORIAS[[#All],[SUBGRUPO]],A17,CATEGORIAS[[#All],[PRODUCCION ANTERIOR]]) -> 37564295 | L17: =+SUMIF(CATEGORIAS[[#All],[SUBGRUPO]],A17,CATEGORIAS[[#All],[PRODUCCION ADICIONALES ANTERIOR]]) -> 17061591 | M17: =K17+L17 -> 54625886 | O17: =G17-K17 -> 0 | P17: =H17-L17 -> 7124.1082 | Q17: =I17-M17 -> 7124.1082
R18: =SUM(D18:Q18) -> 0
A19: 0B00 | B19: B - MATERIALES | D19: =SUM(D20:D28) -> 6.5413681e+08 | E19: =SUM(E20:E28) -> 6.7918319e+08 | G19: =SUM(G20:G27) -> 5.8206097e+08 | H19: =SUM(H20:H27) -> 97122217 | I19: =SUM(I20:I27) -> 6.7918319e+08 | K19: =SUM(K20:K27) -> 5.8206097e+08 | L19: =SUM(L20:L27) -> 97011829 | M19: =SUM(M20:M27) -> 6.790728e+08 | O19: =SUM(O20:O27) -> 0 | P19: =SUM(P20:P27) -> 110388.48 | Q19: =SUM(Q20:Q27) -> 110388.48 | R19: =SUM(D19:Q19) -> 4.0500527e+09
A20: 0B01 | B20: =VLOOKUP(A20,'Analisis por Categorias'!B:C,2,FALSE) -> Civil | D20: =SUMIF(CATEGORIAS[[#All],[SUBGRUPO]],A20,CATEGORIAS[[#All],[PRESUPUESTO (ORIGINAL)]]) -> 5.0495371e+08 | E20: =+SUMIF(CATEGORIAS[[#All],[SUBGRUPO]],A20,CATEGORIAS[[#All],[PRODUCCION PARTIDAS ORIGINALES ACTUAL]]) +SUMIF(CATEGORIAS[[#All],[SUBGRUPO]],A20,CATEGORIAS[[#All],[PRODUCCION ADICIONALES ACTUAL]]) +SUMIF(CATEGORIAS[[#All],[SUBGRUPO]],A20,CATEGORIAS[[#All],[PROYECCION DE INGRESO DEL SALDO]]) -> 4.5245283e+08 | G20: =+SUMIF(CATEGORIAS[[#All],[SUBGRUPO]],A20,CATEGORIAS[[#All],[PRODUCCION PARTIDAS ORIGINALES ACTUAL]]) -> 4.3668072e+08 | H20: =+SUMIF(CATEGORIAS[[#All],[SUBGRUPO]],A20,CATEGORIAS[[#All],[PRODUCCION ADICIONALES ACTUAL]]) -> 15772114 | I20: =G20+H20 -> 4.5245283e+08 | K20: =+SUMIF(CATEGORIAS[[#All],[SUBGRUPO]],A20,CATEGORIAS[[#All],[PRODUCCION ANTERIOR]]) -> 4.3668072e+08 | L20: =+SUMIF(CATEGORIAS[[#All],[SUBGRUPO]],A20,CATEGORIAS[[#All],[PRODUCCION ADICIONALES ANTERIOR]]) -> 15689297 | M20: =K20+L20 -> 4.5237001e+08 | O20: =G20-K20 -> 0 | P20: =H20-L20 -> 82816.959 | Q20: =I20-M20 -> 82816.959 | R20: =SUM(D20:Q20) -> 2.7672179e+09
A21: 0B02 | B21: =VLOOKUP(A21,'Analisis por Categorias'!B:C,2,FALSE) -> #N/A | D21: =SUMIF(CATEGORIAS[[#All],[SUBGRUPO]],A21,CATEGORIAS[[#All],[PRESUPUESTO (ORIGINAL)]]) -> 0 | E21: =+SUMIF(CATEGORIAS[[#All],[SUBGRUPO]],A21,CATEGORIAS[[#All],[PRODUCCION PARTIDAS ORIGINALES ACTUAL]]) +SUMIF(CATEGORIAS[[#All],[SUBGRUPO]],A21,CATEGORIAS[[#All],[PRODUCCION ADICIONALES ACTUAL]]) +SUMIF(CATEGORIAS[[#All],[SUBGRUPO]],A21,CATEGORIAS[[#All],[PROYECCION DE INGRESO DEL SALDO]]) -> 0 | G21: =+SUMIF(CATEGORIAS[[#All],[SUBGRUPO]],A21,CATEGORIAS[[#All],[PRODUCCION PARTIDAS ORIGINALES ACTUAL]]) -> 0 | H21: =+SUMIF(CATEGORIAS[[#All],[SUBGRUPO]],A21,CATEGORIAS[[#All],[PRODUCCION ADICIONALES ACTUAL]]) -> 0 | I21: =G21+H21 -> 0 | K21: =+SUMIF(CATEGORIAS[[#All],[SUBGRUPO]],A21,CATEGORIAS[[#All],[PRODUCCION ANTERIOR]]) -> 0 | L21: =+SUMIF(CATEGORIAS[[#All],[SUBGRUPO]],A21,CATEGORIAS[[#All],[PRODUCCION ADICIONALES ANTERIOR]]) -> 0 | M21: =K21+L21 -> 0 | O21: =G21-K21 -> 0 | P21: =H21-L21 -> 0 | Q21: =I21-M21 -> 0 | R21: =SUM(D21:Q21) -> 0
A22: 0B03 | B22: =VLOOKUP(A22,'Analisis por Categorias'!B:C,2,FALSE) -> #N/A | D22: =SUMIF(CATEGORIAS[[#All],[SUBGRUPO]],A22,CATEGORIAS[[#All],[PRESUPUESTO (ORIGINAL)]]) -> 0 | E22: =+SUMIF(CATEGORIAS[[#All],[SUBGRUPO]],A22,CATEGORIAS[[#All],[PRODUCCION PARTIDAS ORIGINALES ACTUAL]]) +SUMIF(CATEGORIAS[[#All],[SUBGRUPO]],A22,CATEGORIAS[[#All],[PRODUCCION ADICIONALES ACTUAL]]) +SUMIF(CATEGORIAS[[#All],[SUBGRUPO]],A22,CATEGORIAS[[#All],[PROYECCION DE INGRESO DEL SALDO]]) -> 0 | G22: =+SUMIF(CATEGORIAS[[#All],[SUBGRUPO]],A22,CATEGORIAS[[#All],[PRODUCCION PARTIDAS ORIGINALES ACTUAL]]) -> 0 | H22: =+SUMIF(CATEGORIAS[[#All],[SUBGRUPO]],A22,CATEGORIAS[[#All],[PRODUCCION ADICIONALES ACTUAL]]) -> 0 | I22: =G22+H22 -> 0 | K22: =+SUMIF(CATEGORIAS[[#All],[SUBGRUPO]],A22,CATEGORIAS[[#All],[PRODUCCION ANTERIOR]]) -> 0 | L22: =+SUMIF(CATEGORIAS[[#All],[SUBGRUPO]],A22,CATEGORIAS[[#All],[PRODUCCION ADICIONALES ANTERIOR]]) -> 0 | M22: =K22+L22 -> 0 | O22: =G22-K22 -> 0 | P22: =H22-L22 -> 0 | Q22: =I22-M22 -> 0 | R22: =SUM(D22:Q22) -> 0
A23: 0B04 | B23: =VLOOKUP(A23,'Analisis por Categorias'!B:C,2,FALSE) -> Mecánica | D23: =SUMIF(CATEGORIAS[[#All],[SUBGRUPO]],A23,CATEGORIAS[[#All],[PRESUPUESTO (ORIGINAL)]]) -> 1.4433078e+08 | E23: =+SUMIF(CATEGORIAS[[#All],[SUBGRUPO]],A23,CATEGORIAS[[#All],[PRODUCCION PARTIDAS ORIGINALES ACTUAL]]) +SUMIF(CATEGORIAS[[#All],[SUBGRUPO]],A23,CATEGORIAS[[#All],[PRODUCCION ADICIONALES ACTUAL]]) +SUMIF(CATEGORIAS[[#All],[SUBGRUPO]],A23,CATEGORIAS[[#All],[PROYECCION DE INGRESO DEL SALDO]]) -> 2.2469483e+08 | G23: =+SUMIF(CATEGORIAS[[#All],[SUBGRUPO]],A23,CATEGORIAS[[#All],[PRODUCCION PARTIDAS ORIGINALES ACTUAL]]) -> 1.4351057e+08 | H23: =+SUMIF(CATEGORIAS[[#All],[SUBGRUPO]],A23,CATEGORIAS[[#All],[PRODUCCION ADICIONALES ACTUAL]]) -> 81184254 | I23: =G23+H23 -> 2.2469483e+08 | K23: =+SUMIF(CATEGORIAS[[#All],[SUBGRUPO]],A23,CATEGORIAS[[#All],[PRODUCCION ANTERIOR]]) -> 1.4351057e+08 | L23: =+SUMIF(CATEGORIAS[[#All],[SUBGRUPO]],A23,CATEGORIAS[[#All],[PRODUCCION ADICIONALES ANTERIOR]]) -> 81157037 | M23: =K23+L23 -> 2.2466761e+08 | O23: =G23-K23 -> 0 | P23: =H23-L23 -> 27216.932 | Q23: =I23-M23 -> 27216.932 | R23: =SUM(D23:Q23) -> 1.2678049e+09
A24: 0B05 | B24: =VLOOKUP(A24,'Analisis por Categorias'!B:C,2,FALSE) -> Cañería | D24: =SUMIF(CATEGORIAS[[#All],[SUBGRUPO]],A24,CATEGORIAS[[#All],[PRESUPUESTO (ORIGINAL)]]) -> 3653812.6 | E24: =+SUMIF(CATEGORIAS[[#All],[SUBGRUPO]],A24,CATEGORIAS[[#All],[PRODUCCION PARTIDAS ORIGINALES ACTUAL]]) +SUMIF(CATEGORIAS[[#All],[SUBGRUPO]],A24,CATEGORIAS[[#All],[PRODUCCION ADICIONALES ACTUAL]]) +SUMIF(CATEGORIAS[[#All],[SUBGRUPO]],A24,CATEGORIAS[[#All],[PROYECCION DE INGRESO DEL SALDO]]) -> 1069762.3 | G24: =+SUMIF(CATEGORIAS[[#All],[SUBGRUPO]],A24,CATEGORIAS[[#All],[PRODUCCION PARTIDAS ORIGINALES ACTUAL]]) -> 904096.44 | H24: =+SUMIF(CATEGORIAS[[#All],[SUBGRUPO]],A24,CATEGORIAS[[#All],[PRODUCCION ADICIONALES ACTUAL]]) -> 165665.86 | I24: =G24+H24 -> 1069762.3 | K24: =+SUMIF(CATEGORIAS[[#All],[SUBGRUPO]],A24,CATEGORIAS[[#All],[PRODUCCION ANTERIOR]]) -> 904096.44 | L24: =+SUMIF(CATEGORIAS[[#All],[SUBGRUPO]],A24,CATEGORIAS[[#All],[PRODUCCION ADICIONALES ANTERIOR]]) -> 165494.4 | M24: =K24+L24 -> 1069590.8 | O24: =G24-K24 -> 0 | P24: =H24-L24 -> 171.46284 | Q24: =I24-M24 -> 171.46284 | R24: =SUM(D24:Q24) -> 9002624.1
A25: 0B06 | B25: =VLOOKUP(A25,'Analisis por Categorias'!B:C,2,FALSE) -> Electricidad | D25: =SUMIF(CATEGORIAS[[#All],[SUBGRUPO]],A25,CATEGORIAS[[#All],[PRESUPUESTO (ORIGINAL)]]) -> 1198500 | E25: =+SUMIF(CATEGORIAS[[#All],[SUBGRUPO]],A25,CATEGORIAS[[#All],[PRODUCCION PARTIDAS ORIGINALES ACTUAL]]) +SUMIF(CATEGORIAS[[#All],[SUBGRUPO]],A25,CATEGORIAS[[#All],[PRODUCCION ADICIONALES ACTUAL]]) +SUMIF(CATEGORIAS[[#All],[SUBGRUPO]],A25,CATEGORIAS[[#All],[PROYECCION DE INGRESO DEL SALDO]]) -> 965766.64 | G25: =+SUMIF(CATEGORIAS[[#All],[SUBGRUPO]],A25,CATEGORIAS[[#All],[PRODUCCION PARTIDAS ORIGINALES ACTUAL]]) -> 965583.51 | H25: =+SUMIF(CATEGORIAS[[#All],[SUBGRUPO]],A25,CATEGORIAS[[#All],[PRODUCCION ADICIONALES ACTUAL]]) -> 183.12393 | I25: =G25+H25 -> 965766.64 | K25: =+SUMIF(CATEGORIAS[[#All],[SUBGRUPO]],A25,CATEGORIAS[[#All],[PRODUCCION ANTERIOR]]) -> 965583.51 | L25: =+SUMIF(CATEGORIAS[[#All],[SUBGRUPO]],A25,CATEGORIAS[[#All],[PRODUCCION ADICIONALES ANTERIOR]]) -> 0 | M25: =K25+L25 -> 965583.51 | O25: =G25-K25 -> 0 | P25: =H25-L25 -> 183.12393 | Q25: =I25-M25 -> 183.12393 | R25: =SUM(D25:Q25) -> 6027333.2
