Workbook
Name \1: #REF!
Name \q: #REF!
Name \w: #REF!
Name _______us96: #REF!
Name _____us96: #REF!
Name ____BAS1: #REF!
Name ____us96: #REF!
Name ___BAS1: #REF!
Name ___res1: #REF!
Name ___res3: #REF!
Name ___res4: #REF!
Name ___us96: #REF!
Name __BAS1: #REF!
Name __DAT1: #REF!
Name __DAT10: #REF!
Name __DAT11: #REF!
Name __DAT12: #REF!
Name __DAT13: #REF!
Name __DAT14: #REF!
Name __DAT15: #REF!
Name __DAT16: #REF!
Name __DAT17: #REF!
Name __DAT18: #REF!
Name __DAT19: #REF!
Name __DAT2: #REF!
Name __DAT20: #REF!
Name __DAT3: #REF!
Name __DAT4: #REF!
Name __DAT5: #REF!
Name __DAT6: #REF!
Name __DAT7: #REF!
Name __DAT8: #REF!
Name __DAT9: #REF!
Name __res1: #REF!
Name __res2: #REF!
Name __res3: #REF!
Name __res4: #REF!
Name __us96: #REF!
Name _A: #REF!
Name _aa: #REF!
Name _ACT1: #REF!
Name _ACT10: #REF!
Name _ACT11: #REF!
Name _ACT12: #REF!
Name _ACT13: #REF!
Name _ACT14: #REF!
Name _ACT15: #REF!
Name _ACT16: #REF!
Name _ACT17: #REF!
Name _ACT18: #REF!
Name _ACT19: #REF!
Name _ACT2: #REF!
Name _ACT20: #REF!
Name _ACT21: #REF!
Name _ACT22: #REF!
Name _ACT23: #REF!
Name _ACT3: #REF!
Name _ACT4: #REF!
Name _ACT5: #REF!
Name _ACT6: #REF!

Sheet Indice
D2: INDICE | H2: CC: EIMI00412 MONTAJE ELECTROMECÁNICO " PROYECTO NUEVAS PRENSAS DE LODOS"
C4: INFORME DE COSTOS N° 3
G9: Cliente : | H9: CMPC
G10: Administrador de Proyecto : | H10: Jose Petersen
G11: Centros de Costos : | H11: EIMI00412
G12: Periodo | H12: : | I12: 45992
C16: Matriz de Producción
C17: Matriz de Costos
C18: Matriz de Resultado
C19: Matriz de Proyecciones

Sheet Formato General
B1: INFORME DE RESULTADOS
B2: =MID(Indice!H2,1,100) -> CC: EIMI00412 MONTAJE ELECTROMECÁNICO " PROYECTO NUEVAS PRENSAS DE LODOS" | X2: ="Periodo : " & TEXT(Indice!I12,"Mmmm yyyy") -> Periodo : diciembre 2025
A4: FORMATO GENERAL | B4: Num | C4: Partida | E4: Presupuesto Original | F4: PBI | G4: DIFERENCIA | H4: Aumentos o Dism. de Obras y Reajuste | I4: PBI | J4: DIFERENCIA | K4: Presupuesto Corregido | L4: PBI | M4: DIFERENCIA | O4: Gastos Reales del Mes | P4: PBI | Q4: DIFERENCIA | R4: Gastos Reales Acumulados | S4: PBI | T4: DIFERENCIA | U4: Avance Según Obra Ejecutada | V4: PBI | W4: DIFERENCIA | X4: Proyección de gasto por efectuar | Y4: PBI | Z4: DIFERENCIA | AB4: Resultado de la Obra | AC4: PBI | AD4: DIFERENCIA
B5: A. | C5: Costos Directos
B6: A1 | C6: 01 - Obras Civiles | E6: =IF(ISBLANK(A6),"", SUMIF(CATEGORIAS[[#All],[FORMATO GENERAL]], A6, CATEGORIAS[[#All],[PRESUPUESTO (ORIGINAL)]])) | H6: =IF(ISBLANK(A6),"",K6-E6) | K6: =IF(ISBLANK(A6),"",SUMIF(CATEGORIAS[[#All],[FORMATO GENERAL]], A6, CATEGORIAS[[#All],[PRESUPUESTO FINAL PROYECTADO]])) | O6: =IF(ISBLANK(A6),"",R6-SUMIF(CATEGORIAS[[#All],[FORMATO GENERAL]], A6, CATEGORIAS[[#All],[COSTO REAL ANTERIOR]])) | R6: =IF(ISBLANK(A6),"",SUMIF(CATEGORIAS[[#All],[FORMATO GENERAL]], A6, CATEGORIAS[[#All],[COSTO REAL]])) | U6: =IF(ISBLANK(A6),"",SUMIF(CATEGORIAS[[#All],[FORMATO GENERAL]], A6, CATEGORIAS[[#All],[TOTAL PRODUCCION ACTUAL]])) | X6: =IF(ISBLANK(A6),"",SUMIF(CATEGORIAS[[#All],[FORMATO GENERAL]], A6, CATEGORIAS[[#All],[PROYECCION TOTAL DE COSTO]])) | AB6: =IF(ISBLANK(A6),"",TRUNC(K6-R6-X6,2))
A7: 0A01 | C7: Mano de Obra | E7: =IF(ISBLANK(A7),"", SUMIF(CATEGORIAS[[#All],[FORMATO GENERAL]], A7, CATEGORIAS[[#All],[PRESUPUESTO (ORIGINAL)]])) -> 1.4597251e+08 | F7: 145972510 | G7: =+E7-F7 -> 0.11940765 | H7: =IF(ISBLANK(A7),"",K7-E7) -> 14606632 | I7: 14606632 | J7: =+H7-I7 -> -0.11194655 | K7: =IF(ISBLANK(A7),"",SUMIF(CATEGORIAS[[#All],[FORMATO GENERAL]], A7, CATEGORIAS[[#All],[PRESUPUESTO FINAL PROYECTADO]])) -> 1.6057914e+08 | L7: 160579142 | M7: =+K7-L7 -> 0.0074611008 | O7: =IF(ISBLANK(A7),"",R7-SUMIF(CATEGORIAS[[#All],[FORMATO GENERAL]], A7, CATEGORIAS[[#All],[COSTO REAL ANTERIOR]])) -> 48030488 | P7: 48030488 | Q7: =+O7-P7 -> 0.087633081 | R7: =IF(ISBLANK(A7),"",SUMIF(CATEGORIAS[[#All],[FORMATO GENERAL]], A7, CATEGORIAS[[#All],[COSTO REAL]])) -> 1.0783158e+08 | S7: 107831578 | T7: =+R7-S7 -> -0.074529082 | U7: =IF(ISBLANK(A7),"",SUMIF(CATEGORIAS[[#All],[FORMATO GENERAL]], A7, CATEGORIAS[[#All],[TOTAL PRODUCCION ACTUAL]])) -> 1.1662961e+08 | V7: 116629607 | W7: =+U7-V7 -> 0.26106611 | X7: =IF(ISBLANK(A7),"",SUMIF(CATEGORIAS[[#All],[FORMATO GENERAL]], A7, CATEGORIAS[[#All],[PROYECCION TOTAL DE COSTO]])) -> 52747564 | Y7: 52747564 | Z7: =+X7-Y7 -> 0.081990182 | AB7: =IF(ISBLANK(A7),"",TRUNC(K7-R7-X7,2)) -> 0 | AD7: =+AB7-AC7 -> 0
A8: 0A02 | C8: Obras Civiles Reembolsable | E8: =IF(ISBLANK(A8),"", SUMIF(CATEGORIAS[[#All],[FORMATO GENERAL]], A8, CATEGORIAS[[#All],[PRESUPUESTO (ORIGINAL)]])) -> 64602232 | F8: 64602232 | G8: =+E8-F8 -> -0.1283 | H8: =IF(ISBLANK(A8),"",K8-E8) -> 15412760 | I8: 15412760 | J8: =+H8-I8 -> 0.050430097 | K8: =IF(ISBLANK(A8),"",SUMIF(CATEGORIAS[[#All],[FORMATO GENERAL]], A8, CATEGORIAS[[#All],[PRESUPUESTO FINAL PROYECTADO]])) -> 80014992 | L8: 80014992 | M8: =+K8-L8 -> -0.077869907 | O8: =IF(ISBLANK(A8),"",R8-SUMIF(CATEGORIAS[[#All],[FORMATO GENERAL]], A8, CATEGORIAS[[#All],[COSTO REAL ANTERIOR]])) -> 6141908 | P8: 6141908 | Q8: =+O8-P8 -> 0 | R8: =IF(ISBLANK(A8),"",SUMIF(CATEGORIAS[[#All],[FORMATO GENERAL]], A8, CATEGORIAS[[#All],[COSTO REAL]])) -> 21679270 | S8: 21679270 | T8: =+R8-S8 -> 0 | U8: =IF(ISBLANK(A8),"",SUMIF(CATEGORIAS[[#All],[FORMATO GENERAL]], A8, CATEGORIAS[[#All],[TOTAL PRODUCCION ACTUAL]])) -> 26331435 | V8: 26331435 | W8: =+U8-V8 -> 0.4492 | X8: =IF(ISBLANK(A8),"",SUMIF(CATEGORIAS[[#All],[FORMATO GENERAL]], A8, CATEGORIAS[[#All],[PROYECCION TOTAL DE COSTO]])) -> 58335715 | Y8: 58335715 | Z8: =+X8-Y8 -> -0.077869907 | AB8: =IF(ISBLANK(A8),"",TRUNC(K8-R8-X8,2)) -> 7 | AD8: =+AB8-AC8 -> 7
B9: A2 | C9: 02 - Estructura | E9: =IF(ISBLANK(A9),"", SUMIF(CATEGORIAS[[#All],[FORMATO GENERAL]], A9, CATEGORIAS[[#All],[PRESUPUESTO (ORIGINAL)]])) | G9: =+E9-F9 -> #VALUE! | H9: =IF(ISBLANK(A9),"",K9-E9) | J9: =+H9-I9 -> #VALUE! | K9: =IF(ISBLANK(A9),"",SUMIF(CATEGORIAS[[#All],[FORMATO GENERAL]], A9, CATEGORIAS[[#All],[PRESUPUESTO FINAL PROYECTADO]])) | M9: =+K9-L9 -> #VALUE! | O9: =IF(ISBLANK(A9),"",R9-SUMIF(CATEGORIAS[[#All],[FORMATO GENERAL]], A9, CATEGORIAS[[#All],[COSTO REAL ANTERIOR]])) | Q9: =+O9-P9 -> #VALUE! | R9: =IF(ISBLANK(A9),"",SUMIF(CATEGORIAS[[#All],[FORMATO GENERAL]], A9, CATEGORIAS[[#All],[COSTO REAL]])) | T9: =+R9-S9 -> #VALUE! | U9: =IF(ISBLANK(A9),"",SUMIF(CATEGORIAS[[#All],[FORMATO GENERAL]], A9, CATEGORIAS[[#All],[TOTAL PRODUCCION ACTUAL]])) | W9: =+U9-V9 -> #VALUE! | X9: =IF(ISBLANK(A9),"",SUMIF(CATEGORIAS[[#All],[FORMATO GENERAL]], A9, CATEGORIAS[[#All],[PROYECCION TOTAL DE COSTO]])) | Z9: =+X9-Y9 -> #VALUE! | AB9: =IF(ISBLANK(A9),"",TRUNC(K9-R9-X9,2)) | AD9: =+AB9-AC9 -> #VALUE!
A10: 0B01 | C10: Mano de Obra | E10: =IF(ISBLANK(A10),"", SUMIF(CATEGORIAS[[#All],[FORMATO GENERAL]], A10, CATEGORIAS[[#All],[PRESUPUESTO (ORIGINAL)]])) -> 1.7987561e+08 | F10: 179875615 | G10: =+E10-F10 -> -0.11864346 | H10: =IF(ISBLANK(A10),"",K10-E10) -> 612034.1 | I10: 612034 | J10: =+H10-I10 -> 0.098096818 | K10: =IF(ISBLANK(A10),"",SUMIF(CATEGORIAS[[#All],[FORMATO GENERAL]], A10, CATEGORIAS[[#All],[PRESUPUESTO FINAL PROYECTADO]])) -> 1.8048765e+08 | L10: 180487649 | M10: =+K10-L10 -> -0.020546645 | O10: =IF(ISBLANK(A10),"",R10-SUMIF(CATEGORIAS[[#All],[FORMATO GENERAL]], A10, CATEGORIAS[[#All],[COSTO REAL ANTERIOR]])) -> 61673899 | P10: 61673899 | Q10: =+O10-P10 -> 0.13677312 | R10: =IF(ISBLANK(A10),"",SUMIF(CATEGORIAS[[#All],[FORMATO GENERAL]], A10, CATEGORIAS[[#All],[COSTO REAL]])) -> 1.5135843e+08 | S10: 151358428 | T10: =+R10-S10 -> 0.37592137 | U10: =IF(ISBLANK(A10),"",SUMIF(CATEGORIAS[[#All],[FORMATO GENERAL]], A10, CATEGORIAS[[#All],[TOTAL PRODUCCION ACTUAL]])) -> 70290747 | V10: 70290747 | W10: =+U10-V10 -> 0.35645182 | X10: =IF(ISBLANK(A10),"",SUMIF(CATEGORIAS[[#All],[FORMATO GENERAL]], A10, CATEGORIAS[[#All],[PROYECCION TOTAL DE COSTO]])) -> 29129221 | Y10: 29129221 | Z10: =+X10-Y10 -> -0.39646801 | AB10: =IF(ISBLANK(A10),"",TRUNC(K10-R10-X10,2)) -> 0 | AD10: =+AB10-AC10 -> 0
A11: 0B02 | C11: Estructura Reembolsable | E11: =IF(ISBLANK(A11),"", SUMIF(CATEGORIAS[[#All],[FORMATO GENERAL]], A11, CATEGORIAS[[#All],[PRESUPUESTO (ORIGINAL)]])) -> 53940891 | F11: 53940891 | G11: =+E11-F11 -> -0.047499999 | H11: =IF(ISBLANK(A11),"",K11-E11) -> 31204.186 | I11: 31204 | J11: =+H11-I11 -> 0.18552163 | K11: =IF(ISBLANK(A11),"",SUMIF(CATEGORIAS[[#All],[FORMATO GENERAL]], A11, CATEGORIAS[[#All],[PRESUPUESTO FINAL PROYECTADO]])) -> 53972095 | L11: 53972095 | M11: =+K11-L11 -> 0.13802163 | O11: =IF(ISBLANK(A11),"",R11-SUMIF(CATEGORIAS[[#All],[FORMATO GENERAL]], A11, CATEGORIAS[[#All],[COSTO REAL ANTERIOR]])) -> 1917454 | P11: 1917454 | Q11: =+O11-P11 -> 0 | R11: =IF(ISBLANK(A11),"",SUMIF(CATEGORIAS[[#All],[FORMATO GENERAL]], A11, CATEGORIAS[[#All],[COSTO REAL]])) -> 2601319 | S11: 2601319 | T11: =+R11-S11 -> 0 | U11: =IF(ISBLANK(A11),"",SUMIF(CATEGORIAS[[#All],[FORMATO GENERAL]], A11, CATEGORIAS[[#All],[TOTAL PRODUCCION ACTUAL]])) -> 23564053 | V11: 23564053 | W11: =+U11-V11 -> -0.17937837 | X11: =IF(ISBLANK(A11),"",SUMIF(CATEGORIAS[[#All],[FORMATO GENERAL]], A11, CATEGORIAS[[#All],[PROYECCION TOTAL DE COSTO]])) -> 51370776 | Y11: 51370776 | Z11: =+X11-Y11 -> 0.13802163 | AB11: =IF(ISBLANK(A11),"",TRUNC(K11-R11-X11,2)) -> 0 | AD11: =+AB11-AC11 -> 0
B12: A3 | C12: 03 - Mecanica (MO Arquitectura Puentes) | E12: =IF(ISBLANK(A12),"", SUMIF(CATEGORIAS[[#All],[FORMATO GENERAL]], A12, CATEGORIAS[[#All],[PRESUPUESTO (ORIGINAL)]])) | G12: =+E12-F12 -> #VALUE! | H12: =IF(ISBLANK(A12),"",K12-E12) | J12: =+H12-I12 -> #VALUE! | K12: =IF(ISBLANK(A12),"",SUMIF(CATEGORIAS[[#All],[FORMATO GENERAL]], A12, CATEGORIAS[[#All],[PRESUPUESTO FINAL PROYECTADO]])) | M12: =+K12-L12 -> #VALUE! | O12: =IF(ISBLANK(A12),"",R12-SUMIF(CATEGORIAS[[#All],[FORMATO GENERAL]], A12, CATEGORIAS[[#All],[COSTO REAL ANTERIOR]])) | Q12: =+O12-P12 -> #VALUE! | R12: =IF(ISBLANK(A12),"",SUMIF(CATEGORIAS[[#All],[FORMATO GENERAL]], A12, CATEGORIAS[[#All],[COSTO REAL]])) | T12: =+R12-S12 -> #VALUE! | U12: =IF(ISBLANK(A12),"",SUMIF(CATEGORIAS[[#All],[FORMATO GENERAL]], A12, CATEGORIAS[[#All],[TOTAL PRODUCCION ACTUAL]])) | W12: =+U12-V12 -> #VALUE! | X12: =IF(ISBLANK(A12),"",SUMIF(CATEGORIAS[[#All],[FORMATO GENERAL]], A12, CATEGORIAS[[#All],[PROYECCION TOTAL DE COSTO]])) | Z12: =+X12-Y12 -> #VALUE! | AB12: =IF(ISBLANK(A12),"",TRUNC(K12-R12-X12,2)) | AD12: =+AB12-AC12 -> #VALUE!
A13: 0C01 | C13: Mano de Obra | E13: =IF(ISBLANK(A13),"", SUMIF(CATEGORIAS[[#All],[FORMATO GENERAL]], A13, CATEGORIAS[[#All],[PRESUPUESTO (ORIGINAL)]])) -> 1.332508e+08 | F13: 133250804 | G13: =+E13-F13 -> 0.19788337 | H13: =IF(ISBLANK(A13),"",K13-E13) -> 8661404.9 | I13: 8661405 | J13: =+H13-I13 -> -0.065739036 | K13: =IF(ISBLANK(A13),"",SUMIF(CATEGORIAS[[#All],[FORMATO GENERAL]], A13, CATEGORIAS[[#All],[PRESUPUESTO FINAL PROYECTADO]])) -> 1.4191221e+08 | L13: 141912209 | M13: =+K13-L13 -> 0.13214433 | O13: =IF(ISBLANK(A13),"",R13-SUMIF(CATEGORIAS[[#All],[FORMATO GENERAL]], A13, CATEGORIAS[[#All],[COSTO REAL ANTERIOR]])) -> 47992218 | P13: 47992218 | Q13: =+O13-P13 -> -0.25307125 | R13: =IF(ISBLANK(A13),"",SUMIF(CATEGORIAS[[#All],[FORMATO GENERAL]], A13, CATEGORIAS[[#All],[COSTO REAL]])) -> 1.4843688e+08 | S13: 148436879 | T13: =+R13-S13 -> -0.13267812 | U13: =IF(ISBLANK(A13),"",SUMIF(CATEGORIAS[[#All],[FORMATO GENERAL]], A13, CATEGORIAS[[#All],[TOTAL PRODUCCION ACTUAL]])) -> 57846587 | V13: 57846587 | W13: =+U13-V13 -> -0.42201257 | X13: =IF(ISBLANK(A13),"",SUMIF(CATEGORIAS[[#All],[FORMATO GENERAL]], A13, CATEGORIAS[[#All],[PROYECCION TOTAL DE COSTO]])) -> -6524669.7 | Y13: -6524670 | Z13: =+X13-Y13 -> 0.26482245 | AB13: =IF(ISBLANK(A13),"",TRUNC(K13-R13-X13,2)) -> 0 | AD13: =+AB13-AC13 -> 0
A14: 0C02 | C14: Mecanica Reembolsable | E14: =IF(ISBLANK(A14),"", SUMIF(CATEGORIAS[[#All],[FORMATO GENERAL]], A14, CATEGORIAS[[#All],[PRESUPUESTO (ORIGINAL)]])) -> 65364961 | F14: 65364961 | G14: =+E14-F14 -> -0.069499999 | H14: =IF(ISBLANK(A14),"",K14-E14) -> 2398036.9 | I14: 2398037 | J14: =+H14-I14 -> -0.069623649 | K14: =IF(ISBLANK(A14),"",SUMIF(CATEGORIAS[[#All],[FORMATO GENERAL]], A14, CATEGORIAS[[#All],[PRESUPUESTO FINAL PROYECTADO]])) -> 67762998 | L14: 67762998 | M14: =+K14-L14 -> -0.13912365 | O14: =IF(ISBLANK(A14),"",R14-SUMIF(CATEGORIAS[[#All],[FORMATO GENERAL]], A14, CATEGORIAS[[#All],[COSTO REAL ANTERIOR]])) -> 6395578 | P14: 6395578 | Q14: =+O14-P14 -> 0 | R14: =IF(ISBLANK(A14),"",SUMIF(CATEGORIAS[[#All],[FORMATO GENERAL]], A14, CATEGORIAS[[#All],[COSTO REAL]])) -> 15218949 | S14: 15218949 | T14: =+R14-S14 -> 0 | U14: =IF(ISBLANK(A14),"",SUMIF(CATEGORIAS[[#All],[FORMATO GENERAL]], A14, CATEGORIAS[[#All],[TOTAL PRODUCCION ACTUAL]])) -> 21505782 | V14: 21505782 | W14: =+U14-V14 -> 0.40672635 | X14: =IF(ISBLANK(A14),"",SUMIF(CATEGORIAS[[#All],[FORMATO GENERAL]], A14, CATEGORIAS[[#All],[PROYECCION TOTAL DE COSTO]])) -> 52544049 | Y14: 52544049 | Z14: =+X14-Y14 -> -0.13912365 | AB14: =IF(ISBLANK(A14),"",TRUNC(K14-R14-X14,2)) -> 0 | AD14: =+AB14-AC14 -> 0
B15: A4 | C15: 04 - Cañeria | E15: =IF(ISBLANK(A15),"", SUMIF(CATEGORIAS[[#All],[FORMATO GENERAL]], A15, CATEGORIAS[[#All],[PRESUPUESTO (ORIGINAL)]])) | G15: =+E15-F15 -> #VALUE! | H15: =IF(ISBLANK(A15),"",K15-E15) | J15: =+H15-I15 -> #VALUE! | K15: =IF(ISBLANK(A15),"",SUMIF(CATEGORIAS[[#All],[FORMATO GENERAL]], A15, CATEGORIAS[[#All],[PRESUPUESTO FINAL PROYECTADO]])) | M15: =+K15-L15 -> #VALUE! | O15: =IF(ISBLANK(A15),"",R15-SUMIF(CATEGORIAS[[#All],[FORMATO GENERAL]], A15, CATEGORIAS[[#All],[COSTO REAL ANTERIOR]])) | Q15: =+O15-P15 -> #VALUE! | R15: =IF(ISBLANK(A15),"",SUMIF(CATEGORIAS[[#All],[FORMATO GENERAL]], A15, CATEGORIAS[[#All],[COSTO REAL]])) | T15: =+R15-S15 -> #VALUE! | U15: =IF(ISBLANK(A15),"",SUMIF(CATEGORIAS[[#All],[FORMATO GENERAL]], A15, CATEGORIAS[[#All],[TOTAL PRODUCCION ACTUAL]])) | W15: =+U15-V15 -> #VALUE! | X15: =IF(ISBLANK(A15),"",SUMIF(CATEGORIAS[[#All],[FORMATO GENERAL]], A15, CATEGORIAS[[#All],[PROYECCION TOTAL DE COSTO]])) | Z15: =+X15-Y15 -> #VALUE! | AB15: =IF(ISBLANK(A15),"",TRUNC(K15-R15-X15,2)) | AD15: =+AB15-AC15 -> #VALUE!
A16: 0D01 | C16: Mano de Obra | E16: =IF(ISBLANK(A16),"", SUMIF(CATEGORIAS[[#All],[FORMATO GENERAL]], A16, CATEGORIAS[[#All],[PRESUPUESTO (ORIGINAL)]])) -> 4.7397038e+08 | F16: 473970383 | G16: =+E16-F16 -> -0.36377794 | H16: =IF(ISBLANK(A16),"",K16-E16) -> 17687642 | I16: 17687642 | J16: =+H16-I16 -> 0.15925747 | K16: =IF(ISBLANK(A16),"",SUMIF(CATEGORIAS[[#All],[FORMATO GENERAL]], A16, CATEGORIAS[[#All],[PRESUPUESTO FINAL PROYECTADO]])) -> 4.9165802e+08 | L16: 491658025 | M16: =+K16-L16 -> -0.20452046 | O16: =IF(ISBLANK(A16),"",R16-SUMIF(CATEGORIAS[[#All],[FORMATO GENERAL]], A16, CATEGORIAS[[#All],[COSTO REAL ANTERIOR]])) -> 97545747 | P16: 97545748 | Q16: =+O16-P16 -> -0.80016381 | R16: =IF(ISBLANK(A16),"",SUMIF(CATEGORIAS[[#All],[FORMATO GENERAL]], A16, CATEGORIAS[[#All],[COSTO REAL]])) -> 2.4410529e+08 | S16: 244105286 | T16: =+R16-S16 -> -0.39066339 | U16: =IF(ISBLANK(A16),"",SUMIF(CATEGORIAS[[#All],[FORMATO GENERAL]], A16, CATEGORIAS[[#All],[TOTAL PRODUCCION ACTUAL]])) -> 2.0089425e+08 | V16: 200894250 | W16: =+U16-V16 -> -0.026842386 | X16: =IF(ISBLANK(A16),"",SUMIF(CATEGORIAS[[#All],[FORMATO GENERAL]], A16, CATEGORIAS[[#All],[PROYECCION TOTAL DE COSTO]])) -> 2.4755274e+08 | Y16: 247552739 | Z16: =+X16-Y16 -> 0.18614292 | AB16: =IF(ISBLANK(A16),"",TRUNC(K16-R16-X16,2)) -> 0 | AD16: =+AB16-AC16 -> 0
A17: 0D02 | C17: Cañeria Reembolsable | E17: =IF(ISBLANK(A17),"", SUMIF(CATEGORIAS[[#All],[FORMATO GENERAL]], A17, CATEGORIAS[[#All],[PRESUPUESTO (ORIGINAL)]])) -> 1.3799808e+08 | F17: 137998078 | G17: =+E17-F17 -> 0.26400003 | H17: =IF(ISBLANK(A17),"",K17-E17) -> 3121699.7 | I17: 3121700 | J17: =+H17-I17 -> -0.2527684 | K17: =IF(ISBLANK(A17),"",SUMIF(CATEGORIAS[[#All],[FORMATO GENERAL]], A17, CATEGORIAS[[#All],[PRESUPUESTO FINAL PROYECTADO]])) -> 1.4111978e+08 | L17: 141119778 | M17: =+K17-L17 -> 0.011231631 | O17: =IF(ISBLANK(A17),"",R17-SUMIF(CATEGORIAS[[#All],[FORMATO GENERAL]], A17, CATEGORIAS[[#All],[COSTO REAL ANTERIOR]])) -> 21866710 | P17: 21866710 | Q17: =+O17-P17 -> 0 | R17: =IF(ISBLANK(A17),"",SUMIF(CATEGORIAS[[#All],[FORMATO GENERAL]], A17, CATEGORIAS[[#All],[COSTO REAL]])) -> 120804123 | S17: 120804123 | T17: =+R17-S17 -> 0 | U17: =IF(ISBLANK(A17),"",SUMIF(CATEGORIAS[[#All],[FORMATO GENERAL]], A17, CATEGORIAS[[#All],[TOTAL PRODUCCION ACTUAL]])) -> 66472512 | V17: 66472512 | W17: =+U17-V17 -> -0.47079682 | X17: =IF(ISBLANK(A17),"",SUMIF(CATEGORIAS[[#All],[FORMATO GENERAL]], A17, CATEGORIAS[[#All],[PROYECCION TOTAL DE COSTO]])) -> 20315655 | Y17: 20315655 | Z17: =+X17-Y17 -> 0.011231627 | AB17: =IF(ISBLANK(A17),"",TRUNC(K17-R17-X17,2)) -> 0 | AD17: =+AB17-AC17 -> 0
B18: A5 | C18: 05- Electricidad & Instrumentacion | E18: =IF(ISBLANK(A18),"", SUMIF(CATEGORIAS[[#All],[FORMATO GENERAL]], A18, CATEGORIAS[[#All],[PRESUPUESTO (ORIGINAL)]])) | G18: =+E18-F18 -> #VALUE! | H18: =IF(ISBLANK(A18),"",K18-E18) | J18: =+H18-I18 -> #VALUE! | K18: =IF(ISBLANK(A18),"",SUMIF(CATEGORIAS[[#All],[FORMATO GENERAL]], A18, CATEGORIAS[[#All],[PRESUPUESTO FINAL PROYECTADO]])) | M18: =+K18-L18 -> #VALUE! | O18: =IF(ISBLANK(A18),"",R18-SUMIF(CATEGORIAS[[#All],[FORMATO GENERAL]], A18, CATEGORIAS[[#All],[COSTO REAL ANTERIOR]])) | Q18: =+O18-P18 -> #VALUE! | R18: =IF(ISBLANK(A18),"",SUMIF(CATEGORIAS[[#All],[FORMATO GENERAL]], A18, CATEGORIAS[[#All],[COSTO REAL]])) | T18: =+R18-S18 -> #VALUE! | U18: =IF(ISBLANK(A18),"",SUMIF(CATEGORIAS[[#All],[FORMATO GENERAL]], A18, CATEGORIAS[[#All],[TOTAL PRODUCCION ACTUAL]])) | W18: =+U18-V18 -> #VALUE! | X18: =IF(ISBLANK(A18),"",SUMIF(CATEGORIAS[[#All],[FORMATO GENERAL]], A18, CATEGORIAS[[#All],[PROYECCION TOTAL DE COSTO]])) | Z18: =+X18-Y18 -> #VALUE! | AB18: =IF(ISBLANK(A18),"",TRUNC(K18-R18-X18,2)) | AD18: =+AB18-AC18 -> #VALUE!
A19: 0F01 | C19: Mano de Obra | E19: =IF(ISBLANK(A19),"", SUMIF(CATEGORIAS[[#All],[FORMATO GENERAL]], A19, CATEGORIAS[[#All],[PRESUPUESTO (ORIGINAL)]])) -> 3.8799498e+08 | F19: 387994981 | G19: =+E19-F19 -> -0.0095154643 | H19: =IF(ISBLANK(A19),"",K19-E19) -> 11735815 | I19: 11735815 | J19: =+H19-I19 -> 0.31848192 | K19: =IF(ISBLANK(A19),"",SUMIF(CATEGORIAS[[#All],[FORMATO GENERAL]], A19, CATEGORIAS[[#All],[PRESUPUESTO FINAL PROYECTADO]])) -> 3.997308e+08 | L19: 399730796 | M19: =+K19-L19 -> 0.30896646 | O19: =IF(ISBLANK(A19),"",R19-SUMIF(CATEGORIAS[[#All],[FORMATO GENERAL]], A19, CATEGORIAS[[#All],[COSTO REAL ANTERIOR]])) -> 48101003 | P19: 48101003 | Q19: =+O19-P19 -> 0.41932841 | R19: =IF(ISBLANK(A19),"",SUMIF(CATEGORIAS[[#All],[FORMATO GENERAL]], A19, CATEGORIAS[[#All],[COSTO REAL]])) -> 94638932 | S19: 94638932 | T19: =+R19-S19 -> 0.37510237 | U19: =IF(ISBLANK(A19),"",SUMIF(CATEGORIAS[[#All],[FORMATO GENERAL]], A19, CATEGORIAS[[#All],[TOTAL PRODUCCION ACTUAL]])) -> 50124938 | V19: 50124938 | W19: =+U19-V19 -> -0.29480966 | X19: =IF(ISBLANK(A19),"",SUMIF(CATEGORIAS[[#All],[FORMATO GENERAL]], A19, CATEGORIAS[[#All],[PROYECCION TOTAL DE COSTO]])) -> 3.0509186e+08 | Y19: 305091864 | Z19: =+X19-Y19 -> -0.066135883 | AB19: =IF(ISBLANK(A19),"",TRUNC(K19-R19-X19,2)) -> 0 | AD19: =+AB19-AC19 -> 0
A20: 0F02 | C20: Electricidad Reembolsable | E20: =IF(ISBLANK(A20),"", SUMIF(CATEGORIAS[[#All],[FORMATO GENERAL]], A20, CATEGORIAS[[#All],[PRESUPUESTO (ORIGINAL)]])) -> 1.1524467e+08 | F20: 115244667 | G20: =+E20-F20 -> -0.017499998 | H20: =IF(ISBLANK(A20),"",K20-E20) -> 7814199.6 | I20: 7814200 | J20: =+H20-I20 -> -0.39764924 | K20: =IF(ISBLANK(A20),"",SUMIF(CATEGORIAS[[#All],[FORMATO GENERAL]], A20, CATEGORIAS[[#All],[PRESUPUESTO FINAL PROYECTADO]])) -> 1.2305887e+08 | L20: 123058867 | M20: =+K20-L20 -> -0.41514924 | O20: =IF(ISBLANK(A20),"",R20-SUMIF(CATEGORIAS[[#All],[FORMATO GENERAL]], A20, CATEGORIAS[[#All],[COSTO REAL ANTERIOR]])) -> 20231798 | P20: 20231798 | Q20: =+O20-P20 -> 0 | R20: =IF(ISBLANK(A20),"",SUMIF(CATEGORIAS[[#All],[FORMATO GENERAL]], A20, CATEGORIAS[[#All],[COSTO REAL]])) -> 41128877 | S20: 41128877 | T20: =+R20-S20 -> 0 | U20: =IF(ISBLANK(A20),"",SUMIF(CATEGORIAS[[#All],[FORMATO GENERAL]], A20, CATEGORIAS[[#All],[TOTAL PRODUCCION ACTUAL]])) -> 25860927 | V20: 25860927 | W20: =+U20-V20 -> 0.068724085 | X20: =IF(ISBLANK(A20),"",SUMIF(CATEGORIAS[[#All],[FORMATO GENERAL]], A20, CATEGORIAS[[#All],[PROYECCION TOTAL DE COSTO]])) -> 81929990 | Y20: 81929990 | Z20: =+X20-Y20 -> -0.41514924 | AB20: =IF(ISBLANK(A20),"",TRUNC(K20-R20-X20,2)) -> 0 | AD20: =+AB20-AC20 -> 0
B21: A6 | C21: 06 - Andamios | E21: =IF(ISBLANK(A21),"", SUMIF(CATEGORIAS[[#All],[FORMATO GENERAL]], A21, CATEGORIAS[[#All],[PRESUPUESTO (ORIGINAL)]])) | G21: =+E21-F21 -> #VALUE! | H21: =IF(ISBLANK(A21),"",K21-E21) | J21: =+H21-I21 -> #VALUE! | K21: =IF(ISBLANK(A21),"",SUMIF(CATEGORIAS[[#All],[FORMATO GENERAL]], A21, CATEGORIAS[[#All],[PRESUPUESTO FINAL PROYECTADO]])) | M21: =+K21-L21 -> #VALUE! | O21: =IF(ISBLANK(A21),"",R21-SUMIF(CATEGORIAS[[#All],[FORMATO GENERAL]], A21, CATEGORIAS[[#All],[COSTO REAL ANTERIOR]])) | Q21: =+O21-P21 -> #VALUE! | R21: =IF(ISBLANK(A21),"",SUMIF(CATEGORIAS[[#All],[FORMATO GENERAL]], A21, CATEGORIAS[[#All],[COSTO REAL]])) | T21: =+R21-S21 -> #VALUE! | U21: =IF(ISBLANK(A21),"",SUMIF(CATEGORIAS[[#All],[FORMATO GENERAL]], A21, CATEGORIAS[[#All],[TOTAL PRODUCCION ACTUAL]])) | W21: =+U21-V21 -> #VALUE! | X21: =IF(ISBLANK(A21),"",SUMIF(CATEGORIAS[[#All],[FORMATO GENERAL]], A21, CATEGORIAS[[#All],[PROYECCION TOTAL DE COSTO]])) | Z21: =+X21-Y21 -> #VALUE! | AB21: =IF(ISBLANK(A21),"",TRUNC(K21-R21-X21,2)) | AD21: =+AB21-AC21 -> #VALUE!
A22: 0G01 | C22: Mano de Obra | E22: =IF(ISBLANK(A22),"", SUMIF(CATEGORIAS[[#All],[FORMATO GENERAL]], A22, CATEGORIAS[[#All],[PRESUPUESTO (ORIGINAL)]])) -> 79797653 | F22: 79797653 | G22: =+E22-F22 -> -0.18236393 | H22: =IF(ISBLANK(A22),"",K22-E22) -> 2031426.5 | I22: 2031427 | J22: =+H22-I22 -> -0.4911463 | K22: =IF(ISBLANK(A22),"",SUMIF(CATEGORIAS[[#All],[FORMATO GENERAL]], A22, CATEGORIAS[[#All],[PRESUPUESTO FINAL PROYECTADO]])) -> 81829079 | L22: 81829079 | M22: =+K22-L22 -> 0.32648978 | O22: =IF(ISBLANK(A22),"",R22-SUMIF(CATEGORIAS[[#All],[FORMATO GENERAL]], A22, CATEGORIAS[[#All],[COSTO REAL ANTERIOR]])) -> 43427321 | P22: 43427321 | Q22: =+O22-P22 -> -0.37264537 | R22: =IF(ISBLANK(A22),"",SUMIF(CATEGORIAS[[#All],[FORMATO GENERAL]], A22, CATEGORIAS[[#All],[COSTO REAL]])) -> 88410801 | S22: 88410801 | T22: =+R22-S22 -> 0.12121212 | U22: =IF(ISBLANK(A22),"",SUMIF(CATEGORIAS[[#All],[FORMATO GENERAL]], A22, CATEGORIAS[[#All],[TOTAL PRODUCCION ACTUAL]])) -> 32123966 | V22: 32123966 | W22: =+U22-V22 -> -0.21972494 | X22: =IF(ISBLANK(A22),"",SUMIF(CATEGORIAS[[#All],[FORMATO GENERAL]], A22, CATEGORIAS[[#All],[PROYECCION TOTAL DE COSTO]])) -> -6581721.8 | Y22: -6581722 | Z22: =+X22-Y22 -> 0.20527765 | AB22: =IF(ISBLANK(A22),"",TRUNC(K22-R22-X22,2)) -> 0 | AD22: =+AB22-AC22 -> 0
B23: A7 | C23: 07 - Aislación | E23: =IF(ISBLANK(A23),"", SUMIF(CATEGORIAS[[#All],[FORMATO GENERAL]], A23, CATEGORIAS[[#All],[PRESUPUESTO (ORIGINAL)]])) | G23: =+E23-F23 -> #VALUE! | H23: =IF(ISBLANK(A23),"",K23-E23) | J23: =+H23-I23 -> #VALUE! | K23: =IF(ISBLANK(A23),"",SUMIF(CATEGORIAS[[#All],[FORMATO GENERAL]], A23, CATEGORIAS[[#All],[PRESUPUESTO FINAL PROYECTADO]])) | M23: =+K23-L23 -> #VALUE! | O23: =IF(ISBLANK(A23),"",R23-SUMIF(CATEGORIAS[[#All],[FORMATO GENERAL]], A23, CATEGORIAS[[#All],[COSTO REAL ANTERIOR]])) | Q23: =+O23-P23 -> #VALUE! | R23: =IF(ISBLANK(A23),"",SUMIF(CATEGORIAS[[#All],[FORMATO GENERAL]], A23, CATEGORIAS[[#All],[COSTO REAL]])) | T23: =+R23-S23 -> #VALUE! | U23: =IF(ISBLANK(A23),"",SUMIF(CATEGORIAS[[#All],[FORMATO GENERAL]], A23, CATEGORIAS[[#All],[TOTAL PRODUCCION ACTUAL]])) | W23: =+U23-V23 -> #VALUE! | X23: =IF(ISBLANK(A23),"",SUMIF(CATEGORIAS[[#All],[FORMATO GENERAL]], A23, CATEGORIAS[[#All],[PROYECCION TOTAL DE COSTO]])) | Z23: =+X23-Y23 -> #VALUE! | AB23: =IF(ISBLANK(A23),"",TRUNC(K23-R23-X23,2)) | AD23: =+AB23-AC23 -> #VALUE!
A24: 0H01 | C24: Mano de Obra | E24: =IF(ISBLANK(A24),"", SUMIF(CATEGORIAS[[#All],[FORMATO GENERAL]], A24, CATEGORIAS[[#All],[PRESUPUESTO (ORIGINAL)]])) -> 25004643 | F24: 25004643 | G24: =+E24-F24 -> -0.37450741 | H24: =IF(ISBLANK(A24),"",K24-E24) -> 0 | J24: =+H24-I24 -> 0 | K24: =IF(ISBLANK(A24),"",SUMIF(CATEGORIAS[[#All],[FORMATO GENERAL]], A24, CATEGORIAS[[#All],[PRESUPUESTO FINAL PROYECTADO]])) -> 25004643 | L24: 25004643 | M24: =+K24-L24 -> -0.37450741 | O24: =IF(ISBLANK(A24),"",R24-SUMIF(CATEGORIAS[[#All],[FORMATO GENERAL]], A24, CATEGORIAS[[#All],[COSTO REAL ANTERIOR]])) -> 0 | Q24: =+O24-P24 -> 0 | R24: =IF(ISBLANK(A24),"",SUMIF(CATEGORIAS[[#All],[FORMATO GENERAL]], A24, CATEGORIAS[[#All],[COSTO REAL]])) -> 0 | T24: =+R24-S24 -> 0 | U24: =IF(ISBLANK(A24),"",SUMIF(CATEGORIAS[[#All],[FORMATO GENERAL]], A24, CATEGORIAS[[#All],[TOTAL PRODUCCION ACTUAL]])) -> 0 | W24: =+U24-V24 -> 0 | X24: =IF(ISBLANK(A24),"",SUMIF(CATEGORIAS[[#All],[FORMATO GENERAL]], A24, CATEGORIAS[[#All],[PROYECCION TOTAL DE COSTO]])) -> 25004643 | Y24: 25004643 | Z24: =+X24-Y24 -> -0.37450741 | AB24: =IF(ISBLANK(A24),"",TRUNC(K24-R24-X24,2)) -> 0 | AD24: =+AB24-AC24 -> 0
A25: 0H02 | C25: Aislación Reembolsable | E25: =IF(ISBLANK(A25),"", SUMIF(CATEGORIAS[[#All],[FORMATO GENERAL]], A25, CATEGORIAS[[#All],[PRESUPUESTO (ORIGINAL)]])) -> 18524724 | F25: 18524724 | G25: =+E25-F25 -> 0.39 | H25: =IF(ISBLANK(A25),"",K25-E25) -> 0 | J25: =+H25-I25 -> 0 | K25: =IF(ISBLANK(A25),"",SUMIF(CATEGORIAS[[#All],[FORMATO GENERAL]], A25, CATEGORIAS[[#All],[PRESUPUESTO FINAL PROYECTADO]])) -> 18524724 | L25: 18524724 | M25: =+K25-L25 -> 0.39 | O25: =IF(ISBLANK(A25),"",R25-SUMIF(CATEGORIAS[[#All],[FORMATO GENERAL]], A25, CATEGORIAS[[#All],[COSTO REAL ANTERIOR]])) -> 0 | Q25: =+O25-P25 -> 0 | R25: =IF(ISBLANK(A25),"",SUMIF(CATEGORIAS[[#All],[FORMATO GENERAL]], A25, CATEGORIAS[[#All],[COSTO REAL]])) -> 0 | T25: =+R25-S25 -> 0 | U25: =IF(ISBLANK(A25),"",SUMIF(CATEGORIAS[[#All],[FORMATO GENERAL]], A25, CATEGORIAS[[#All],[TOTAL PRODUCCION ACTUAL]])) -> 15433050 | V25: 15433050 | W25: =+U25-V25 -> 0 | X25: =IF(ISBLANK(A25),"",SUMIF(CATEGORIAS[[#All],[FORMATO GENERAL]], A25, CATEGORIAS[[#All],[PROYECCION TOTAL DE COSTO]])) -> 18524724 | Y25: 18524724 | Z25: =+X25-Y25 -> 0.39 | AB25: =IF(ISBLANK(A25),"",TRUNC(K25-R25-X25,2)) -> 0 | AD25: =+AB25-AC25 -> 0
B26: A8 | C26: 08 - Caldera | E26: =IF(ISBLANK(A26),"", SUMIF(CATEGORIAS[[#All],[FORMATO GENERAL]], A26, CATEGORIAS[[#All],[PRESUPUESTO (ORIGINAL)]])) | G26: =+E26-F26 -> #VALUE! | H26: =IF(ISBLANK(A26),"",K26-E26) | J26: =+H26-I26 -> #VALUE! | K26: =IF(ISBLANK(A26),"",SUMIF(CATEGORIAS[[#All],[FORMATO GENERAL]], A26, CATEGORIAS[[#All],[PRESUPUESTO FINAL PROYECTADO]])) | M26: =+K26-L26 -> #VALUE! | O26: =IF(ISBLANK(A26),"",R26-SUMIF(CATEGORIAS[[#All],[FORMATO GENERAL]], A26, CATEGORIAS[[#All],[COSTO REAL ANTERIOR]])) | Q26: =+O26-P26 -> #VALUE! | R26: =IF(ISBLANK(A26),"",SUMIF(CATEGORIAS[[#All],[FORMATO GENERAL]], A26, CATEGORIAS[[#All],[COSTO REAL]])) | T26: =+R26-S26 -> #VALUE! | U26: =IF(ISBLANK(A26),"",SUMIF(CATEGORIAS[[#All],[FORMATO GENERAL]], A26, CATEGORIAS[[#All],[TOTAL PRODUCCION ACTUAL]])) | W26: =+U26-V26 -> #VALUE! | X26: =IF(ISBLANK(A26),"",SUMIF(CATEGORIAS[[#All],[FORMATO GENERAL]], A26, CATEGORIAS[[#All],[PROYECCION TOTAL DE COSTO]])) | Z26: =+X26-Y26 -> #VALUE! | AB26: =IF(ISBLANK(A26),"",TRUNC(K26-R26-X26,2)) | AD26: =+AB26-AC26 -> #VALUE!
A27: 0I01 | C27: Mano de Obra | E27: =IF(ISBLANK(A27),"", SUMIF(CATEGORIAS[[#All],[FORMATO GENERAL]], A27, CATEGORIAS[[#All],[PRESUPUESTO (ORIGINAL)]])) -> 0 | G27: =+E27-F27 -> 0 | H27: =IF(ISBLANK(A27),"",K27-E27) -> 0 | J27: =+H27-I27 -> 0 | K27: =IF(ISBLANK(A27),"",SUMIF(CATEGORIAS[[#All],[FORMATO GENERAL]], A27, CATEGORIAS[[#All],[PRESUPUESTO FINAL PROYECTADO]])) -> 0 | M27: =+K27-L27 -> 0 | O27: =IF(ISBLANK(A27),"",R27-SUMIF(CATEGORIAS[[#All],[FORMATO GENERAL]], A27, CATEGORIAS[[#All],[COSTO REAL ANTERIOR]])) -> 0 | Q27: =+O27-P27 -> 0 | R27: =IF(ISBLANK(A27),"",SUMIF(CATEGORIAS[[#All],[FORMATO GENERAL]], A27, CATEGORIAS[[#All],[COSTO REAL]])) -> 0 | T27: =+R27-S27 -> 0 | U27: =IF(ISBLANK(A27),"",SUMIF(CATEGORIAS[[#All],[FORMATO GENERAL]], A27, CATEGORIAS[[#All],[TOTAL PRODUCCION ACTUAL]])) -> 0 | W27: =+U27-V27 -> 0 | X27: =IF(ISBLANK(A27),"",SUMIF(CATEGORIAS[[#All],[FORMATO GENERAL]], A27, CATEGORIAS[[#All],[PROYECCION TOTAL DE COSTO]])) -> 0 | Z27: =+X27-Y27 -> 0 | AB27: =IF(ISBLANK(A27),"",TRUNC(K27-R27-X27,2)) -> 0 | AD27: =+AB27-AC27 -> 0
A28: 0I02 | C28: Caldera Reembolsable | E28: =IF(ISBLANK(A28),"", SUMIF(CATEGORIAS[[#All],[FORMATO GENERAL]], A28, CATEGORIAS[[#All],[PRESUPUESTO (ORIGINAL)]])) -> 0 | G28: =+E28-F28 -> 0 | H28: =IF(ISBLANK(A28),"",K28-E28) -> 0 | J28: =+H28-I28 -> 0 | K28: =IF(ISBLANK(A28),"",SUMIF(CATEGORIAS[[#All],[FORMATO GENERAL]], A28, CATEGORIAS[[#All],[PRESUPUESTO FINAL PROYECTADO]])) -> 0 | M28: =+K28-L28 -> 0 | O28: =IF(ISBLANK(A28),"",R28-SUMIF(CATEGORIAS[[#All],[FORMATO GENERAL]], A28, CATEGORIAS[[#All],[COSTO REAL ANTERIOR]])) -> 0 | Q28: =+O28-P28 -> 0 | R28: =IF(ISBLANK(A28),"",SUMIF(CATEGORIAS[[#All],[FORMATO GENERAL]], A28, CATEGORIAS[[#All],[COSTO REAL]])) -> 0 | T28: =+R28-S28 -> 0 | U28: =IF(ISBLANK(A28),"",SUMIF(CATEGORIAS[[#All],[FORMATO GENERAL]], A28, CATEGORIAS[[#All],[TOTAL PRODUCCION ACTUAL]])) -> 0 | W28: =+U28-V28 -> 0 | X28: =IF(ISBLANK(A28),"",SUMIF(CATEGORIAS[[#All],[FORMATO GENERAL]], A28, CATEGORIAS[[#All],[PROYECCION TOTAL DE COSTO]])) -> 0 | Z28: =+X28-Y28 -> 0 | AB28: =IF(ISBLANK(A28),"",TRUNC(K28-R28-X28,2)) -> 0 | AD28: =+AB28-AC28 -> 0
B29: A9 | C29: 09 - Ducto | E29: =IF(ISBLANK(A29),"", SUMIF(CATEGORIAS[[#All],[FORMATO GENERAL]], A29, CATEGORIAS[[#All],[PRESUPUESTO (ORIGINAL)]])) | G29: =+E29-F29 -> #VALUE! | H29: =IF(ISBLANK(A29),"",K29-E29) | J29: =+H29-I29 -> #VALUE! | K29: =IF(ISBLANK(A29),"",SUMIF(CATEGORIAS[[#All],[FORMATO GENERAL]], A29, CATEGORIAS[[#All],[PRESUPUESTO FINAL PROYECTADO]])) | M29: =+K29-L29 -> #VALUE! | O29: =IF(ISBLANK(A29),"",R29-SUMIF(CATEGORIAS[[#All],[FORMATO GENERAL]], A29, CATEGORIAS[[#All],[COSTO REAL ANTERIOR]])) | Q29: =+O29-P29 -> #VALUE! | R29: =IF(ISBLANK(A29),"",SUMIF(CATEGORIAS[[#All],[FORMATO GENERAL]], A29, CATEGORIAS[[#All],[COSTO REAL]])) | T29: =+R29-S29 -> #VALUE! | U29: =IF(ISBLANK(A29),"",SUMIF(CATEGORIAS[[#All],[FORMATO GENERAL]], A29, CATEGORIAS[[#All],[TOTAL PRODUCCION ACTUAL]])) | W29: =+U29-V29 -> #VALUE! | X29: =IF(ISBLANK(A29),"",SUMIF(CATEGORIAS[[#All],[FORMATO GENERAL]], A29, CATEGORIAS[[#All],[PROYECCION TOTAL DE COSTO]])) | Z29: =+X29-Y29 -> #VALUE! | AB29: =IF(ISBLANK(A29),"",TRUNC(K29-R29-X29,2)) | AD29: =+AB29-AC29 -> #VALUE!
A30: 0J01 | C30: Mano de Obra | E30: =IF(ISBLANK(A30),"", SUMIF(CATEGORIAS[[#All],[FORMATO GENERAL]], A30, CATEGORIAS[[#All],[PRESUPUESTO (ORIGINAL)]])) -> 0 | G30: =+E30-F30 -> 0 | H30: =IF(ISBLANK(A30),"",K30-E30) -> 0 | J30: =+H30-I30 -> 0 | K30: =IF(ISBLANK(A30),"",SUMIF(CATEGORIAS[[#All],[FORMATO GENERAL]], A30, CATEGORIAS[[#All],[PRESUPUESTO FINAL PROYECTADO]])) -> 0 | M30: =+K30-L30 -> 0 | O30: =IF(ISBLANK(A30),"",R30-SUMIF(CATEGORIAS[[#All],[FORMATO GENERAL]], A30, CATEGORIAS[[#All],[COSTO REAL ANTERIOR]])) -> 0 | Q30: =+O30-P30 -> 0 | R30: =IF(ISBLANK(A30),"",SUMIF(CATEGORIAS[[#All],[FORMATO GENERAL]], A30, CATEGORIAS[[#All],[COSTO REAL]])) -> 0 | T30: =+R30-S30 -> 0 | U30: =IF(ISBLANK(A30),"",SUMIF(CATEGORIAS[[#All],[FORMATO GENERAL]], A30, CATEGORIAS[[#All],[TOTAL PRODUCCION ACTUAL]])) -> 0 | W30: =+U30-V30 -> 0 | X30: =IF(ISBLANK(A30),"",SUMIF(CATEGORIAS[[#All],[FORMATO GENERAL]], A30, CATEGORIAS[[#All],[PROYECCION TOTAL DE COSTO]])) -> 0 | Z30: =+X30-Y30 -> 0 | AB30: =IF(ISBLANK(A30),"",TRUNC(K30-R30-X30,2)) -> 0 | AD30: =+AB30-AC30 -> 0
A31: 0J02 | C31: Ducto Reembolsable | E31: =IF(ISBLANK(A31),"", SUMIF(CATEGORIAS[[#All],[FORMATO GENERAL]], A31, CATEGORIAS[[#All],[PRESUPUESTO (ORIGINAL)]])) -> 0 | G31: =+E31-F31 -> 0 | H31: =IF(ISBLANK(A31),"",K31-E31) -> 0 | J31: =+H31-I31 -> 0 | K31: =IF(ISBLANK(A31),"",SUMIF(CATEGORIAS[[#All],[FORMATO GENERAL]], A31, CATEGORIAS[[#All],[PRESUPUESTO FINAL PROYECTADO]])) -> 0 | M31: =+K31-L31 -> 0 | O31: =IF(ISBLANK(A31),"",R31-SUMIF(CATEGORIAS[[#All],[FORMATO GENERAL]], A31, CATEGORIAS[[#All],[COSTO REAL ANTERIOR]])) -> 0 | Q31: =+O31-P31 -> 0 | R31: =IF(ISBLANK(A31),"",SUMIF(CATEGORIAS[[#All],[FORMATO GENERAL]], A31, CATEGORIAS[[#All],[COSTO REAL]])) -> 0 | T31: =+R31-S31 -> 0 | U31: =IF(ISBLANK(A31),"",SUMIF(CATEGORIAS[[#All],[FORMATO GENERAL]], A31, CATEGORIAS[[#All],[TOTAL PRODUCCION ACTUAL]])) -> 0 | W31: =+U31-V31 -> 0 | X31: =IF(ISBLANK(A31),"",SUMIF(CATEGORIAS[[#All],[FORMATO GENERAL]], A31, CATEGORIAS[[#All],[PROYECCION TOTAL DE COSTO]])) -> 0 | Z31: =+X31-Y31 -> 0 | AB31: =IF(ISBLANK(A31),"",TRUNC(K31-R31-X31,2)) -> 0 | AD31: =+AB31-AC31 -> 0
B32: A10 | C32: 10 - Comisionamiento - PEM | E32: =IF(ISBLANK(A32),"", SUMIF(CATEGORIAS[[#All],[FORMATO GENERAL]], A32, CATEGORIAS[[#All],[PRESUPUESTO (ORIGINAL)]])) | G32: =+E32-F32 -> #VALUE! | H32: =IF(ISBLANK(A32),"",K32-E32) | J32: =+H32-I32 -> #VALUE! | K32: =IF(ISBLANK(A32),"",SUMIF(CATEGORIAS[[#All],[FORMATO GENERAL]], A32, CATEGORIAS[[#All],[PRESUPUESTO FINAL PROYECTADO]])) | M32: =+K32-L32 -> #VALUE! | O32: =IF(ISBLANK(A32),"",R32-SUMIF(CATEGORIAS[[#All],[FORMATO GENERAL]], A32, CATEGORIAS[[#All],[COSTO REAL ANTERIOR]])) | Q32: =+O32-P32 -> #VALUE! | R32: =IF(ISBLANK(A32),"",SUMIF(CATEGORIAS[[#All],[FORMATO GENERAL]], A32, CATEGORIAS[[#All],[COSTO REAL]])) | T32: =+R32-S32 -> #VALUE! | U32: =IF(ISBLANK(A32),"",SUMIF(CATEGORIAS[[#All],[FORMATO GENERAL]], A32, CATEGORIAS[[#All],[TOTAL PRODUCCION ACTUAL]])) | W32: =+U32-V32 -> #VALUE! | X32: =IF(ISBLANK(A32),"",SUMIF(CATEGORIAS[[#All],[FORMATO GENERAL]], A32, CATEGORIAS[[#All],[PROYECCION TOTAL DE COSTO]])) | Z32: =+X32-Y32 -> #VALUE! | AB32: =IF(ISBLANK(A32),"",TRUNC(K32-R32-X32,2)) | AD32: =+AB32-AC32 -> #VALUE!
A33: 0L01 | C33: Mano de Obra | E33: =IF(ISBLANK(A33),"", SUMIF(CATEGORIAS[[#All],[FORMATO GENERAL]], A33, CATEGORIAS[[#All],[PRESUPUESTO (ORIGINAL)]])) -> 0 | G33: =+E33-F33 -> 0 | H33: =IF(ISBLANK(A33),"",K33-E33) -> 0 | J33: =+H33-I33 -> 0 | K33: =IF(ISBLANK(A33),"",SUMIF(CATEGORIAS[[#All],[FORMATO GENERAL]], A33, CATEGORIAS[[#All],[PRESUPUESTO FINAL PROYECTADO]])) -> 0 | M33: =+K33-L33 -> 0 | O33: =IF(ISBLANK(A33),"",R33-SUMIF(CATEGORIAS[[#All],[FORMATO GENERAL]], A33, CATEGORIAS[[#All],[COSTO REAL ANTERIOR]])) -> 0 | Q33: =+O33-P33 -> 0 | R33: =IF(ISBLANK(A33),"",SUMIF(CATEGORIAS[[#All],[FORMATO GENERAL]], A33, CATEGORIAS[[#All],[COSTO REAL]])) -> 0 | T33: =+R33-S33 -> 0 | U33: =IF(ISBLANK(A33),"",SUMIF(CATEGORIAS[[#All],[FORMATO GENERAL]], A33, CATEGORIAS[[#All],[TOTAL PRODUCCION ACTUAL]])) -> 0 | W33: =+U33-V33 -> 0 | X33: =IF(ISBLANK(A33),"",SUMIF(CATEGORIAS[[#All],[FORMATO GENERAL]], A33, CATEGORIAS[[#All],[PROYECCION TOTAL DE COSTO]])) -> 0 | Z33: =+X33-Y33 -> 0 | AB33: =IF(ISBLANK(A33),"",TRUNC(K33-R33-X33,2)) -> 0 | AD33: =+AB33-AC33 -> 0
B34: A11 | C34: 11 - Arquitectura | E34: =IF(ISBLANK(A34),"", SUMIF(CATEGORIAS[[#All],[FORMATO GENERAL]], A34, CATEGORIAS[[#All],[PRESUPUESTO (ORIGINAL)]])) | G34: =+E34-F34 -> #VALUE! | H34: =IF(ISBLANK(A34),"",K34-E34) | J34: =+H34-I34 -> #VALUE! | K34: =IF(ISBLANK(A34),"",SUMIF(CATEGORIAS[[#All],[FORMATO GENERAL]], A34, CATEGORIAS[[#All],[PRESUPUESTO FINAL PROYECTADO]])) | M34: =+K34-L34 -> #VALUE! | O34: =IF(ISBLANK(A34),"",R34-SUMIF(CATEGORIAS[[#All],[FORMATO GENERAL]], A34, CATEGORIAS[[#All],[COSTO REAL ANTERIOR]])) | Q34: =+O34-P34 -> #VALUE! | R34: =IF(ISBLANK(A34),"",SUMIF(CATEGORIAS[[#All],[FORMATO GENERAL]], A34, CATEGORIAS[[#All],[COSTO REAL]])) | T34: =+R34-S34 -> #VALUE! | U34: =IF(ISBLANK(A34),"",SUMIF(CATEGORIAS[[#All],[FORMATO GENERAL]], A34, CATEGORIAS[[#All],[TOTAL PRODUCCION ACTUAL]])) | W34: =+U34-V34 -> #VALUE! | X34: =IF(ISBLANK(A34),"",SUMIF(CATEGORIAS[[#All],[FORMATO GENERAL]], A34, CATEGORIAS[[#All],[PROYECCION TOTAL DE COSTO]])) | Z34: =+X34-Y34 -> #VALUE! | AB34: =IF(ISBLANK(A34),"",TRUNC(K34-R34-X34,2)) | AD34: =+AB34-AC34 -> #VALUE!
A35: 0M01 | C35: Mano de Obra | E35: =IF(ISBLANK(A35),"", SUMIF(CATEGORIAS[[#All],[FORMATO GENERAL]], A35, CATEGORIAS[[#All],[PRESUPUESTO (ORIGINAL)]])) -> 0 | G35: =+E35-F35 -> 0 | H35: =IF(ISBLANK(A35),"",K35-E35) -> 0 | J35: =+H35-I35 -> 0 | K35: =IF(ISBLANK(A35),"",SUMIF(CATEGORIAS[[#All],[FORMATO GENERAL]], A35, CATEGORIAS[[#All],[PRESUPUESTO FINAL PROYECTADO]])) -> 0 | M35: =+K35-L35 -> 0 | O35: =IF(ISBLANK(A35),"",R35-SUMIF(CATEGORIAS[[#All],[FORMATO GENERAL]], A35, CATEGORIAS[[#All],[COSTO REAL ANTERIOR]])) -> 2325389 | P35: 2325389 | Q35: =+O35-P35 -> 0.025389026 | R35: =IF(ISBLANK(A35),"",SUMIF(CATEGORIAS[[#All],[FORMATO GENERAL]], A35, CATEGORIAS[[#All],[COSTO REAL]])) -> 2325389 | S35: 2325389 | T35: =+R35-S35 -> 0.025389026 | U35: =IF(ISBLANK(A35),"",SUMIF(CATEGORIAS[[#All],[FORMATO GENERAL]], A35, CATEGORIAS[[#All],[TOTAL PRODUCCION ACTUAL]])) -> 0 | W35: =+U35-V35 -> 0 | X35: =IF(ISBLANK(A35),"",SUMIF(CATEGORIAS[[#All],[FORMATO GENERAL]], A35, CATEGORIAS[[#All],[PROYECCION TOTAL DE COSTO]])) -> 0 | Z35: =+X35-Y35 -> 0 | AB35: =IF(ISBLANK(A35),"",TRUNC(K35-R35-X35,2)) -> -2325389 | AC35: -2325389 | AD35: =+AB35-AC35 -> -0.02
A36: 0M02 | C36: Arquitectura Reembolsable | E36: =IF(ISBLANK(A36),"", SUMIF(CATEGORIAS[[#All],[FORMATO GENERAL]], A36, CATEGORIAS[[#All],[PRESUPUESTO (ORIGINAL)]])) -> 0 | G36: =+E36-F36 -> 0 | H36: =IF(ISBLANK(A36),"",K36-E36) -> 0 | J36: =+H36-I36 -> 0 | K36: =IF(ISBLANK(A36),"",SUMIF(CATEGORIAS[[#All],[FORMATO GENERAL]], A36, CATEGORIAS[[#All],[PRESUPUESTO FINAL PROYECTADO]])) -> 0 | M36: =+K36-L36 -> 0 | O36: =IF(ISBLANK(A36),"",R36-SUMIF(CATEGORIAS[[#All],[FORMATO GENERAL]], A36, CATEGORIAS[[#All],[COSTO REAL ANTERIOR]])) -> 0 | Q36: =+O36-P36 -> 0 | R36: =IF(ISBLANK(A36),"",SUMIF(CATEGORIAS[[#All],[FORMATO GENERAL]], A36, CATEGORIAS[[#All],[COSTO REAL]])) -> 0 | T36: =+R36-S36 -> 0 | U36: =IF(ISBLANK(A36),"",SUMIF(CATEGORIAS[[#All],[FORMATO GENERAL]], A36, CATEGORIAS[[#All],[TOTAL PRODUCCION ACTUAL]])) -> 0 | W36: =+U36-V36 -> 0 | X36: =IF(ISBLANK(A36),"",SUMIF(CATEGORIAS[[#All],[FORMATO GENERAL]], A36, CATEGORIAS[[#All],[PROYECCION TOTAL DE COSTO]])) -> 0 | Z36: =+X36-Y36 -> 0 | AB36: =IF(ISBLANK(A36),"",TRUNC(K36-R36-X36,2)) -> 0 | AD36: =+AB36-AC36 -> 0
B37: A12 | C37: 12 - Estanque | E37: =IF(ISBLANK(A37),"", SUMIF(CATEGORIAS[[#All],[FORMATO GENERAL]], A37, CATEGORIAS[[#All],[PRESUPUESTO (ORIGINAL)]])) | G37: =+E37-F37 -> #VALUE! | H37: =IF(ISBLANK(A37),"",K37-E37) | J37: =+H37-I37 -> #VALUE! | K37: =IF(ISBLANK(A37),"",SUMIF(CATEGORIAS[[#All],[FORMATO GENERAL]], A37, CATEGORIAS[[#All],[PRESUPUESTO FINAL PROYECTADO]])) | M37: =+K37-L37 -> #VALUE! | O37: =IF(ISBLANK(A37),"",R37-SUMIF(CATEGORIAS[[#All],[FORMATO GENERAL]], A37, CATEGORIAS[[#All],[COSTO REAL ANTERIOR]])) | Q37: =+O37-P37 -> #VALUE! | R37: =IF(ISBLANK(A37),"",SUMIF(CATEGORIAS[[#All],[FORMATO GENERAL]], A37, CATEGORIAS[[#All],[COSTO REAL]])) | T37: =+R37-S37 -> #VALUE! | U37: =IF(ISBLANK(A37),"",SUMIF(CATEGORIAS[[#All],[FORMATO GENERAL]], A37, CATEGORIAS[[#All],[TOTAL PRODUCCION ACTUAL]])) | W37: =+U37-V37 -> #VALUE! | X37: =IF(ISBLANK(A37),"",SUMIF(CATEGORIAS[[#All],[FORMATO GENERAL]], A37, CATEGORIAS[[#All],[PROYECCION TOTAL DE COSTO]])) | Z37: =+X37-Y37 -> #VALUE! | AB37: =IF(ISBLANK(A37),"",TRUNC(K37-R37-X37,2)) | AD37: =+AB37-AC37 -> #VALUE!
A38: 0N01 | C38: Mano de Obra | E38: =IF(ISBLANK(A38),"", SUMIF(CATEGORIAS[[#All],[FORMATO GENERAL]], A38, CATEGORIAS[[#All],[PRESUPUESTO (ORIGINAL)]])) -> 0 | G38: =+E38-F38 -> 0 | H38: =IF(ISBLANK(A38),"",K38-E38) -> 0 | J38: =+H38-I38 -> 0 | K38: =IF(ISBLANK(A38),"",SUMIF(CATEGORIAS[[#All],[FORMATO GENERAL]], A38, CATEGORIAS[[#All],[PRESUPUESTO FINAL PROYECTADO]])) -> 0 | M38: =+K38-L38 -> 0 | O38: =IF(ISBLANK(A38),"",R38-SUMIF(CATEGORIAS[[#All],[FORMATO GENERAL]], A38, CATEGORIAS[[#All],[COSTO REAL ANTERIOR]])) -> 0 | Q38: =+O38-P38 -> 0 | R38: =IF(ISBLANK(A38),"",SUMIF(CATEGORIAS[[#All],[FORMATO GENERAL]], A38, CATEGORIAS[[#All],[COSTO REAL]])) -> 0 | T38: =+R38-S38 -> 0 | U38: =IF(ISBLANK(A38),"",SUMIF(CATEGORIAS[[#All],[FORMATO GENERAL]], A38, CATEGORIAS[[#All],[TOTAL PRODUCCION ACTUAL]])) -> 0 | W38: =+U38-V38 -> 0 | X38: =IF(ISBLANK(A38),"",SUMIF(CATEGORIAS[[#All],[FORMATO GENERAL]], A38, CATEGORIAS[[#All],[PROYECCION TOTAL DE COSTO]])) -> 0 | Z38: =+X38-Y38 -> 0 | AB38: =IF(ISBLANK(A38),"",TRUNC(K38-R38-X38,2)) -> 0 | AD38: =+AB38-AC38 -> 0
A39: 0N02 | C39: Estanque Reembolsable | E39: =IF(ISBLANK(A39),"", SUMIF(CATEGORIAS[[#All],[FORMATO GENERAL]], A39, CATEGORIAS[[#All],[PRESUPUESTO (ORIGINAL)]])) -> 0 | G39: =+E39-F39 -> 0 | H39: =IF(ISBLANK(A39),"",K39-E39) -> 0 | J39: =+H39-I39 -> 0 | K39: =IF(ISBLANK(A39),"",SUMIF(CATEGORIAS[[#All],[FORMATO GENERAL]], A39, CATEGORIAS[[#All],[PRESUPUESTO FINAL PROYECTADO]])) -> 0 | M39: =+K39-L39 -> 0 | O39: =IF(ISBLANK(A39),"",R39-SUMIF(CATEGORIAS[[#All],[FORMATO GENERAL]], A39, CATEGORIAS[[#All],[COSTO REAL ANTERIOR]])) -> 0 | Q39: =+O39-P39 -> 0 | R39: =IF(ISBLANK(A39),"",SUMIF(CATEGORIAS[[#All],[FORMATO GENERAL]], A39, CATEGORIAS[[#All],[COSTO REAL]])) -> 0 | T39: =+R39-S39 -> 0 | U39: =IF(ISBLANK(A39),"",SUMIF(CATEGORIAS[[#All],[FORMATO GENERAL]], A39, CATEGORIAS[[#All],[TOTAL PRODUCCION ACTUAL]])) -> 0 | W39: =+U39-V39 -> 0 | X39: =IF(ISBLANK(A39),"",SUMIF(CATEGORIAS[[#All],[FORMATO GENERAL]], A39, CATEGORIAS[[#All],[PROYECCION TOTAL DE COSTO]])) -> 0 | Z39: =+X39-Y39 -> 0 | AB39: =IF(ISBLANK(A39),"",TRUNC(K39-R39-X39,2)) -> 0 | AD39: =+AB39-AC39 -> 0
B40: A13 | C40: Costo Proporcional HH | E40: =IF(ISBLANK(A40),"", SUMIF(CATEGORIAS[[#All],[FORMATO GENERAL]], A40, CATEGORIAS[[#All],[PRESUPUESTO (ORIGINAL)]])) | G40: =+E40-F40 -> #VALUE! | H40: =IF(ISBLANK(A40),"",K40-E40) | J40: =+H40-I40 -> #VALUE! | K40: =IF(ISBLANK(A40),"",SUMIF(CATEGORIAS[[#All],[FORMATO GENERAL]], A40, CATEGORIAS[[#All],[PRESUPUESTO FINAL PROYECTADO]])) | M40: =+K40-L40 -> #VALUE! | O40: =IF(ISBLANK(A40),"",R40-SUMIF(CATEGORIAS[[#All],[FORMATO GENERAL]], A40, CATEGORIAS[[#All],[COSTO REAL ANTERIOR]])) | Q40: =+O40-P40 -> #VALUE! | R40: =IF(ISBLANK(A40),"",SUMIF(CATEGORIAS[[#All],[FORMATO GENERAL]], A40, CATEGORIAS[[#All],[COSTO REAL]])) | T40: =+R40-S40 -> #VALUE! | U40: =IF(ISBLANK(A40),"",SUMIF(CATEGORIAS[[#All],[FORMATO GENERAL]], A40, CATEGORIAS[[#All],[TOTAL PRODUCCION ACTUAL]])) | W40: =+U40-V40 -> #VALUE! | X40: =IF(ISBLANK(A40),"",SUMIF(CATEGORIAS[[#All],[FORMATO GENERAL]], A40, CATEGORIAS[[#All],[PROYECCION TOTAL DE COSTO]])) | Z40: =+X40-Y40 -> #VALUE! | AB40: =IF(ISBLANK(A40),"",TRUNC(K40-R40-X40,2)) | AD40: =+AB40-AC40 -> #VALUE!
A41: 0P01 | C41: Movilización | E41: =IF(ISBLANK(A41),"", SUMIF(CATEGORIAS[[#All],[FORMATO GENERAL]], A41, CATEGORIAS[[#All],[PRESUPUESTO (ORIGINAL)]])) -> 91680058 | F41: 91680058 | G41: =+E41-F41 -> 0.29098517 | H41: =IF(ISBLANK(A41),"",K41-E41) -> 5566468 | I41: 5566468 | J41: =+H41-I41 -> -0.042836323 | K41: =IF(ISBLANK(A41),"",SUMIF(CATEGORIAS[[#All],[FORMATO GENERAL]], A41, CATEGORIAS[[#All],[PRESUPUESTO FINAL PROYECTADO]])) -> 97246526 | L41: 97246526 | M41: =+K41-L41 -> 0.24814884 | O41: =IF(ISBLANK(A41),"",R41-SUMIF(CATEGORIAS[[#All],[FORMATO GENERAL]], A41, CATEGORIAS[[#All],[COSTO REAL ANTERIOR]])) -> 0 | Q41: =+O41-P41 -> 0 | R41: =IF(ISBLANK(A41),"",SUMIF(CATEGORIAS[[#All],[FORMATO GENERAL]], A41, CATEGORIAS[[#All],[COSTO REAL]])) -> 14593364 | S41: 14593364 | T41: =+R41-S41 -> -0.2 | U41: =IF(ISBLANK(A41),"",SUMIF(CATEGORIAS[[#All],[FORMATO GENERAL]], A41, CATEGORIAS[[#All],[TOTAL PRODUCCION ACTUAL]])) -> 33939880 | V41: 33939880 | W41: =+U41-V41 -> 0.11119501 | X41: =IF(ISBLANK(A41),"",SUMIF(CATEGORIAS[[#All],[FORMATO GENERAL]], A41, CATEGORIAS[[#All],[PROYECCION TOTAL DE COSTO]])) -> 82653162 | Y41: 82653162 | Z41: =+X41-Y41 -> 0.44814885 | AB41: =IF(ISBLANK(A41),"",TRUNC(K41-R41-X41,2)) -> 0 | AD41: =+AB41-AC41 -> 0
A42: 0P02 | C42: Alimentación | E42: =IF(ISBLANK(A42),"", SUMIF(CATEGORIAS[[#All],[FORMATO GENERAL]], A42, CATEGORIAS[[#All],[PRESUPUESTO (ORIGINAL)]])) -> 97917949 | F42: 97917949 | G42: =+E42-F42 -> -0.37927309 | H42: =IF(ISBLANK(A42),"",K42-E42) -> 14065113 | I42: 14065113 | J42: =+H42-I42 -> -0.074690655 | K42: =IF(ISBLANK(A42),"",SUMIF(CATEGORIAS[[#All],[FORMATO GENERAL]], A42, CATEGORIAS[[#All],[PRESUPUESTO FINAL PROYECTADO]])) -> 1.1198306e+08 | L42: 111983062 | M42: =+K42-L42 -> -0.45396374 | O42: =IF(ISBLANK(A42),"",R42-SUMIF(CATEGORIAS[[#All],[FORMATO GENERAL]], A42, CATEGORIAS[[#All],[COSTO REAL ANTERIOR]])) -> 8072824.4 | P42: 8072824 | Q42: =+O42-P42 -> 0.4 | R42: =IF(ISBLANK(A42),"",SUMIF(CATEGORIAS[[#All],[FORMATO GENERAL]], A42, CATEGORIAS[[#All],[COSTO REAL]])) -> 27299906 | S42: 27299906 | T42: =+R42-S42 -> 0.4 | U42: =IF(ISBLANK(A42),"",SUMIF(CATEGORIAS[[#All],[FORMATO GENERAL]], A42, CATEGORIAS[[#All],[TOTAL PRODUCCION ACTUAL]])) -> 36626306 | V42: 36626306 | W42: =+U42-V42 -> -0.075604945 | X42: =IF(ISBLANK(A42),"",SUMIF(CATEGORIAS[[#All],[FORMATO GENERAL]], A42, CATEGORIAS[[#All],[PROYECCION TOTAL DE COSTO]])) -> 84683155 | Y42: 84683155 | Z42: =+X42-Y42 -> 0.14603627 | AB42: =IF(ISBLANK(A42),"",TRUNC(K42-R42-X42,2)) -> 0 | AD42: =+AB42-AC42 -> 0
A43: 0P03 | C43: Cursos y Examenes | E43: =IF(ISBLANK(A43),"", SUMIF(CATEGORIAS[[#All],[FORMATO GENERAL]], A43, CATEGORIAS[[#All],[PRESUPUESTO (ORIGINAL)]])) -> 1.6900763e+08 | F43: 169007626 | G43: =+E43-F43 -> 0.47784966 | H43: =IF(ISBLANK(A43),"",K43-E43) -> 0 | J43: =+H43-I43 -> 0 | K43: =IF(ISBLANK(A43),"",SUMIF(CATEGORIAS[[#All],[FORMATO GENERAL]], A43, CATEGORIAS[[#All],[PRESUPUESTO FINAL PROYECTADO]])) -> 1.6900763e+08 | L43: 169007626 | M43: =+K43-L43 -> 0.47784966 | O43: =IF(ISBLANK(A43),"",R43-SUMIF(CATEGORIAS[[#All],[FORMATO GENERAL]], A43, CATEGORIAS[[#All],[COSTO REAL ANTERIOR]])) -> 9351964 | P43: 9351964 | Q43: =+O43-P43 -> 0 | R43: =IF(ISBLANK(A43),"",SUMIF(CATEGORIAS[[#All],[FORMATO GENERAL]], A43, CATEGORIAS[[#All],[COSTO REAL]])) -> 26964885 | S43: 26964885 | T43: =+R43-S43 -> 0 | U43: =IF(ISBLANK(A43),"",SUMIF(CATEGORIAS[[#All],[FORMATO GENERAL]], A43, CATEGORIAS[[#All],[TOTAL PRODUCCION ACTUAL]])) -> 64347808 | V43: 64347808 | W43: =+U43-V43 -> 0.25306838 | X43: =IF(ISBLANK(A43),"",SUMIF(CATEGORIAS[[#All],[FORMATO GENERAL]], A43, CATEGORIAS[[#All],[PROYECCION TOTAL DE COSTO]])) -> 1.4204274e+08 | Y43: 142042741 | Z43: =+X43-Y43 -> 0.47784966 | AB43: =IF(ISBLANK(A43),"",TRUNC(K43-R43-X43,2)) -> 0 | AD43: =+AB43-AC43 -> 0
A44: 0P04 | C44: Elem. de Seguridad | E44: =IF(ISBLANK(A44),"", SUMIF(CATEGORIAS[[#All],[FORMATO GENERAL]], A44, CATEGORIAS[[#All],[PRESUPUESTO (ORIGINAL)]])) -> 59671798 | F44: 59671798 | G44: =+E44-F44 -> 0.12500001 | H44: =IF(ISBLANK(A44),"",K44-E44) -> 3952523.4 | I44: 3952523 | J44: =+H44-I44 -> 0.35984983 | K44: =IF(ISBLANK(A44),"",SUMIF(CATEGORIAS[[#All],[FORMATO GENERAL]], A44, CATEGORIAS[[#All],[PRESUPUESTO FINAL PROYECTADO]])) -> 63624321 | L44: 63624321 | M44: =+K44-L44 -> 0.48484983 | O44: =IF(ISBLANK(A44),"",R44-SUMIF(CATEGORIAS[[#All],[FORMATO GENERAL]], A44, CATEGORIAS[[#All],[COSTO REAL ANTERIOR]])) -> 9086877 | P44: 9086877 | Q44: =+O44-P44 -> 0 | R44: =IF(ISBLANK(A44),"",SUMIF(CATEGORIAS[[#All],[FORMATO GENERAL]], A44, CATEGORIAS[[#All],[COSTO REAL]])) -> 35331776 | S44: 35331776 | T44: =+R44-S44 -> 0 | U44: =IF(ISBLANK(A44),"",SUMIF(CATEGORIAS[[#All],[FORMATO GENERAL]], A44, CATEGORIAS[[#All],[TOTAL PRODUCCION ACTUAL]])) -> 22703670 | V44: 22703670 | W44: =+U44-V44 -> -0.39395485 | X44: =IF(ISBLANK(A44),"",SUMIF(CATEGORIAS[[#All],[FORMATO GENERAL]], A44, CATEGORIAS[[#All],[PROYECCION TOTAL DE COSTO]])) -> 28292545 | Y44: 28292545 | Z44: =+X44-Y44 -> 0.48484983 | AB44: =IF(ISBLANK(A44),"",TRUNC(K44-R44-X44,2)) -> 0 | AD44: =+AB44-AC44 -> 0
A45: 0P05 | C45: Mat. de Consumo | E45: =IF(ISBLANK(A45),"", SUMIF(CATEGORIAS[[#All],[FORMATO GENERAL]], A45, CATEGORIAS[[#All],[PRESUPUESTO (ORIGINAL)]])) -> 14063139 | F45: 14063139 | G45: =+E45-F45 -> 0.45 | H45: =IF(ISBLANK(A45),"",K45-E45) -> 454313.03 | I45: 454313 | J45: =+H45-I45 -> 0.029867796 | K45: =IF(ISBLANK(A45),"",SUMIF(CATEGORIAS[[#All],[FORMATO GENERAL]], A45, CATEGORIAS[[#All],[PRESUPUESTO FINAL PROYECTADO]])) -> 14517452 | L45: 14517452 | M45: =+K45-L45 -> 0.4798678 | O45: =IF(ISBLANK(A45),"",R45-SUMIF(CATEGORIAS[[#All],[FORMATO GENERAL]], A45, CATEGORIAS[[#All],[COSTO REAL ANTERIOR]])) -> 5633842 | P45: 5633842 | Q45: =+O45-P45 -> 0 | R45: =IF(ISBLANK(A45),"",SUMIF(CATEGORIAS[[#All],[FORMATO GENERAL]], A45, CATEGORIAS[[#All],[COSTO REAL]])) -> 14022512 | S45: 14022512 | T45: =+R45-S45 -> 0 | U45: =IF(ISBLANK(A45),"",SUMIF(CATEGORIAS[[#All],[FORMATO GENERAL]], A45, CATEGORIAS[[#All],[TOTAL PRODUCCION ACTUAL]])) -> 4959072.8 | V45: 4959073 | W45: =+U45-V45 -> -0.23943037 | X45: =IF(ISBLANK(A45),"",SUMIF(CATEGORIAS[[#All],[FORMATO GENERAL]], A45, CATEGORIAS[[#All],[PROYECCION TOTAL DE COSTO]])) -> 494940.48 | Y45: 494940 | Z45: =+X45-Y45 -> 0.4798678 | AB45: =IF(ISBLANK(A45),"",TRUNC(K45-R45-X45,2)) -> 0 | AD45: =+AB45-AC45 -> 0
A46: 0P06 | C46: Herramienta Menor | E46: =IF(ISBLANK(A46),"", SUMIF(CATEGORIAS[[#All],[FORMATO GENERAL]], A46, CATEGORIAS[[#All],[PRESUPUESTO (ORIGINAL)]])) -> 11480361 | F46: 11480361 | G46: =+E46-F46 -> 0.030000003 | H46: =IF(ISBLANK(A46),"",K46-E46) -> 454313.03 | I46: 454313 | J46: =+H46-I46 -> 0.029867796 | K46: =IF(ISBLANK(A46),"",SUMIF(CATEGORIAS[[#All],[FORMATO GENERAL]], A46, CATEGORIAS[[#All],[PRESUPUESTO FINAL PROYECTADO]])) -> 11934674 | L46: 11934674 | M46: =+K46-L46 -> 0.059867799 | O46: =IF(ISBLANK(A46),"",R46-SUMIF(CATEGORIAS[[#All],[FORMATO GENERAL]], A46, CATEGORIAS[[#All],[COSTO REAL ANTERIOR]])) -> 93195 | P46: 93195 | Q46: =+O46-P46 -> 0 | R46: =IF(ISBLANK(A46),"",SUMIF(CATEGORIAS[[#All],[FORMATO GENERAL]], A46, CATEGORIAS[[#All],[COSTO REAL]])) -> 347266 | S46: 347266 | T46: =+R46-S46 -> 0 | U46: =IF(ISBLANK(A46),"",SUMIF(CATEGORIAS[[#All],[FORMATO GENERAL]], A46, CATEGORIAS[[#All],[TOTAL PRODUCCION ACTUAL]])) -> 4147332.9 | V46: 4147333 | W46: =+U46-V46 -> -0.092430368 | X46: =IF(ISBLANK(A46),"",SUMIF(CATEGORIAS[[#All],[FORMATO GENERAL]], A46, CATEGORIAS[[#All],[PROYECCION TOTAL DE COSTO]])) -> 11587408 | Y46: 11587408 | Z46: =+X46-Y46 -> 0.059867799 | AB46: =IF(ISBLANK(A46),"",TRUNC(K46-R46-X46,2)) -> 0 | AD46: =+AB46-AC46 -> 0
A47: 0P07 | C47: Artículos de Oficina | E47: =IF(ISBLANK(A47),"", SUMIF(CATEGORIAS[[#All],[FORMATO GENERAL]], A47, CATEGORIAS[[#All],[PRESUPUESTO (ORIGINAL)]])) -> 0 | G47: =+E47-F47 -> 0 | H47: =IF(ISBLANK(A47),"",K47-E47) -> 0 | J47: =+H47-I47 -> 0 | K47: =IF(ISBLANK(A47),"",SUMIF(CATEGORIAS[[#All],[FORMATO GENERAL]], A47, CATEGORIAS[[#All],[PRESUPUESTO FINAL PROYECTADO]])) -> 0 | M47: =+K47-L47 -> 0 | O47: =IF(ISBLANK(A47),"",R47-SUMIF(CATEGORIAS[[#All],[FORMATO GENERAL]], A47, CATEGORIAS[[#All],[COSTO REAL ANTERIOR]])) -> 0 | Q47: =+O47-P47 -> 0 | R47: =IF(ISBLANK(A47),"",SUMIF(CATEGORIAS[[#All],[FORMATO GENERAL]], A47, CATEGORIAS[[#All],[COSTO REAL]])) -> 0 | T47: =+R47-S47 -> 0 | U47: =IF(ISBLANK(A47),"",SUMIF(CATEGORIAS[[#All],[FORMATO GENERAL]], A47, CATEGORIAS[[#All],[TOTAL PRODUCCION ACTUAL]])) -> 0 | W47: =+U47-V47 -> 0 | X47: =IF(ISBLANK(A47),"",SUMIF(CATEGORIAS[[#All],[FORMATO GENERAL]], A47, CATEGORIAS[[#All],[PROYECCION TOTAL DE COSTO]])) -> 0 | Z47: =+X47-Y47 -> 0 | AB47: =IF(ISBLANK(A47),"",TRUNC(K47-R47-X47,2)) -> 0 | AD47: =+AB47-AC47 -> 0
A48: 0P08 | C48: Movilización Interna | E48: =IF(ISBLANK(A48),"", SUMIF(CATEGORIAS[[#All],[FORMATO GENERAL]], A48, CATEGORIAS[[#All],[PRESUPUESTO (ORIGINAL)]])) -> 0 | G48: =+E48-F48 -> 0 | H48: =IF(ISBLANK(A48),"",K48-E48) -> 0 | J48: =+H48-I48 -> 0 | K48: =IF(ISBLANK(A48),"",SUMIF(CATEGORIAS[[#All],[FORMATO GENERAL]], A48, CATEGORIAS[[#All],[PRESUPUESTO FINAL PROYECTADO]])) -> 0 | M48: =+K48-L48 -> 0 | O48: =IF(ISBLANK(A48),"",R48-SUMIF(CATEGORIAS[[#All],[FORMATO GENERAL]], A48, CATEGORIAS[[#All],[COSTO REAL ANTERIOR]])) -> 0 | Q48: =+O48-P48 -> 0 | R48: =IF(ISBLANK(A48),"",SUMIF(CATEGORIAS[[#All],[FORMATO GENERAL]], A48, CATEGORIAS[[#All],[COSTO REAL]])) -> 0 | T48: =+R48-S48 -> 0 | U48: =IF(ISBLANK(A48),"",SUMIF(CATEGORIAS[[#All],[FORMATO GENERAL]], A48, CATEGORIAS[[#All],[TOTAL PRODUCCION ACTUAL]])) -> 0 | W48: =+U48-V48 -> 0 | X48: =IF(ISBLANK(A48),"",SUMIF(CATEGORIAS[[#All],[FORMATO GENERAL]], A48, CATEGORIAS[[#All],[PROYECCION TOTAL DE COSTO]])) -> 0 | Z48: =+X48-Y48 -> 0 | AB48: =IF(ISBLANK(A48),"",TRUNC(K48-R48-X48,2)) -> 0 | AD48: =+AB48-AC48 -> 0
A49: 0P09 | C49: Movilización Interna | E49: =IF(ISBLANK(A49),"", SUMIF(CATEGORIAS[[#All],[FORMATO GENERAL]], A49, CATEGORIAS[[#All],[PRESUPUESTO (ORIGINAL)]])) -> 0 | G49: =+E49-F49 -> 0 | H49: =IF(ISBLANK(A49),"",K49-E49) -> 0 | J49: =+H49-I49 -> 0 | K49: =IF(ISBLANK(A49),"",SUMIF(CATEGORIAS[[#All],[FORMATO GENERAL]], A49, CATEGORIAS[[#All],[PRESUPUESTO FINAL PROYECTADO]])) -> 0 | M49: =+K49-L49 -> 0 | O49: =IF(ISBLANK(A49),"",R49-SUMIF(CATEGORIAS[[#All],[FORMATO GENERAL]], A49, CATEGORIAS[[#All],[COSTO REAL ANTERIOR]])) -> 0 | Q49: =+O49-P49 -> 0 | R49: =IF(ISBLANK(A49),"",SUMIF(CATEGORIAS[[#All],[FORMATO GENERAL]], A49, CATEGORIAS[[#All],[COSTO REAL]])) -> 0 | T49: =+R49-S49 -> 0 | U49: =IF(ISBLANK(A49),"",SUMIF(CATEGORIAS[[#All],[FORMATO GENERAL]], A49, CATEGORIAS[[#All],[TOTAL PRODUCCION ACTUAL]])) -> 0 | W49: =+U49-V49 -> 0 | X49: =IF(ISBLANK(A49),"",SUMIF(CATEGORIAS[[#All],[FORMATO GENERAL]], A49, CATEGORIAS[[#All],[PROYECCION TOTAL DE COSTO]])) -> 0 | Z49: =+X49-Y49 -> 0 | AB49: =IF(ISBLANK(A49),"",TRUNC(K49-R49-X49,2)) -> 0 | AD49: =+AB49-AC49 -> 0
A50: 0P10 | C50: Movilización Interna | E50: =IF(ISBLANK(A50),"", SUMIF(CATEGORIAS[[#All],[FORMATO GENERAL]], A50, CATEGORIAS[[#All],[PRESUPUESTO (ORIGINAL)]])) -> 0 | G50: =+E50-F50 -> 0 | H50: =IF(ISBLANK(A50),"",K50-E50) -> 0 | J50: =+H50-I50 -> 0 | K50: =IF(ISBLANK(A50),"",SUMIF(CATEGORIAS[[#All],[FORMATO GENERAL]], A50, CATEGORIAS[[#All],[PRESUPUESTO FINAL PROYECTADO]])) -> 0 | M50: =+K50-L50 -> 0 | O50: =IF(ISBLANK(A50),"",R50-SUMIF(CATEGORIAS[[#All],[FORMATO GENERAL]], A50, CATEGORIAS[[#All],[COSTO REAL ANTERIOR]])) -> 0 | Q50: =+O50-P50 -> 0 | R50: =IF(ISBLANK(A50),"",SUMIF(CATEGORIAS[[#All],[FORMATO GENERAL]], A50, CATEGORIAS[[#All],[COSTO REAL]])) -> 0 | T50: =+R50-S50 -> 0 | U50: =IF(ISBLANK(A50),"",SUMIF(CATEGORIAS[[#All],[FORMATO GENERAL]], A50, CATEGORIAS[[#All],[TOTAL PRODUCCION ACTUAL]])) -> 0 | W50: =+U50-V50 -> 0 | X50: =IF(ISBLANK(A50),"",SUMIF(CATEGORIAS[[#All],[FORMATO GENERAL]], A50, CATEGORIAS[[#All],[PROYECCION TOTAL DE COSTO]])) -> 0 | Z50: =+X50-Y50 -> 0 | AB50: =IF(ISBLANK(A50),"",TRUNC(K50-R50-X50,2)) -> 0 | AD50: =+AB50-AC50 -> 0
C51: Otros Directos | E51: =IF(ISBLANK(A51),"", SUMIF(CATEGORIAS[[#All],[FORMATO GENERAL]], A51, CATEGORIAS[[#All],[PRESUPUESTO (ORIGINAL)]])) | G51: =+E51-F51 -> #VALUE! | H51: =IF(ISBLANK(A51),"",K51-E51) | J51: =+H51-I51 -> #VALUE! | K51: =IF(ISBLANK(A51),"",SUMIF(CATEGORIAS[[#All],[FORMATO GENERAL]], A51, CATEGORIAS[[#All],[PRESUPUESTO FINAL PROYECTADO]])) | M51: =+K51-L51 -> #VALUE! | O51: =IF(ISBLANK(A51),"",R51-SUMIF(CATEGORIAS[[#All],[FORMATO GENERAL]], A51, CATEGORIAS[[#All],[COSTO REAL ANTERIOR]])) | Q51: =+O51-P51 -> #VALUE! | R51: =IF(ISBLANK(A51),"",SUMIF(CATEGORIAS[[#All],[FORMATO GENERAL]], A51, CATEGORIAS[[#All],[COSTO REAL]])) | T51: =+R51-S51 -> #VALUE! | U51: =IF(ISBLANK(A51),"",SUMIF(CATEGORIAS[[#All],[FORMATO GENERAL]], A51, CATEGORIAS[[#All],[TOTAL PRODUCCION ACTUAL]])) | W51: =+U51-V51 -> #VALUE! | X51: =IF(ISBLANK(A51),"",SUMIF(CATEGORIAS[[#All],[FORMATO GENERAL]], A51, CATEGORIAS[[#All],[PROYECCION TOTAL DE COSTO]])) | Z51: =+X51-Y51 -> #VALUE! | AB51: =IF(ISBLANK(A51),"",TRUNC(K51-R51-X51,2)) | AD51: =+AB51-AC51 -> #VALUE!
A52: 0Q01 | B52: A14 | C52: Equipos | E52: =IF(ISBLANK(A52),"", SUMIF(CATEGORIAS[[#All],[FORMATO GENERAL]], A52, CATEGORIAS[[#All],[PRESUPUESTO (ORIGINAL)]])) -> 7.4087263e+08 | F52: 740872631 | G52: =+E52-F52 -> 0.098100066 | H52: =IF(ISBLANK(A52),"",K52-E52) -> 53856436 | I52: 53856436 | J52: =+H52-I52 -> -0.069090009 | K52: =IF(ISBLANK(A52),"",SUMIF(CATEGORIAS[[#All],[FORMATO GENERAL]], A52, CATEGORIAS[[#All],[PRESUPUESTO FINAL PROYECTADO]])) -> 7.9472907e+08 | L52: 794729067 | M52: =+K52-L52 -> 0.029010057 | O52: =IF(ISBLANK(A52),"",R52-SUMIF(CATEGORIAS[[#All],[FORMATO GENERAL]], A52, CATEGORIAS[[#All],[COSTO REAL ANTERIOR]])) -> 65382208 | P52: 65382208 | Q52: =+O52-P52 -> 0.41441441 | R52: =IF(ISBLANK(A52),"",SUMIF(CATEGORIAS[[#All],[FORMATO GENERAL]], A52, CATEGORIAS[[#All],[COSTO REAL]])) -> 2.6746605e+08 | S52: 267466045 | T52: =+R52-S52 -> 0.17854217 | U52: =IF(ISBLANK(A52),"",SUMIF(CATEGORIAS[[#All],[FORMATO GENERAL]], A52, CATEGORIAS[[#All],[TOTAL PRODUCCION ACTUAL]])) -> 3.1113235e+08 | V52: 311132350 | W52: =+U52-V52 -> -0.1408034 | X52: =IF(ISBLANK(A52),"",SUMIF(CATEGORIAS[[#All],[FORMATO GENERAL]], A52, CATEGORIAS[[#All],[PROYECCION TOTAL DE COSTO]])) -> 5.2726302e+08 | Y52: 527263019 | Z52: =+X52-Y52 -> -0.14953208 | AB52: =IF(ISBLANK(A52),"",TRUNC(K52-R52-X52,2)) -> 3 | AD52: =+AB52-AC52 -> 3
A53: 0Q02 | B53: A15 | C53: Subcontratos | E53: =IF(ISBLANK(A53),"", SUMIF(CATEGORIAS[[#All],[FORMATO GENERAL]], A53, CATEGORIAS[[#All],[PRESUPUESTO (ORIGINAL)]])) -> 1.0404485e+08 | F53: 104044850 | G53: =+E53-F53 -> 0.4409 | H53: =IF(ISBLANK(A53),"",K53-E53) -> 1169952.4 | I53: 1169952 | J53: =+H53-I53 -> 0.42485359 | K53: =IF(ISBLANK(A53),"",SUMIF(CATEGORIAS[[#All],[FORMATO GENERAL]], A53, CATEGORIAS[[#All],[PRESUPUESTO FINAL PROYECTADO]])) -> 1.052148e+08 | L53: 105214803 | M53: =+K53-L53 -> -0.13424641 | O53: =IF(ISBLANK(A53),"",R53-SUMIF(CATEGORIAS[[#All],[FORMATO GENERAL]], A53, CATEGORIAS[[#All],[COSTO REAL ANTERIOR]])) -> 42302276 | P53: 42302276 | Q53: =+O53-P53 -> -0.3604 | R53: =IF(ISBLANK(A53),"",SUMIF(CATEGORIAS[[#All],[FORMATO GENERAL]], A53, CATEGORIAS[[#All],[COSTO REAL]])) -> 47669482 | S53: 47669482 | T53: =+R53-S53 -> 0 | U53: =IF(ISBLANK(A53),"",SUMIF(CATEGORIAS[[#All],[FORMATO GENERAL]], A53, CATEGORIAS[[#All],[TOTAL PRODUCCION ACTUAL]])) -> 48494030 | V53: 48494030 | W53: =+U53-V53 -> 0.32325359 | X53: =IF(ISBLANK(A53),"",SUMIF(CATEGORIAS[[#All],[FORMATO GENERAL]], A53, CATEGORIAS[[#All],[PROYECCION TOTAL DE COSTO]])) -> 57545321 | Y53: 57545321 | Z53: =+X53-Y53 -> -0.13424641 | AB53: =IF(ISBLANK(A53),"",TRUNC(K53-R53-X53,2)) -> 0 | AD53: =+AB53-AC53 -> 0
A54: 0Q03 | B54: A15 | C54: Subcontratos | E54: =IF(ISBLANK(A54),"", SUMIF(CATEGORIAS[[#All],[FORMATO GENERAL]], A54, CATEGORIAS[[#All],[PRESUPUESTO (ORIGINAL)]])) -> 1.6481157e+08 | F54: 164811574 | G54: =+E54-F54 -> -0.37860504 | H54: =IF(ISBLANK(A54),"",K54-E54) -> 1945496.9 | I54: 1945497 | J54: =+H54-I54 -> -0.068159997 | K54: =IF(ISBLANK(A54),"",SUMIF(CATEGORIAS[[#All],[FORMATO GENERAL]], A54, CATEGORIAS[[#All],[PRESUPUESTO FINAL PROYECTADO]])) -> 1.6675707e+08 | L54: 166757071 | M54: =+K54-L54 -> -0.44676504 | O54: =IF(ISBLANK(A54),"",R54-SUMIF(CATEGORIAS[[#All],[FORMATO GENERAL]], A54, CATEGORIAS[[#All],[COSTO REAL ANTERIOR]])) -> 22600348 | P54: 22600348 | Q54: =+O54-P54 -> 0 | R54: =IF(ISBLANK(A54),"",SUMIF(CATEGORIAS[[#All],[FORMATO GENERAL]], A54, CATEGORIAS[[#All],[COSTO REAL]])) -> 44689035 | S54: 44689035 | T54: =+R54-S54 -> 0 | U54: =IF(ISBLANK(A54),"",SUMIF(CATEGORIAS[[#All],[FORMATO GENERAL]], A54, CATEGORIAS[[#All],[TOTAL PRODUCCION ACTUAL]])) -> 1.1781349e+08 | V54: 117813489 | W54: =+U54-V54 -> -0.38172881 | X54: =IF(ISBLANK(A54),"",SUMIF(CATEGORIAS[[#All],[FORMATO GENERAL]], A54, CATEGORIAS[[#All],[PROYECCION TOTAL DE COSTO]])) -> 1.2206804e+08 | Y54: 122068036 | Z54: =+X54-Y54 -> -0.44676504 | AB54: =IF(ISBLANK(A54),"",TRUNC(K54-R54-X54,2)) -> 0 | AD54: =+AB54-AC54 -> 0
A55: 0Q04 | B55: A16 | C55: Instalación de Faenas | E55: =IF(ISBLANK(A55),"", SUMIF(CATEGORIAS[[#All],[FORMATO GENERAL]], A55, CATEGORIAS[[#All],[PRESUPUESTO (ORIGINAL)]])) -> 0 | G55: =+E55-F55 -> 0 | H55: =IF(ISBLANK(A55),"",K55-E55) -> 0 | J55: =+H55-I55 -> 0 | K55: =IF(ISBLANK(A55),"",SUMIF(CATEGORIAS[[#All],[FORMATO GENERAL]], A55, CATEGORIAS[[#All],[PRESUPUESTO FINAL PROYECTADO]])) -> 0 | M55: =+K55-L55 -> 0 | O55: =IF(ISBLANK(A55),"",R55-SUMIF(CATEGORIAS[[#All],[FORMATO GENERAL]], A55, CATEGORIAS[[#All],[COSTO REAL ANTERIOR]])) -> 0 | Q55: =+O55-P55 -> 0 | R55: =IF(ISBLANK(A55),"",SUMIF(CATEGORIAS[[#All],[FORMATO GENERAL]], A55, CATEGORIAS[[#All],[COSTO REAL]])) -> 0 | T55: =+R55-S55 -> 0 | U55: =IF(ISBLANK(A55),"",SUMIF(CATEGORIAS[[#All],[FORMATO GENERAL]], A55, CATEGORIAS[[#All],[TOTAL PRODUCCION ACTUAL]])) -> 0 | W55: =+U55-V55 -> 0 | X55: =IF(ISBLANK(A55),"",SUMIF(CATEGORIAS[[#All],[FORMATO GENERAL]], A55, CATEGORIAS[[#All],[PROYECCION TOTAL DE COSTO]])) -> 0 | Z55: =+X55-Y55 -> 0 | AB55: =IF(ISBLANK(A55),"",TRUNC(K55-R55-X55,2)) -> 0 | AD55: =+AB55-AC55 -> 0
G56: =+E56-F56 -> 0 | J56: =+H56-I56 -> 0 | M56: =+K56-L56 -> 0 | Q56: =+O56-P56 -> 0 | T56: =+R56-S56 -> 0 | W56: =+U56-V56 -> 0 | Z56: =+X56-Y56 -> 0 | AD56: =+AB56-AC56 -> 0
C57: Subtotal Costos Directos | E57: =SUM(E6:E55) -> 3.3350921e+09 | F57: 3335092129 | G57: =+E57-F57 -> -0.18536043 | H57: =SUM(H6:H55) -> 1.6557747e+08 | I57: 165577471 | J57: =+H57-I57 -> 0.012576789 | K57: =SUM(K6:K55) -> 3.5006696e+09 | L57: 3500669600 | M57: =+K57-L57 -> -0.17278337 | O57: =SUM(O6:O55) -> 5.6817305e+08 | P57: 568173049 | Q57: =+O57-P57 -> -1.3027424 | R57: =SUM(R6:R55) -> 1.5169241e+09 | S57: 1516924103 | T57: =+R57-S57 -> -0.32170343 | U57: =SUM(U6:U55) -> 1.3512418e+09 | V57: 1351241792 | W57: =+U57-V57 -> 0.29216766 | X57: =SUM(X6:X55) -> 1.9860709e+09 | Y57: 1986070876 | Z57: =+X57-Y57 -> 0.17430949 | AB57: =SUM(AB6:AB55) -> -2325379 | AC57: -2325379 | AD57: =+AB57-AC57 -> -0.02
G58: =+E58-F58 -> 0 | J58: =+H58-I58 -> 0 | M58: =+K58-L58 -> 0 | Q58: =+O58-P58 -> 0 | T58: =+R58-S58 -> 0 | W58: =+U58-V58 -> 0 | Z58: =+X58-Y58 -> 0 | AD58: =+AB58-AC58 -> 0
A59: B. | B59: B. | C59: Costos Indirectos | G59: =+E59-F59 -> 0 | J59: =+H59-I59 -> 0 | M59: =+K59-L59 -> #VALUE! | Q59: =+O59-P59 -> 0 | T59: =+R59-S59 -> 0 | W59: =+U59-V59 -> 0 | Z59: =+X59-Y59 -> 0 | AD59: =+AB59-AC59 -> 0
B60: B1 | C60: Mano de Obra Indirecta | E60: =IF(ISBLANK(A60),"", SUMIF(CATEGORIAS[[#All],[FORMATO GENERAL]], A60, CATEGORIAS[[#All],[PRESUPUESTO (ORIGINAL)]])) | G60: =+E60-F60 -> #VALUE! | H60: =IF(ISBLANK(A60),"",K60-E60) | J60: =+H60-I60 -> #VALUE! | K60: =IF(ISBLANK(A60),"",SUMIF(CATEGORIAS[[#All],[FORMATO GENERAL]], A60, CATEGORIAS[[#All],[PRESUPUESTO FINAL PROYECTADO]])) | M60: =+K60-L60 -> #VALUE! | O60: =IF(ISBLANK(A60),"",R60-SUMIF(CATEGORIAS[[#All],[FORMATO GENERAL]], A60, CATEGORIAS[[#All],[COSTO REAL ANTERIOR]])) | Q60: =+O60-P60 -> #VALUE! | R60: =IF(ISBLANK(A60),"",SUMIF(CATEGORIAS[[#All],[FORMATO GENERAL]], A60, CATEGORIAS[[#All],[COSTO REAL]])) | T60: =+R60-S60 -> #VALUE! | U60: =IF(ISBLANK(A60),"",SUMIF(CATEGORIAS[[#All],[FORMATO GENERAL]], A60, CATEGORIAS[[#All],[TOTAL PRODUCCION ACTUAL]])) | W60: =+U60-V60 -> #VALUE! | X60: =IF(ISBLANK(A60),"",SUMIF(CATEGORIAS[[#All],[FORMATO GENERAL]], A60, CATEGORIAS[[#All],[PROYECCION TOTAL DE COSTO]])) | Z60: =+X60-Y60 -> #VALUE! | AB60: =IF(ISBLANK(A60),"",TRUNC(K60-R60-X60,2)) | AD60: =+AB60-AC60 -> #VALUE!
A61: 1Y01 | C61: Staff Superior | E61: =IF(ISBLANK(A61),"", SUMIF(CATEGORIAS[[#All],[FORMATO GENERAL]], A61, CATEGORIAS[[#All],[PRESUPUESTO (ORIGINAL)]])) -> 3.4491885e+08 | F61: 344918851 | G61: =+E61-F61 -> 0.26215672 | H61: =IF(ISBLANK(A61),"",K61-E61) -> 5384284.5 | I61: 5384285 | J61: =+H61-I61 -> -0.5 | K61: =IF(ISBLANK(A61),"",SUMIF(CATEGORIAS[[#All],[FORMATO GENERAL]], A61, CATEGORIAS[[#All],[PRESUPUESTO FINAL PROYECTADO]])) -> 3.5030314e+08 | L61: 350303136 | M61: =+K61-L61 -> -0.23784328 | O61: =IF(ISBLANK(A61),"",R61-SUMIF(CATEGORIAS[[#All],[FORMATO GENERAL]], A61, CATEGORIAS[[#All],[COSTO REAL ANTERIOR]])) -> 53404983 | P61: 53404983 | Q61: =+O61-P61 -> 0.33333334 | R61: =IF(ISBLANK(A61),"",SUMIF(CATEGORIAS[[#All],[FORMATO GENERAL]], A61, CATEGORIAS[[#All],[COSTO REAL]])) -> 1.3921789e+08 | S61: 139217894 | T61: =+R61-S61 -> -0.25864044 | U61: =IF(ISBLANK(A61),"",SUMIF(CATEGORIAS[[#All],[FORMATO GENERAL]], A61, CATEGORIAS[[#All],[TOTAL PRODUCCION ACTUAL]])) -> 1.6108802e+08 | V61: 161088024 | W61: =+U61-V61 -> -0.23837593 | X61: =IF(ISBLANK(A61),"",SUMIF(CATEGORIAS[[#All],[FORMATO GENERAL]], A61, CATEGORIAS[[#All],[PROYECCION TOTAL DE COSTO]])) -> 2.1108524e+08 | Y61: 211085242 | Z61: =+X61-Y61 -> 0.020797163 | AB61: =IF(ISBLANK(A61),"",TRUNC(K61-R61-X61,2)) -> 0 | AD61: =+AB61-AC61 -> 0
A62: 1Y02 | C62: Oficina Técnica | E62: =IF(ISBLANK(A62),"", SUMIF(CATEGORIAS[[#All],[FORMATO GENERAL]], A62, CATEGORIAS[[#All],[PRESUPUESTO (ORIGINAL)]])) -> 1.7579984e+08 | F62: 175799842 | G62: =+E62-F62 -> -0.45636973 | H62: =IF(ISBLANK(A62),"",K62-E62) -> 5384284.5 | I62: 5384285 | J62: =+H62-I62 -> -0.5 | K62: =IF(ISBLANK(A62),"",SUMIF(CATEGORIAS[[#All],[FORMATO GENERAL]], A62, CATEGORIAS[[#All],[PRESUPUESTO FINAL PROYECTADO]])) -> 1.8118413e+08 | L62: 181184126 | M62: =+K62-L62 -> 0.043630272 | O62: =IF(ISBLANK(A62),"",R62-SUMIF(CATEGORIAS[[#All],[FORMATO GENERAL]], A62, CATEGORIAS[[#All],[COSTO REAL ANTERIOR]])) -> 28782198 | P62: 28782198 | Q62: =+O62-P62 -> 0.24815725 | R62: =IF(ISBLANK(A62),"",SUMIF(CATEGORIAS[[#All],[FORMATO GENERAL]], A62, CATEGORIAS[[#All],[COSTO REAL]])) -> 92671896 | S62: 92671896 | T62: =+R62-S62 -> 0.44701065 | U62: =IF(ISBLANK(A62),"",SUMIF(CATEGORIAS[[#All],[FORMATO GENERAL]], A62, CATEGORIAS[[#All],[TOTAL PRODUCCION ACTUAL]])) -> 82104092 | V62: 82104092 | W62: =+U62-V62 -> -0.1295736 | X62: =IF(ISBLANK(A62),"",SUMIF(CATEGORIAS[[#All],[FORMATO GENERAL]], A62, CATEGORIAS[[#All],[PROYECCION TOTAL DE COSTO]])) -> 88512230 | Y62: 88512230 | Z62: =+X62-Y62 -> -0.40338038 | AB62: =IF(ISBLANK(A62),"",TRUNC(K62-R62-X62,2)) -> 0 | AD62: =+AB62-AC62 -> 0
A63: 1Y03 | C63: Supervisión | E63: =IF(ISBLANK(A63),"", SUMIF(CATEGORIAS[[#All],[FORMATO GENERAL]], A63, CATEGORIAS[[#All],[PRESUPUESTO (ORIGINAL)]])) -> 1.0108102e+08 | F63: 101081024 | G63: =+E63-F63 -> -0.238664 | H63: =IF(ISBLANK(A63),"",K63-E63) -> 6026317.5 | I63: 6026318 | J63: =+H63-I63 -> -0.5 | K63: =IF(ISBLANK(A63),"",SUMIF(CATEGORIAS[[#All],[FORMATO GENERAL]], A63, CATEGORIAS[[#All],[PRESUPUESTO FINAL PROYECTADO]])) -> 1.0710734e+08 | L63: 107107341 | M63: =+K63-L63 -> 0.261336 | O63: =IF(ISBLANK(A63),"",R63-SUMIF(CATEGORIAS[[#All],[FORMATO GENERAL]], A63, CATEGORIAS[[#All],[COSTO REAL ANTERIOR]])) -> 21135125 | P63: 21135126 | Q63: =+O63-P63 -> -0.76576576 | R63: =IF(ISBLANK(A63),"",SUMIF(CATEGORIAS[[#All],[FORMATO GENERAL]], A63, CATEGORIAS[[#All],[COSTO REAL]])) -> 63486717 | S63: 63486717 | T63: =+R63-S63 -> -0.37018837 | U63: =IF(ISBLANK(A63),"",SUMIF(CATEGORIAS[[#All],[FORMATO GENERAL]], A63, CATEGORIAS[[#All],[TOTAL PRODUCCION ACTUAL]])) -> 47208038 | V63: 47208038 | W63: =+U63-V63 -> 0.34853165 | X63: =IF(ISBLANK(A63),"",SUMIF(CATEGORIAS[[#All],[FORMATO GENERAL]], A63, CATEGORIAS[[#All],[PROYECCION TOTAL DE COSTO]])) -> 43620625 | Y63: 43620625 | Z63: =+X63-Y63 -> -0.36847563 | AB63: =IF(ISBLANK(A63),"",TRUNC(K63-R63-X63,2)) -> 0 | AD63: =+AB63-AC63 -> 0
A64: 1Y04 | C64: Seguridad / Medio Ambiente | E64: =IF(ISBLANK(A64),"", SUMIF(CATEGORIAS[[#All],[FORMATO GENERAL]], A64, CATEGORIAS[[#All],[PRESUPUESTO (ORIGINAL)]])) -> 1.4142956e+08 | F64: 141429555 | G64: =+E64-F64 -> 0.027206749 | H64: =IF(ISBLANK(A64),"",K64-E64) -> 6026317.5 | I64: 6026318 | J64: =+H64-I64 -> -0.5 | K64: =IF(ISBLANK(A64),"",SUMIF(CATEGORIAS[[#All],[FORMATO GENERAL]], A64, CATEGORIAS[[#All],[PRESUPUESTO FINAL PROYECTADO]])) -> 1.4745587e+08 | L64: 147455873 | M64: =+K64-L64 -> -0.47279325 | O64: =IF(ISBLANK(A64),"",R64-SUMIF(CATEGORIAS[[#All],[FORMATO GENERAL]], A64, CATEGORIAS[[#All],[COSTO REAL ANTERIOR]])) -> 24554016 | P64: 24554015 | Q64: =+O64-P64 -> 0.6036036 | R64: =IF(ISBLANK(A64),"",SUMIF(CATEGORIAS[[#All],[FORMATO GENERAL]], A64, CATEGORIAS[[#All],[COSTO REAL]])) -> 61633223 | S64: 61633223 | T64: =+R64-S64 -> 0.16871417 | U64: =IF(ISBLANK(A64),"",SUMIF(CATEGORIAS[[#All],[FORMATO GENERAL]], A64, CATEGORIAS[[#All],[TOTAL PRODUCCION ACTUAL]])) -> 66052080 | V64: 66052080 | W64: =+U64-V64 -> -0.10511889 | X64: =IF(ISBLANK(A64),"",SUMIF(CATEGORIAS[[#All],[FORMATO GENERAL]], A64, CATEGORIAS[[#All],[PROYECCION TOTAL DE COSTO]])) -> 85822649 | Y64: 85822649 | Z64: =+X64-Y64 -> 0.35849258 | AB64: =IF(ISBLANK(A64),"",TRUNC(K64-R64-X64,2)) -> 0 | AD64: =+AB64-AC64 -> 0
A65: 1Y05 | C65: Control de Calidad | E65: =IF(ISBLANK(A65),"", SUMIF(CATEGORIAS[[#All],[FORMATO GENERAL]], A65, CATEGORIAS[[#All],[PRESUPUESTO (ORIGINAL)]])) -> 62286054 | F65: 62286054 | G65: =+E65-F65 -> -0.0060266554 | H65: =IF(ISBLANK(A65),"",K65-E65) -> 5384284.5 | I65: 5384285 | J65: =+H65-I65 -> -0.5 | K65: =IF(ISBLANK(A65),"",SUMIF(CATEGORIAS[[#All],[FORMATO GENERAL]], A65, CATEGORIAS[[#All],[PRESUPUESTO FINAL PROYECTADO]])) -> 67670338 | L65: 67670338 | M65: =+K65-L65 -> 0.49397334 | O65: =IF(ISBLANK(A65),"",R65-SUMIF(CATEGORIAS[[#All],[FORMATO GENERAL]], A65, CATEGORIAS[[#All],[COSTO REAL ANTERIOR]])) -> 8813412 | P65: 8813412 | Q65: =+O65-P65 -> 0.045045044 | R65: =IF(ISBLANK(A65),"",SUMIF(CATEGORIAS[[#All],[FORMATO GENERAL]], A65, CATEGORIAS[[#All],[COSTO REAL]])) -> 26934034 | S65: 26934034 | T65: =+R65-S65 -> -0.20720721 | U65: =IF(ISBLANK(A65),"",SUMIF(CATEGORIAS[[#All],[FORMATO GENERAL]], A65, CATEGORIAS[[#All],[TOTAL PRODUCCION ACTUAL]])) -> 29089559 | V65: 29089559 | W65: =+U65-V65 -> 0.20815401 | X65: =IF(ISBLANK(A65),"",SUMIF(CATEGORIAS[[#All],[FORMATO GENERAL]], A65, CATEGORIAS[[#All],[PROYECCION TOTAL DE COSTO]])) -> 40736305 | Y65: 40736305 | Z65: =+X65-Y65 -> -0.29881945 | AB65: =IF(ISBLANK(A65),"",TRUNC(K65-R65-X65,2)) -> 0 | AD65: =+AB65-AC65 -> 0
A66: 1Y06 | C66: Administración | E66: =IF(ISBLANK(A66),"", SUMIF(CATEGORIAS[[#All],[FORMATO GENERAL]], A66, CATEGORIAS[[#All],[PRESUPUESTO (ORIGINAL)]])) -> 50846869 | F66: 50846869 | G66: =+E66-F66 -> 0.032810956 | H66: =IF(ISBLANK(A66),"",K66-E66) -> 5384284.5 | I66: 5384285 | J66: =+H66-I66 -> -0.5 | K66: =IF(ISBLANK(A66),"",SUMIF(CATEGORIAS[[#All],[FORMATO GENERAL]], A66, CATEGORIAS[[#All],[PRESUPUESTO FINAL PROYECTADO]])) -> 56231154 | L66: 56231154 | M66: =+K66-L66 -> -0.46718904 | O66: =IF(ISBLANK(A66),"",R66-SUMIF(CATEGORIAS[[#All],[FORMATO GENERAL]], A66, CATEGORIAS[[#All],[COSTO REAL ANTERIOR]])) -> 6951507.7 | P66: 6951508 | Q66: =+O66-P66 -> -0.25880426 | R66: =IF(ISBLANK(A66),"",SUMIF(CATEGORIAS[[#All],[FORMATO GENERAL]], A66, CATEGORIAS[[#All],[COSTO REAL]])) -> 24940109 | S66: 24940109 | T66: =+R66-S66 -> -0.43488944 | U66: =IF(ISBLANK(A66),"",SUMIF(CATEGORIAS[[#All],[FORMATO GENERAL]], A66, CATEGORIAS[[#All],[TOTAL PRODUCCION ACTUAL]])) -> 23747098 | V66: 23747098 | W66: =+U66-V66 -> -0.33633483 | X66: =IF(ISBLANK(A66),"",SUMIF(CATEGORIAS[[#All],[FORMATO GENERAL]], A66, CATEGORIAS[[#All],[PROYECCION TOTAL DE COSTO]])) -> 31291045 | Y66: 31291045 | Z66: =+X66-Y66 -> -0.032299608 | AB66: =IF(ISBLANK(A66),"",TRUNC(K66-R66-X66,2)) -> 0 | AD66: =+AB66-AC66 -> 0
A67: 1Y07 | C67: Servicios | E67: =IF(ISBLANK(A67),"", SUMIF(CATEGORIAS[[#All],[FORMATO GENERAL]], A67, CATEGORIAS[[#All],[PRESUPUESTO (ORIGINAL)]])) -> 1.0286084e+08 | F67: 102860837 | G67: =+E67-F67 -> 0.035145372 | H67: =IF(ISBLANK(A67),"",K67-E67) -> 5384284.5 | I67: 5384285 | J67: =+H67-I67 -> -0.5 | K67: =IF(ISBLANK(A67),"",SUMIF(CATEGORIAS[[#All],[FORMATO GENERAL]], A67, CATEGORIAS[[#All],[PRESUPUESTO FINAL PROYECTADO]])) -> 1.0824512e+08 | L67: 108245122 | M67: =+K67-L67 -> -0.46485463 | O67: =IF(ISBLANK(A67),"",R67-SUMIF(CATEGORIAS[[#All],[FORMATO GENERAL]], A67, CATEGORIAS[[#All],[COSTO REAL ANTERIOR]])) -> 35308969 | P67: 35308969 | Q67: =+O67-P67 -> 0.38738738 | R67: =IF(ISBLANK(A67),"",SUMIF(CATEGORIAS[[#All],[FORMATO GENERAL]], A67, CATEGORIAS[[#All],[COSTO REAL]])) -> 1.0962651e+08 | S67: 109626507 | T67: =+R67-S67 -> 0.36805896 | U67: =IF(ISBLANK(A67),"",SUMIF(CATEGORIAS[[#All],[FORMATO GENERAL]], A67, CATEGORIAS[[#All],[TOTAL PRODUCCION ACTUAL]])) -> 48039267 | V67: 48039268 | W67: =+U67-V67 -> -0.50323967 | X67: =IF(ISBLANK(A67),"",SUMIF(CATEGORIAS[[#All],[FORMATO GENERAL]], A67, CATEGORIAS[[#All],[PROYECCION TOTAL DE COSTO]])) -> -1381385.8 | Y67: -1381386 | Z67: =+X67-Y67 -> 0.16708641 | AB67: =IF(ISBLANK(A67),"",TRUNC(K67-R67-X67,2)) -> 0 | AD67: =+AB67-AC67 -> 0
A68: 1Y08 | C68: Topografía | E68: =IF(ISBLANK(A68),"", SUMIF(CATEGORIAS[[#All],[FORMATO GENERAL]], A68, CATEGORIAS[[#All],[PRESUPUESTO (ORIGINAL)]])) -> 47989913 | F68: 47989913 | G68: =+E68-F68 -> 0.093136542 | H68: =IF(ISBLANK(A68),"",K68-E68) -> 0 | J68: =+H68-I68 -> 0 | K68: =IF(ISBLANK(A68),"",SUMIF(CATEGORIAS[[#All],[FORMATO GENERAL]], A68, CATEGORIAS[[#All],[PRESUPUESTO FINAL PROYECTADO]])) -> 47989913 | L68: 47989913 | M68: =+K68-L68 -> 0.093136542 | O68: =IF(ISBLANK(A68),"",R68-SUMIF(CATEGORIAS[[#All],[FORMATO GENERAL]], A68, CATEGORIAS[[#All],[COSTO REAL ANTERIOR]])) -> 10634928 | P68: 10634928 | Q68: =+O68-P68 -> 0.40540541 | R68: =IF(ISBLANK(A68),"",SUMIF(CATEGORIAS[[#All],[FORMATO GENERAL]], A68, CATEGORIAS[[#All],[COSTO REAL]])) -> 31389825 | S68: 31389825 | T68: =+R68-S68 -> 0.047502048 | U68: =IF(ISBLANK(A68),"",SUMIF(CATEGORIAS[[#All],[FORMATO GENERAL]], A68, CATEGORIAS[[#All],[TOTAL PRODUCCION ACTUAL]])) -> 22412809 | V68: 22412809 | W68: =+U68-V68 -> -0.21214461 | X68: =IF(ISBLANK(A68),"",SUMIF(CATEGORIAS[[#All],[FORMATO GENERAL]], A68, CATEGORIAS[[#All],[PROYECCION TOTAL DE COSTO]])) -> 16600088 | Y68: 16600088 | Z68: =+X68-Y68 -> 0.045634493 | AB68: =IF(ISBLANK(A68),"",TRUNC(K68-R68-X68,2)) -> 0 | AD68: =+AB68-AC68 -> 0
A69: 1Y09 | C69: Movilización | E69: =IF(ISBLANK(A69),"", SUMIF(CATEGORIAS[[#All],[FORMATO GENERAL]], A69, CATEGORIAS[[#All],[PRESUPUESTO (ORIGINAL)]])) -> 50970000 | F69: 50970000 | G69: =+E69-F69 -> 0 | H69: =IF(ISBLANK(A69),"",K69-E69) -> 0 | J69: =+H69-I69 -> 0 | K69: =IF(ISBLANK(A69),"",SUMIF(CATEGORIAS[[#All],[FORMATO GENERAL]], A69, CATEGORIAS[[#All],[PRESUPUESTO FINAL PROYECTADO]])) -> 50970000 | L69: 50970000 | M69: =+K69-L69 -> 0 | O69: =IF(ISBLANK(A69),"",R69-SUMIF(CATEGORIAS[[#All],[FORMATO GENERAL]], A69, CATEGORIAS[[#All],[COSTO REAL ANTERIOR]])) -> 320873 | P69: 320873 | Q69: =+O69-P69 -> 0 | R69: =IF(ISBLANK(A69),"",SUMIF(CATEGORIAS[[#All],[FORMATO GENERAL]], A69, CATEGORIAS[[#All],[COSTO REAL]])) -> 10078282 | S69: 10078282 | T69: =+R69-S69 -> 0 | U69: =IF(ISBLANK(A69),"",SUMIF(CATEGORIAS[[#All],[FORMATO GENERAL]], A69, CATEGORIAS[[#All],[TOTAL PRODUCCION ACTUAL]])) -> 23804604 | V69: 23804604 | W69: =+U69-V69 -> -0.27629851 | X69: =IF(ISBLANK(A69),"",SUMIF(CATEGORIAS[[#All],[FORMATO GENERAL]], A69, CATEGORIAS[[#All],[PROYECCION TOTAL DE COSTO]])) -> 40891718 | Y69: 40891718 | Z69: =+X69-Y69 -> 0 | AB69: =IF(ISBLANK(A69),"",TRUNC(K69-R69-X69,2)) -> 0 | AD69: =+AB69-AC69 -> 0
A70: 1Y10 | C70: Movilización | E70: =IF(ISBLANK(A70),"", SUMIF(CATEGORIAS[[#All],[FORMATO GENERAL]], A70, CATEGORIAS[[#All],[PRESUPUESTO (ORIGINAL)]])) -> 1.2760671e+08 | F70: 127606714 | G70: =+E70-F70 -> 0.28571428 | H70: =IF(ISBLANK(A70),"",K70-E70) -> 0 | J70: =+H70-I70 -> 0 | K70: =IF(ISBLANK(A70),"",SUMIF(CATEGORIAS[[#All],[FORMATO GENERAL]], A70, CATEGORIAS[[#All],[PRESUPUESTO FINAL PROYECTADO]])) -> 1.2760671e+08 | L70: 127606714 | M70: =+K70-L70 -> 0.28571428 | O70: =IF(ISBLANK(A70),"",R70-SUMIF(CATEGORIAS[[#All],[FORMATO GENERAL]], A70, CATEGORIAS[[#All],[COSTO REAL ANTERIOR]])) -> 5685397 | P70: 5685397 | Q70: =+O70-P70 -> 0 | R70: =IF(ISBLANK(A70),"",SUMIF(CATEGORIAS[[#All],[FORMATO GENERAL]], A70, CATEGORIAS[[#All],[COSTO REAL]])) -> 19418586 | S70: 19418586 | T70: =+R70-S70 -> 0 | U70: =IF(ISBLANK(A70),"",SUMIF(CATEGORIAS[[#All],[FORMATO GENERAL]], A70, CATEGORIAS[[#All],[TOTAL PRODUCCION ACTUAL]])) -> 59596376 | V70: 59596376 | W70: =+U70-V70 -> -0.36619528 | X70: =IF(ISBLANK(A70),"",SUMIF(CATEGORIAS[[#All],[FORMATO GENERAL]], A70, CATEGORIAS[[#All],[PROYECCION TOTAL DE COSTO]])) -> 1.0818813e+08 | Y70: 108188128 | Z70: =+X70-Y70 -> 0.28571428 | AB70: =IF(ISBLANK(A70),"",TRUNC(K70-R70-X70,2)) -> 0 | AD70: =+AB70-AC70 -> 0
A71: 1Y11 | C71: Pensión y Alimentación | E71: =IF(ISBLANK(A71),"", SUMIF(CATEGORIAS[[#All],[FORMATO GENERAL]], A71, CATEGORIAS[[#All],[PRESUPUESTO (ORIGINAL)]])) -> 6483651.4 | F71: 6483651 | G71: =+E71-F71 -> 0.42857143 | H71: =IF(ISBLANK(A71),"",K71-E71) -> 0 | J71: =+H71-I71 -> 0 | K71: =IF(ISBLANK(A71),"",SUMIF(CATEGORIAS[[#All],[FORMATO GENERAL]], A71, CATEGORIAS[[#All],[PRESUPUESTO FINAL PROYECTADO]])) -> 6483651.4 | L71: 6483651 | M71: =+K71-L71 -> 0.42857143 | O71: =IF(ISBLANK(A71),"",R71-SUMIF(CATEGORIAS[[#All],[FORMATO GENERAL]], A71, CATEGORIAS[[#All],[COSTO REAL ANTERIOR]])) -> 1067029 | P71: 1067029 | Q71: =+O71-P71 -> 0 | R71: =IF(ISBLANK(A71),"",SUMIF(CATEGORIAS[[#All],[FORMATO GENERAL]], A71, CATEGORIAS[[#All],[COSTO REAL]])) -> 4714066 | S71: 4714066 | T71: =+R71-S71 -> 0 | U71: =IF(ISBLANK(A71),"",SUMIF(CATEGORIAS[[#All],[FORMATO GENERAL]], A71, CATEGORIAS[[#All],[TOTAL PRODUCCION ACTUAL]])) -> 3028070.5 | V71: 3028070 | W71: =+U71-V71 -> 0.49126455 | X71: =IF(ISBLANK(A71),"",SUMIF(CATEGORIAS[[#All],[FORMATO GENERAL]], A71, CATEGORIAS[[#All],[PROYECCION TOTAL DE COSTO]])) -> 1769585.4 | Y71: 1769585 | Z71: =+X71-Y71 -> 0.42857143 | AB71: =IF(ISBLANK(A71),"",TRUNC(K71-R71-X71,2)) -> 0 | AD71: =+AB71-AC71 -> 0
G72: =+E72-F72 -> 0 | J72: =+H72-I72 -> 0 | M72: =+K72-L72 -> 0 | Q72: =+O72-P72 -> 0 | T72: =+R72-S72 -> 0 | W72: =+U72-V72 -> 0 | Z72: =+X72-Y72 -> 0 | AD72: =+AB72-AC72 -> 0
C73: Otros Indirectos | E73: =IF(ISBLANK(A73),"", SUMIF(CATEGORIAS[[#All],[FORMATO GENERAL]], A73, CATEGORIAS[[#All],[PRESUPUESTO (ORIGINAL)]])) | G73: =+E73-F73 -> #VALUE! | H73: =IF(ISBLANK(A73),"",K73-E73) | J73: =+H73-I73 -> #VALUE! | K73: =IF(ISBLANK(A73),"",SUMIF(CATEGORIAS[[#All],[FORMATO GENERAL]], A73, CATEGORIAS[[#All],[PRESUPUESTO FINAL PROYECTADO]])) | M73: =+K73-L73 -> #VALUE! | O73: =IF(ISBLANK(A73),"",R73-SUMIF(CATEGORIAS[[#All],[FORMATO GENERAL]], A73, CATEGORIAS[[#All],[COSTO REAL ANTERIOR]])) | Q73: =+O73-P73 -> #VALUE! | R73: =IF(ISBLANK(A73),"",SUMIF(CATEGORIAS[[#All],[FORMATO GENERAL]], A73, CATEGORIAS[[#All],[COSTO REAL]])) | T73: =+R73-S73 -> #VALUE! | U73: =IF(ISBLANK(A73),"",SUMIF(CATEGORIAS[[#All],[FORMATO GENERAL]], A73, CATEGORIAS[[#All],[TOTAL PRODUCCION ACTUAL]])) | W73: =+U73-V73 -> #VALUE! | X73: =IF(ISBLANK(A73),"",SUMIF(CATEGORIAS[[#All],[FORMATO GENERAL]], A73, CATEGORIAS[[#All],[PROYECCION TOTAL DE COSTO]])) | Z73: =+X73-Y73 -> #VALUE! | AB73: =IF(ISBLANK(A73),"",TRUNC(K73-R73-X73,2)) | AD73: =+AB73-AC73 -> #VALUE!
A74: 1Z01 | B74: B2 | C74: Equipos Indirectos | E74: =IF(ISBLANK(A74),"", SUMIF(CATEGORIAS[[#All],[FORMATO GENERAL]], A74, CATEGORIAS[[#All],[PRESUPUESTO (ORIGINAL)]])) -> 90537195 | F74: 90537195 | G74: =+E74-F74 -> -0.11999997 | H74: =IF(ISBLANK(A74),"",K74-E74) -> 0 | J74: =+H74-I74 -> 0 | K74: =IF(ISBLANK(A74),"",SUMIF(CATEGORIAS[[#All],[FORMATO GENERAL]], A74, CATEGORIAS[[#All],[PRESUPUESTO FINAL PROYECTADO]])) -> 90537195 | L74: 90537195 | M74: =+K74-L74 -> -0.11999997 | O74: =IF(ISBLANK(A74),"",R74-SUMIF(CATEGORIAS[[#All],[FORMATO GENERAL]], A74, CATEGORIAS[[#All],[COSTO REAL ANTERIOR]])) -> 3275095 | P74: 3275095 | Q74: =+O74-P74 -> 0 | R74: =IF(ISBLANK(A74),"",SUMIF(CATEGORIAS[[#All],[FORMATO GENERAL]], A74, CATEGORIAS[[#All],[COSTO REAL]])) -> 22130647 | S74: 22130647 | T74: =+R74-S74 -> 0 | U74: =IF(ISBLANK(A74),"",SUMIF(CATEGORIAS[[#All],[FORMATO GENERAL]], A74, CATEGORIAS[[#All],[TOTAL PRODUCCION ACTUAL]])) -> 42283736 | V74: 42283736 | W74: =+U74-V74 -> 0.44053239 | X74: =IF(ISBLANK(A74),"",SUMIF(CATEGORIAS[[#All],[FORMATO GENERAL]], A74, CATEGORIAS[[#All],[PROYECCION TOTAL DE COSTO]])) -> 68406548 | Y74: 68406548 | Z74: =+X74-Y74 -> -0.11999997 | AB74: =IF(ISBLANK(A74),"",TRUNC(K74-R74-X74,2)) -> 0 | AD74: =+AB74-AC74 -> 0
A75: 1Z02 | B75: B3 | C75: Gastos Generales | E75: =IF(ISBLANK(A75),"", SUMIF(CATEGORIAS[[#All],[FORMATO GENERAL]], A75, CATEGORIAS[[#All],[PRESUPUESTO (ORIGINAL)]])) -> 59588645 | F75: 59588645 | G75: =+E75-F75 -> -0.09312094 | H75: =IF(ISBLANK(A75),"",K75-E75) -> 549015.27 | I75: 549015 | J75: =+H75-I75 -> 0.26663345 | K75: =IF(ISBLANK(A75),"",SUMIF(CATEGORIAS[[#All],[FORMATO GENERAL]], A75, CATEGORIAS[[#All],[PRESUPUESTO FINAL PROYECTADO]])) -> 60137660 | L75: 60137660 | M75: =+K75-L75 -> 0.17351251 | O75: =IF(ISBLANK(A75),"",R75-SUMIF(CATEGORIAS[[#All],[FORMATO GENERAL]], A75, CATEGORIAS[[#All],[COSTO REAL ANTERIOR]])) -> 19002308 | P75: 19002308 | Q75: =+O75-P75 -> 0.4712 | R75: =IF(ISBLANK(A75),"",SUMIF(CATEGORIAS[[#All],[FORMATO GENERAL]], A75, CATEGORIAS[[#All],[COSTO REAL]])) -> 58458192 | S75: 58458192 | T75: =+R75-S75 -> 0.4712 | U75: =IF(ISBLANK(A75),"",SUMIF(CATEGORIAS[[#All],[FORMATO GENERAL]], A75, CATEGORIAS[[#All],[TOTAL PRODUCCION ACTUAL]])) -> 27038376 | V75: 27038376 | W75: =+U75-V75 -> 0.012357906 | X75: =IF(ISBLANK(A75),"",SUMIF(CATEGORIAS[[#All],[FORMATO GENERAL]], A75, CATEGORIAS[[#All],[PROYECCION TOTAL DE COSTO]])) -> 1679467.7 | Y75: 1679468 | Z75: =+X75-Y75 -> -0.29768749 | AB75: =IF(ISBLANK(A75),"",TRUNC(K75-R75-X75,2)) -> 0 | AD75: =+AB75-AC75 -> 0
A76: 1Z03 | B76: B4 | C76: Gastos Financieros | E76: =IF(ISBLANK(A76),"", SUMIF(CATEGORIAS[[#All],[FORMATO GENERAL]], A76, CATEGORIAS[[#All],[PRESUPUESTO (ORIGINAL)]])) -> 27821679 | F76: 27821679 | G76: =+E76-F76 -> -0.20890154 | H76: =IF(ISBLANK(A76),"",K76-E76) -> 0 | J76: =+H76-I76 -> 0 | K76: =IF(ISBLANK(A76),"",SUMIF(CATEGORIAS[[#All],[FORMATO GENERAL]], A76, CATEGORIAS[[#All],[PRESUPUESTO FINAL PROYECTADO]])) -> 27821679 | L76: 27821679 | M76: =+K76-L76 -> -0.20890154 | O76: =IF(ISBLANK(A76),"",R76-SUMIF(CATEGORIAS[[#All],[FORMATO GENERAL]], A76, CATEGORIAS[[#All],[COSTO REAL ANTERIOR]])) -> 6072529.3 | P76: 6072530 | Q76: =+O76-P76 -> -0.66103138 | R76: =IF(ISBLANK(A76),"",SUMIF(CATEGORIAS[[#All],[FORMATO GENERAL]], A76, CATEGORIAS[[#All],[COSTO REAL]])) -> 12993605 | S76: 12993605 | T76: =+R76-S76 -> -0.1628368 | U76: =IF(ISBLANK(A76),"",SUMIF(CATEGORIAS[[#All],[FORMATO GENERAL]], A76, CATEGORIAS[[#All],[TOTAL PRODUCCION ACTUAL]])) -> 12993605 | V76: 12993605 | W76: =+U76-V76 -> -0.16283678 | X76: =IF(ISBLANK(A76),"",SUMIF(CATEGORIAS[[#All],[FORMATO GENERAL]], A76, CATEGORIAS[[#All],[PROYECCION TOTAL DE COSTO]])) -> 14828074 | Y76: 14828074 | Z76: =+X76-Y76 -> -0.04606474 | AB76: =IF(ISBLANK(A76),"",TRUNC(K76-R76-X76,2)) -> 0 | AD76: =+AB76-AC76 -> 0
A77: 1Z04 | B77: B5 | C77: Seguros y Boletas de Garantia | E77: =IF(ISBLANK(A77),"", SUMIF(CATEGORIAS[[#All],[FORMATO GENERAL]], A77, CATEGORIAS[[#All],[PRESUPUESTO (ORIGINAL)]])) -> 53522314 | F77: 53522314 | G77: =+E77-F77 -> -0.008223556 | H77: =IF(ISBLANK(A77),"",K77-E77) -> 0 | J77: =+H77-I77 -> 0 | K77: =IF(ISBLANK(A77),"",SUMIF(CATEGORIAS[[#All],[FORMATO GENERAL]], A77, CATEGORIAS[[#All],[PRESUPUESTO FINAL PROYECTADO]])) -> 53522314 | L77: 53522314 | M77: =+K77-L77 -> -0.008223556 | O77: =IF(ISBLANK(A77),"",R77-SUMIF(CATEGORIAS[[#All],[FORMATO GENERAL]], A77, CATEGORIAS[[#All],[COSTO REAL ANTERIOR]])) -> 11682107 | P77: 11682106 | Q77: =+O77-P77 -> 0.76447538 | R77: =IF(ISBLANK(A77),"",SUMIF(CATEGORIAS[[#All],[FORMATO GENERAL]], A77, CATEGORIAS[[#All],[COSTO REAL]])) -> 24996615 | S77: 24996615 | T77: =+R77-S77 -> 0.1647981 | U77: =IF(ISBLANK(A77),"",SUMIF(CATEGORIAS[[#All],[FORMATO GENERAL]], A77, CATEGORIAS[[#All],[TOTAL PRODUCCION ACTUAL]])) -> 24996615 | V77: 24996615 | W77: =+U77-V77 -> 0.16479816 | X77: =IF(ISBLANK(A77),"",SUMIF(CATEGORIAS[[#All],[FORMATO GENERAL]], A77, CATEGORIAS[[#All],[PROYECCION TOTAL DE COSTO]])) -> 28525699 | Y77: 28525699 | Z77: =+X77-Y77 -> -0.17302166 | AB77: =IF(ISBLANK(A77),"",TRUNC(K77-R77-X77,2)) -> 0 | AD77: =+AB77-AC77 -> 0
A78: 1Z05 | B78: B6 | C78: Perdida de Reajuste | E78: =IF(ISBLANK(A78),"", SUMIF(CATEGORIAS[[#All],[FORMATO GENERAL]], A78, CATEGORIAS[[#All],[PRESUPUESTO (ORIGINAL)]])) -> 0 | G78: =+E78-F78 -> 0 | H78: =IF(ISBLANK(A78),"",K78-E78) -> 0 | J78: =+H78-I78 -> 0 | K78: =IF(ISBLANK(A78),"",SUMIF(CATEGORIAS[[#All],[FORMATO GENERAL]], A78, CATEGORIAS[[#All],[PRESUPUESTO FINAL PROYECTADO]])) -> 0 | M78: =+K78-L78 -> 0 | O78: =IF(ISBLANK(A78),"",R78-SUMIF(CATEGORIAS[[#All],[FORMATO GENERAL]], A78, CATEGORIAS[[#All],[COSTO REAL ANTERIOR]])) -> 0 | Q78: =+O78-P78 -> 0 | R78: =IF(ISBLANK(A78),"",SUMIF(CATEGORIAS[[#All],[FORMATO GENERAL]], A78, CATEGORIAS[[#All],[COSTO REAL]])) -> 0 | T78: =+R78-S78 -> 0 | U78: =IF(ISBLANK(A78),"",SUMIF(CATEGORIAS[[#All],[FORMATO GENERAL]], A78, CATEGORIAS[[#All],[TOTAL PRODUCCION ACTUAL]])) -> 0 | W78: =+U78-V78 -> 0 | X78: =IF(ISBLANK(A78),"",SUMIF(CATEGORIAS[[#All],[FORMATO GENERAL]], A78, CATEGORIAS[[#All],[PROYECCION TOTAL DE COSTO]])) -> 0 | Z78: =+X78-Y78 -> 0 | AB78: =IF(ISBLANK(A78),"",TRUNC(K78-R78-X78,2)) -> 0 | AD78: =+AB78-AC78 -> 0
G79: =+E79-F79 -> 0 | J79: =+H79-I79 -> 0 | M79: =+K79-L79 -> 0 | Q79: =+O79-P79 -> 0 | T79: =+R79-S79 -> 0 | W79: =+U79-V79 -> 0 | Z79: =+X79-Y79 -> 0 | AD79: =+AB79-AC79 -> 0
C80: Subtotal Costos Indirectos | E80: =SUM(E60:E79) -> 1.4437431e+09 | F80: 1443743143 | G80: =+E80-F80 -> 0.033435822 | H80: =SUM(H60:H79) -> 39523073 | I80: 39523073 | J80: =+H80-I80 -> -0.23336655 | K80: =SUM(K60:K79) -> 1.4832662e+09 | L80: 1483266216 | M80: =+K80-L80 -> -0.19993067 | O80: =SUM(O60:O79) -> 2.3669048e+08 | P80: 236690477 | Q80: =+O80-P80 -> 1.573006 | R80: =SUM(R60:R79) -> 7.026902e+08 | S80: 702690198 | T80: =+R80-S80 -> 0.23352182 | U80: =SUM(U60:U79) -> 6.7348235e+08 | V80: 673482349 | W80: =+U80-V80 -> 0.33552063 | X80: =SUM(X60:X79) -> 7.8057602e+08 | Y80: 780576018 | Z80: =+X80-Y80 -> -0.43345249 | AB80: =SUM(AB60:AB79) -> 0 | AD80: =+AB80-AC80 -> 0
G81: =+E81-F81 -> 0 | J81: =+H81-I81 -> 0 | M81: =+K81-L81 -> 0 | Q81: =+O81-P81 -> 0 | T81: =+R81-S81 -> 0 | W81: =+U81-V81 -> 0 | Z81: =+X81-Y81 -> 0 | AD81: =+AB81-AC81 -> 0
A82: 2A00 | B82: C. | C82: Margen Esperado | E82: =+SUM(E83:E85) -> 5.309817e+08 | F82: 530981697 | G82: =+E82-F82 -> -0.12796879 | H82: =+SUM(H83:H85) -> 0 | J82: =+H82-I82 -> 0 | K82: =+SUM(K83:K85) -> 5.309817e+08 | L82: 530981697 | M82: =+K82-L82 -> -0.12796879 | O82: =+SUM(O83:O85) -> 0 | Q82: =+O82-P82 -> 0 | R82: =+SUM(R83:R85) -> 0 | T82: =+R82-S82 -> 0 | U82: =+SUM(U83:U85) -> 2.4798526e+08 | V82: 247985263 | W82: =+U82-V82 -> 0.46041375 | X82: =+SUM(X83:X85) -> 0 | Z82: =+X82-Y82 -> 0 | AB82: =+SUM(AB83:AB85) -> 5.309817e+08 | AC82: 530981697 | AD82: =+AB82-AC82 -> -0.12796879
A83: 1K01 | C83: Oficina Central | E83: =IF(ISBLANK(A83),"", SUMIF(CATEGORIAS[[#All],[SUBGRUPO]], A83, CATEGORIAS[[#All],[PRESUPUESTO (ORIGINAL)]])) -> 2.1239268e+08 | F83: 212392679 | G83: =+E83-F83 -> -0.25118753 | J83: =+H83-I83 -> 0 | K83: =IF(ISBLANK(A83),"", SUMIF(CATEGORIAS[[#All],[SUBGRUPO]], A83, CATEGORIAS[[#All],[PRESUPUESTO FINAL PROYECTADO]])) -> 2.1239268e+08 | L83: 212392679 | M83: =+K83-L83 -> -0.25118753 | O83: 0 | Q83: =+O83-P83 -> 0 | R83: 0 | T83: =+R83-S83 -> 0 | U83: =IF(ISBLANK(A83),"",SUMIF(CATEGORIAS[[#All],[SUBGRUPO]], A83, CATEGORIAS[[#All],[TOTAL PRODUCCION ACTUAL]])) -> 99194105 | V83: 99194105 | W83: =+U83-V83 -> 0.38416551 | X83: 0 | Z83: =+X83-Y83 -> 0 | AB83: =IF(ISBLANK(A83),"",K83-R83-X83) -> 2.1239268e+08 | AC83: 212392679 | AD83: =+AB83-AC83 -> -0.25118753
A84: 1K02 | C84: Imprevistos | E84: =IF(ISBLANK(A84),"", SUMIF(CATEGORIAS[[#All],[SUBGRUPO]], A84, CATEGORIAS[[#All],[PRESUPUESTO (ORIGINAL)]])) -> 1.0619634e+08 | F84: 106196339 | G84: =+E84-F84 -> 0.37440623 | J84: =+H84-I84 -> 0 | K84: =IF(ISBLANK(A84),"", SUMIF(CATEGORIAS[[#All],[SUBGRUPO]], A84, CATEGORIAS[[#All],[PRESUPUESTO FINAL PROYECTADO]])) -> 1.0619634e+08 | L84: 106196339 | M84: =+K84-L84 -> 0.37440623 | O84: 0 | Q84: =+O84-P84 -> 0 | R84: 0 | T84: =+R84-S84 -> 0 | U84: =IF(ISBLANK(A84),"",SUMIF(CATEGORIAS[[#All],[SUBGRUPO]], A84, CATEGORIAS[[#All],[TOTAL PRODUCCION ACTUAL]])) -> 49597053 | V84: 49597053 | W84: =+U84-V84 -> -0.30791724 | X84: 0 | Z84: =+X84-Y84 -> 0 | AB84: =IF(ISBLANK(A84),"",K84-R84-X84) -> 1.0619634e+08 | AC84: 106196339 | AD84: =+AB84-AC84 -> 0.37440623
A85: 1K03 | C85: Utilidad | E85: =IF(ISBLANK(A85),"", SUMIF(CATEGORIAS[[#All],[SUBGRUPO]], A85, CATEGORIAS[[#All],[PRESUPUESTO (ORIGINAL)]])) -> 2.1239268e+08 | F85: 212392679 | G85: =+E85-F85 -> -0.25118753 | J85: =+H85-I85 -> 0 | K85: =IF(ISBLANK(A85),"", SUMIF(CATEGORIAS[[#All],[SUBGRUPO]], A85, CATEGORIAS[[#All],[PRESUPUESTO FINAL PROYECTADO]])) -> 2.1239268e+08 | L85: 212392679 | M85: =+K85-L85 -> -0.25118753 | O85: 0 | Q85: =+O85-P85 -> 0 | R85: 0 | T85: =+R85-S85 -> 0 | U85: =IF(ISBLANK(A85),"",SUMIF(CATEGORIAS[[#All],[SUBGRUPO]], A85, CATEGORIAS[[#All],[TOTAL PRODUCCION ACTUAL]])) -> 99194105 | V85: 99194105 | W85: =+U85-V85 -> 0.38416551 | X85: 0 | Z85: =+X85-Y85 -> 0 | AB85: =IF(ISBLANK(A85),"",K85-R85-X85) -> 2.1239268e+08 | AC85: 212392679 | AD85: =+AB85-AC85 -> -0.25118753
G86: =+E86-F86 -> 0 | J86: =+H86-I86 -> 0 | M86: =+K86-L86 -> 0 | Q86: =+O86-P86 -> 0 | T86: =+R86-S86 -> 0 | W86: =+U86-V86 -> 0 | Z86: =+X86-Y86 -> 0 | AD86: =+AB86-AC86 -> 0
B87: D. | C87: TOTAL | E87: =E57+E80+E82 -> 5.309817e+09 | F87: 5309816969 | G87: =+E87-F87 -> -0.27989292 | H87: =H57+H80+H82 -> 2.0510054e+08 | I87: 205100544 | J87: =+H87-I87 -> -0.22078976 | K87: =K57+K80+K82 -> 5.5149175e+09 | L87: 5514917512 | M87: =+K87-L87 -> 0.49931717 | O87: =O57+O80+O82 -> 8.0486353e+08 | P87: 804863526 | Q87: =+O87-P87 -> 0.27026367 | R87: =R57+R80+R82 -> 2.2196143e+09 | S87: 2219614301 | T87: =+R87-S87 -> -0.088181496 | U87: =U57+U80+U82 -> 2.2727094e+09 | V87: 2272709405 | W87: =+U87-V87 -> 0.088102341 | X87: =X57+X80+X82 -> 2.7666469e+09 | Y87: 2766646894 | Z87: =+X87-Y87 -> -0.25914288 | AB87: =AB57+AB80+AB82+AB86 -> 5.2865632e+08 | AC87: 528656318 | AD87: =+AB87-AC87 -> -0.14796877
B88: E. | C88: Oficina Central (4%) | AB88: =-4%*K87 -> -2.205967e+08 | AC88: -220596700 | AD88: =+AB88-AC88 -> -0.4999727
B89: F. | C89: TOTAL | AB89: =+AB87+AB88 -> 3.0805962e+08 | AC89: 308059617 | AD89: =+AB89-AC89 -> 0.35205853
X98: Administrador Obra
C102: INFORME COSTOS DIC-25
C103: PBI | E103: 5309816969 | H103: 205100544
C104: DIFERENCIA

Sheet Analisis por Categorias
E1: ERROR DE PRODUCCION - ADICIONALES | G1: 4 | H1: 5 | I1: 6 | L1: 7 | M1: 8 | N1: 9 | O1: 10 | P1: 11 | Q1: 12 | R1: 13 | S1: 14 | T1: 15 | U1: 16 | V1: 17 | W1: 18 | X1: 19 | Y1: 20 | Z1: 21 | AA1: 22 | AB1: 23 | AC1: 24 | AD1: 25 | AE1: 26
E2: ERROR DE PRODUCCION - ADICIONALES | G2: =SUBTOTAL(9,CATEGORIAS[PRESUPUESTO (ORIGINAL)]) -> 5.309817e+09 | H2: =SUBTOTAL(9,CATEGORIAS[POM]) -> 5.309817e+09 | I2: =SUBTOTAL(9,CATEGORIAS[ADICIONALES]) -> 2.0510054e+08 | L2: =SUBTOTAL(9,CATEGORIAS[PRESUPUESTO FINAL PROYECTADO]) -> 5.5149175e+09 | M2: =SUBTOTAL(9,CATEGORIAS[PRODUCCION PARTIDAS ORIGINALES ACTUAL]) -> 2.2581711e+09 | N2: =SUBTOTAL(9,CATEGORIAS[PRODUCCION ADICIONALES ACTUAL]) -> 14538275 | O2: =SUBTOTAL(9,CATEGORIAS[TOTAL PRODUCCION ACTUAL]) -> 2.2727094e+09 | P2: =SUBTOTAL(9,CATEGORIAS[PRODUCCION ANTERIOR]) -> 1.5184201e+09 | Q2: =SUBTOTAL(9,CATEGORIAS[PRODUCCION ADICIONALES ANTERIOR]) -> 14927094 | R2: =SUBTOTAL(9,CATEGORIAS[TOTAL PRODUCCION ANTERIOR]) -> 1.5333472e+09 | S2: =SUBTOTAL(9,CATEGORIAS[COSTO ACUMULADO AX]) -> 1.9279227e+09 | T2: =SUM(CATEGORIAS[CAMBIO DE CATEGORIA]) -> -0.3288 | U2: =SUBTOTAL(9,CATEGORIAS[PROVISIONES]) -> 5.3967687e+08 | V2: =SUBTOTAL(9,CATEGORIAS[COSTO REAL]) -> 2.4675996e+09 | W2: =SUBTOTAL(9,CATEGORIAS[COSTO ACUMULADO ANTERIOR]) -> 1.2145999e+09 | X2: =SUBTOTAL(9,CATEGORIAS[CAMBIO DE CATEGORIA ANTERIOR]) -> -0.30211412 | Y2: =SUBTOTAL(9,CATEGORIAS[PROVISIONES ANTERIOR]) -> 3.3224083e+08 | Z2: =SUBTOTAL(9,CATEGORIAS[COSTO REAL ANTERIOR]) -> 1.5468407e+09 | AA2: =SUBTOTAL(9,CATEGORIAS[PROYECCION DE INGRESO DEL SALDO]) -> 3.2422081e+09 | AB2: =SUBTOTAL(9,CATEGORIAS[INVENTARIO]) -> 219920096 | AC2: =SUBTOTAL(9,CATEGORIAS[PEDIDOS DE COMPRA NO RECIBIDOS]) -> 0 | AD2: =SUBTOTAL(9,CATEGORIAS[PROYECCION DE COSTO DEL SALDO]) -> 2.8297232e+09 | AE2: =SUBTOTAL(9,CATEGORIAS[PROYECCION TOTAL DE COSTO]) -> 3.0496433e+09
E3: ERROR DE COSTO - CAMBIO CATEGORIA - PROVISION | M3: PRODUCCION | S3: COSTOS | AA3: PROYECCION
E4: ERROR DE PROYECCION - INVENTARIO | M4: ACUMULADA | P4: ACUMULADA ANTERIOR | S4: ACUMULADO | W4: ACUMULADO ANTERIOR | AA4: PRODUCCION | AB4: COSTOS
G5: CARGA MANUAL | H5: CARGA MANUAL | I5: CARGA MANUAL | L5: FORMULA | M5: CARGA MANUAL | N5: CARGA MANUAL | O5: FORMULA | P5: CARGA MANUAL | Q5: CARGA MANUAL | R5: FORMULA | S5: DESDE AX | T5: CARGA MANUAL | U5: CARGA MANUAL | V5: FORMULA | W5: CARGA MANUAL | X5: CARGA MANUAL | Y5: CARGA MANUAL | Z5: FORMULA | AA5: FORMULA | AB5: DESDE AX | AC5: DESDE AX | AD5: CARGA MANUAL | AE5: FORMULA
A6: FORMATO GENERAL | B6: SUBGRUPO | C6: NOMBRE SUBGRUPO | D6: CATEGORIA2 | E6: NOMBRE CATEGORIA | F6: INCLUIR | G6: PRESUPUESTO (ORIGINAL) | H6: POM | I6: ADICIONALES | J6: REAJUSTE PAGADO | K6: REAJUSTE PROYECTADO | L6: PRESUPUESTO FINAL PROYECTADO | M6: PRODUCCION PARTIDAS ORIGINALES ACTUAL | N6: PRODUCCION ADICIONALES ACTUAL | O6: TOTAL PRODUCCION ACTUAL | P6: PRODUCCION ANTERIOR | Q6: PRODUCCION ADICIONALES ANTERIOR | R6: TOTAL PRODUCCION ANTERIOR | S6: COSTO ACUMULADO AX | T6: CAMBIO DE CATEGORIA | U6: PROVISIONES | V6: COSTO REAL | W6: COSTO ACUMULADO ANTERIOR | X6: CAMBIO DE CATEGORIA ANTERIOR | Y6: PROVISIONES ANTERIOR | Z6: COSTO REAL ANTERIOR | AA6: PROYECCION DE INGRESO DEL SALDO | AB6: INVENTARIO | AC6: PEDIDOS DE COMPRA NO RECIBIDOS | AD6: PROYECCION DE COSTO DEL SALDO | AE6: PROYECCION TOTAL DE COSTO | AF6: ITEM | AG6: Columna1
A7: =+IFERROR(VLOOKUP(CATEGORIAS[[#This Row],[CATEGORIA2]],[1]HOMOLOGACION!$A$1:$I$571,9,FALSE),0) -> 0 | B7: =+IFERROR(VLOOKUP(CATEGORIAS[[#This Row],[CATEGORIA2]],[1]HOMOLOGACION!$A$1:$C$571,3,FALSE),0) -> 0 | C7: =+IFERROR(VLOOKUP(CATEGORIAS[[#This Row],[CATEGORIA2]],[1]HOMOLOGACION!$A$1:$D$571,4,FALSE),0) -> 0 | D7: 10-0000-000G | E7: MAO / Por Distribuir (G) | F7: NO | G7: 0 | H7: 0 | L7: =CATEGORIAS[[#This Row],[ADICIONALES]]+CATEGORIAS[[#This Row],[POM]] -> 0 | M7: 0 | N7: 0 | O7: =+CATEGORIAS[[#This Row],[PRODUCCION PARTIDAS ORIGINALES ACTUAL]]+CATEGORIAS[[#This Row],[PRODUCCION ADICIONALES ACTUAL]] -> 0 | R7: =CATEGORIAS[[#This Row],[PRODUCCION ANTERIOR]]+CATEGORIAS[[#This Row],[PRODUCCION ADICIONALES ANTERIOR]] -> 0 | S7: 0 | V7: =SUM(CATEGORIAS[[#This Row],[COSTO ACUMULADO AX]:[PROVISIONES]]) -> 0 | Z7: =SUM(CATEGORIAS[[#This Row],[COSTO ACUMULADO ANTERIOR]:[PROVISIONES ANTERIOR]]) -> 0 | AA7: =CATEGORIAS[[#This Row],[PRESUPUESTO FINAL PROYECTADO]]-CATEGORIAS[[#This Row],[TOTAL PRODUCCION ACTUAL]] -> 0 | AB7: 0 | AE7: =SUM(CATEGORIAS[[#This Row],[INVENTARIO]:[PROYECCION DE COSTO DEL SALDO]]) -> 0 | AG7: =+CATEGORIAS[[#This Row],[PRESUPUESTO FINAL PROYECTADO]]-CATEGORIAS[[#This Row],[COSTO REAL]]-CATEGORIAS[[#This Row],[PROYECCION TOTAL DE COSTO]] -> 0
A8: =+IFERROR(VLOOKUP(CATEGORIAS[[#This Row],[CATEGORIA2]],[1]HOMOLOGACION!$A$1:$I$571,9,FALSE),0) -> 0A01 | B8: =+IFERROR(VLOOKUP(CATEGORIAS[[#This Row],[CATEGORIA2]],[1]HOMOLOGACION!$A$1:$C$571,3,FALSE),0) -> 0A01 | C8: =+IFERROR(VLOOKUP(CATEGORIAS[[#This Row],[CATEGORIA2]],[1]HOMOLOGACION!$A$1:$D$571,4,FALSE),0) -> Civil | D8: 11-0101-000G | E8: MAO CD - Civil / Movimiento de tierra (G) | F8: NO | G8: 0 | H8: 0 | L8: =CATEGORIAS[[#This Row],[ADICIONALES]]+CATEGORIAS[[#This Row],[POM]] -> 0 | M8: 0 | N8: 0 | O8: =CATEGORIAS[[#This Row],[PRODUCCION PARTIDAS ORIGINALES ACTUAL]]+CATEGORIAS[[#This Row],[PRODUCCION ADICIONALES ACTUAL]] -> 0 | R8: =CATEGORIAS[[#This Row],[PRODUCCION ANTERIOR]]+CATEGORIAS[[#This Row],[PRODUCCION ADICIONALES ANTERIOR]] -> 0 | S8: 0 | V8: =SUM(CATEGORIAS[[#This Row],[COSTO ACUMULADO AX]:[PROVISIONES]]) -> 0 | Z8: =SUM(CATEGORIAS[[#This Row],[COSTO ACUMULADO ANTERIOR]:[PROVISIONES ANTERIOR]]) -> 0 | AA8: =CATEGORIAS[[#This Row],[PRESUPUESTO FINAL PROYECTADO]]-CATEGORIAS[[#This Row],[TOTAL PRODUCCION ACTUAL]] -> 0 | AB8: 0 | AE8: =SUM(CATEGORIAS[[#This Row],[INVENTARIO]:[PROYECCION DE COSTO DEL SALDO]]) -> 0 | AG8: =+CATEGORIAS[[#This Row],[PRESUPUESTO FINAL PROYECTADO]]-CATEGORIAS[[#This Row],[COSTO REAL]]-CATEGORIAS[[#This Row],[PROYECCION TOTAL DE COSTO]] -> 0
A9: =+IFERROR(VLOOKUP(CATEGORIAS[[#This Row],[CATEGORIA2]],[1]HOMOLOGACION!$A$1:$I$571,9,FALSE),0) -> 0A01 | B9: =+IFERROR(VLOOKUP(CATEGORIAS[[#This Row],[CATEGORIA2]],[1]HOMOLOGACION!$A$1:$C$571,3,FALSE),0) -> 0A01 | C9: =+IFERROR(VLOOKUP(CATEGORIAS[[#This Row],[CATEGORIA2]],[1]HOMOLOGACION!$A$1:$D$571,4,FALSE),0) -> Civil | D9: 11-0102-000G | E9: MAO CD - Civil / Hormigón (G) | F9: NO | G9: 0 | H9: 0 | L9: =CATEGORIAS[[#This Row],[ADICIONALES]]+CATEGORIAS[[#This Row],[POM]] -> 0 | M9: 0 | N9: 0 | O9: =CATEGORIAS[[#This Row],[PRODUCCION PARTIDAS ORIGINALES ACTUAL]]+CATEGORIAS[[#This Row],[PRODUCCION ADICIONALES ACTUAL]] -> 0 | R9: =CATEGORIAS[[#This Row],[PRODUCCION ANTERIOR]]+CATEGORIAS[[#This Row],[PRODUCCION ADICIONALES ANTERIOR]] -> 0 | S9: 0 | V9: =SUM(CATEGORIAS[[#This Row],[COSTO ACUMULADO AX]:[PROVISIONES]]) -> 0 | Z9: =SUM(CATEGORIAS[[#This Row],[COSTO ACUMULADO ANTERIOR]:[PROVISIONES ANTERIOR]]) -> 0 | AA9: =CATEGORIAS[[#This Row],[PRESUPUESTO FINAL PROYECTADO]]-CATEGORIAS[[#This Row],[TOTAL PRODUCCION ACTUAL]] -> 0 | AB9: 0 | AE9: =SUM(CATEGORIAS[[#This Row],[INVENTARIO]:[PROYECCION DE COSTO DEL SALDO]]) -> 0 | AG9: =+CATEGORIAS[[#This Row],[PRESUPUESTO FINAL PROYECTADO]]-CATEGORIAS[[#This Row],[COSTO REAL]]-CATEGORIAS[[#This Row],[PROYECCION TOTAL DE COSTO]] -> 0
A10: =+IFERROR(VLOOKUP(CATEGORIAS[[#This Row],[CATEGORIA2]],[1]HOMOLOGACION!$A$1:$I$571,9,FALSE),0) -> 0A01 | B10: =+IFERROR(VLOOKUP(CATEGORIAS[[#This Row],[CATEGORIA2]],[1]HOMOLOGACION!$A$1:$C$571,3,FALSE),0) -> 0A01 | C10: =+IFERROR(VLOOKUP(CATEGORIAS[[#This Row],[CATEGORIA2]],[1]HOMOLOGACION!$A$1:$D$571,4,FALSE),0) -> Civil | D10: 11-0103-000G | E10: MAO CD - Civil / Moldaje (G) | F10: NO | G10: 0 | H10: 0 | L10: =CATEGORIAS[[#This Row],[ADICIONALES]]+CATEGORIAS[[#This Row],[POM]] -> 0 | M10: 0 | N10: 0 | O10: =CATEGORIAS[[#This Row],[PRODUCCION PARTIDAS ORIGINALES ACTUAL]]+CATEGORIAS[[#This Row],[PRODUCCION ADICIONALES ACTUAL]] -> 0 | R10: =CATEGORIAS[[#This Row],[PRODUCCION ANTERIOR]]+CATEGORIAS[[#This Row],[PRODUCCION ADICIONALES ANTERIOR]] -> 0 | S10: 0 | V10: =SUM(CATEGORIAS[[#This Row],[COSTO ACUMULADO AX]:[PROVISIONES]]) -> 0 | Z10: =SUM(CATEGORIAS[[#This Row],[COSTO ACUMULADO ANTERIOR]:[PROVISIONES ANTERIOR]]) -> 0 | AA10: =CATEGORIAS[[#This Row],[PRESUPUESTO FINAL PROYECTADO]]-CATEGORIAS[[#This Row],[TOTAL PRODUCCION ACTUAL]] -> 0 | AB10: 0 | AE10: =SUM(CATEGORIAS[[#This Row],[INVENTARIO]:[PROYECCION DE COSTO DEL SALDO]]) -> 0 | AG10: =+CATEGORIAS[[#This Row],[PRESUPUESTO FINAL PROYECTADO]]-CATEGORIAS[[#This Row],[COSTO REAL]]-CATEGORIAS[[#This Row],[PROYECCION TOTAL DE COSTO]] -> 0
A11: =+IFERROR(VLOOKUP(CATEGORIAS[[#This Row],[CATEGORIA2]],[1]HOMOLOGACION!$A$1:$I$571,9,FALSE),0) -> 0A01 | B11: =+IFERROR(VLOOKUP(CATEGORIAS[[#This Row],[CATEGORIA2]],[1]HOMOLOGACION!$A$1:$C$571,3,FALSE),0) -> 0A01 | C11: =+IFERROR(VLOOKUP(CATEGORIAS[[#This Row],[CATEGORIA2]],[1]HOMOLOGACION!$A$1:$D$571,4,FALSE),0) -> Civil | D11: 11-0104-000G | E11: MAO CD - Civil / Enfierradura (G) | F11: NO | G11: 0 | H11: 0 | L11: =CATEGORIAS[[#This Row],[ADICIONALES]]+CATEGORIAS[[#This Row],[POM]] -> 0 | M11: 0 | N11: 0 | O11: =CATEGORIAS[[#This Row],[PRODUCCION PARTIDAS ORIGINALES ACTUAL]]+CATEGORIAS[[#This Row],[PRODUCCION ADICIONALES ACTUAL]] -> 0 | R11: =CATEGORIAS[[#This Row],[PRODUCCION ANTERIOR]]+CATEGORIAS[[#This Row],[PRODUCCION ADICIONALES ANTERIOR]] -> 0 | S11: 0 | V11: =SUM(CATEGORIAS[[#This Row],[COSTO ACUMULADO AX]:[PROVISIONES]]) -> 0 | Z11: =SUM(CATEGORIAS[[#This Row],[COSTO ACUMULADO ANTERIOR]:[PROVISIONES ANTERIOR]]) -> 0 | AA11: =CATEGORIAS[[#This Row],[PRESUPUESTO FINAL PROYECTADO]]-CATEGORIAS[[#This Row],[TOTAL PRODUCCION ACTUAL]] -> 0 | AB11: 0 | AE11: =SUM(CATEGORIAS[[#This Row],[INVENTARIO]:[PROYECCION DE COSTO DEL SALDO]]) -> 0 | AG11: =+CATEGORIAS[[#This Row],[PRESUPUESTO FINAL PROYECTADO]]-CATEGORIAS[[#This Row],[COSTO REAL]]-CATEGORIAS[[#This Row],[PROYECCION TOTAL DE COSTO]] -> 0
A12: =+IFERROR(VLOOKUP(CATEGORIAS[[#This Row],[CATEGORIA2]],[1]HOMOLOGACION!$A$1:$I$571,9,FALSE),0) -> 0M01 | B12: =+IFERROR(VLOOKUP(CATEGORIAS[[#This Row],[CATEGORIA2]],[1]HOMOLOGACION!$A$1:$C$571,3,FALSE),0) -> 0A11 | C12: =+IFERROR(VLOOKUP(CATEGORIAS[[#This Row],[CATEGORIA2]],[1]HOMOLOGACION!$A$1:$D$571,4,FALSE),0) -> Arquitectura | D12: 11-0105-000G | E12: MAO CD - Civil / Arquitectura (G) | F12: NO | G12: 0 | H12: 0 | L12: =CATEGORIAS[[#This Row],[ADICIONALES]]+CATEGORIAS[[#This Row],[POM]] -> 0 | M12: 0 | N12: 0 | O12: =CATEGORIAS[[#This Row],[PRODUCCION PARTIDAS ORIGINALES ACTUAL]]+CATEGORIAS[[#This Row],[PRODUCCION ADICIONALES ACTUAL]] -> 0 | R12: =CATEGORIAS[[#This Row],[PRODUCCION ANTERIOR]]+CATEGORIAS[[#This Row],[PRODUCCION ADICIONALES ANTERIOR]] -> 0 | S12: 0 | V12: =SUM(CATEGORIAS[[#This Row],[COSTO ACUMULADO AX]:[PROVISIONES]]) -> 0 | Z12: =SUM(CATEGORIAS[[#This Row],[COSTO ACUMULADO ANTERIOR]:[PROVISIONES ANTERIOR]]) -> 0 | AA12: =CATEGORIAS[[#This Row],[PRESUPUESTO FINAL PROYECTADO]]-CATEGORIAS[[#This Row],[TOTAL PRODUCCION ACTUAL]] -> 0 | AB12: 0 | AE12: =SUM(CATEGORIAS[[#This Row],[INVENTARIO]:[PROYECCION DE COSTO DEL SALDO]]) -> 0 | AG12: =+CATEGORIAS[[#This Row],[PRESUPUESTO FINAL PROYECTADO]]-CATEGORIAS[[#This Row],[COSTO REAL]]-CATEGORIAS[[#This Row],[PROYECCION TOTAL DE COSTO]] -> 0
A13: =+IFERROR(VLOOKUP(CATEGORIAS[[#This Row],[CATEGORIA2]],[1]HOMOLOGACION!$A$1:$I$571,9,FALSE),0) -> 0A01 | B13: =+IFERROR(VLOOKUP(CATEGORIAS[[#This Row],[CATEGORIA2]],[1]HOMOLOGACION!$A$1:$C$571,3,FALSE),0) -> 0A01 | C13: =+IFERROR(VLOOKUP(CATEGORIAS[[#This Row],[CATEGORIA2]],[1]HOMOLOGACION!$A$1:$D$571,4,FALSE),0) -> Civil | D13: 11-0199-000G | E13: MAO CD - Civil / Otros (G) | F13: SI | G13: 1.4597251e+08 | H13: 1.4597251e+08 | I13: 14606632 | L13: =CATEGORIAS[[#This Row],[ADICIONALES]]+CATEGORIAS[[#This Row],[POM]] -> 1.6057914e+08 | M13: 1.1662961e+08 | N13: 0 | O13: =CATEGORIAS[[#This Row],[PRODUCCION PARTIDAS ORIGINALES ACTUAL]]+CATEGORIAS[[#This Row],[PRODUCCION ADICIONALES ACTUAL]] -> 1.1662961e+08 | P13: 1.0791622e+08 | Q13: 436740.47 | R13: =CATEGORIAS[[#This Row],[PRODUCCION ANTERIOR]]+CATEGORIAS[[#This Row],[PRODUCCION ADICIONALES ANTERIOR]] -> 1.0835296e+08 | S13: 99656107 | U13: 8175470.9 | V13: =SUM(CATEGORIAS[[#This Row],[COSTO ACUMULADO AX]:[PROVISIONES]]) -> 1.0783158e+08 | W13: 53713252 | Y13: 6087837.8 | Z13: =SUM(CATEGORIAS[[#This Row],[COSTO ACUMULADO ANTERIOR]:[PROVISIONES ANTERIOR]]) -> 59801090 | AA13: =CATEGORIAS[[#This Row],[PRESUPUESTO FINAL PROYECTADO]]-CATEGORIAS[[#This Row],[TOTAL PRODUCCION ACTUAL]] -> 43949535 | AB13: 0 | AD13: 52747564 | AE13: =SUM(CATEGORIAS[[#This Row],[INVENTARIO]:[PROYECCION DE COSTO DEL SALDO]]) -> 52747564 | AG13: =+CATEGORIAS[[#This Row],[PRESUPUESTO FINAL PROYECTADO]]-CATEGORIAS[[#This Row],[COSTO REAL]]-CATEGORIAS[[#This Row],[PROYECCION TOTAL DE COSTO]] -> 0
A14: =+IFERROR(VLOOKUP(CATEGORIAS[[#This Row],[CATEGORIA2]],[1]HOMOLOGACION!$A$1:$I$571,9,FALSE),0) -> 0B01 | B14: =+IFERROR(VLOOKUP(CATEGORIAS[[#This Row],[CATEGORIA2]],[1]HOMOLOGACION!$A$1:$C$571,3,FALSE),0) -> 0A02 | C14: =+IFERROR(VLOOKUP(CATEGORIAS[[#This Row],[CATEGORIA2]],[1]HOMOLOGACION!$A$1:$D$571,4,FALSE),0) -> Estructura | D14: 11-0207-000G | E14: MAO CD - Estructura / Soldadura (G) | F14: NO | G14: 0 | H14: 0 | I14: 0 | L14: =CATEGORIAS[[#This Row],[ADICIONALES]]+CATEGORIAS[[#This Row],[POM]] -> 0 | M14: 0 | N14: 0 | O14: =CATEGORIAS[[#This Row],[PRODUCCION PARTIDAS ORIGINALES ACTUAL]]+CATEGORIAS[[#This Row],[PRODUCCION ADICIONALES ACTUAL]] -> 0 | P14: 0 | Q14: 0 | R14: =CATEGORIAS[[#This Row],[PRODUCCION ANTERIOR]]+CATEGORIAS[[#This Row],[PRODUCCION ADICIONALES ANTERIOR]] -> 0 | S14: 0 | V14: =SUM(CATEGORIAS[[#This Row],[COSTO ACUMULADO AX]:[PROVISIONES]]) -> 0 | W14: 0 | Z14: =SUM(CATEGORIAS[[#This Row],[COSTO ACUMULADO ANTERIOR]:[PROVISIONES ANTERIOR]]) -> 0 | AA14: =CATEGORIAS[[#This Row],[PRESUPUESTO FINAL PROYECTADO]]-CATEGORIAS[[#This Row],[TOTAL PRODUCCION ACTUAL]] -> 0 | AB14: 0 | AE14: =SUM(CATEGORIAS[[#This Row],[INVENTARIO]:[PROYECCION DE COSTO DEL SALDO]]) -> 0 | AG14: =+CATEGORIAS[[#This Row],[PRESUPUESTO FINAL PROYECTADO]]-CATEGORIAS[[#This Row],[COSTO REAL]]-CATEGORIAS[[#This Row],[PROYECCION TOTAL DE COSTO]] -> 0
A15: =+IFERROR(VLOOKUP(CATEGORIAS[[#This Row],[CATEGORIA2]],[1]HOMOLOGACION!$A$1:$I$571,9,FALSE),0) -> 0B01 | B15: =+IFERROR(VLOOKUP(CATEGORIAS[[#This Row],[CATEGORIA2]],[1]HOMOLOGACION!$A$1:$C$571,3,FALSE),0) -> 0A02 | C15: =+IFERROR(VLOOKUP(CATEGORIAS[[#This Row],[CATEGORIA2]],[1]HOMOLOGACION!$A$1:$D$571,4,FALSE),0) -> Estructura | D15: 11-0208-000G | E15: MAO CD - Estructura / Montajes (G) | F15: SI | G15: 1.7987561e+08 | H15: 1.7987561e+08 | I15: 612034.1 | L15: =CATEGORIAS[[#This Row],[ADICIONALES]]+CATEGORIAS[[#This Row],[POM]] -> 1.8048765e+08 | M15: 69920211 | N15: 370536.65 | O15: =CATEGORIAS[[#This Row],[PRODUCCION PARTIDAS ORIGINALES ACTUAL]]+CATEGORIAS[[#This Row],[PRODUCCION ADICIONALES ACTUAL]] -> 70290747 | P15: 50928692 | Q15: 826054.81 | R15: =CATEGORIAS[[#This Row],[PRODUCCION ANTERIOR]]+CATEGORIAS[[#This Row],[PRODUCCION ADICIONALES ANTERIOR]] -> 51754747 | S15: 142125812 | T15: -6268305 | U15: 15500921 | V15: =SUM(CATEGORIAS[[#This Row],[COSTO ACUMULADO AX]:[PROVISIONES]]) -> 1.5135843e+08 | W15: 81257881 | Y15: 8426648.2 | Z15: =SUM(CATEGORIAS[[#This Row],[COSTO ACUMULADO ANTERIOR]:[PROVISIONES ANTERIOR]]) -> 89684529 | AA15: =CATEGORIAS[[#This Row],[PRESUPUESTO FINAL PROYECTADO]]-CATEGORIAS[[#This Row],[TOTAL PRODUCCION ACTUAL]] -> 1.101969e+08 | AB15: 0 | AD15: 29129221 | AE15: =SUM(CATEGORIAS[[#This Row],[INVENTARIO]:[PROYECCION DE COSTO DEL SALDO]]) -> 29129221 | AG15: =+CATEGORIAS[[#This Row],[PRESUPUESTO FINAL PROYECTADO]]-CATEGORIAS[[#This Row],[COSTO REAL]]-CATEGORIAS[[#This Row],[PROYECCION TOTAL DE COSTO]] -> 0
A16: =+IFERROR(VLOOKUP(CATEGORIAS[[#This Row],[CATEGORIA2]],[1]HOMOLOGACION!$A$1:$I$571,9,FALSE),0) -> 0 | B16: =+IFERROR(VLOOKUP(CATEGORIAS[[#This Row],[CATEGORIA2]],[1]HOMOLOGACION!$A$1:$C$571,3,FALSE),0) -> 0 | C16: =+IFERROR(VLOOKUP(CATEGORIAS[[#This Row],[CATEGORIA2]],[1]HOMOLOGACION!$A$1:$D$571,4,FALSE),0) -> 0 | D16: 11-0231-201G | E16: Remuneraciones / Otros Gastos / Prov. Vacaciones | F16: NO | G16: 0 | H16: 0 | I16: 0 | L16: =CATEGORIAS[[#This Row],[ADICIONALES]]+CATEGORIAS[[#This Row],[POM]] -> 0 | M16: 0 | N16: 0 | O16: =CATEGORIAS[[#This Row],[PRODUCCION PARTIDAS ORIGINALES ACTUAL]]+CATEGORIAS[[#This Row],[PRODUCCION ADICIONALES ACTUAL]] -> 0 | P16: 0 | Q16: 0 | R16: =CATEGORIAS[[#This Row],[PRODUCCION ANTERIOR]]+CATEGORIAS[[#This Row],[PRODUCCION ADICIONALES ANTERIOR]] -> 0 | S16: 0 | V16: =SUM(CATEGORIAS[[#This Row],[COSTO ACUMULADO AX]:[PROVISIONES]]) -> 0 | W16: 0 | Z16: =SUM(CATEGORIAS[[#This Row],[COSTO ACUMULADO ANTERIOR]:[PROVISIONES ANTERIOR]]) -> 0 | AA16: =CATEGORIAS[[#This Row],[PRESUPUESTO FINAL PROYECTADO]]-CATEGORIAS[[#This Row],[TOTAL PRODUCCION ACTUAL]] -> 0 | AB16: 0 | AE16: =SUM(CATEGORIAS[[#This Row],[INVENTARIO]:[PROYECCION DE COSTO DEL SALDO]]) -> 0 | AG16: =+CATEGORIAS[[#This Row],[PRESUPUESTO FINAL PROYECTADO]]-CATEGORIAS[[#This Row],[COSTO REAL]]-CATEGORIAS[[#This Row],[PROYECCION TOTAL DE COSTO]] -> 0
A17: =+IFERROR(VLOOKUP(CATEGORIAS[[#This Row],[CATEGORIA2]],[1]HOMOLOGACION!$A$1:$I$571,9,FALSE),0) -> 0C01 | B17: =+IFERROR(VLOOKUP(CATEGORIAS[[#This Row],[CATEGORIA2]],[1]HOMOLOGACION!$A$1:$C$571,3,FALSE),0) -> 0A03 | C17: =+IFERROR(VLOOKUP(CATEGORIAS[[#This Row],[CATEGORIA2]],[1]HOMOLOGACION!$A$1:$D$571,4,FALSE),0) -> Mecánica | D17: 11-0307-000G | E17: MAO CD - Mecánica / Soldadura (G) | F17: NO | G17: 0 | H17: 0 | I17: 0 | L17: =CATEGORIAS[[#This Row],[ADICIONALES]]+CATEGORIAS[[#This Row],[POM]] -> 0 | M17: 0 | N17: 0 | O17: =CATEGORIAS[[#This Row],[PRODUCCION PARTIDAS ORIGINALES ACTUAL]]+CATEGORIAS[[#This Row],[PRODUCCION ADICIONALES ACTUAL]] -> 0 | P17: 0 | Q17: 0 | R17: =CATEGORIAS[[#This Row],[PRODUCCION ANTERIOR]]+CATEGORIAS[[#This Row],[PRODUCCION ADICIONALES ANTERIOR]] -> 0 | S17: 0 | V17: =SUM(CATEGORIAS[[#This Row],[COSTO ACUMULADO AX]:[PROVISIONES]]) -> 0 | W17: 0 | Z17: =SUM(CATEGORIAS[[#This Row],[COSTO ACUMULADO ANTERIOR]:[PROVISIONES ANTERIOR]]) -> 0 | AA17: =CATEGORIAS[[#This Row],[PRESUPUESTO FINAL PROYECTADO]]-CATEGORIAS[[#This Row],[TOTAL PRODUCCION ACTUAL]] -> 0 | AB17: 0 | AE17: =SUM(CATEGORIAS[[#This Row],[INVENTARIO]:[PROYECCION DE COSTO DEL SALDO]]) -> 0 | AG17: =+CATEGORIAS[[#This Row],[PRESUPUESTO FINAL PROYECTADO]]-CATEGORIAS[[#This Row],[COSTO REAL]]-CATEGORIAS[[#This Row],[PROYECCION TOTAL DE COSTO]] -> 0
A18: =+IFERROR(VLOOKUP(CATEGORIAS[[#This Row],[CATEGORIA2]],[1]HOMOLOGACION!$A$1:$I$571,9,FALSE),0) -> 0C01 | B18: =+IFERROR(VLOOKUP(CATEGORIAS[[#This Row],[CATEGORIA2]],[1]HOMOLOGACION!$A$1:$C$571,3,FALSE),0) -> 0A03 | C18: =+IFERROR(VLOOKUP(CATEGORIAS[[#This Row],[CATEGORIA2]],[1]HOMOLOGACION!$A$1:$D$571,4,FALSE),0) -> Mecánica | D18: 11-0308-000G | E18: MAO CD - Mecánica / Montajes (G) | F18: SI | G18: 1.332508e+08 | H18: 1.332508e+08 | I18: 8661404.9 | L18: =CATEGORIAS[[#This Row],[ADICIONALES]]+CATEGORIAS[[#This Row],[POM]] -> 1.4191221e+08 | M18: 56546059 | N18: 1300527.4 | O18: =CATEGORIAS[[#This Row],[PRODUCCION PARTIDAS ORIGINALES ACTUAL]]+CATEGORIAS[[#This Row],[PRODUCCION ADICIONALES ACTUAL]] -> 57846587 | P18: 38060530 | Q18: 891589.72 | R18: =CATEGORIAS[[#This Row],[PRODUCCION ANTERIOR]]+CATEGORIAS[[#This Row],[PRODUCCION ADICIONALES ANTERIOR]] -> 38952120 | S18: 137932801 | T18: -5925744 | U18: 16429822 | V18: =SUM(CATEGORIAS[[#This Row],[COSTO ACUMULADO AX]:[PROVISIONES]]) -> 1.4843688e+08 | W18: 90949268 | Y18: 9495393.1 | Z18: =SUM(CATEGORIAS[[#This Row],[COSTO ACUMULADO ANTERIOR]:[PROVISIONES ANTERIOR]]) -> 1.0044466e+08 | AA18: =CATEGORIAS[[#This Row],[PRESUPUESTO FINAL PROYECTADO]]-CATEGORIAS[[#This Row],[TOTAL PRODUCCION ACTUAL]] -> 84065623 | AB18: 0 | AD18: -6524669.7 | AE18: =SUM(CATEGORIAS[[#This Row],[INVENTARIO]:[PROYECCION DE COSTO DEL SALDO]]) -> -6524669.7 | AG18: =+CATEGORIAS[[#This Row],[PRESUPUESTO FINAL PROYECTADO]]-CATEGORIAS[[#This Row],[COSTO REAL]]-CATEGORIAS[[#This Row],[PROYECCION TOTAL DE COSTO]] -> 0
A19: =+IFERROR(VLOOKUP(CATEGORIAS[[#This Row],[CATEGORIA2]],[1]HOMOLOGACION!$A$1:$I$571,9,FALSE),0) -> 0 | B19: =+IFERROR(VLOOKUP(CATEGORIAS[[#This Row],[CATEGORIA2]],[1]HOMOLOGACION!$A$1:$C$571,3,FALSE),0) -> 0 | C19: =+IFERROR(VLOOKUP(CATEGORIAS[[#This Row],[CATEGORIA2]],[1]HOMOLOGACION!$A$1:$D$571,4,FALSE),0) -> 0 | D19: 11-0321-619A | E19: Remuneraciones / Remuneraciones / Otros Dsctos. al Personal | F19: NO | G19: 0 | H19: 0 | I19: 0 | L19: =CATEGORIAS[[#This Row],[ADICIONALES]]+CATEGORIAS[[#This Row],[POM]] -> 0 | M19: 0 | N19: 0 | O19: =CATEGORIAS[[#This Row],[PRODUCCION PARTIDAS ORIGINALES ACTUAL]]+CATEGORIAS[[#This Row],[PRODUCCION ADICIONALES ACTUAL]] -> 0 | P19: 0 | Q19: 0 | R19: =CATEGORIAS[[#This Row],[PRODUCCION ANTERIOR]]+CATEGORIAS[[#This Row],[PRODUCCION ADICIONALES ANTERIOR]] -> 0 | S19: 0 | V19: =SUM(CATEGORIAS[[#This Row],[COSTO ACUMULADO AX]:[PROVISIONES]]) -> 0 | W19: 0 | Z19: =SUM(CATEGORIAS[[#This Row],[COSTO ACUMULADO ANTERIOR]:[PROVISIONES ANTERIOR]]) -> 0 | AA19: =CATEGORIAS[[#This Row],[PRESUPUESTO FINAL PROYECTADO]]-CATEGORIAS[[#This Row],[TOTAL PRODUCCION ACTUAL]] -> 0 | AB19: 0 | AE19: =SUM(CATEGORIAS[[#This Row],[INVENTARIO]:[PROYECCION DE COSTO DEL SALDO]]) -> 0 | AG19: =+CATEGORIAS[[#This Row],[PRESUPUESTO FINAL PROYECTADO]]-CATEGORIAS[[#This Row],[COSTO REAL]]-CATEGORIAS[[#This Row],[PROYECCION TOTAL DE COSTO]] -> 0
A20: =+IFERROR(VLOOKUP(CATEGORIAS[[#This Row],[CATEGORIA2]],[1]HOMOLOGACION!$A$1:$I$571,9,FALSE),0) -> 0 | B20: =+IFERROR(VLOOKUP(CATEGORIAS[[#This Row],[CATEGORIA2]],[1]HOMOLOGACION!$A$1:$C$571,3,FALSE),0) -> 0 | C20: =+IFERROR(VLOOKUP(CATEGORIAS[[#This Row],[CATEGORIA2]],[1]HOMOLOGACION!$A$1:$D$571,4,FALSE),0) -> 0 | D20: 11-0321-619G | E20: Remuneraciones / Remuneraciones / Otros Dsctos. al Personal | F20: NO | G20: 0 | H20: 0 | I20: 0 | L20: =CATEGORIAS[[#This Row],[ADICIONALES]]+CATEGORIAS[[#This Row],[POM]] -> 0 | M20: 0 | N20: 0 | O20: =CATEGORIAS[[#This Row],[PRODUCCION PARTIDAS ORIGINALES ACTUAL]]+CATEGORIAS[[#This Row],[PRODUCCION ADICIONALES ACTUAL]] -> 0 | P20: 0 | Q20: 0 | R20: =CATEGORIAS[[#This Row],[PRODUCCION ANTERIOR]]+CATEGORIAS[[#This Row],[PRODUCCION ADICIONALES ANTERIOR]] -> 0 | S20: 0 | V20: =SUM(CATEGORIAS[[#This Row],[COSTO ACUMULADO AX]:[PROVISIONES]]) -> 0 | W20: 0 | Z20: =SUM(CATEGORIAS[[#This Row],[COSTO ACUMULADO ANTERIOR]:[PROVISIONES ANTERIOR]]) -> 0 | AA20: =CATEGORIAS[[#This Row],[PRESUPUESTO FINAL PROYECTADO]]-CATEGORIAS[[#This Row],[TOTAL PRODUCCION ACTUAL]] -> 0 | AB20: 0 | AE20: =SUM(CATEGORIAS[[#This Row],[INVENTARIO]:[PROYECCION DE COSTO DEL SALDO]]) -> 0 | AG20: =+CATEGORIAS[[#This Row],[PRESUPUESTO FINAL PROYECTADO]]-CATEGORIAS[[#This Row],[COSTO REAL]]-CATEGORIAS[[#This Row],[PROYECCION TOTAL DE COSTO]] -> 0
A21: =+IFERROR(VLOOKUP(CATEGORIAS[[#This Row],[CATEGORIA2]],[1]HOMOLOGACION!$A$1:$I$571,9,FALSE),0) -> 0 | B21: =+IFERROR(VLOOKUP(CATEGORIAS[[#This Row],[CATEGORIA2]],[1]HOMOLOGACION!$A$1:$C$571,3,FALSE),0) -> 0 | C21: =+IFERROR(VLOOKUP(CATEGORIAS[[#This Row],[CATEGORIA2]],[1]HOMOLOGACION!$A$1:$D$571,4,FALSE),0) -> 0 | D21: 11-0331-201G | E21: Remuneraciones / Remuneraciones / Remuneraciones | F21: NO | G21: 0 | H21: 0 | I21: 0 | L21: =CATEGORIAS[[#This Row],[ADICIONALES]]+CATEGORIAS[[#This Row],[POM]] -> 0 | M21: 0 | N21: 0 | O21: =CATEGORIAS[[#This Row],[PRODUCCION PARTIDAS ORIGINALES ACTUAL]]+CATEGORIAS[[#This Row],[PRODUCCION ADICIONALES ACTUAL]] -> 0 | P21: 0 | Q21: 0 | R21: =CATEGORIAS[[#This Row],[PRODUCCION ANTERIOR]]+CATEGORIAS[[#This Row],[PRODUCCION ADICIONALES ANTERIOR]] -> 0 | S21: 0 | V21: =SUM(CATEGORIAS[[#This Row],[COSTO ACUMULADO AX]:[PROVISIONES]]) -> 0 | W21: 0 | Z21: =SUM(CATEGORIAS[[#This Row],[COSTO ACUMULADO ANTERIOR]:[PROVISIONES ANTERIOR]]) -> 0 | AA21: =CATEGORIAS[[#This Row],[PRESUPUESTO FINAL PROYECTADO]]-CATEGORIAS[[#This Row],[TOTAL PRODUCCION ACTUAL]] -> 0 | AB21: 0 | AE21: =SUM(CATEGORIAS[[#This Row],[INVENTARIO]:[PROYECCION DE COSTO DEL SALDO]]) -> 0 | AG21: =+CATEGORIAS[[#This Row],[PRESUPUESTO FINAL PROYECTADO]]-CATEGORIAS[[#This Row],[COSTO REAL]]-CATEGORIAS[[#This Row],[PROYECCION TOTAL DE COSTO]] -> 0
A22: =+IFERROR(VLOOKUP(CATEGORIAS[[#This Row],[CATEGORIA2]],[1]HOMOLOGACION!$A$1:$I$571,9,FALSE),0) -> 0D01 | B22: =+IFERROR(VLOOKUP(CATEGORIAS[[#This Row],[CATEGORIA2]],[1]HOMOLOGACION!$A$1:$C$571,3,FALSE),0) -> 0A04 | C22: =+IFERROR(VLOOKUP(CATEGORIAS[[#This Row],[CATEGORIA2]],[1]HOMOLOGACION!$A$1:$D$571,4,FALSE),0) -> Cañería | D22: 11-0407-000G | E22: MAO CD - Cañería / Soldadura (G) | F22: NO | G22: 0 | H22: 0 | I22: 0 | L22: =CATEGORIAS[[#This Row],[ADICIONALES]]+CATEGORIAS[[#This Row],[POM]] -> 0 | M22: 0 | N22: 0 | O22: =CATEGORIAS[[#This Row],[PRODUCCION PARTIDAS ORIGINALES ACTUAL]]+CATEGORIAS[[#This Row],[PRODUCCION ADICIONALES ACTUAL]] -> 0 | P22: 0 | Q22: 0 | R22: =CATEGORIAS[[#This Row],[PRODUCCION ANTERIOR]]+CATEGORIAS[[#This Row],[PRODUCCION ADICIONALES ANTERIOR]] -> 0 | S22: 0 | V22: =SUM(CATEGORIAS[[#This Row],[COSTO ACUMULADO AX]:[PROVISIONES]]) -> 0 | W22: 0 | Z22: =SUM(CATEGORIAS[[#This Row],[COSTO ACUMULADO ANTERIOR]:[PROVISIONES ANTERIOR]]) -> 0 | AA22: =CATEGORIAS[[#This Row],[PRESUPUESTO FINAL PROYECTADO]]-CATEGORIAS[[#This Row],[TOTAL PRODUCCION ACTUAL]] -> 0 | AB22: 0 | AE22: =SUM(CATEGORIAS[[#This Row],[INVENTARIO]:[PROYECCION DE COSTO DEL SALDO]]) -> 0 | AG22: =+CATEGORIAS[[#This Row],[PRESUPUESTO FINAL PROYECTADO]]-CATEGORIAS[[#This Row],[COSTO REAL]]-CATEGORIAS[[#This Row],[PROYECCION TOTAL DE COSTO]] -> 0
A23: =+IFERROR(VLOOKUP(CATEGORIAS[[#This Row],[CATEGORIA2]],[1]HOMOLOGACION!$A$1:$I$571,9,FALSE),0) -> 0D01 | B23: =+IFERROR(VLOOKUP(CATEGORIAS[[#This Row],[CATEGORIA2]],[1]HOMOLOGACION!$A$1:$C$571,3,FALSE),0) -> 0A04 | C23: =+IFERROR(VLOOKUP(CATEGORIAS[[#This Row],[CATEGORIA2]],[1]HOMOLOGACION!$A$1:$D$571,4,FALSE),0) -> Cañería | D23: 11-0408-000G | E23: MAO CD - Cañería / Montajes (G) | F23: SI | G23: 4.7397038e+08 | H23: 4.7397038e+08 | I23: 17687642 | L23: =CATEGORIAS[[#This Row],[ADICIONALES]]+CATEGORIAS[[#This Row],[POM]] -> 4.9165802e+08 | M23: 2.0047752e+08 | N23: 416727.76 | O23: =CATEGORIAS[[#This Row],[PRODUCCION PARTIDAS ORIGINALES ACTUAL]]+CATEGORIAS[[#This Row],[PRODUCCION ADICIONALES ACTUAL]] -> 2.0089425e+08 | P23: 1.0242814e+08 | Q23: 416727.76 | R23: =CATEGORIAS[[#This Row],[PRODUCCION ANTERIOR]]+CATEGORIAS[[#This Row],[PRODUCCION ADICIONALES ANTERIOR]] -> 1.0284487e+08 | S23: 216183449 | U23: 27921837 | V23: =SUM(CATEGORIAS[[#This Row],[COSTO ACUMULADO AX]:[PROVISIONES]]) -> 2.4410529e+08 | W23: 131900038 | Y23: 14659500 | Z23: =SUM(CATEGORIAS[[#This Row],[COSTO ACUMULADO ANTERIOR]:[PROVISIONES ANTERIOR]]) -> 1.4655954e+08 | AA23: =CATEGORIAS[[#This Row],[PRESUPUESTO FINAL PROYECTADO]]-CATEGORIAS[[#This Row],[TOTAL PRODUCCION ACTUAL]] -> 2.9076377e+08 | AB23: 0 | AD23: 2.4755274e+08 | AE23: =SUM(CATEGORIAS[[#This Row],[INVENTARIO]:[PROYECCION DE COSTO DEL SALDO]]) -> 2.4755274e+08 | AG23: =+CATEGORIAS[[#This Row],[PRESUPUESTO FINAL PROYECTADO]]-CATEGORIAS[[#This Row],[COSTO REAL]]-CATEGORIAS[[#This Row],[PROYECCION TOTAL DE COSTO]] -> 0
A24: =+IFERROR(VLOOKUP(CATEGORIAS[[#This Row],[CATEGORIA2]],[1]HOMOLOGACION!$A$1:$I$571,9,FALSE),0) -> 0F01 | B24: =+IFERROR(VLOOKUP(CATEGORIAS[[#This Row],[CATEGORIA2]],[1]HOMOLOGACION!$A$1:$C$571,3,FALSE),0) -> 0A05 | C24: =+IFERROR(VLOOKUP(CATEGORIAS[[#This Row],[CATEGORIA2]],[1]HOMOLOGACION!$A$1:$D$571,4,FALSE),0) -> Electricidad & Instrumentación | D24: 11-0507-000G | E24: MAO CD - Electricidad / Soldadura (G) | F24: NO | G24: 0 | H24: 0 | I24: 0 | L24: =CATEGORIAS[[#This Row],[ADICIONALES]]+CATEGORIAS[[#This Row],[POM]] -> 0 | M24: 0 | N24: 0 | O24: =CATEGORIAS[[#This Row],[PRODUCCION PARTIDAS ORIGINALES ACTUAL]]+CATEGORIAS[[#This Row],[PRODUCCION ADICIONALES ACTUAL]] -> 0 | P24: 0 | Q24: 0 | R24: =CATEGORIAS[[#This Row],[PRODUCCION ANTERIOR]]+CATEGORIAS[[#This Row],[PRODUCCION ADICIONALES ANTERIOR]] -> 0 | S24: 0 | V24: =SUM(CATEGORIAS[[#This Row],[COSTO ACUMULADO AX]:[PROVISIONES]]) -> 0 | W24: 0 | Z24: =SUM(CATEGORIAS[[#This Row],[COSTO ACUMULADO ANTERIOR]:[PROVISIONES ANTERIOR]]) -> 0 | AA24: =CATEGORIAS[[#This Row],[PRESUPUESTO FINAL PROYECTADO]]-CATEGORIAS[[#This Row],[TOTAL PRODUCCION ACTUAL]] -> 0 | AB24: 0 | AE24: =SUM(CATEGORIAS[[#This Row],[INVENTARIO]:[PROYECCION DE COSTO DEL SALDO]]) -> 0 | AG24: =+CATEGORIAS[[#This Row],[PRESUPUESTO FINAL PROYECTADO]]-CATEGORIAS[[#This Row],[COSTO REAL]]-CATEGORIAS[[#This Row],[PROYECCION TOTAL DE COSTO]] -> 0
A25: =+IFERROR(VLOOKUP(CATEGORIAS[[#This Row],[CATEGORIA2]],[1]HOMOLOGACION!$A$1:$I$571,9,FALSE),0) -> 0F01 | B25: =+IFERROR(VLOOKUP(CATEGORIAS[[#This Row],[CATEGORIA2]],[1]HOMOLOGACION!$A$1:$C$571,3,FALSE),0) -> 0A05 | C25: =+IFERROR(VLOOKUP(CATEGORIAS[[#This Row],[CATEGORIA2]],[1]HOMOLOGACION!$A$1:$D$571,4,FALSE),0) -> Electricidad & Instrumentación | D25: 11-0508-000G | E25: MAO CD - Electricidad / Montajes (G) | F25: SI | G25: 3.8799498e+08 | H25: 3.8799498e+08 | I25: 11735815 | L25: =CATEGORIAS[[#This Row],[ADICIONALES]]+CATEGORIAS[[#This Row],[POM]] -> 3.997308e+08 | M25: 49962829 | N25: 162108.68 | O25: =CATEGORIAS[[#This Row],[PRODUCCION PARTIDAS ORIGINALES ACTUAL]]+CATEGORIAS[[#This Row],[PRODUCCION ADICIONALES ACTUAL]] -> 50124938 | P25: 24524013 | Q25: 162108.68 | R25: =CATEGORIAS[[#This Row],[PRODUCCION ANTERIOR]]+CATEGORIAS[[#This Row],[PRODUCCION ADICIONALES ANTERIOR]] -> 24686122 | S25: 83013830 | U25: 11625102 | V25: =SUM(CATEGORIAS[[#This Row],[COSTO ACUMULADO AX]:[PROVISIONES]]) -> 94638932 | W25: 41894655 | Y25: 4643274 | Z25: =SUM(CATEGORIAS[[#This Row],[COSTO ACUMULADO ANTERIOR]:[PROVISIONES ANTERIOR]]) -> 46537929 | AA25: =CATEGORIAS[[#This Row],[PRESUPUESTO FINAL PROYECTADO]]-CATEGORIAS[[#This Row],[TOTAL PRODUCCION ACTUAL]] -> 3.4960586e+08 | AB25: 0 | AD25: 3.0509186e+08 | AE25: =SUM(CATEGORIAS[[#This Row],[INVENTARIO]:[PROYECCION DE COSTO DEL SALDO]]) -> 3.0509186e+08 | AG25: =+CATEGORIAS[[#This Row],[PRESUPUESTO FINAL PROYECTADO]]-CATEGORIAS[[#This Row],[COSTO REAL]]-CATEGORIAS[[#This Row],[PROYECCION TOTAL DE COSTO]] -> 0
A26: =+IFERROR(VLOOKUP(CATEGORIAS[[#This Row],[CATEGORIA2]],[1]HOMOLOGACION!$A$1:$I$571,9,FALSE),0) -> 0F01 | B26: =+IFERROR(VLOOKUP(CATEGORIAS[[#This Row],[CATEGORIA2]],[1]HOMOLOGACION!$A$1:$C$571,3,FALSE),0) -> 0A05 | C26: =+IFERROR(VLOOKUP(CATEGORIAS[[#This Row],[CATEGORIA2]],[1]HOMOLOGACION!$A$1:$D$571,4,FALSE),0) -> Electricidad & Instrumentación | D26: 11-0607-000G | E26: MAO CD - Instrumentación / Soldadura (G) | F26: NO | G26: 0 | H26: 0 | I26: 0 | L26: =CATEGORIAS[[#This Row],[ADICIONALES]]+CATEGORIAS[[#This Row],[POM]] -> 0 | M26: 0 | N26: 0 | O26: =CATEGORIAS[[#This Row],[PRODUCCION PARTIDAS ORIGINALES ACTUAL]]+CATEGORIAS[[#This Row],[PRODUCCION ADICIONALES ACTUAL]] -> 0 | P26: 0 | Q26: 0 | R26: =CATEGORIAS[[#This Row],[PRODUCCION ANTERIOR]]+CATEGORIAS[[#This Row],[PRODUCCION ADICIONALES ANTERIOR]] -> 0 | S26: 0 | V26: =SUM(CATEGORIAS[[#This Row],[COSTO ACUMULADO AX]:[PROVISIONES]]) -> 0 | W26: 0 | Z26: =SUM(CATEGORIAS[[#This Row],[COSTO ACUMULADO ANTERIOR]:[PROVISIONES ANTERIOR]]) -> 0 | AA26: =CATEGORIAS[[#This Row],[PRESUPUESTO FINAL PROYECTADO]]-CATEGORIAS[[#This Row],[TOTAL PRODUCCION ACTUAL]] -> 0 | AB26: 0 | AE26: =SUM(CATEGORIAS[[#This Row],[INVENTARIO]:[PROYECCION DE COSTO DEL SALDO]]) -> 0 | AG26: =+CATEGORIAS[[#This Row],[PRESUPUESTO FINAL PROYECTADO]]-CATEGORIAS[[#This Row],[COSTO REAL]]-CATEGORIAS[[#This Row],[PROYECCION TOTAL DE COSTO]] -> 0
A27: =+IFERROR(VLOOKUP(CATEGORIAS[[#This Row],[CATEGORIA2]],[1]HOMOLOGACION!$A$1:$I$571,9,FALSE),0) -> 0F01 | B27: =+IFERROR(VLOOKUP(CATEGORIAS[[#This Row],[CATEGORIA2]],[1]HOMOLOGACION!$A$1:$C$571,3,FALSE),0) -> 0A05 | C27: =+IFERROR(VLOOKUP(CATEGORIAS[[#This Row],[CATEGORIA2]],[1]HOMOLOGACION!$A$1:$D$571,4,FALSE),0) -> Electricidad & Instrumentación | D27: 11-0608-000G | E27: MAO CD - Instrumentación / Montajes (G) | F27: NO | G27: 0 | H27: 0 | I27: 0 | L27: =CATEGORIAS[[#This Row],[ADICIONALES]]+CATEGORIAS[[#This Row],[POM]] -> 0 | M27: 0 | N27: 0 | O27: =CATEGORIAS[[#This Row],[PRODUCCION PARTIDAS ORIGINALES ACTUAL]]+CATEGORIAS[[#This Row],[PRODUCCION ADICIONALES ACTUAL]] -> 0 | P27: 0 | Q27: 0 | R27: =CATEGORIAS[[#This Row],[PRODUCCION ANTERIOR]]+CATEGORIAS[[#This Row],[PRODUCCION ADICIONALES ANTERIOR]] -> 0 | S27: 0 | V27: =SUM(CATEGORIAS[[#This Row],[COSTO ACUMULADO AX]:[PROVISIONES]]) -> 0 | W27: 0 | Z27: =SUM(CATEGORIAS[[#This Row],[COSTO ACUMULADO ANTERIOR]:[PROVISIONES ANTERIOR]]) -> 0 | AA27: =CATEGORIAS[[#This Row],[PRESUPUESTO FINAL PROYECTADO]]-CATEGORIAS[[#This Row],[TOTAL PRODUCCION ACTUAL]] -> 0 | AB27: 0 | AE27: =SUM(CATEGORIAS[[#This Row],[INVENTARIO]:[PROYECCION DE COSTO DEL SALDO]]) -> 0 | AG27: =+CATEGORIAS[[#This Row],[PRESUPUESTO FINAL PROYECTADO]]-CATEGORIAS[[#This Row],[COSTO REAL]]-CATEGORIAS[[#This Row],[PROYECCION TOTAL DE COSTO]] -> 0
A28: =+IFERROR(VLOOKUP(CATEGORIAS[[#This Row],[CATEGORIA2]],[1]HOMOLOGACION!$A$1:$I$571,9,FALSE),0) -> 0H01 | B28: =+IFERROR(VLOOKUP(CATEGORIAS[[#This Row],[CATEGORIA2]],[1]HOMOLOGACION!$A$1:$C$571,3,FALSE),0) -> 0A06 | C28: =+IFERROR(VLOOKUP(CATEGORIAS[[#This Row],[CATEGORIA2]],[1]HOMOLOGACION!$A$1:$D$571,4,FALSE),0) -> Aislación | D28: 11-0701-000G | E28: MAO CD - Aislación / Aislación (G) | F28: SI | G28: 25004643 | H28: 25004643 | I28: 0 | L28: =CATEGORIAS[[#This Row],[ADICIONALES]]+CATEGORIAS[[#This Row],[POM]] -> 25004643 | M28: 0 | N28: 0 | O28: =CATEGORIAS[[#This Row],[PRODUCCION PARTIDAS ORIGINALES ACTUAL]]+CATEGORIAS[[#This Row],[PRODUCCION ADICIONALES ACTUAL]] -> 0 | P28: 13932771 | Q28: 0 | R28: =CATEGORIAS[[#This Row],[PRODUCCION ANTERIOR]]+CATEGORIAS[[#This Row],[PRODUCCION ADICIONALES ANTERIOR]] -> 13932771 | S28: 0 | V28: =SUM(CATEGORIAS[[#This Row],[COSTO ACUMULADO AX]:[PROVISIONES]]) -> 0 | W28: 0 | Z28: =SUM(CATEGORIAS[[#This Row],[COSTO ACUMULADO ANTERIOR]:[PROVISIONES ANTERIOR]]) -> 0 | AA28: =CATEGORIAS[[#This Row],[PRESUPUESTO FINAL PROYECTADO]]-CATEGORIAS[[#This Row],[TOTAL PRODUCCION ACTUAL]] -> 25004643 | AB28: 0 | AD28: 25004643 | AE28: =SUM(CATEGORIAS[[#This Row],[INVENTARIO]:[PROYECCION DE COSTO DEL SALDO]]) -> 25004643 | AG28: =+CATEGORIAS[[#This Row],[PRESUPUESTO FINAL PROYECTADO]]-CATEGORIAS[[#This Row],[COSTO REAL]]-CATEGORIAS[[#This Row],[PROYECCION TOTAL DE COSTO]] -> 0
A29: =+IFERROR(VLOOKUP(CATEGORIAS[[#This Row],[CATEGORIA2]],[1]HOMOLOGACION!$A$1:$I$571,9,FALSE),0) -> 0I01 | B29: =+IFERROR(VLOOKUP(CATEGORIAS[[#This Row],[CATEGORIA2]],[1]HOMOLOGACION!$A$1:$C$571,3,FALSE),0) -> 0A07 | C29: =+IFERROR(VLOOKUP(CATEGORIAS[[#This Row],[CATEGORIA2]],[1]HOMOLOGACION!$A$1:$D$571,4,FALSE),0) -> Caldera | D29: 11-0807-000G | E29: MAO CD - Caldera / Soldadura (G) | F29: NO | G29: 0 | H29: 0 | I29: 0 | L29: =CATEGORIAS[[#This Row],[ADICIONALES]]+CATEGORIAS[[#This Row],[POM]] -> 0 | M29: 0 | N29: 0 | O29: =CATEGORIAS[[#This Row],[PRODUCCION PARTIDAS ORIGINALES ACTUAL]]+CATEGORIAS[[#This Row],[PRODUCCION ADICIONALES ACTUAL]] -> 0 | P29: 0 | Q29: 0 | R29: =CATEGORIAS[[#This Row],[PRODUCCION ANTERIOR]]+CATEGORIAS[[#This Row],[PRODUCCION ADICIONALES ANTERIOR]] -> 0 | S29: 0 | V29: =SUM(CATEGORIAS[[#This Row],[COSTO ACUMULADO AX]:[PROVISIONES]]) -> 0 | W29: 0 | Z29: =SUM(CATEGORIAS[[#This Row],[COSTO ACUMULADO ANTERIOR]:[PROVISIONES ANTERIOR]]) -> 0 | AA29: =CATEGORIAS[[#This Row],[PRESUPUESTO FINAL PROYECTADO]]-CATEGORIAS[[#This Row],[TOTAL PRODUCCION ACTUAL]] -> 0 | AB29: 0 | AE29: =SUM(CATEGORIAS[[#This Row],[INVENTARIO]:[PROYECCION DE COSTO DEL SALDO]]) -> 0 | AG29: =+CATEGORIAS[[#This Row],[PRESUPUESTO FINAL PROYECTADO]]-CATEGORIAS[[#This Row],[COSTO REAL]]-CATEGORIAS[[#This Row],[PROYECCION TOTAL DE COSTO]] -> 0
A30: =+IFERROR(VLOOKUP(CATEGORIAS[[#This Row],[CATEGORIA2]],[1]HOMOLOGACION!$A$1:$I$571,9,FALSE),0) -> 0I01 | B30: =+IFERROR(VLOOKUP(CATEGORIAS[[#This Row],[CATEGORIA2]],[1]HOMOLOGACION!$A$1:$C$571,3,FALSE),0) -> 0A07 | C30: =+IFERROR(VLOOKUP(CATEGORIAS[[#This Row],[CATEGORIA2]],[1]HOMOLOGACION!$A$1:$D$571,4,FALSE),0) -> Caldera | D30: 11-0808-000G | E30: MAO CD - Caldera / Montajes (G) | F30: NO | G30: 0 | H30: 0 | I30: 0 | L30: =CATEGORIAS[[#This Row],[ADICIONALES]]+CATEGORIAS[[#This Row],[POM]] -> 0 | M30: 0 | N30: 0 | O30: =CATEGORIAS[[#This Row],[PRODUCCION PARTIDAS ORIGINALES ACTUAL]]+CATEGORIAS[[#This Row],[PRODUCCION ADICIONALES ACTUAL]] -> 0 | P30: 0 | Q30: 0 | R30: =CATEGORIAS[[#This Row],[PRODUCCION ANTERIOR]]+CATEGORIAS[[#This Row],[PRODUCCION ADICIONALES ANTERIOR]] -> 0 | S30: 0 | V30: =SUM(CATEGORIAS[[#This Row],[COSTO ACUMULADO AX]:[PROVISIONES]]) -> 0 | W30: 0 | Z30: =SUM(CATEGORIAS[[#This Row],[COSTO ACUMULADO ANTERIOR]:[PROVISIONES ANTERIOR]]) -> 0 | AA30: =CATEGORIAS[[#This Row],[PRESUPUESTO FINAL PROYECTADO]]-CATEGORIAS[[#This Row],[TOTAL PRODUCCION ACTUAL]] -> 0 | AB30: 0 | AE30: =SUM(CATEGORIAS[[#This Row],[INVENTARIO]:[PROYECCION DE COSTO DEL SALDO]]) -> 0 | AG30: =+CATEGORIAS[[#This Row],[PRESUPUESTO FINAL PROYECTADO]]-CATEGORIAS[[#This Row],[COSTO REAL]]-CATEGORIAS[[#This Row],[PROYECCION TOTAL DE COSTO]] -> 0
A31: =+IFERROR(VLOOKUP(CATEGORIAS[[#This Row],[CATEGORIA2]],[1]HOMOLOGACION!$A$1:$I$571,9,FALSE),0) -> 0J01 | B31: =+IFERROR(VLOOKUP(CATEGORIAS[[#This Row],[CATEGORIA2]],[1]HOMOLOGACION!$A$1:$C$571,3,FALSE),0) -> 0A09 | C31: =+IFERROR(VLOOKUP(CATEGORIAS[[#This Row],[CATEGORIA2]],[1]HOMOLOGACION!$A$1:$D$571,4,FALSE),0) -> Ductos | D31: 11-0907-000G | E31: MAO CD - Ductos / Soldadura (G) | F31: NO | G31: 0 | H31: 0 | I31: 0 | L31: =CATEGORIAS[[#This Row],[ADICIONALES]]+CATEGORIAS[[#This Row],[POM]] -> 0 | M31: 0 | N31: 0 | O31: =CATEGORIAS[[#This Row],[PRODUCCION PARTIDAS ORIGINALES ACTUAL]]+CATEGORIAS[[#This Row],[PRODUCCION ADICIONALES ACTUAL]] -> 0 | P31: 0 | Q31: 0 | R31: =CATEGORIAS[[#This Row],[PRODUCCION ANTERIOR]]+CATEGORIAS[[#This Row],[PRODUCCION ADICIONALES ANTERIOR]] -> 0 | S31: 0 | V31: =SUM(CATEGORIAS[[#This Row],[COSTO ACUMULADO AX]:[PROVISIONES]]) -> 0 | W31: 0 | Z31: =SUM(CATEGORIAS[[#This Row],[COSTO ACUMULADO ANTERIOR]:[PROVISIONES ANTERIOR]]) -> 0 | AA31: =CATEGORIAS[[#This Row],[PRESUPUESTO FINAL PROYECTADO]]-CATEGORIAS[[#This Row],[TOTAL PRODUCCION ACTUAL]] -> 0 | AB31: 0 | AE31: =SUM(CATEGORIAS[[#This Row],[INVENTARIO]:[PROYECCION DE COSTO DEL SALDO]]) -> 0 | AG31: =+CATEGORIAS[[#This Row],[PRESUPUESTO FINAL PROYECTADO]]-CATEGORIAS[[#This Row],[COSTO REAL]]-CATEGORIAS[[#This Row],[PROYECCION TOTAL DE COSTO]] -> 0
A32: =+IFERROR(VLOOKUP(CATEGORIAS[[#This Row],[CATEGORIA2]],[1]HOMOLOGACION!$A$1:$I$571,9,FALSE),0) -> 0J01 | B32: =+IFERROR(VLOOKUP(CATEGORIAS[[#This Row],[CATEGORIA2]],[1]HOMOLOGACION!$A$1:$C$571,3,FALSE),0) -> 0A09 | C32: =+IFERROR(VLOOKUP(CATEGORIAS[[#This Row],[CATEGORIA2]],[1]HOMOLOGACION!$A$1:$D$571,4,FALSE),0) -> Ductos | D32: 11-0908-000G | E32: MAO CD - Ductos / Montajes (G) | F32: NO | G32: 0 | H32: 0 | I32: 0 | L32: =CATEGORIAS[[#This Row],[ADICIONALES]]+CATEGORIAS[[#This Row],[POM]] -> 0 | M32: 0 | N32: 0 | O32: =CATEGORIAS[[#This Row],[PRODUCCION PARTIDAS ORIGINALES ACTUAL]]+CATEGORIAS[[#This Row],[PRODUCCION ADICIONALES ACTUAL]] -> 0 | P32: 0 | Q32: 0 | R32: =CATEGORIAS[[#This Row],[PRODUCCION ANTERIOR]]+CATEGORIAS[[#This Row],[PRODUCCION ADICIONALES ANTERIOR]] -> 0 | S32: 0 | V32: =SUM(CATEGORIAS[[#This Row],[COSTO ACUMULADO AX]:[PROVISIONES]]) -> 0 | W32: 0 | Z32: =SUM(CATEGORIAS[[#This Row],[COSTO ACUMULADO ANTERIOR]:[PROVISIONES ANTERIOR]]) -> 0 | AA32: =CATEGORIAS[[#This Row],[PRESUPUESTO FINAL PROYECTADO]]-CATEGORIAS[[#This Row],[TOTAL PRODUCCION ACTUAL]] -> 0 | AB32: 0 | AE32: =SUM(CATEGORIAS[[#This Row],[INVENTARIO]:[PROYECCION DE COSTO DEL SALDO]]) -> 0 | AG32: =+CATEGORIAS[[#This Row],[PRESUPUESTO FINAL PROYECTADO]]-CATEGORIAS[[#This Row],[COSTO REAL]]-CATEGORIAS[[#This Row],[PROYECCION TOTAL DE COSTO]] -> 0
A33: =+IFERROR(VLOOKUP(CATEGORIAS[[#This Row],[CATEGORIA2]],[1]HOMOLOGACION!$A$1:$I$571,9,FALSE),0) -> 0L01 | B33: =+IFERROR(VLOOKUP(CATEGORIAS[[#This Row],[CATEGORIA2]],[1]HOMOLOGACION!$A$1:$C$571,3,FALSE),0) -> 0A10 | C33: =+IFERROR(VLOOKUP(CATEGORIAS[[#This Row],[CATEGORIA2]],[1]HOMOLOGACION!$A$1:$D$571,4,FALSE),0) -> Comisionamiento | D33: 11-1001-000G | E33: MAO CD - Comisionamiento / Comisionamiento (G) | F33: NO | G33: 0 | H33: 0 | I33: 0 | L33: =CATEGORIAS[[#This Row],[ADICIONALES]]+CATEGORIAS[[#This Row],[POM]] -> 0 | M33: 0 | N33: 0 | O33: =CATEGORIAS[[#This Row],[PRODUCCION PARTIDAS ORIGINALES ACTUAL]]+CATEGORIAS[[#This Row],[PRODUCCION ADICIONALES ACTUAL]] -> 0 | P33: 0 | Q33: 0 | R33: =CATEGORIAS[[#This Row],[PRODUCCION ANTERIOR]]+CATEGORIAS[[#This Row],[PRODUCCION ADICIONALES ANTERIOR]] -> 0 | S33: 0 | V33: =SUM(CATEGORIAS[[#This Row],[COSTO ACUMULADO AX]:[PROVISIONES]]) -> 0 | W33: 0 | Z33: =SUM(CATEGORIAS[[#This Row],[COSTO ACUMULADO ANTERIOR]:[PROVISIONES ANTERIOR]]) -> 0 | AA33: =CATEGORIAS[[#This Row],[PRESUPUESTO FINAL PROYECTADO]]-CATEGORIAS[[#This Row],[TOTAL PRODUCCION ACTUAL]] -> 0 | AB33: 0 | AE33: =SUM(CATEGORIAS[[#This Row],[INVENTARIO]:[PROYECCION DE COSTO DEL SALDO]]) -> 0 | AG33: =+CATEGORIAS[[#This Row],[PRESUPUESTO FINAL PROYECTADO]]-CATEGORIAS[[#This Row],[COSTO REAL]]-CATEGORIAS[[#This Row],[PROYECCION TOTAL DE COSTO]] -> 0
A34: =+IFERROR(VLOOKUP(CATEGORIAS[[#This Row],[CATEGORIA2]],[1]HOMOLOGACION!$A$1:$I$571,9,FALSE),0) -> 0G01 | B34: =+IFERROR(VLOOKUP(CATEGORIAS[[#This Row],[CATEGORIA2]],[1]HOMOLOGACION!$A$1:$C$571,3,FALSE),0) -> 0A08 | C34: =+IFERROR(VLOOKUP(CATEGORIAS[[#This Row],[CATEGORIA2]],[1]HOMOLOGACION!$A$1:$D$571,4,FALSE),0) -> Andamios | D34: 11-1101-000G | E34: MAO CD - Andamios / Andamios (G) | F34: SI | G34: 79797653 | H34: 79797653 | I34: 2031426.5 | L34: =CATEGORIAS[[#This Row],[ADICIONALES]]+CATEGORIAS[[#This Row],[POM]] -> 81829079 | M34: 31773307 | N34: 350658.41 | O34: =CATEGORIAS[[#This Row],[PRODUCCION PARTIDAS ORIGINALES ACTUAL]]+CATEGORIAS[[#This Row],[PRODUCCION ADICIONALES ACTUAL]] -> 32123966 | P34: 21884239 | Q34: 309145.6 | R34: =CATEGORIAS[[#This Row],[PRODUCCION ANTERIOR]]+CATEGORIAS[[#This Row],[PRODUCCION ADICIONALES ANTERIOR]] -> 22193384 | S34: 76664589 | U34: 11746212 | V34: =SUM(CATEGORIAS[[#This Row],[COSTO ACUMULADO AX]:[PROVISIONES]]) -> 88410801 | W34: 40114623 | Y34: 4868857.5 | Z34: =SUM(CATEGORIAS[[#This Row],[COSTO ACUMULADO ANTERIOR]:[PROVISIONES ANTERIOR]]) -> 44983480 | AA34: =CATEGORIAS[[#This Row],[PRESUPUESTO FINAL PROYECTADO]]-CATEGORIAS[[#This Row],[TOTAL PRODUCCION ACTUAL]] -> 49705114 | AB34: 0 | AD34: -6581721.8 | AE34: =SUM(CATEGORIAS[[#This Row],[INVENTARIO]:[PROYECCION DE COSTO DEL SALDO]]) -> -6581721.8 | AG34: =+CATEGORIAS[[#This Row],[PRESUPUESTO FINAL PROYECTADO]]-CATEGORIAS[[#This Row],[COSTO REAL]]-CATEGORIAS[[#This Row],[PROYECCION TOTAL DE COSTO]] -> 0
A35: =+IFERROR(VLOOKUP(CATEGORIAS[[#This Row],[CATEGORIA2]],[1]HOMOLOGACION!$A$1:$I$571,9,FALSE),0) -> 0M01 | B35: =+IFERROR(VLOOKUP(CATEGORIAS[[#This Row],[CATEGORIA2]],[1]HOMOLOGACION!$A$1:$C$571,3,FALSE),0) -> 0A11 | C35: =+IFERROR(VLOOKUP(CATEGORIAS[[#This Row],[CATEGORIA2]],[1]HOMOLOGACION!$A$1:$D$571,4,FALSE),0) -> Arquitectura | D35: 11-1201-000G | E35: MAO CD - Pintura / Pintura (G) | F35: NO | G35: 0 | H35: 0 | I35: 0 | L35: =CATEGORIAS[[#This Row],[ADICIONALES]]+CATEGORIAS[[#This Row],[POM]] -> 0 | M35: 0 | N35: 0 | O35: =CATEGORIAS[[#This Row],[PRODUCCION PARTIDAS ORIGINALES ACTUAL]]+CATEGORIAS[[#This Row],[PRODUCCION ADICIONALES ACTUAL]] -> 0 | P35: 0 | Q35: 0 | R35: =CATEGORIAS[[#This Row],[PRODUCCION ANTERIOR]]+CATEGORIAS[[#This Row],[PRODUCCION ADICIONALES ANTERIOR]] -> 0 | S35: 0 | U35: 2325389 | V35: =SUM(CATEGORIAS[[#This Row],[COSTO ACUMULADO AX]:[PROVISIONES]]) -> 2325389 | W35: 0 | Z35: =SUM(CATEGORIAS[[#This Row],[COSTO ACUMULADO ANTERIOR]:[PROVISIONES ANTERIOR]]) -> 0 | AA35: =CATEGORIAS[[#This Row],[PRESUPUESTO FINAL PROYECTADO]]-CATEGORIAS[[#This Row],[TOTAL PRODUCCION ACTUAL]] -> 0 | AB35: 0 | AE35: =SUM(CATEGORIAS[[#This Row],[INVENTARIO]:[PROYECCION DE COSTO DEL SALDO]]) -> 0 | AG35: =+CATEGORIAS[[#This Row],[PRESUPUESTO FINAL PROYECTADO]]-CATEGORIAS[[#This Row],[COSTO REAL]]-CATEGORIAS[[#This Row],[PROYECCION TOTAL DE COSTO]] -> -2325389
A36: =+IFERROR(VLOOKUP(CATEGORIAS[[#This Row],[CATEGORIA2]],[1]HOMOLOGACION!$A$1:$I$571,9,FALSE),0) -> 0Q01 | B36: =+IFERROR(VLOOKUP(CATEGORIAS[[#This Row],[CATEGORIA2]],[1]HOMOLOGACION!$A$1:$C$571,3,FALSE),0) -> 0D07 | C36: =+IFERROR(VLOOKUP(CATEGORIAS[[#This Row],[CATEGORIA2]],[1]HOMOLOGACION!$A$1:$D$571,4,FALSE),0) -> Operador | D36: 11-1201-010G | E36: MAO CD - Equipos / Equipos / Operador (G) | F36: SI | G36: 93476145 | H36: 93476145 | I36: 0 | L36: =CATEGORIAS[[#This Row],[ADICIONALES]]+CATEGORIAS[[#This Row],[POM]] -> 93476145 | M36: 43656319 | N36: 0 | O36: =CATEGORIAS[[#This Row],[PRODUCCION PARTIDAS ORIGINALES ACTUAL]]+CATEGORIAS[[#This Row],[PRODUCCION ADICIONALES ACTUAL]] -> 43656319 | P36: 23253645 | Q36: 0 | R36: =CATEGORIAS[[#This Row],[PRODUCCION ANTERIOR]]+CATEGORIAS[[#This Row],[PRODUCCION ADICIONALES ANTERIOR]] -> 23253645 | S36: 48932267 | U36: 2325389 | V36: =SUM(CATEGORIAS[[#This Row],[COSTO ACUMULADO AX]:[PROVISIONES]]) -> 51257656 | W36: 33848884 | Y36: 2109735.9 | Z36: =SUM(CATEGORIAS[[#This Row],[COSTO ACUMULADO ANTERIOR]:[PROVISIONES ANTERIOR]]) -> 35958620 | AA36: =CATEGORIAS[[#This Row],[PRESUPUESTO FINAL PROYECTADO]]-CATEGORIAS[[#This Row],[TOTAL PRODUCCION ACTUAL]] -> 49819826 | AB36: 0 | AD36: 42218489 | AE36: =SUM(CATEGORIAS[[#This Row],[INVENTARIO]:[PROYECCION DE COSTO DEL SALDO]]) -> 42218489 | AG36: =+CATEGORIAS[[#This Row],[PRESUPUESTO FINAL PROYECTADO]]-CATEGORIAS[[#This Row],[COSTO REAL]]-CATEGORIAS[[#This Row],[PROYECCION TOTAL DE COSTO]] -> 0
A37: =+IFERROR(VLOOKUP(CATEGORIAS[[#This Row],[CATEGORIA2]],[1]HOMOLOGACION!$A$1:$I$571,9,FALSE),0) -> 0Q01 | B37: =+IFERROR(VLOOKUP(CATEGORIAS[[#This Row],[CATEGORIA2]],[1]HOMOLOGACION!$A$1:$C$571,3,FALSE),0) -> 0D08 | C37: =+IFERROR(VLOOKUP(CATEGORIAS[[#This Row],[CATEGORIA2]],[1]HOMOLOGACION!$A$1:$D$571,4,FALSE),0) -> Rigger | D37: 11-1201-020G | E37: MAO CD - Equipos / Equipos / Rigger (G) | F37: SI | G37: 42918681 | H37: 42918681 | I37: 0 | L37: =CATEGORIAS[[#This Row],[ADICIONALES]]+CATEGORIAS[[#This Row],[POM]] -> 42918681 | M37: 20044383 | N37: 0 | O37: =CATEGORIAS[[#This Row],[PRODUCCION PARTIDAS ORIGINALES ACTUAL]]+CATEGORIAS[[#This Row],[PRODUCCION ADICIONALES ACTUAL]] -> 20044383 | P37: 10676690 | Q37: 0 | R37: =CATEGORIAS[[#This Row],[PRODUCCION ANTERIOR]]+CATEGORIAS[[#This Row],[PRODUCCION ADICIONALES ANTERIOR]] -> 10676690 | S37: 11060840 | U37: 1590653.2 | V37: =SUM(CATEGORIAS[[#This Row],[COSTO ACUMULADO AX]:[PROVISIONES]]) -> 12651493 | W37: 7800342 | Y37: 954391.89 | Z37: =SUM(CATEGORIAS[[#This Row],[COSTO ACUMULADO ANTERIOR]:[PROVISIONES ANTERIOR]]) -> 8754733.9 | AA37: =CATEGORIAS[[#This Row],[PRESUPUESTO FINAL PROYECTADO]]-CATEGORIAS[[#This Row],[TOTAL PRODUCCION ACTUAL]] -> 22874298 | AB37: 0 | AD37: 30267188 | AE37: =SUM(CATEGORIAS[[#This Row],[INVENTARIO]:[PROYECCION DE COSTO DEL SALDO]]) -> 30267188 | AG37: =+CATEGORIAS[[#This Row],[PRESUPUESTO FINAL PROYECTADO]]-CATEGORIAS[[#This Row],[COSTO REAL]]-CATEGORIAS[[#This Row],[PROYECCION TOTAL DE COSTO]] -> 0
A38: =+IFERROR(VLOOKUP(CATEGORIAS[[#This Row],[CATEGORIA2]],[1]HOMOLOGACION!$A$1:$I$571,9,FALSE),0) -> 0Q01 | B38: =+IFERROR(VLOOKUP(CATEGORIAS[[#This Row],[CATEGORIA2]],[1]HOMOLOGACION!$A$1:$C$571,3,FALSE),0) -> 0D07 | C38: =+IFERROR(VLOOKUP(CATEGORIAS[[#This Row],[CATEGORIA2]],[1]HOMOLOGACION!$A$1:$D$571,4,FALSE),0) -> Operador | D38: 11-1201-030G | E38: MAO CD - Equipos / Equipos / Operador dpto Equipos (G) | F38: NO | G38: 0 | H38: 0 | I38: 0 | L38: =CATEGORIAS[[#This Row],[ADICIONALES]]+CATEGORIAS[[#This Row],[POM]] -> 0 | M38: 0 | N38: 0 | O38: =CATEGORIAS[[#This Row],[PRODUCCION PARTIDAS ORIGINALES ACTUAL]]+CATEGORIAS[[#This Row],[PRODUCCION ADICIONALES ACTUAL]] -> 0 | P38: 0 | Q38: 0 | R38: =CATEGORIAS[[#This Row],[PRODUCCION ANTERIOR]]+CATEGORIAS[[#This Row],[PRODUCCION ADICIONALES ANTERIOR]] -> 0 | S38: 0 | V38: =SUM(CATEGORIAS[[#This Row],[COSTO ACUMULADO AX]:[PROVISIONES]]) -> 0 | W38: 0 | Z38: =SUM(CATEGORIAS[[#This Row],[COSTO ACUMULADO ANTERIOR]:[PROVISIONES ANTERIOR]]) -> 0 | AA38: =CATEGORIAS[[#This Row],[PRESUPUESTO FINAL PROYECTADO]]-CATEGORIAS[[#This Row],[TOTAL PRODUCCION ACTUAL]] -> 0 | AB38: 0 | AE38: =SUM(CATEGORIAS[[#This Row],[INVENTARIO]:[PROYECCION DE COSTO DEL SALDO]]) -> 0 | AG38: =+CATEGORIAS[[#This Row],[PRESUPUESTO FINAL PROYECTADO]]-CATEGORIAS[[#This Row],[COSTO REAL]]-CATEGORIAS[[#This Row],[PROYECCION TOTAL DE COSTO]] -> 0
A39: =+IFERROR(VLOOKUP(CATEGORIAS[[#This Row],[CATEGORIA2]],[1]HOMOLOGACION!$A$1:$I$571,9,FALSE),0) -> 0Q01 | B39: =+IFERROR(VLOOKUP(CATEGORIAS[[#This Row],[CATEGORIA2]],[1]HOMOLOGACION!$A$1:$C$571,3,FALSE),0) -> 0D08 | C39: =+IFERROR(VLOOKUP(CATEGORIAS[[#This Row],[CATEGORIA2]],[1]HOMOLOGACION!$A$1:$D$571,4,FALSE),0) -> Rigger | D39: 11-1201-040G | E39: MAO CD - Equipos / Equipos / Rigger dpto Equipos(G) | F39: NO | G39: 0 | H39: 0 | I39: 0 | L39: =CATEGORIAS[[#This Row],[ADICIONALES]]+CATEGORIAS[[#This Row],[POM]] -> 0 | M39: 0 | N39: 0 | O39: =CATEGORIAS[[#This Row],[PRODUCCION PARTIDAS ORIGINALES ACTUAL]]+CATEGORIAS[[#This Row],[PRODUCCION ADICIONALES ACTUAL]] -> 0 | P39: 0 | Q39: 0 | R39: =CATEGORIAS[[#This Row],[PRODUCCION ANTERIOR]]+CATEGORIAS[[#This Row],[PRODUCCION ADICIONALES ANTERIOR]] -> 0 | S39: 0 | V39: =SUM(CATEGORIAS[[#This Row],[COSTO ACUMULADO AX]:[PROVISIONES]]) -> 0 | W39: 0 | Z39: =SUM(CATEGORIAS[[#This Row],[COSTO ACUMULADO ANTERIOR]:[PROVISIONES ANTERIOR]]) -> 0 | AA39: =CATEGORIAS[[#This Row],[PRESUPUESTO FINAL PROYECTADO]]-CATEGORIAS[[#This Row],[TOTAL PRODUCCION ACTUAL]] -> 0 | AB39: 0 | AE39: =SUM(CATEGORIAS[[#This Row],[INVENTARIO]:[PROYECCION DE COSTO DEL SALDO]]) -> 0 | AG39: =+CATEGORIAS[[#This Row],[PRESUPUESTO FINAL PROYECTADO]]-CATEGORIAS[[#This Row],[COSTO REAL]]-CATEGORIAS[[#This Row],[PROYECCION TOTAL DE COSTO]] -> 0
A40: =+IFERROR(VLOOKUP(CATEGORIAS[[#This Row],[CATEGORIA2]],[1]HOMOLOGACION!$A$1:$I$571,9,FALSE),0) -> 0N01 | B40: =+IFERROR(VLOOKUP(CATEGORIAS[[#This Row],[CATEGORIA2]],[1]HOMOLOGACION!$A$1:$C$571,3,FALSE),0) -> 0A12 | C40: =+IFERROR(VLOOKUP(CATEGORIAS[[#This Row],[CATEGORIA2]],[1]HOMOLOGACION!$A$1:$D$571,4,FALSE),0) -> Estanque | D40: 11-1307-000G | E40: MAO CD - Estanque / Soldadura (G) | F40: NO | G40: 0 | H40: 0 | I40: 0 | L40: =CATEGORIAS[[#This Row],[ADICIONALES]]+CATEGORIAS[[#This Row],[POM]] -> 0 | M40: 0 | N40: 0 | O40: =CATEGORIAS[[#This Row],[PRODUCCION PARTIDAS ORIGINALES ACTUAL]]+CATEGORIAS[[#This Row],[PRODUCCION ADICIONALES ACTUAL]] -> 0 | P40: 0 | Q40: 0 | R40: =CATEGORIAS[[#This Row],[PRODUCCION ANTERIOR]]+CATEGORIAS[[#This Row],[PRODUCCION ADICIONALES ANTERIOR]] -> 0 | S40: 0 | V40: =SUM(CATEGORIAS[[#This Row],[COSTO ACUMULADO AX]:[PROVISIONES]]) -> 0 | W40: 0 | Z40: =SUM(CATEGORIAS[[#This Row],[COSTO ACUMULADO ANTERIOR]:[PROVISIONES ANTERIOR]]) -> 0 | AA40: =CATEGORIAS[[#This Row],[PRESUPUESTO FINAL PROYECTADO]]-CATEGORIAS[[#This Row],[TOTAL PRODUCCION ACTUAL]] -> 0 | AB40: 0 | AE40: =SUM(CATEGORIAS[[#This Row],[INVENTARIO]:[PROYECCION DE COSTO DEL SALDO]]) -> 0 | AG40: =+CATEGORIAS[[#This Row],[PRESUPUESTO FINAL PROYECTADO]]-CATEGORIAS[[#This Row],[COSTO REAL]]-CATEGORIAS[[#This Row],[PROYECCION TOTAL DE COSTO]] -> 0
A41: =+IFERROR(VLOOKUP(CATEGORIAS[[#This Row],[CATEGORIA2]],[1]HOMOLOGACION!$A$1:$I$571,9,FALSE),0) -> 0N01 | B41: =+IFERROR(VLOOKUP(CATEGORIAS[[#This Row],[CATEGORIA2]],[1]HOMOLOGACION!$A$1:$C$571,3,FALSE),0) -> 0A12 | C41: =+IFERROR(VLOOKUP(CATEGORIAS[[#This Row],[CATEGORIA2]],[1]HOMOLOGACION!$A$1:$D$571,4,FALSE),0) -> Estanque | D41: 11-1308-000G | E41: MAO CD - Estanque / Montajes (G) | F41: NO | G41: 0 | H41: 0 | I41: 0 | L41: =CATEGORIAS[[#This Row],[ADICIONALES]]+CATEGORIAS[[#This Row],[POM]] -> 0 | M41: 0 | N41: 0 | O41: =CATEGORIAS[[#This Row],[PRODUCCION PARTIDAS ORIGINALES ACTUAL]]+CATEGORIAS[[#This Row],[PRODUCCION ADICIONALES ACTUAL]] -> 0 | P41: 0 | Q41: 0 | R41: =CATEGORIAS[[#This Row],[PRODUCCION ANTERIOR]]+CATEGORIAS[[#This Row],[PRODUCCION ADICIONALES ANTERIOR]] -> 0 | S41: 0 | V41: =SUM(CATEGORIAS[[#This Row],[COSTO ACUMULADO AX]:[PROVISIONES]]) -> 0 | W41: 0 | Z41: =SUM(CATEGORIAS[[#This Row],[COSTO ACUMULADO ANTERIOR]:[PROVISIONES ANTERIOR]]) -> 0 | AA41: =CATEGORIAS[[#This Row],[PRESUPUESTO FINAL PROYECTADO]]-CATEGORIAS[[#This Row],[TOTAL PRODUCCION ACTUAL]] -> 0 | AB41: 0 | AE41: =SUM(CATEGORIAS[[#This Row],[INVENTARIO]:[PROYECCION DE COSTO DEL SALDO]]) -> 0 | AG41: =+CATEGORIAS[[#This Row],[PRESUPUESTO FINAL PROYECTADO]]-CATEGORIAS[[#This Row],[COSTO REAL]]-CATEGORIAS[[#This Row],[PROYECCION TOTAL DE COSTO]] -> 0
A42: =+IFERROR(VLOOKUP(CATEGORIAS[[#This Row],[CATEGORIA2]],[1]HOMOLOGACION!$A$1:$I$571,9,FALSE),0) -> 0P10 | B42: =+IFERROR(VLOOKUP(CATEGORIAS[[#This Row],[CATEGORIA2]],[1]HOMOLOGACION!$A$1:$C$571,3,FALSE),0) -> 0A13 | C42: =+IFERROR(VLOOKUP(CATEGORIAS[[#This Row],[CATEGORIA2]],[1]HOMOLOGACION!$A$1:$D$571,4,FALSE),0) -> Multas Costo Directo | D42: 11-7101-000G | E42: MAO CD - Multas (G) | F42: NO | G42: 0 | H42: 0 | I42: 0 | L42: =CATEGORIAS[[#This Row],[ADICIONALES]]+CATEGORIAS[[#This Row],[POM]] -> 0 | M42: 0 | N42: 0 | O42: 0 | P42: 0 | Q42: 0 | R42: =CATEGORIAS[[#This Row],[PRODUCCION ANTERIOR]]+CATEGORIAS[[#This Row],[PRODUCCION ADICIONALES ANTERIOR]] -> 0 | S42: 0 | V42: =SUM(CATEGORIAS[[#This Row],[COSTO ACUMULADO AX]:[PROVISIONES]]) -> 0 | W42: 0 | Z42: =SUM(CATEGORIAS[[#This Row],[COSTO ACUMULADO ANTERIOR]:[PROVISIONES ANTERIOR]]) -> 0 | AA42: =CATEGORIAS[[#This Row],[PRESUPUESTO FINAL PROYECTADO]]-CATEGORIAS[[#This Row],[TOTAL PRODUCCION ACTUAL]] -> 0 | AB42: 0 | AE42: =SUM(CATEGORIAS[[#This Row],[INVENTARIO]:[PROYECCION DE COSTO DEL SALDO]]) -> 0 | AG42: =+CATEGORIAS[[#This Row],[PRESUPUESTO FINAL PROYECTADO]]-CATEGORIAS[[#This Row],[COSTO REAL]]-CATEGORIAS[[#This Row],[PROYECCION TOTAL DE COSTO]] -> 0
A43: =+IFERROR(VLOOKUP(CATEGORIAS[[#This Row],[CATEGORIA2]],[1]HOMOLOGACION!$A$1:$I$571,9,FALSE),0) -> 1Y01 | B43: =+IFERROR(VLOOKUP(CATEGORIAS[[#This Row],[CATEGORIA2]],[1]HOMOLOGACION!$A$1:$C$571,3,FALSE),0) -> 1F01 | C43: =+IFERROR(VLOOKUP(CATEGORIAS[[#This Row],[CATEGORIA2]],[1]HOMOLOGACION!$A$1:$D$571,4,FALSE),0) -> Staff Superior | D43: 12-5101-000G | E43: MAO CI - Staff Superior / Staff Superior (G) | F43: SI | G43: 3.4491885e+08 | H43: 3.4491885e+08 | I43: 5384284.5 | L43: =CATEGORIAS[[#This Row],[ADICIONALES]]+CATEGORIAS[[#This Row],[POM]] -> 3.5030314e+08 | M43: 1.6108802e+08 | N43: 0 | O43: =CATEGORIAS[[#This Row],[PRODUCCION PARTIDAS ORIGINALES ACTUAL]]+CATEGORIAS[[#This Row],[PRODUCCION ADICIONALES ACTUAL]] -> 1.6108802e+08 | P43: 1.0994825e+08 | Q43: 0 | R43: =CATEGORIAS[[#This Row],[PRODUCCION ANTERIOR]]+CATEGORIAS[[#This Row],[PRODUCCION ADICIONALES ANTERIOR]] -> 1.0994825e+08 | S43: 1.30358e+08 | T43: 4110204 | U43: 4749692.9 | V43: =SUM(CATEGORIAS[[#This Row],[COSTO ACUMULADO AX]:[PROVISIONES]]) -> 1.3921789e+08 | W43: 79725188 | X43: 3421363 | Y43: 2666359.5 | Z43: =SUM(CATEGORIAS[[#This Row],[COSTO ACUMULADO ANTERIOR]:[PROVISIONES ANTERIOR]]) -> 85812910 | AA43: =CATEGORIAS[[#This Row],[PRESUPUESTO FINAL PROYECTADO]]-CATEGORIAS[[#This Row],[TOTAL PRODUCCION ACTUAL]] -> 1.8921511e+08 | AB43: 0 | AD43: 2.1108524e+08 | AE43: =SUM(CATEGORIAS[[#This Row],[INVENTARIO]:[PROYECCION DE COSTO DEL SALDO]]) -> 2.1108524e+08 | AG43: =+CATEGORIAS[[#This Row],[PRESUPUESTO FINAL PROYECTADO]]-CATEGORIAS[[#This Row],[COSTO REAL]]-CATEGORIAS[[#This Row],[PROYECCION TOTAL DE COSTO]] -> 0
A44: =+IFERROR(VLOOKUP(CATEGORIAS[[#This Row],[CATEGORIA2]],[1]HOMOLOGACION!$A$1:$I$571,9,FALSE),0) -> 1Y02 | B44: =+IFERROR(VLOOKUP(CATEGORIAS[[#This Row],[CATEGORIA2]],[1]HOMOLOGACION!$A$1:$C$571,3,FALSE),0) -> 1F02 | C44: =+IFERROR(VLOOKUP(CATEGORIAS[[#This Row],[CATEGORIA2]],[1]HOMOLOGACION!$A$1:$D$571,4,FALSE),0) -> Oficina Técnica | D44: 12-5201-000G | E44: MAO CI - Oficina Técnica / Oficina Técnica (G) | F44: SI | G44: 1.7579984e+08 | H44: 1.7579984e+08 | I44: 5384284.5 | L44: =CATEGORIAS[[#This Row],[ADICIONALES]]+CATEGORIAS[[#This Row],[POM]] -> 1.8118413e+08 | M44: 82104092 | N44: 0 | O44: =CATEGORIAS[[#This Row],[PRODUCCION PARTIDAS ORIGINALES ACTUAL]]+CATEGORIAS[[#This Row],[PRODUCCION ADICIONALES ACTUAL]] -> 82104092 | P44: 56038935 | Q44: 0 | R44: =CATEGORIAS[[#This Row],[PRODUCCION ANTERIOR]]+CATEGORIAS[[#This Row],[PRODUCCION ADICIONALES ANTERIOR]] -> 56038935 | S44: 85595198 | T44: 721354 | U44: 6355344 | V44: =SUM(CATEGORIAS[[#This Row],[COSTO ACUMULADO AX]:[PROVISIONES]]) -> 92671896 | W44: 59911645 | X44: 183366 | Y44: 3794686.7 | Z44: =SUM(CATEGORIAS[[#This Row],[COSTO ACUMULADO ANTERIOR]:[PROVISIONES ANTERIOR]]) -> 63889698 | AA44: =CATEGORIAS[[#This Row],[PRESUPUESTO FINAL PROYECTADO]]-CATEGORIAS[[#This Row],[TOTAL PRODUCCION ACTUAL]] -> 99080034 | AB44: 0 | AD44: 88512230 | AE44: =SUM(CATEGORIAS[[#This Row],[INVENTARIO]:[PROYECCION DE COSTO DEL SALDO]]) -> 88512230 | AG44: =+CATEGORIAS[[#This Row],[PRESUPUESTO FINAL PROYECTADO]]-CATEGORIAS[[#This Row],[COSTO REAL]]-CATEGORIAS[[#This Row],[PROYECCION TOTAL DE COSTO]] -> 0
A45: =+IFERROR(VLOOKUP(CATEGORIAS[[#This Row],[CATEGORIA2]],[1]HOMOLOGACION!$A$1:$I$571,9,FALSE),0) -> 1Y03 | B45: =+IFERROR(VLOOKUP(CATEGORIAS[[#This Row],[CATEGORIA2]],[1]HOMOLOGACION!$A$1:$C$571,3,FALSE),0) -> 1F03 | C45: =+IFERROR(VLOOKUP(CATEGORIAS[[#This Row],[CATEGORIA2]],[1]HOMOLOGACION!$A$1:$D$571,4,FALSE),0) -> Supervisión | D45: 12-5301-000G | E45: MAO CI - Supervisión / Supervisión (G) | F45: SI | G45: 1.0108102e+08 | H45: 1.0108102e+08 | I45: 6026317.5 | L45: =CATEGORIAS[[#This Row],[ADICIONALES]]+CATEGORIAS[[#This Row],[POM]] -> 1.0710734e+08 | M45: 47208038 | N45: 0 | O45: =CATEGORIAS[[#This Row],[PRODUCCION PARTIDAS ORIGINALES ACTUAL]]+CATEGORIAS[[#This Row],[PRODUCCION ADICIONALES ACTUAL]] -> 47208038 | P45: 32221149 | Q45: 0 | R45: =CATEGORIAS[[#This Row],[PRODUCCION ANTERIOR]]+CATEGORIAS[[#This Row],[PRODUCCION ADICIONALES ANTERIOR]] -> 32221149 | S45: 56856905 | U45: 6629811.6 | V45: =SUM(CATEGORIAS[[#This Row],[COSTO ACUMULADO AX]:[PROVISIONES]]) -> 63486717 | W45: 38706014 | Y45: 3645577.4 | Z45: =SUM(CATEGORIAS[[#This Row],[COSTO ACUMULADO ANTERIOR]:[PROVISIONES ANTERIOR]]) -> 42351591 | AA45: =CATEGORIAS[[#This Row],[PRESUPUESTO FINAL PROYECTADO]]-CATEGORIAS[[#This Row],[TOTAL PRODUCCION ACTUAL]] -> 59899303 | AB45: 0 | AD45: 43620625 | AE45: =SUM(CATEGORIAS[[#This Row],[INVENTARIO]:[PROYECCION DE COSTO DEL SALDO]]) -> 43620625 | AG45: =+CATEGORIAS[[#This Row],[PRESUPUESTO FINAL PROYECTADO]]-CATEGORIAS[[#This Row],[COSTO REAL]]-CATEGORIAS[[#This Row],[PROYECCION TOTAL DE COSTO]] -> 0
A46: =+IFERROR(VLOOKUP(CATEGORIAS[[#This Row],[CATEGORIA2]],[1]HOMOLOGACION!$A$1:$I$571,9,FALSE),0) -> 1Y06 | B46: =+IFERROR(VLOOKUP(CATEGORIAS[[#This Row],[CATEGORIA2]],[1]HOMOLOGACION!$A$1:$C$571,3,FALSE),0) -> 1F06 | C46: =+IFERROR(VLOOKUP(CATEGORIAS[[#This Row],[CATEGORIA2]],[1]HOMOLOGACION!$A$1:$D$571,4,FALSE),0) -> Administración | D46: 12-5401-000G | E46: MAO CI - Administración / Administración (G) | F46: SI | G46: 50846869 | H46: 50846869 | I46: 5384284.5 | L46: =CATEGORIAS[[#This Row],[ADICIONALES]]+CATEGORIAS[[#This Row],[POM]] -> 56231154 | M46: 23747098 | N46: 0 | O46: =CATEGORIAS[[#This Row],[PRODUCCION PARTIDAS ORIGINALES ACTUAL]]+CATEGORIAS[[#This Row],[PRODUCCION ADICIONALES ACTUAL]] -> 23747098 | P46: 16208231 | Q46: 0 | R46: =CATEGORIAS[[#This Row],[PRODUCCION ANTERIOR]]+CATEGORIAS[[#This Row],[PRODUCCION ADICIONALES ANTERIOR]] -> 16208231 | S46: 22187498 | U46: 2752610.6 | V46: =SUM(CATEGORIAS[[#This Row],[COSTO ACUMULADO AX]:[PROVISIONES]]) -> 24940109 | W46: 16289686 | Y46: 1698914.8 | Z46: =SUM(CATEGORIAS[[#This Row],[COSTO ACUMULADO ANTERIOR]:[PROVISIONES ANTERIOR]]) -> 17988601 | AA46: =CATEGORIAS[[#This Row],[PRESUPUESTO FINAL PROYECTADO]]-CATEGORIAS[[#This Row],[TOTAL PRODUCCION ACTUAL]] -> 32484056 | AB46: 0 | AD46: 31291045 | AE46: =SUM(CATEGORIAS[[#This Row],[INVENTARIO]:[PROYECCION DE COSTO DEL SALDO]]) -> 31291045 | AG46: =+CATEGORIAS[[#This Row],[PRESUPUESTO FINAL PROYECTADO]]-CATEGORIAS[[#This Row],[COSTO REAL]]-CATEGORIAS[[#This Row],[PROYECCION TOTAL DE COSTO]] -> 0
A47: =+IFERROR(VLOOKUP(CATEGORIAS[[#This Row],[CATEGORIA2]],[1]HOMOLOGACION!$A$1:$I$571,9,FALSE),0) -> 1Y04 | B47: =+IFERROR(VLOOKUP(CATEGORIAS[[#This Row],[CATEGORIA2]],[1]HOMOLOGACION!$A$1:$C$571,3,FALSE),0) -> 1F04 | C47: =+IFERROR(VLOOKUP(CATEGORIAS[[#This Row],[CATEGORIA2]],[1]HOMOLOGACION!$A$1:$D$571,4,FALSE),0) -> Prevención de Riesgos | D47: 12-5501-000G | E47: MAO CI - Prevención De Riesgos / Prevención De Riesgos (G) | F47: SI | G47: 1.4142956e+08 | H47: 1.4142956e+08 | I47: 6026317.5 | L47: =CATEGORIAS[[#This Row],[ADICIONALES]]+CATEGORIAS[[#This Row],[POM]] -> 1.4745587e+08 | M47: 66052080 | N47: 0 | O47: =CATEGORIAS[[#This Row],[PRODUCCION PARTIDAS ORIGINALES ACTUAL]]+CATEGORIAS[[#This Row],[PRODUCCION ADICIONALES ACTUAL]] -> 66052080 | P47: 45082871 | Q47: 0 | R47: =CATEGORIAS[[#This Row],[PRODUCCION ANTERIOR]]+CATEGORIAS[[#This Row],[PRODUCCION ADICIONALES ANTERIOR]] -> 45082871 | S47: 54964509 | U47: 6668714.2 | V47: =SUM(CATEGORIAS[[#This Row],[COSTO ACUMULADO AX]:[PROVISIONES]]) -> 61633223 | W47: 34014097 | Y47: 3065110.6 | Z47: =SUM(CATEGORIAS[[#This Row],[COSTO ACUMULADO ANTERIOR]:[PROVISIONES ANTERIOR]]) -> 37079208 | AA47: =CATEGORIAS[[#This Row],[PRESUPUESTO FINAL PROYECTADO]]-CATEGORIAS[[#This Row],[TOTAL PRODUCCION ACTUAL]] -> 81403793 | AB47: 0 | AD47: 85822649 | AE47: =SUM(CATEGORIAS[[#This Row],[INVENTARIO]:[PROYECCION DE COSTO DEL SALDO]]) -> 85822649 | AG47: =+CATEGORIAS[[#This Row],[PRESUPUESTO FINAL PROYECTADO]]-CATEGORIAS[[#This Row],[COSTO REAL]]-CATEGORIAS[[#This Row],[PROYECCION TOTAL DE COSTO]] -> 0
A48: =+IFERROR(VLOOKUP(CATEGORIAS[[#This Row],[CATEGORIA2]],[1]HOMOLOGACION!$A$1:$I$571,9,FALSE),0) -> 1Y05 | B48: =+IFERROR(VLOOKUP(CATEGORIAS[[#This Row],[CATEGORIA2]],[1]HOMOLOGACION!$A$1:$C$571,3,FALSE),0) -> 1F05 | C48: =+IFERROR(VLOOKUP(CATEGORIAS[[#This Row],[CATEGORIA2]],[1]HOMOLOGACION!$A$1:$D$571,4,FALSE),0) -> Control De Calidad | D48: 12-5601-000G | E48: MAO CI - Control De Calidad / Control De Calidad (G) | F48: SI | G48: 62286054 | H48: 62286054 | I48: 5384284.5 | L48: =CATEGORIAS[[#This Row],[ADICIONALES]]+CATEGORIAS[[#This Row],[POM]] -> 67670338 | M48: 29089559 | N48: 0 | O48: =CATEGORIAS[[#This Row],[PRODUCCION PARTIDAS ORIGINALES ACTUAL]]+CATEGORIAS[[#This Row],[PRODUCCION ADICIONALES ACTUAL]] -> 29089559 | P48: 19854649 | Q48: 0 | R48: =CATEGORIAS[[#This Row],[PRODUCCION ANTERIOR]]+CATEGORIAS[[#This Row],[PRODUCCION ADICIONALES ANTERIOR]] -> 19854649 | S48: 24141241 | U48: 2792792.8 | V48: =SUM(CATEGORIAS[[#This Row],[COSTO ACUMULADO AX]:[PROVISIONES]]) -> 26934034 | W48: 16622874 | Y48: 1497747.7 | Z48: =SUM(CATEGORIAS[[#This Row],[COSTO ACUMULADO ANTERIOR]:[PROVISIONES ANTERIOR]]) -> 18120622 | AA48: =CATEGORIAS[[#This Row],[PRESUPUESTO FINAL PROYECTADO]]-CATEGORIAS[[#This Row],[TOTAL PRODUCCION ACTUAL]] -> 38580779 | AB48: 0 | AD48: 40736305 | AE48: =SUM(CATEGORIAS[[#This Row],[INVENTARIO]:[PROYECCION DE COSTO DEL SALDO]]) -> 40736305 | AG48: =+CATEGORIAS[[#This Row],[PRESUPUESTO FINAL PROYECTADO]]-CATEGORIAS[[#This Row],[COSTO REAL]]-CATEGORIAS[[#This Row],[PROYECCION TOTAL DE COSTO]] -> 0
A49: =+IFERROR(VLOOKUP(CATEGORIAS[[#This Row],[CATEGORIA2]],[1]HOMOLOGACION!$A$1:$I$571,9,FALSE),0) -> 1Y07 | B49: =+IFERROR(VLOOKUP(CATEGORIAS[[#This Row],[CATEGORIA2]],[1]HOMOLOGACION!$A$1:$C$571,3,FALSE),0) -> 1F07 | C49: =+IFERROR(VLOOKUP(CATEGORIAS[[#This Row],[CATEGORIA2]],[1]HOMOLOGACION!$A$1:$D$571,4,FALSE),0) -> Servicios | D49: 12-5701-000G | E49: MAO CI - Servicios / Servicios (G) | F49: SI | G49: 1.0286084e+08 | H49: 1.0286084e+08 | I49: 5384284.5 | L49: =CATEGORIAS[[#This Row],[ADICIONALES]]+CATEGORIAS[[#This Row],[POM]] -> 1.0824512e+08 | M49: 48039267 | N49: 0 | O49: =CATEGORIAS[[#This Row],[PRODUCCION PARTIDAS ORIGINALES ACTUAL]]+CATEGORIAS[[#This Row],[PRODUCCION ADICIONALES ACTUAL]] -> 48039267 | P49: 32788492 | Q49: 0 | R49: =CATEGORIAS[[#This Row],[PRODUCCION ANTERIOR]]+CATEGORIAS[[#This Row],[PRODUCCION ADICIONALES ANTERIOR]] -> 32788492 | S49: 98070627 | T49: 254488 | U49: 11301392 | V49: =SUM(CATEGORIAS[[#This Row],[COSTO ACUMULADO AX]:[PROVISIONES]]) -> 1.0962651e+08 | W49: 67764198 | X49: 139335 | Y49: 6414004.9 | Z49: =SUM(CATEGORIAS[[#This Row],[COSTO ACUMULADO ANTERIOR]:[PROVISIONES ANTERIOR]]) -> 74317538 | AA49: =CATEGORIAS[[#This Row],[PRESUPUESTO FINAL PROYECTADO]]-CATEGORIAS[[#This Row],[TOTAL PRODUCCION ACTUAL]] -> 60205854 | AB49: 0 | AD49: -1381385.8 | AE49: =SUM(CATEGORIAS[[#This Row],[INVENTARIO]:[PROYECCION DE COSTO DEL SALDO]]) -> -1381385.8 | AG49: =+CATEGORIAS[[#This Row],[PRESUPUESTO FINAL PROYECTADO]]-CATEGORIAS[[#This Row],[COSTO REAL]]-CATEGORIAS[[#This Row],[PROYECCION TOTAL DE COSTO]] -> 0
A50: =+IFERROR(VLOOKUP(CATEGORIAS[[#This Row],[CATEGORIA2]],[1]HOMOLOGACION!$A$1:$I$571,9,FALSE),0) -> 1Y08 | B50: =+IFERROR(VLOOKUP(CATEGORIAS[[#This Row],[CATEGORIA2]],[1]HOMOLOGACION!$A$1:$C$571,3,FALSE),0) -> 1F08 | C50: =+IFERROR(VLOOKUP(CATEGORIAS[[#This Row],[CATEGORIA2]],[1]HOMOLOGACION!$A$1:$D$571,4,FALSE),0) -> Topografia | D50: 12-5902-000G | E50: MAO CI - Servicios / Topografía (G) | F50: SI | G50: 47989913 | H50: 47989913 | I50: 0 | L50: =CATEGORIAS[[#This Row],[ADICIONALES]]+CATEGORIAS[[#This Row],[POM]] -> 47989913 | M50: 22412809 | N50: 0 | O50: =CATEGORIAS[[#This Row],[PRODUCCION PARTIDAS ORIGINALES ACTUAL]]+CATEGORIAS[[#This Row],[PRODUCCION ADICIONALES ACTUAL]] -> 22412809 | P50: 15297532 | Q50: 0 | R50: =CATEGORIAS[[#This Row],[PRODUCCION ANTERIOR]]+CATEGORIAS[[#This Row],[PRODUCCION ADICIONALES ANTERIOR]] -> 15297532 | S50: 28154823 | U50: 3235002 | V50: =SUM(CATEGORIAS[[#This Row],[COSTO ACUMULADO AX]:[PROVISIONES]]) -> 31389825 | W50: 19050300 | Y50: 1704596.6 | Z50: =SUM(CATEGORIAS[[#This Row],[COSTO ACUMULADO ANTERIOR]:[PROVISIONES ANTERIOR]]) -> 20754897 | AA50: =CATEGORIAS[[#This Row],[PRESUPUESTO FINAL PROYECTADO]]-CATEGORIAS[[#This Row],[TOTAL PRODUCCION ACTUAL]] -> 25577104 | AB50: 0 | AD50: 16600088 | AE50: =SUM(CATEGORIAS[[#This Row],[INVENTARIO]:[PROYECCION DE COSTO DEL SALDO]]) -> 16600088 | AG50: =+CATEGORIAS[[#This Row],[PRESUPUESTO FINAL PROYECTADO]]-CATEGORIAS[[#This Row],[COSTO REAL]]-CATEGORIAS[[#This Row],[PROYECCION TOTAL DE COSTO]] -> 0
A51: =+IFERROR(VLOOKUP(CATEGORIAS[[#This Row],[CATEGORIA2]],[1]HOMOLOGACION!$A$1:$I$571,9,FALSE),0) -> 1Y11 | B51: =+IFERROR(VLOOKUP(CATEGORIAS[[#This Row],[CATEGORIA2]],[1]HOMOLOGACION!$A$1:$C$571,3,FALSE),0) -> 1F12 | C51: =+IFERROR(VLOOKUP(CATEGORIAS[[#This Row],[CATEGORIA2]],[1]HOMOLOGACION!$A$1:$D$571,4,FALSE),0) -> Provisiones | D51: 12-6001-000G | E51: MAO CI - Prov. Pers. Planta / PROVAC (G) | F51: NO | G51: 0 | H51: 0 | I51: 0 | L51: =CATEGORIAS[[#This Row],[ADICIONALES]]+CATEGORIAS[[#This Row],[POM]] -> 0 | M51: 0 | N51: 0 | O51: =CATEGORIAS[[#This Row],[PRODUCCION PARTIDAS ORIGINALES ACTUAL]]+CATEGORIAS[[#This Row],[PRODUCCION ADICIONALES ACTUAL]] -> 0 | P51: 0 | Q51: 0 | R51: =CATEGORIAS[[#This Row],[PRODUCCION ANTERIOR]]+CATEGORIAS[[#This Row],[PRODUCCION ADICIONALES ANTERIOR]] -> 0 | S51: 4480242 | T51: -4480242 | V51: =SUM(CATEGORIAS[[#This Row],[COSTO ACUMULADO AX]:[PROVISIONES]]) -> 0 | W51: 3497493 | X51: -3497493 | Z51: =SUM(CATEGORIAS[[#This Row],[COSTO ACUMULADO ANTERIOR]:[PROVISIONES ANTERIOR]]) -> 0 | AA51: =CATEGORIAS[[#This Row],[PRESUPUESTO FINAL PROYECTADO]]-CATEGORIAS[[#This Row],[TOTAL PRODUCCION ACTUAL]] -> 0 | AB51: 0 | AE51: =SUM(CATEGORIAS[[#This Row],[INVENTARIO]:[PROYECCION DE COSTO DEL SALDO]]) -> 0 | AG51: =+CATEGORIAS[[#This Row],[PRESUPUESTO FINAL PROYECTADO]]-CATEGORIAS[[#This Row],[COSTO REAL]]-CATEGORIAS[[#This Row],[PROYECCION TOTAL DE COSTO]] -> 0
A52: =+IFERROR(VLOOKUP(CATEGORIAS[[#This Row],[CATEGORIA2]],[1]HOMOLOGACION!$A$1:$I$571,9,FALSE),0) -> 1Y11 | B52: =+IFERROR(VLOOKUP(CATEGORIAS[[#This Row],[CATEGORIA2]],[1]HOMOLOGACION!$A$1:$C$571,3,FALSE),0) -> 1F12 | C52: =+IFERROR(VLOOKUP(CATEGORIAS[[#This Row],[CATEGORIA2]],[1]HOMOLOGACION!$A$1:$D$571,4,FALSE),0) -> Provisiones | D52: 12-6002-000G | E52: MAO CI - Prov. Pers. Planta / PIAS (G) | F52: NO | G52: 0 | H52: 0 | I52: 0 | L52: =CATEGORIAS[[#This Row],[ADICIONALES]]+CATEGORIAS[[#This Row],[POM]] -> 0 | M52: 0 | N52: 0 | O52: =CATEGORIAS[[#This Row],[PRODUCCION PARTIDAS ORIGINALES ACTUAL]]+CATEGORIAS[[#This Row],[PRODUCCION ADICIONALES ACTUAL]] -> 0 | P52: 0 | Q52: 0 | R52: =CATEGORIAS[[#This Row],[PRODUCCION ANTERIOR]]+CATEGORIAS[[#This Row],[PRODUCCION ADICIONALES ANTERIOR]] -> 0 | S52: 0 | V52: =SUM(CATEGORIAS[[#This Row],[COSTO ACUMULADO AX]:[PROVISIONES]]) -> 0 | W52: 0 | Z52: =SUM(CATEGORIAS[[#This Row],[COSTO ACUMULADO ANTERIOR]:[PROVISIONES ANTERIOR]]) -> 0 | AA52: =CATEGORIAS[[#This Row],[PRESUPUESTO FINAL PROYECTADO]]-CATEGORIAS[[#This Row],[TOTAL PRODUCCION ACTUAL]] -> 0 | AB52: 0 | AE52: =SUM(CATEGORIAS[[#This Row],[INVENTARIO]:[PROYECCION DE COSTO DEL SALDO]]) -> 0 | AG52: =+CATEGORIAS[[#This Row],[PRESUPUESTO FINAL PROYECTADO]]-CATEGORIAS[[#This Row],[COSTO REAL]]-CATEGORIAS[[#This Row],[PROYECCION TOTAL DE COSTO]] -> 0
A53: =+IFERROR(VLOOKUP(CATEGORIAS[[#This Row],[CATEGORIA2]],[1]HOMOLOGACION!$A$1:$I$571,9,FALSE),0) -> 1Y11 | B53: =+IFERROR(VLOOKUP(CATEGORIAS[[#This Row],[CATEGORIA2]],[1]HOMOLOGACION!$A$1:$C$571,3,FALSE),0) -> 1F13 | C53: =+IFERROR(VLOOKUP(CATEGORIAS[[#This Row],[CATEGORIA2]],[1]HOMOLOGACION!$A$1:$D$571,4,FALSE),0) -> Otros | D53: 12-7101-000G | E53: MAO CI - Multas (G) | F53: NO | G53: 0 | H53: 0 | I53: 0 | L53: =CATEGORIAS[[#This Row],[ADICIONALES]]+CATEGORIAS[[#This Row],[POM]] -> 0 | M53: 0 | N53: 0 | O53: =CATEGORIAS[[#This Row],[PRODUCCION PARTIDAS ORIGINALES ACTUAL]]+CATEGORIAS[[#This Row],[PRODUCCION ADICIONALES ACTUAL]] -> 0 | P53: 0 | Q53: 0 | R53: =CATEGORIAS[[#This Row],[PRODUCCION ANTERIOR]]+CATEGORIAS[[#This Row],[PRODUCCION ADICIONALES ANTERIOR]] -> 0 | S53: 0 | V53: =SUM(CATEGORIAS[[#This Row],[COSTO ACUMULADO AX]:[PROVISIONES]]) -> 0 | W53: 0 | Z53: =SUM(CATEGORIAS[[#This Row],[COSTO ACUMULADO ANTERIOR]:[PROVISIONES ANTERIOR]]) -> 0 | AA53: =CATEGORIAS[[#This Row],[PRESUPUESTO FINAL PROYECTADO]]-CATEGORIAS[[#This Row],[TOTAL PRODUCCION ACTUAL]] -> 0 | AB53: 0 | AE53: =SUM(CATEGORIAS[[#This Row],[INVENTARIO]:[PROYECCION DE COSTO DEL SALDO]]) -> 0 | AG53: =+CATEGORIAS[[#This Row],[PRESUPUESTO FINAL PROYECTADO]]-CATEGORIAS[[#This Row],[COSTO REAL]]-CATEGORIAS[[#This Row],[PROYECCION TOTAL DE COSTO]] -> 0
A54: =+IFERROR(VLOOKUP(CATEGORIAS[[#This Row],[CATEGORIA2]],[1]HOMOLOGACION!$A$1:$I$571,9,FALSE),0) -> 1Y11 | B54: =+IFERROR(VLOOKUP(CATEGORIAS[[#This Row],[CATEGORIA2]],[1]HOMOLOGACION!$A$1:$C$571,3,FALSE),0) -> 1F13 | C54: =+IFERROR(VLOOKUP(CATEGORIAS[[#This Row],[CATEGORIA2]],[1]HOMOLOGACION!$A$1:$D$571,4,FALSE),0) -> Otros | D54: 12-9999-990G | E54: MO / Personal Inclusion / (G) | F54: NO | G54: 0 | H54: 0 | I54: 0 | L54: =CATEGORIAS[[#This Row],[ADICIONALES]]+CATEGORIAS[[#This Row],[POM]] -> 0 | M54: 0 | N54: 0 | O54: =CATEGORIAS[[#This Row],[PRODUCCION PARTIDAS ORIGINALES ACTUAL]]+CATEGORIAS[[#This Row],[PRODUCCION ADICIONALES ACTUAL]] -> 0 | P54: 0 | Q54: 0 | R54: =CATEGORIAS[[#This Row],[PRODUCCION ANTERIOR]]+CATEGORIAS[[#This Row],[PRODUCCION ADICIONALES ANTERIOR]] -> 0 | S54: 605804 | T54: -605804 | V54: =SUM(CATEGORIAS[[#This Row],[COSTO ACUMULADO AX]:[PROVISIONES]]) -> 0 | W54: 246571 | X54: -246571 | Z54: =SUM(CATEGORIAS[[#This Row],[COSTO ACUMULADO ANTERIOR]:[PROVISIONES ANTERIOR]]) -> 0 | AA54: =CATEGORIAS[[#This Row],[PRESUPUESTO FINAL PROYECTADO]]-CATEGORIAS[[#This Row],[TOTAL PRODUCCION ACTUAL]] -> 0 | AB54: 0 | AE54: =SUM(CATEGORIAS[[#This Row],[INVENTARIO]:[PROYECCION DE COSTO DEL SALDO]]) -> 0 | AG54: =+CATEGORIAS[[#This Row],[PRESUPUESTO FINAL PROYECTADO]]-CATEGORIAS[[#This Row],[COSTO REAL]]-CATEGORIAS[[#This Row],[PROYECCION TOTAL DE COSTO]] -> 0
A55: =+IFERROR(VLOOKUP(CATEGORIAS[[#This Row],[CATEGORIA2]],[1]HOMOLOGACION!$A$1:$I$571,9,FALSE),0) -> 0A02 | B55: =+IFERROR(VLOOKUP(CATEGORIAS[[#This Row],[CATEGORIA2]],[1]HOMOLOGACION!$A$1:$C$571,3,FALSE),0) -> 0B01 | C55: =+IFERROR(VLOOKUP(CATEGORIAS[[#This Row],[CATEGORIA2]],[1]HOMOLOGACION!$A$1:$D$571,4,FALSE),0) -> Civil | D55: 21-0102-010A | E55: MAT CD - Civil / Hormigón / Hormigón (A) | F55: SI | G55: 12119811 | H55: 12119811 | I55: 8873088.9 | L55: =CATEGORIAS[[#This Row],[ADICIONALES]]+CATEGORIAS[[#This Row],[POM]] -> 20992899 | M55: 11511894 | N55: 0 | O55: =CATEGORIAS[[#This Row],[PRODUCCION PARTIDAS ORIGINALES ACTUAL]]+CATEGORIAS[[#This Row],[PRODUCCION ADICIONALES ACTUAL]] -> 11511894 | P55: 11335042 | Q55: 0 | R55: =CATEGORIAS[[#This Row],[PRODUCCION ANTERIOR]]+CATEGORIAS[[#This Row],[PRODUCCION ADICIONALES ANTERIOR]] -> 11335042 | S55: 10524004 | V55: =SUM(CATEGORIAS[[#This Row],[COSTO ACUMULADO AX]:[PROVISIONES]]) -> 10524004 | W55: 10189810 | Z55: =SUM(CATEGORIAS[[#This Row],[COSTO ACUMULADO ANTERIOR]:[PROVISIONES ANTERIOR]]) -> 10189810 | AA55: =CATEGORIAS[[#This Row],[PRESUPUESTO FINAL PROYECTADO]]-CATEGORIAS[[#This Row],[TOTAL PRODUCCION ACTUAL]] -> 9481005.2 | AB55: 0 | AD55: 10468895 | AE55: =SUM(CATEGORIAS[[#This Row],[INVENTARIO]:[PROYECCION DE COSTO DEL SALDO]]) -> 10468895 | AG55: =+CATEGORIAS[[#This Row],[PRESUPUESTO FINAL PROYECTADO]]-CATEGORIAS[[#This Row],[COSTO REAL]]-CATEGORIAS[[#This Row],[PROYECCION TOTAL DE COSTO]] -> 0
A56: =+IFERROR(VLOOKUP(CATEGORIAS[[#This Row],[CATEGORIA2]],[1]HOMOLOGACION!$A$1:$I$571,9,FALSE),0) -> 0A02 | B56: =+IFERROR(VLOOKUP(CATEGORIAS[[#This Row],[CATEGORIA2]],[1]HOMOLOGACION!$A$1:$C$571,3,FALSE),0) -> 0B01 | C56: =+IFERROR(VLOOKUP(CATEGORIAS[[#This Row],[CATEGORIA2]],[1]HOMOLOGACION!$A$1:$D$571,4,FALSE),0) -> Civil | D56: 21-0102-010G | E56: MAT CD - Civil / Hormigón / Hormigón (G) | F56: NO | G56: 0 | H56: 0 | I56: 0 | L56: =CATEGORIAS[[#This Row],[ADICIONALES]]+CATEGORIAS[[#This Row],[POM]] -> 0 | M56: 0 | N56: 0 | O56: =CATEGORIAS[[#This Row],[PRODUCCION PARTIDAS ORIGINALES ACTUAL]]+CATEGORIAS[[#This Row],[PRODUCCION ADICIONALES ACTUAL]] -> 0 | P56: 0 | Q56: 0 | R56: =CATEGORIAS[[#This Row],[PRODUCCION ANTERIOR]]+CATEGORIAS[[#This Row],[PRODUCCION ADICIONALES ANTERIOR]] -> 0 | S56: 0 | V56: =SUM(CATEGORIAS[[#This Row],[COSTO ACUMULADO AX]:[PROVISIONES]]) -> 0 | W56: 0 | Z56: =SUM(CATEGORIAS[[#This Row],[COSTO ACUMULADO ANTERIOR]:[PROVISIONES ANTERIOR]]) -> 0 | AA56: =CATEGORIAS[[#This Row],[PRESUPUESTO FINAL PROYECTADO]]-CATEGORIAS[[#This Row],[TOTAL PRODUCCION ACTUAL]] -> 0 | AB56: 0 | AE56: =SUM(CATEGORIAS[[#This Row],[INVENTARIO]:[PROYECCION DE COSTO DEL SALDO]]) -> 0 | AG56: =+CATEGORIAS[[#This Row],[PRESUPUESTO FINAL PROYECTADO]]-CATEGORIAS[[#This Row],[COSTO REAL]]-CATEGORIAS[[#This Row],[PROYECCION TOTAL DE COSTO]] -> 0
A57: =+IFERROR(VLOOKUP(CATEGORIAS[[#This Row],[CATEGORIA2]],[1]HOMOLOGACION!$A$1:$I$571,9,FALSE),0) -> 0A02 | B57: =+IFERROR(VLOOKUP(CATEGORIAS[[#This Row],[CATEGORIA2]],[1]HOMOLOGACION!$A$1:$C$571,3,FALSE),0) -> 0B01 | C57: =+IFERROR(VLOOKUP(CATEGORIAS[[#This Row],[CATEGORIA2]],[1]HOMOLOGACION!$A$1:$D$571,4,FALSE),0) -> Civil | D57: 21-0102-020A | E57: MAT CD - Civil / Hormigón / Hormigón Prefabricado (A) | F57: NO | G57: 0 | H57: 0 | I57: 0 | L57: =CATEGORIAS[[#This Row],[ADICIONALES]]+CATEGORIAS[[#This Row],[POM]] -> 0 | M57: 0 | N57: 0 | O57: =CATEGORIAS[[#This Row],[PRODUCCION PARTIDAS ORIGINALES ACTUAL]]+CATEGORIAS[[#This Row],[PRODUCCION ADICIONALES ACTUAL]] -> 0 | P57: 0 | Q57: 0 | R57: =CATEGORIAS[[#This Row],[PRODUCCION ANTERIOR]]+CATEGORIAS[[#This Row],[PRODUCCION ADICIONALES ANTERIOR]] -> 0 | S57: 0 | V57: =SUM(CATEGORIAS[[#This Row],[COSTO ACUMULADO AX]:[PROVISIONES]]) -> 0 | W57: 0 | Z57: =SUM(CATEGORIAS[[#This Row],[COSTO ACUMULADO ANTERIOR]:[PROVISIONES ANTERIOR]]) -> 0 | AA57: =CATEGORIAS[[#This Row],[PRESUPUESTO FINAL PROYECTADO]]-CATEGORIAS[[#This Row],[TOTAL PRODUCCION ACTUAL]] -> 0 | AB57: 0 | AE57: =SUM(CATEGORIAS[[#This Row],[INVENTARIO]:[PROYECCION DE COSTO DEL SALDO]]) -> 0 | AG57: =+CATEGORIAS[[#This Row],[PRESUPUESTO FINAL PROYECTADO]]-CATEGORIAS[[#This Row],[COSTO REAL]]-CATEGORIAS[[#This Row],[PROYECCION TOTAL DE COSTO]] -> 0
A58: =+IFERROR(VLOOKUP(CATEGORIAS[[#This Row],[CATEGORIA2]],[1]HOMOLOGACION!$A$1:$I$571,9,FALSE),0) -> 0A02 | B58: =+IFERROR(VLOOKUP(CATEGORIAS[[#This Row],[CATEGORIA2]],[1]HOMOLOGACION!$A$1:$C$571,3,FALSE),0) -> 0B01 | C58: =+IFERROR(VLOOKUP(CATEGORIAS[[#This Row],[CATEGORIA2]],[1]HOMOLOGACION!$A$1:$D$571,4,FALSE),0) -> Civil | D58: 21-0102-020G | E58: MAT CD - Civil / Hormigón / Hormigón Prefabricado (G) | F58: NO | G58: 0 | H58: 0 | I58: 0 | L58: =CATEGORIAS[[#This Row],[ADICIONALES]]+CATEGORIAS[[#This Row],[POM]] -> 0 | M58: 0 | N58: 0 | O58: =CATEGORIAS[[#This Row],[PRODUCCION PARTIDAS ORIGINALES ACTUAL]]+CATEGORIAS[[#This Row],[PRODUCCION ADICIONALES ACTUAL]] -> 0 | P58: 0 | Q58: 0 | R58: =CATEGORIAS[[#This Row],[PRODUCCION ANTERIOR]]+CATEGORIAS[[#This Row],[PRODUCCION ADICIONALES ANTERIOR]] -> 0 | S58: 0 | V58: =SUM(CATEGORIAS[[#This Row],[COSTO ACUMULADO AX]:[PROVISIONES]]) -> 0 | W58: 0 | Z58: =SUM(CATEGORIAS[[#This Row],[COSTO ACUMULADO ANTERIOR]:[PROVISIONES ANTERIOR]]) -> 0 | AA58: =CATEGORIAS[[#This Row],[PRESUPUESTO FINAL PROYECTADO]]-CATEGORIAS[[#This Row],[TOTAL PRODUCCION ACTUAL]] -> 0 | AB58: 0 | AE58: =SUM(CATEGORIAS[[#This Row],[INVENTARIO]:[PROYECCION DE COSTO DEL SALDO]]) -> 0 | AG58: =+CATEGORIAS[[#This Row],[PRESUPUESTO FINAL PROYECTADO]]-CATEGORIAS[[#This Row],[COSTO REAL]]-CATEGORIAS[[#This Row],[PROYECCION TOTAL DE COSTO]] -> 0
A59: =+IFERROR(VLOOKUP(CATEGORIAS[[#This Row],[CATEGORIA2]],[1]HOMOLOGACION!$A$1:$I$571,9,FALSE),0) -> 0A02 | B59: =+IFERROR(VLOOKUP(CATEGORIAS[[#This Row],[CATEGORIA2]],[1]HOMOLOGACION!$A$1:$C$571,3,FALSE),0) -> 0B01 | C59: =+IFERROR(VLOOKUP(CATEGORIAS[[#This Row],[CATEGORIA2]],[1]HOMOLOGACION!$A$1:$D$571,4,FALSE),0) -> Civil | D59: 21-0102-030A | E59: MAT CD - Civil / Hormigón / Flete prefabricado (A) | F59: NO | G59: 0 | H59: 0 | I59: 0 | L59: =CATEGORIAS[[#This Row],[ADICIONALES]]+CATEGORIAS[[#This Row],[POM]] -> 0 | M59: 0 | N59: 0 | O59: =CATEGORIAS[[#This Row],[PRODUCCION PARTIDAS ORIGINALES ACTUAL]]+CATEGORIAS[[#This Row],[PRODUCCION ADICIONALES ACTUAL]] -> 0 | P59: 0 | Q59: 0 | R59: =CATEGORIAS[[#This Row],[PRODUCCION ANTERIOR]]+CATEGORIAS[[#This Row],[PRODUCCION ADICIONALES ANTERIOR]] -> 0 | S59: 0 | V59: =SUM(CATEGORIAS[[#This Row],[COSTO ACUMULADO AX]:[PROVISIONES]]) -> 0 | W59: 0 | Z59: =SUM(CATEGORIAS[[#This Row],[COSTO ACUMULADO ANTERIOR]:[PROVISIONES ANTERIOR]]) -> 0 | AA59: =CATEGORIAS[[#This Row],[PRESUPUESTO FINAL PROYECTADO]]-CATEGORIAS[[#This Row],[TOTAL PRODUCCION ACTUAL]] -> 0 | AB59: 0 | AE59: =SUM(CATEGORIAS[[#This Row],[INVENTARIO]:[PROYECCION DE COSTO DEL SALDO]]) -> 0 | AG59: =+CATEGORIAS[[#This Row],[PRESUPUESTO FINAL PROYECTADO]]-CATEGORIAS[[#This Row],[COSTO REAL]]-CATEGORIAS[[#This Row],[PROYECCION TOTAL DE COSTO]] -> 0
A60: =+IFERROR(VLOOKUP(CATEGORIAS[[#This Row],[CATEGORIA2]],[1]HOMOLOGACION!$A$1:$I$571,9,FALSE),0) -> 0A02 | B60: =+IFERROR(VLOOKUP(CATEGORIAS[[#This Row],[CATEGORIA2]],[1]HOMOLOGACION!$A$1:$C$571,3,FALSE),0) -> 0B01 | C60: =+IFERROR(VLOOKUP(CATEGORIAS[[#This Row],[CATEGORIA2]],[1]HOMOLOGACION!$A$1:$D$571,4,FALSE),0) -> Civil | D60: 21-0102-030G | E60: MAT CD - Civil / Hormigón / Flete prefabricado (G) | F60: NO | G60: 0 | H60: 0 | I60: 0 | L60: =CATEGORIAS[[#This Row],[ADICIONALES]]+CATEGORIAS[[#This Row],[POM]] -> 0 | M60: 0 | N60: 0 | O60: =CATEGORIAS[[#This Row],[PRODUCCION PARTIDAS ORIGINALES ACTUAL]]+CATEGORIAS[[#This Row],[PRODUCCION ADICIONALES ACTUAL]] -> 0 | P60: 0 | Q60: 0 | R60: =CATEGORIAS[[#This Row],[PRODUCCION ANTERIOR]]+CATEGORIAS[[#This Row],[PRODUCCION ADICIONALES ANTERIOR]] -> 0 | S60: 0 | V60: =SUM(CATEGORIAS[[#This Row],[COSTO ACUMULADO AX]:[PROVISIONES]]) -> 0 | W60: 0 | Z60: =SUM(CATEGORIAS[[#This Row],[COSTO ACUMULADO ANTERIOR]:[PROVISIONES ANTERIOR]]) -> 0 | AA60: =CATEGORIAS[[#This Row],[PRESUPUESTO FINAL PROYECTADO]]-CATEGORIAS[[#This Row],[TOTAL PRODUCCION ACTUAL]] -> 0 | AB60: 0 | AE60: =SUM(CATEGORIAS[[#This Row],[INVENTARIO]:[PROYECCION DE COSTO DEL SALDO]]) -> 0 | AG60: =+CATEGORIAS[[#This Row],[PRESUPUESTO FINAL PROYECTADO]]-CATEGORIAS[[#This Row],[COSTO REAL]]-CATEGORIAS[[#This Row],[PROYECCION TOTAL DE COSTO]] -> 0
A61: =+IFERROR(VLOOKUP(CATEGORIAS[[#This Row],[CATEGORIA2]],[1]HOMOLOGACION!$A$1:$I$571,9,FALSE),0) -> 0A02 | B61: =+IFERROR(VLOOKUP(CATEGORIAS[[#This Row],[CATEGORIA2]],[1]HOMOLOGACION!$A$1:$C$571,3,FALSE),0) -> 0B01 | C61: =+IFERROR(VLOOKUP(CATEGORIAS[[#This Row],[CATEGORIA2]],[1]HOMOLOGACION!$A$1:$D$571,4,FALSE),0) -> Civil | D61: 21-0103-010A | E61: MAT CD - Civil / Moldaje / Moldajes (A) | F61: SI | G61: 325251.5 | H61: 325251.5 | I61: 322526.47 | L61: =CATEGORIAS[[#This Row],[ADICIONALES]]+CATEGORIAS[[#This Row],[POM]] -> 647777.97 | M61: 55757.4 | N61: 0 | O61: =CATEGORIAS[[#This Row],[PRODUCCION PARTIDAS ORIGINALES ACTUAL]]+CATEGORIAS[[#This Row],[PRODUCCION ADICIONALES ACTUAL]] -> 55757.4 | P61: 0 | Q61: 0 | R61: =CATEGORIAS[[#This Row],[PRODUCCION ANTERIOR]]+CATEGORIAS[[#This Row],[PRODUCCION ADICIONALES ANTERIOR]] -> 0 | S61: 0 | V61: =SUM(CATEGORIAS[[#This Row],[COSTO ACUMULADO AX]:[PROVISIONES]]) -> 0 | W61: 0 | Z61: =SUM(CATEGORIAS[[#This Row],[COSTO ACUMULADO ANTERIOR]:[PROVISIONES ANTERIOR]]) -> 0 | AA61: =CATEGORIAS[[#This Row],[PRESUPUESTO FINAL PROYECTADO]]-CATEGORIAS[[#This Row],[TOTAL PRODUCCION ACTUAL]] -> 592020.57 | AB61: 0 | AD61: 647777.97 | AE61: =SUM(CATEGORIAS[[#This Row],[INVENTARIO]:[PROYECCION DE COSTO DEL SALDO]]) -> 647777.97 | AG61: =+CATEGORIAS[[#This Row],[PRESUPUESTO FINAL PROYECTADO]]-CATEGORIAS[[#This Row],[COSTO REAL]]-CATEGORIAS[[#This Row],[PROYECCION TOTAL DE COSTO]] -> 0
A62: =+IFERROR(VLOOKUP(CATEGORIAS[[#This Row],[CATEGORIA2]],[1]HOMOLOGACION!$A$1:$I$571,9,FALSE),0) -> 0A02 | B62: =+IFERROR(VLOOKUP(CATEGORIAS[[#This Row],[CATEGORIA2]],[1]HOMOLOGACION!$A$1:$C$571,3,FALSE),0) -> 0B01 | C62: =+IFERROR(VLOOKUP(CATEGORIAS[[#This Row],[CATEGORIA2]],[1]HOMOLOGACION!$A$1:$D$571,4,FALSE),0) -> Civil | D62: 21-0103-010G | E62: MAT CD - Civil / Moldaje / Moldajes (G) | F62: NO | G62: 0 | H62: 0 | I62: 0 | L62: =CATEGORIAS[[#This Row],[ADICIONALES]]+CATEGORIAS[[#This Row],[POM]] -> 0 | M62: 0 | N62: 0 | O62: =CATEGORIAS[[#This Row],[PRODUCCION PARTIDAS ORIGINALES ACTUAL]]+CATEGORIAS[[#This Row],[PRODUCCION ADICIONALES ACTUAL]] -> 0 | P62: 0 | Q62: 0 | R62: =CATEGORIAS[[#This Row],[PRODUCCION ANTERIOR]]+CATEGORIAS[[#This Row],[PRODUCCION ADICIONALES ANTERIOR]] -> 0 | S62: 0 | V62: =SUM(CATEGORIAS[[#This Row],[COSTO ACUMULADO AX]:[PROVISIONES]]) -> 0 | W62: 0 | Z62: =SUM(CATEGORIAS[[#This Row],[COSTO ACUMULADO ANTERIOR]:[PROVISIONES ANTERIOR]]) -> 0 | AA62: =CATEGORIAS[[#This Row],[PRESUPUESTO FINAL PROYECTADO]]-CATEGORIAS[[#This Row],[TOTAL PRODUCCION ACTUAL]] -> 0 | AB62: 0 | AE62: =SUM(CATEGORIAS[[#This Row],[INVENTARIO]:[PROYECCION DE COSTO DEL SALDO]]) -> 0 | AG62: =+CATEGORIAS[[#This Row],[PRESUPUESTO FINAL PROYECTADO]]-CATEGORIAS[[#This Row],[COSTO REAL]]-CATEGORIAS[[#This Row],[PROYECCION TOTAL DE COSTO]] -> 0
A63: =+IFERROR(VLOOKUP(CATEGORIAS[[#This Row],[CATEGORIA2]],[1]HOMOLOGACION!$A$1:$I$571,9,FALSE),0) -> 0A02 | B63: =+IFERROR(VLOOKUP(CATEGORIAS[[#This Row],[CATEGORIA2]],[1]HOMOLOGACION!$A$1:$C$571,3,FALSE),0) -> 0B01 | C63: =+IFERROR(VLOOKUP(CATEGORIAS[[#This Row],[CATEGORIA2]],[1]HOMOLOGACION!$A$1:$D$571,4,FALSE),0) -> Civil | D63: 21-0104-010A | E63: MAT CD - Civil / Enfierradura / Varios (A) | F63: SI | G63: 4416803.3 | H63: 4416803.3 | I63: 5741832.8 | L63: =CATEGORIAS[[#This Row],[ADICIONALES]]+CATEGORIAS[[#This Row],[POM]] -> 10158636 | M63: 4169480.3 | N63: 0 | O63: =CATEGORIAS[[#This Row],[PRODUCCION PARTIDAS ORIGINALES ACTUAL]]+CATEGORIAS[[#This Row],[PRODUCCION ADICIONALES ACTUAL]] -> 4169480.3 | P63: 4117849.3 | Q63: 0 | R63: =CATEGORIAS[[#This Row],[PRODUCCION ANTERIOR]]+CATEGORIAS[[#This Row],[PRODUCCION ADICIONALES ANTERIOR]] -> 4117849.3 | S63: 0 | V63: =SUM(CATEGORIAS[[#This Row],[COSTO ACUMULADO AX]:[PROVISIONES]]) -> 0 | W63: 0 | Z63: =SUM(CATEGORIAS[[#This Row],[COSTO ACUMULADO ANTERIOR]:[PROVISIONES ANTERIOR]]) -> 0 | AA63: =CATEGORIAS[[#This Row],[PRESUPUESTO FINAL PROYECTADO]]-CATEGORIAS[[#This Row],[TOTAL PRODUCCION ACTUAL]] -> 5989155.8 | AB63: 0 | AD63: 10158636 | AE63: =SUM(CATEGORIAS[[#This Row],[INVENTARIO]:[PROYECCION DE COSTO DEL SALDO]]) -> 10158636 | AG63: =+CATEGORIAS[[#This Row],[PRESUPUESTO FINAL PROYECTADO]]-CATEGORIAS[[#This Row],[COSTO REAL]]-CATEGORIAS[[#This Row],[PROYECCION TOTAL DE COSTO]] -> 0
A64: =+IFERROR(VLOOKUP(CATEGORIAS[[#This Row],[CATEGORIA2]],[1]HOMOLOGACION!$A$1:$I$571,9,FALSE),0) -> 0A02 | B64: =+IFERROR(VLOOKUP(CATEGORIAS[[#This Row],[CATEGORIA2]],[1]HOMOLOGACION!$A$1:$C$571,3,FALSE),0) -> 0B01 | C64: =+IFERROR(VLOOKUP(CATEGORIAS[[#This Row],[CATEGORIA2]],[1]HOMOLOGACION!$A$1:$D$571,4,FALSE),0) -> Civil | D64: 21-0104-010G | E64: MAT CD - Civil / Enfierradura / Varios (G) | F64: NO | G64: 0 | H64: 0 | I64: 0 | L64: =CATEGORIAS[[#This Row],[ADICIONALES]]+CATEGORIAS[[#This Row],[POM]] -> 0 | M64: 0 | N64: 0 | O64: =CATEGORIAS[[#This Row],[PRODUCCION PARTIDAS ORIGINALES ACTUAL]]+CATEGORIAS[[#This Row],[PRODUCCION ADICIONALES ACTUAL]] -> 0 | P64: 0 | Q64: 0 | R64: =CATEGORIAS[[#This Row],[PRODUCCION ANTERIOR]]+CATEGORIAS[[#This Row],[PRODUCCION ADICIONALES ANTERIOR]] -> 0 | S64: 0 | V64: =SUM(CATEGORIAS[[#This Row],[COSTO ACUMULADO AX]:[PROVISIONES]]) -> 0 | W64: 0 | Z64: =SUM(CATEGORIAS[[#This Row],[COSTO ACUMULADO ANTERIOR]:[PROVISIONES ANTERIOR]]) -> 0 | AA64: =CATEGORIAS[[#This Row],[PRESUPUESTO FINAL PROYECTADO]]-CATEGORIAS[[#This Row],[TOTAL PRODUCCION ACTUAL]] -> 0 | AB64: 0 | AE64: =SUM(CATEGORIAS[[#This Row],[INVENTARIO]:[PROYECCION DE COSTO DEL SALDO]]) -> 0 | AG64: =+CATEGORIAS[[#This Row],[PRESUPUESTO FINAL PROYECTADO]]-CATEGORIAS[[#This Row],[COSTO REAL]]-CATEGORIAS[[#This Row],[PROYECCION TOTAL DE COSTO]] -> 0
A65: =+IFERROR(VLOOKUP(CATEGORIAS[[#This Row],[CATEGORIA2]],[1]HOMOLOGACION!$A$1:$I$571,9,FALSE),0) -> 0M02 | B65: =+IFERROR(VLOOKUP(CATEGORIAS[[#This Row],[CATEGORIA2]],[1]HOMOLOGACION!$A$1:$C$571,3,FALSE),0) -> 0B10 | C65: =+IFERROR(VLOOKUP(CATEGORIAS[[#This Row],[CATEGORIA2]],[1]HOMOLOGACION!$A$1:$D$571,4,FALSE),0) -> Arquitectura | D65: 21-0105-010A | E65: MAT CD - Civil / Arquitectura / Suministro Mat. Arq (A) | F65: NO | G65: 0 | H65: 0 | I65: 0 | L65: =CATEGORIAS[[#This Row],[ADICIONALES]]+CATEGORIAS[[#This Row],[POM]] -> 0 | M65: 0 | N65: 0 | O65: =CATEGORIAS[[#This Row],[PRODUCCION PARTIDAS ORIGINALES ACTUAL]]+CATEGORIAS[[#This Row],[PRODUCCION ADICIONALES ACTUAL]] -> 0 | P65: 0 | Q65: 0 | R65: =CATEGORIAS[[#This Row],[PRODUCCION ANTERIOR]]+CATEGORIAS[[#This Row],[PRODUCCION ADICIONALES ANTERIOR]] -> 0 | S65: 0 | V65: =SUM(CATEGORIAS[[#This Row],[COSTO ACUMULADO AX]:[PROVISIONES]]) -> 0 | W65: 0 | Z65: =SUM(CATEGORIAS[[#This Row],[COSTO ACUMULADO ANTERIOR]:[PROVISIONES ANTERIOR]]) -> 0 | AA65: =CATEGORIAS[[#This Row],[PRESUPUESTO FINAL PROYECTADO]]-CATEGORIAS[[#This Row],[TOTAL PRODUCCION ACTUAL]] -> 0 | AB65: 0 | AE65: =SUM(CATEGORIAS[[#This Row],[INVENTARIO]:[PROYECCION DE COSTO DEL SALDO]]) -> 0 | AG65: =+CATEGORIAS[[#This Row],[PRESUPUESTO FINAL PROYECTADO]]-CATEGORIAS[[#This Row],[COSTO REAL]]-CATEGORIAS[[#This Row],[PROYECCION TOTAL DE COSTO]] -> 0
A66: =+IFERROR(VLOOKUP(CATEGORIAS[[#This Row],[CATEGORIA2]],[1]HOMOLOGACION!$A$1:$I$571,9,FALSE),0) -> 0M02 | B66: =+IFERROR(VLOOKUP(CATEGORIAS[[#This Row],[CATEGORIA2]],[1]HOMOLOGACION!$A$1:$C$571,3,FALSE),0) -> 0B10 | C66: =+IFERROR(VLOOKUP(CATEGORIAS[[#This Row],[CATEGORIA2]],[1]HOMOLOGACION!$A$1:$D$571,4,FALSE),0) -> Arquitectura | D66: 21-0105-010G | E66: MAT CD - Civil / Arquitectura / Suministro Mat. Arq (G) | F66: NO | G66: 0 | H66: 0 | I66: 0 | L66: =CATEGORIAS[[#This Row],[ADICIONALES]]+CATEGORIAS[[#This Row],[POM]] -> 0 | M66: 0 | N66: 0 | O66: =CATEGORIAS[[#This Row],[PRODUCCION PARTIDAS ORIGINALES ACTUAL]]+CATEGORIAS[[#This Row],[PRODUCCION ADICIONALES ACTUAL]] -> 0 | P66: 0 | Q66: 0 | R66: =CATEGORIAS[[#This Row],[PRODUCCION ANTERIOR]]+CATEGORIAS[[#This Row],[PRODUCCION ADICIONALES ANTERIOR]] -> 0 | S66: 0 | V66: =SUM(CATEGORIAS[[#This Row],[COSTO ACUMULADO AX]:[PROVISIONES]]) -> 0 | W66: 0 | Z66: =SUM(CATEGORIAS[[#This Row],[COSTO ACUMULADO ANTERIOR]:[PROVISIONES ANTERIOR]]) -> 0 | AA66: =CATEGORIAS[[#This Row],[PRESUPUESTO FINAL PROYECTADO]]-CATEGORIAS[[#This Row],[TOTAL PRODUCCION ACTUAL]] -> 0 | AB66: 0 | AE66: =SUM(CATEGORIAS[[#This Row],[INVENTARIO]:[PROYECCION DE COSTO DEL SALDO]]) -> 0 | AG66: =+CATEGORIAS[[#This Row],[PRESUPUESTO FINAL PROYECTADO]]-CATEGORIAS[[#This Row],[COSTO REAL]]-CATEGORIAS[[#This Row],[PROYECCION TOTAL DE COSTO]] -> 0
A67: =+IFERROR(VLOOKUP(CATEGORIAS[[#This Row],[CATEGORIA2]],[1]HOMOLOGACION!$A$1:$I$571,9,FALSE),0) -> 0M02 | B67: =+IFERROR(VLOOKUP(CATEGORIAS[[#This Row],[CATEGORIA2]],[1]HOMOLOGACION!$A$1:$C$571,3,FALSE),0) -> 0B10 | C67: =+IFERROR(VLOOKUP(CATEGORIAS[[#This Row],[CATEGORIA2]],[1]HOMOLOGACION!$A$1:$D$571,4,FALSE),0) -> Arquitectura | D67: 21-0105-990A | E67: MAT CD - Civil / Arquitectura / Otros (A) | F67: NO | G67: 0 | H67: 0 | I67: 0 | L67: =CATEGORIAS[[#This Row],[ADICIONALES]]+CATEGORIAS[[#This Row],[POM]] -> 0 | M67: 0 | N67: 0 | O67: =CATEGORIAS[[#This Row],[PRODUCCION PARTIDAS ORIGINALES ACTUAL]]+CATEGORIAS[[#This Row],[PRODUCCION ADICIONALES ACTUAL]] -> 0 | P67: 0 | Q67: 0 | R67: =CATEGORIAS[[#This Row],[PRODUCCION ANTERIOR]]+CATEGORIAS[[#This Row],[PRODUCCION ADICIONALES ANTERIOR]] -> 0 | S67: 0 | V67: =SUM(CATEGORIAS[[#This Row],[COSTO ACUMULADO AX]:[PROVISIONES]]) -> 0 | W67: 0 | Z67: =SUM(CATEGORIAS[[#This Row],[COSTO ACUMULADO ANTERIOR]:[PROVISIONES ANTERIOR]]) -> 0 | AA67: =CATEGORIAS[[#This Row],[PRESUPUESTO FINAL PROYECTADO]]-CATEGORIAS[[#This Row],[TOTAL PRODUCCION ACTUAL]] -> 0 | AB67: 0 | AE67: =SUM(CATEGORIAS[[#This Row],[INVENTARIO]:[PROYECCION DE COSTO DEL SALDO]]) -> 0 | AG67: =+CATEGORIAS[[#This Row],[PRESUPUESTO FINAL PROYECTADO]]-CATEGORIAS[[#This Row],[COSTO REAL]]-CATEGORIAS[[#This Row],[PROYECCION TOTAL DE COSTO]] -> 0
A68: =+IFERROR(VLOOKUP(CATEGORIAS[[#This Row],[CATEGORIA2]],[1]HOMOLOGACION!$A$1:$I$571,9,FALSE),0) -> 0M02 | B68: =+IFERROR(VLOOKUP(CATEGORIAS[[#This Row],[CATEGORIA2]],[1]HOMOLOGACION!$A$1:$C$571,3,FALSE),0) -> 0B10 | C68: =+IFERROR(VLOOKUP(CATEGORIAS[[#This Row],[CATEGORIA2]],[1]HOMOLOGACION!$A$1:$D$571,4,FALSE),0) -> Arquitectura | D68: 21-0105-990G | E68: MAT CD - Civil / Arquitectura / Otros (G) | F68: NO | G68: 0 | H68: 0 | I68: 0 | L68: =CATEGORIAS[[#This Row],[ADICIONALES]]+CATEGORIAS[[#This Row],[POM]] -> 0 | M68: 0 | N68: 0 | O68: =CATEGORIAS[[#This Row],[PRODUCCION PARTIDAS ORIGINALES ACTUAL]]+CATEGORIAS[[#This Row],[PRODUCCION ADICIONALES ACTUAL]] -> 0 | P68: 0 | Q68: 0 | R68: =CATEGORIAS[[#This Row],[PRODUCCION ANTERIOR]]+CATEGORIAS[[#This Row],[PRODUCCION ADICIONALES ANTERIOR]] -> 0 | S68: 0 | V68: =SUM(CATEGORIAS[[#This Row],[COSTO ACUMULADO AX]:[PROVISIONES]]) -> 0 | W68: 0 | Z68: =SUM(CATEGORIAS[[#This Row],[COSTO ACUMULADO ANTERIOR]:[PROVISIONES ANTERIOR]]) -> 0 | AA68: =CATEGORIAS[[#This Row],[PRESUPUESTO FINAL PROYECTADO]]-CATEGORIAS[[#This Row],[TOTAL PRODUCCION ACTUAL]] -> 0 | AB68: 0 | AE68: =SUM(CATEGORIAS[[#This Row],[INVENTARIO]:[PROYECCION DE COSTO DEL SALDO]]) -> 0 | AG68: =+CATEGORIAS[[#This Row],[PRESUPUESTO FINAL PROYECTADO]]-CATEGORIAS[[#This Row],[COSTO REAL]]-CATEGORIAS[[#This Row],[PROYECCION TOTAL DE COSTO]] -> 0
A69: =+IFERROR(VLOOKUP(CATEGORIAS[[#This Row],[CATEGORIA2]],[1]HOMOLOGACION!$A$1:$I$571,9,FALSE),0) -> 0A02 | B69: =+IFERROR(VLOOKUP(CATEGORIAS[[#This Row],[CATEGORIA2]],[1]HOMOLOGACION!$A$1:$C$571,3,FALSE),0) -> 0B01 | C69: =+IFERROR(VLOOKUP(CATEGORIAS[[#This Row],[CATEGORIA2]],[1]HOMOLOGACION!$A$1:$D$571,4,FALSE),0) -> Civil | D69: 21-0111-010A | E69: MAT CD - Civil / Pernos e Insertos / Pernos e Insertos (A) | F69: SI | G69: 2327122.5 | H69: 2327122.5 | I69: 278691.19 | L69: =CATEGORIAS[[#This Row],[ADICIONALES]]+CATEGORIAS[[#This Row],[POM]] -> 2605813.7 | M69: 1259647.5 | N69: 0 | O69: =CATEGORIAS[[#This Row],[PRODUCCION PARTIDAS ORIGINALES ACTUAL]]+CATEGORIAS[[#This Row],[PRODUCCION ADICIONALES ACTUAL]] -> 1259647.5 | P69: 1224997.5 | Q69: 0 | R69: =CATEGORIAS[[#This Row],[PRODUCCION ANTERIOR]]+CATEGORIAS[[#This Row],[PRODUCCION ADICIONALES ANTERIOR]] -> 1224997.5 | S69: 58800 | V69: =SUM(CATEGORIAS[[#This Row],[COSTO ACUMULADO AX]:[PROVISIONES]]) -> 58800 | W69: 58800 | Z69: =SUM(CATEGORIAS[[#This Row],[COSTO ACUMULADO ANTERIOR]:[PROVISIONES ANTERIOR]]) -> 58800 | AA69: =CATEGORIAS[[#This Row],[PRESUPUESTO FINAL PROYECTADO]]-CATEGORIAS[[#This Row],[TOTAL PRODUCCION ACTUAL]] -> 1346166.2 | AB69: 164910 | AD69: 2382103.7 | AE69: =SUM(CATEGORIAS[[#This Row],[INVENTARIO]:[PROYECCION DE COSTO DEL SALDO]]) -> 2547013.7 | AG69: =+CATEGORIAS[[#This Row],[PRESUPUESTO FINAL PROYECTADO]]-CATEGORIAS[[#This Row],[COSTO REAL]]-CATEGORIAS[[#This Row],[PROYECCION TOTAL DE COSTO]] -> 0
A70: =+IFERROR(VLOOKUP(CATEGORIAS[[#This Row],[CATEGORIA2]],[1]HOMOLOGACION!$A$1:$I$571,9,FALSE),0) -> 0A02 | B70: =+IFERROR(VLOOKUP(CATEGORIAS[[#This Row],[CATEGORIA2]],[1]HOMOLOGACION!$A$1:$C$571,3,FALSE),0) -> 0B01 | C70: =+IFERROR(VLOOKUP(CATEGORIAS[[#This Row],[CATEGORIA2]],[1]HOMOLOGACION!$A$1:$D$571,4,FALSE),0) -> Civil | D70: 21-0111-010G | E70: MAT CD - Civil / Pernos e Insertos / Pernos e Insertos (G) | F70: NO | G70: 0 | H70: 0 | I70: 0 | L70: =CATEGORIAS[[#This Row],[ADICIONALES]]+CATEGORIAS[[#This Row],[POM]] -> 0 | M70: 0 | N70: 0 | O70: =CATEGORIAS[[#This Row],[PRODUCCION PARTIDAS ORIGINALES ACTUAL]]+CATEGORIAS[[#This Row],[PRODUCCION ADICIONALES ACTUAL]] -> 0 | P70: 0 | Q70: 0 | R70: =CATEGORIAS[[#This Row],[PRODUCCION ANTERIOR]]+CATEGORIAS[[#This Row],[PRODUCCION ADICIONALES ANTERIOR]] -> 0 | S70: 0 | V70: =SUM(CATEGORIAS[[#This Row],[COSTO ACUMULADO AX]:[PROVISIONES]]) -> 0 | W70: 0 | Z70: =SUM(CATEGORIAS[[#This Row],[COSTO ACUMULADO ANTERIOR]:[PROVISIONES ANTERIOR]]) -> 0 | AA70: =CATEGORIAS[[#This Row],[PRESUPUESTO FINAL PROYECTADO]]-CATEGORIAS[[#This Row],[TOTAL PRODUCCION ACTUAL]] -> 0 | AB70: 0 | AE70: =SUM(CATEGORIAS[[#This Row],[INVENTARIO]:[PROYECCION DE COSTO DEL SALDO]]) -> 0 | AG70: =+CATEGORIAS[[#This Row],[PRESUPUESTO FINAL PROYECTADO]]-CATEGORIAS[[#This Row],[COSTO REAL]]-CATEGORIAS[[#This Row],[PROYECCION TOTAL DE COSTO]] -> 0
A71: =+IFERROR(VLOOKUP(CATEGORIAS[[#This Row],[CATEGORIA2]],[1]HOMOLOGACION!$A$1:$I$571,9,FALSE),0) -> 0A02 | B71: =+IFERROR(VLOOKUP(CATEGORIAS[[#This Row],[CATEGORIA2]],[1]HOMOLOGACION!$A$1:$C$571,3,FALSE),0) -> 0B01 | C71: =+IFERROR(VLOOKUP(CATEGORIAS[[#This Row],[CATEGORIA2]],[1]HOMOLOGACION!$A$1:$D$571,4,FALSE),0) -> Civil | D71: 21-0199-010A | E71: MAT CD - Civil / Otros / Materiales varios (A) | F71: SI | G71: 45413244 | H71: 45413244 | I71: 196620.74 | L71: =CATEGORIAS[[#This Row],[ADICIONALES]]+CATEGORIAS[[#This Row],[POM]] -> 45609865 | M71: 9334656 | N71: 0 | O71: =CATEGORIAS[[#This Row],[PRODUCCION PARTIDAS ORIGINALES ACTUAL]]+CATEGORIAS[[#This Row],[PRODUCCION ADICIONALES ACTUAL]] -> 9334656 | P71: 6308000.9 | Q71: 16078.892 | R71: =CATEGORIAS[[#This Row],[PRODUCCION ANTERIOR]]+CATEGORIAS[[#This Row],[PRODUCCION ADICIONALES ANTERIOR]] -> 6324079.8 | S71: 11096473 | V71: =SUM(CATEGORIAS[[#This Row],[COSTO ACUMULADO AX]:[PROVISIONES]]) -> 11096473 | W71: 5288752 | Z71: =SUM(CATEGORIAS[[#This Row],[COSTO ACUMULADO ANTERIOR]:[PROVISIONES ANTERIOR]]) -> 5288752 | AA71: =CATEGORIAS[[#This Row],[PRESUPUESTO FINAL PROYECTADO]]-CATEGORIAS[[#This Row],[TOTAL PRODUCCION ACTUAL]] -> 36275209 | AB71: 20085947 | AD71: 14427445 | AE71: =SUM(CATEGORIAS[[#This Row],[INVENTARIO]:[PROYECCION DE COSTO DEL SALDO]]) -> 34513392 | AG71: =+CATEGORIAS[[#This Row],[PRESUPUESTO FINAL PROYECTADO]]-CATEGORIAS[[#This Row],[COSTO REAL]]-CATEGORIAS[[#This Row],[PROYECCION TOTAL DE COSTO]] -> 0
A72: =+IFERROR(VLOOKUP(CATEGORIAS[[#This Row],[CATEGORIA2]],[1]HOMOLOGACION!$A$1:$I$571,9,FALSE),0) -> 0A02 | B72: =+IFERROR(VLOOKUP(CATEGORIAS[[#This Row],[CATEGORIA2]],[1]HOMOLOGACION!$A$1:$C$571,3,FALSE),0) -> 0B01 | C72: =+IFERROR(VLOOKUP(CATEGORIAS[[#This Row],[CATEGORIA2]],[1]HOMOLOGACION!$A$1:$D$571,4,FALSE),0) -> Civil | D72: 21-0199-010G | E72: MAT CD - Civil / Otros / Materiales varios (G) | F72: NO | G72: 0 | H72: 0 | I72: 0 | L72: =CATEGORIAS[[#This Row],[ADICIONALES]]+CATEGORIAS[[#This Row],[POM]] -> 0 | M72: 0 | N72: 0 | O72: =CATEGORIAS[[#This Row],[PRODUCCION PARTIDAS ORIGINALES ACTUAL]]+CATEGORIAS[[#This Row],[PRODUCCION ADICIONALES ACTUAL]] -> 0 | P72: 0 | Q72: 0 | R72: =CATEGORIAS[[#This Row],[PRODUCCION ANTERIOR]]+CATEGORIAS[[#This Row],[PRODUCCION ADICIONALES ANTERIOR]] -> 0 | S72: -7 | V72: =SUM(CATEGORIAS[[#This Row],[COSTO ACUMULADO AX]:[PROVISIONES]]) -> -7 | W72: -7 | Y72: 7 | Z72: =SUM(CATEGORIAS[[#This Row],[COSTO ACUMULADO ANTERIOR]:[PROVISIONES ANTERIOR]]) -> 0 | AA72: =CATEGORIAS[[#This Row],[PRESUPUESTO FINAL PROYECTADO]]-CATEGORIAS[[#This Row],[TOTAL PRODUCCION ACTUAL]] -> 0 | AB72: 0 | AE72: =SUM(CATEGORIAS[[#This Row],[INVENTARIO]:[PROYECCION DE COSTO DEL SALDO]]) -> 0 | AG72: =+CATEGORIAS[[#This Row],[PRESUPUESTO FINAL PROYECTADO]]-CATEGORIAS[[#This Row],[COSTO REAL]]-CATEGORIAS[[#This Row],[PROYECCION TOTAL DE COSTO]] -> 7
A73: =+IFERROR(VLOOKUP(CATEGORIAS[[#This Row],[CATEGORIA2]],[1]HOMOLOGACION!$A$1:$I$571,9,FALSE),0) -> 0B02 | B73: =+IFERROR(VLOOKUP(CATEGORIAS[[#This Row],[CATEGORIA2]],[1]HOMOLOGACION!$A$1:$C$571,3,FALSE),0) -> 0B02 | C73: =+IFERROR(VLOOKUP(CATEGORIAS[[#This Row],[CATEGORIA2]],[1]HOMOLOGACION!$A$1:$D$571,4,FALSE),0) -> Estructura | D73: 21-0212-010A | E73: MAT CD - Estructura / Suministro Estructura / Todos (A) | F73: SI | G73: 16891600 | H73: 16891600 | I73: 0 | L73: =CATEGORIAS[[#This Row],[ADICIONALES]]+CATEGORIAS[[#This Row],[POM]] -> 16891600 | M73: 16891600 | N73: 0 | O73: =CATEGORIAS[[#This Row],[PRODUCCION PARTIDAS ORIGINALES ACTUAL]]+CATEGORIAS[[#This Row],[PRODUCCION ADICIONALES ACTUAL]] -> 16891600 | P73: 16891600 | Q73: 0 | R73: =CATEGORIAS[[#This Row],[PRODUCCION ANTERIOR]]+CATEGORIAS[[#This Row],[PRODUCCION ADICIONALES ANTERIOR]] -> 16891600 | S73: 0 | V73: =SUM(CATEGORIAS[[#This Row],[COSTO ACUMULADO AX]:[PROVISIONES]]) -> 0 | W73: 0 | Z73: =SUM(CATEGORIAS[[#This Row],[COSTO ACUMULADO ANTERIOR]:[PROVISIONES ANTERIOR]]) -> 0 | AA73: =CATEGORIAS[[#This Row],[PRESUPUESTO FINAL PROYECTADO]]-CATEGORIAS[[#This Row],[TOTAL PRODUCCION ACTUAL]] -> 0 | AB73: 0 | AD73: 16891600 | AE73: =SUM(CATEGORIAS[[#This Row],[INVENTARIO]:[PROYECCION DE COSTO DEL SALDO]]) -> 16891600 | AG73: =+CATEGORIAS[[#This Row],[PRESUPUESTO FINAL PROYECTADO]]-CATEGORIAS[[#This Row],[COSTO REAL]]-CATEGORIAS[[#This Row],[PROYECCION TOTAL DE COSTO]] -> 0
A74: =+IFERROR(VLOOKUP(CATEGORIAS[[#This Row],[CATEGORIA2]],[1]HOMOLOGACION!$A$1:$I$571,9,FALSE),0) -> 0B02 | B74: =+IFERROR(VLOOKUP(CATEGORIAS[[#This Row],[CATEGORIA2]],[1]HOMOLOGACION!$A$1:$C$571,3,FALSE),0) -> 0B02 | C74: =+IFERROR(VLOOKUP(CATEGORIAS[[#This Row],[CATEGORIA2]],[1]HOMOLOGACION!$A$1:$D$571,4,FALSE),0) -> Estructura | D74: 21-0212-010G | E74: MAT CD - Estructura / Suministro Estructura / Todos (G) | F74: NO | G74: 0 | H74: 0 | I74: 0 | L74: =CATEGORIAS[[#This Row],[ADICIONALES]]+CATEGORIAS[[#This Row],[POM]] -> 0 | M74: 0 | N74: 0 | O74: =CATEGORIAS[[#This Row],[PRODUCCION PARTIDAS ORIGINALES ACTUAL]]+CATEGORIAS[[#This Row],[PRODUCCION ADICIONALES ACTUAL]] -> 0 | P74: 0 | Q74: 0 | R74: =CATEGORIAS[[#This Row],[PRODUCCION ANTERIOR]]+CATEGORIAS[[#This Row],[PRODUCCION ADICIONALES ANTERIOR]] -> 0 | S74: 0 | V74: =SUM(CATEGORIAS[[#This Row],[COSTO ACUMULADO AX]:[PROVISIONES]]) -> 0 | W74: 0 | Z74: =SUM(CATEGORIAS[[#This Row],[COSTO ACUMULADO ANTERIOR]:[PROVISIONES ANTERIOR]]) -> 0 | AA74: =CATEGORIAS[[#This Row],[PRESUPUESTO FINAL PROYECTADO]]-CATEGORIAS[[#This Row],[TOTAL PRODUCCION ACTUAL]] -> 0 | AB74: 0 | AE74: =SUM(CATEGORIAS[[#This Row],[INVENTARIO]:[PROYECCION DE COSTO DEL SALDO]]) -> 0 | AG74: =+CATEGORIAS[[#This Row],[PRESUPUESTO FINAL PROYECTADO]]-CATEGORIAS[[#This Row],[COSTO REAL]]-CATEGORIAS[[#This Row],[PROYECCION TOTAL DE COSTO]] -> 0
A75: =+IFERROR(VLOOKUP(CATEGORIAS[[#This Row],[CATEGORIA2]],[1]HOMOLOGACION!$A$1:$I$571,9,FALSE),0) -> 0B02 | B75: =+IFERROR(VLOOKUP(CATEGORIAS[[#This Row],[CATEGORIA2]],[1]HOMOLOGACION!$A$1:$C$571,3,FALSE),0) -> 0B02 | C75: =+IFERROR(VLOOKUP(CATEGORIAS[[#This Row],[CATEGORIA2]],[1]HOMOLOGACION!$A$1:$D$571,4,FALSE),0) -> Estructura | D75: 21-0213-010A | E75: MAT CD - Estructura / Pernos / Todos (A) | F75: SI | G75: 624349.44 | H75: 624349.44 | I75: 0 | L75: =CATEGORIAS[[#This Row],[ADICIONALES]]+CATEGORIAS[[#This Row],[POM]] -> 624349.44 | M75: 134895.29 | N75: 0 | O75: =CATEGORIAS[[#This Row],[PRODUCCION PARTIDAS ORIGINALES ACTUAL]]+CATEGORIAS[[#This Row],[PRODUCCION ADICIONALES ACTUAL]] -> 134895.29 | P75: 115022.69 | Q75: 0 | R75: =CATEGORIAS[[#This Row],[PRODUCCION ANTERIOR]]+CATEGORIAS[[#This Row],[PRODUCCION ADICIONALES ANTERIOR]] -> 115022.69 | S75: 0 | V75: =SUM(CATEGORIAS[[#This Row],[COSTO ACUMULADO AX]:[PROVISIONES]]) -> 0 | W75: 0 | Z75: =SUM(CATEGORIAS[[#This Row],[COSTO ACUMULADO ANTERIOR]:[PROVISIONES ANTERIOR]]) -> 0 | AA75: =CATEGORIAS[[#This Row],[PRESUPUESTO FINAL PROYECTADO]]-CATEGORIAS[[#This Row],[TOTAL PRODUCCION ACTUAL]] -> 489454.15 | AB75: 0 | AD75: 624349.44 | AE75: =SUM(CATEGORIAS[[#This Row],[INVENTARIO]:[PROYECCION DE COSTO DEL SALDO]]) -> 624349.44 | AG75: =+CATEGORIAS[[#This Row],[PRESUPUESTO FINAL PROYECTADO]]-CATEGORIAS[[#This Row],[COSTO REAL]]-CATEGORIAS[[#This Row],[PROYECCION TOTAL DE COSTO]] -> 0
A76: =+IFERROR(VLOOKUP(CATEGORIAS[[#This Row],[CATEGORIA2]],[1]HOMOLOGACION!$A$1:$I$571,9,FALSE),0) -> 0B02 | B76: =+IFERROR(VLOOKUP(CATEGORIAS[[#This Row],[CATEGORIA2]],[1]HOMOLOGACION!$A$1:$C$571,3,FALSE),0) -> 0B02 | C76: =+IFERROR(VLOOKUP(CATEGORIAS[[#This Row],[CATEGORIA2]],[1]HOMOLOGACION!$A$1:$D$571,4,FALSE),0) -> Estructura | D76: 21-0213-010G | E76: MAT CD - Estructura / Pernos / Todos (G) | F76: NO | G76: 0 | H76: 0 | I76: 0 | L76: =CATEGORIAS[[#This Row],[ADICIONALES]]+CATEGORIAS[[#This Row],[POM]] -> 0 | M76: 0 | N76: 0 | O76: =CATEGORIAS[[#This Row],[PRODUCCION PARTIDAS ORIGINALES ACTUAL]]+CATEGORIAS[[#This Row],[PRODUCCION ADICIONALES ACTUAL]] -> 0 | P76: 0 | Q76: 0 | R76: =CATEGORIAS[[#This Row],[PRODUCCION ANTERIOR]]+CATEGORIAS[[#This Row],[PRODUCCION ADICIONALES ANTERIOR]] -> 0 | S76: 0 | V76: =SUM(CATEGORIAS[[#This Row],[COSTO ACUMULADO AX]:[PROVISIONES]]) -> 0 | W76: 0 | Z76: =SUM(CATEGORIAS[[#This Row],[COSTO ACUMULADO ANTERIOR]:[PROVISIONES ANTERIOR]]) -> 0 | AA76: =CATEGORIAS[[#This Row],[PRESUPUESTO FINAL PROYECTADO]]-CATEGORIAS[[#This Row],[TOTAL PRODUCCION ACTUAL]] -> 0 | AB76: 0 | AE76: =SUM(CATEGORIAS[[#This Row],[INVENTARIO]:[PROYECCION DE COSTO DEL SALDO]]) -> 0 | AG76: =+CATEGORIAS[[#This Row],[PRESUPUESTO FINAL PROYECTADO]]-CATEGORIAS[[#This Row],[COSTO REAL]]-CATEGORIAS[[#This Row],[PROYECCION TOTAL DE COSTO]] -> 0
A77: =+IFERROR(VLOOKUP(CATEGORIAS[[#This Row],[CATEGORIA2]],[1]HOMOLOGACION!$A$1:$I$571,9,FALSE),0) -> 0B02 | B77: =+IFERROR(VLOOKUP(CATEGORIAS[[#This Row],[CATEGORIA2]],[1]HOMOLOGACION!$A$1:$C$571,3,FALSE),0) -> 0B02 | C77: =+IFERROR(VLOOKUP(CATEGORIAS[[#This Row],[CATEGORIA2]],[1]HOMOLOGACION!$A$1:$D$571,4,FALSE),0) -> Estructura | D77: 21-0214-010A | E77: MAT CD - Estructura / Soldaduras y Gases / Todos (A) | F77: SI | G77: 6764534.8 | H77: 6764534.8 | I77: 0 | L77: =CATEGORIAS[[#This Row],[ADICIONALES]]+CATEGORIAS[[#This Row],[POM]] -> 6764534.8 | M77: 3022510.4 | N77: 0 | O77: =CATEGORIAS[[#This Row],[PRODUCCION PARTIDAS ORIGINALES ACTUAL]]+CATEGORIAS[[#This Row],[PRODUCCION ADICIONALES ACTUAL]] -> 3022510.4 | P77: 2095103.1 | Q77: 0 | R77: =CATEGORIAS[[#This Row],[PRODUCCION ANTERIOR]]+CATEGORIAS[[#This Row],[PRODUCCION ADICIONALES ANTERIOR]] -> 2095103.1 | S77: 388439 | V77: =SUM(CATEGORIAS[[#This Row],[COSTO ACUMULADO AX]:[PROVISIONES]]) -> 388439 | W77: 0 | Z77: =SUM(CATEGORIAS[[#This Row],[COSTO ACUMULADO ANTERIOR]:[PROVISIONES ANTERIOR]]) -> 0 | AA77: =CATEGORIAS[[#This Row],[PRESUPUESTO FINAL PROYECTADO]]-CATEGORIAS[[#This Row],[TOTAL PRODUCCION ACTUAL]] -> 3742024.4 | AB77: 433500 | AD77: 5942595.8 | AE77: =SUM(CATEGORIAS[[#This Row],[INVENTARIO]:[PROYECCION DE COSTO DEL SALDO]]) -> 6376095.8 | AG77: =+CATEGORIAS[[#This Row],[PRESUPUESTO FINAL PROYECTADO]]-CATEGORIAS[[#This Row],[COSTO REAL]]-CATEGORIAS[[#This Row],[PROYECCION TOTAL DE COSTO]] -> 0
A78: =+IFERROR(VLOOKUP(CATEGORIAS[[#This Row],[CATEGORIA2]],[1]HOMOLOGACION!$A$1:$I$571,9,FALSE),0) -> 0B02 | B78: =+IFERROR(VLOOKUP(CATEGORIAS[[#This Row],[CATEGORIA2]],[1]HOMOLOGACION!$A$1:$C$571,3,FALSE),0) -> 0B02 | C78: =+IFERROR(VLOOKUP(CATEGORIAS[[#This Row],[CATEGORIA2]],[1]HOMOLOGACION!$A$1:$D$571,4,FALSE),0) -> Estructura | D78: 21-0214-010G | E78: MAT CD - Estructura / Soldaduras y Gases / Todos (G) | F78: NO | G78: 0 | H78: 0 | I78: 0 | L78: =CATEGORIAS[[#This Row],[ADICIONALES]]+CATEGORIAS[[#This Row],[POM]] -> 0 | M78: 0 | N78: 0 | O78: =CATEGORIAS[[#This Row],[PRODUCCION PARTIDAS ORIGINALES ACTUAL]]+CATEGORIAS[[#This Row],[PRODUCCION ADICIONALES ACTUAL]] -> 0 | P78: 0 | Q78: 0 | R78: =CATEGORIAS[[#This Row],[PRODUCCION ANTERIOR]]+CATEGORIAS[[#This Row],[PRODUCCION ADICIONALES ANTERIOR]] -> 0 | S78: 0 | V78: =SUM(CATEGORIAS[[#This Row],[COSTO ACUMULADO AX]:[PROVISIONES]]) -> 0 | W78: 0 | Z78: =SUM(CATEGORIAS[[#This Row],[COSTO ACUMULADO ANTERIOR]:[PROVISIONES ANTERIOR]]) -> 0 | AA78: =CATEGORIAS[[#This Row],[PRESUPUESTO FINAL PROYECTADO]]-CATEGORIAS[[#This Row],[TOTAL PRODUCCION ACTUAL]] -> 0 | AB78: 0 | AE78: =SUM(CATEGORIAS[[#This Row],[INVENTARIO]:[PROYECCION DE COSTO DEL SALDO]]) -> 0 | AG78: =+CATEGORIAS[[#This Row],[PRESUPUESTO FINAL PROYECTADO]]-CATEGORIAS[[#This Row],[COSTO REAL]]-CATEGORIAS[[#This Row],[PROYECCION TOTAL DE COSTO]] -> 0
A79: =+IFERROR(VLOOKUP(CATEGORIAS[[#This Row],[CATEGORIA2]],[1]HOMOLOGACION!$A$1:$I$571,9,FALSE),0) -> 0B02 | B79: =+IFERROR(VLOOKUP(CATEGORIAS[[#This Row],[CATEGORIA2]],[1]HOMOLOGACION!$A$1:$C$571,3,FALSE),0) -> 0B02 | C79: =+IFERROR(VLOOKUP(CATEGORIAS[[#This Row],[CATEGORIA2]],[1]HOMOLOGACION!$A$1:$D$571,4,FALSE),0) -> Estructura | D79: 21-0215-010A | E79: MAT CD - Estructura / Suministro Revestimiento / Todos (A) | F79: SI | G79: 21717444 | H79: 21717444 | I79: 0 | L79: =CATEGORIAS[[#This Row],[ADICIONALES]]+CATEGORIAS[[#This Row],[POM]] -> 21717444 | M79: 0 | N79: 0 | O79: =CATEGORIAS[[#This Row],[PRODUCCION PARTIDAS ORIGINALES ACTUAL]]+CATEGORIAS[[#This Row],[PRODUCCION ADICIONALES ACTUAL]] -> 0 | P79: 0 | Q79: 0 | R79: =CATEGORIAS[[#This Row],[PRODUCCION ANTERIOR]]+CATEGORIAS[[#This Row],[PRODUCCION ADICIONALES ANTERIOR]] -> 0 | S79: 0 | V79: =SUM(CATEGORIAS[[#This Row],[COSTO ACUMULADO AX]:[PROVISIONES]]) -> 0 | W79: 0 | Z79: =SUM(CATEGORIAS[[#This Row],[COSTO ACUMULADO ANTERIOR]:[PROVISIONES ANTERIOR]]) -> 0 | AA79: =CATEGORIAS[[#This Row],[PRESUPUESTO FINAL PROYECTADO]]-CATEGORIAS[[#This Row],[TOTAL PRODUCCION ACTUAL]] -> 21717444 | AB79: 0 | AD79: 21717444 | AE79: =SUM(CATEGORIAS[[#This Row],[INVENTARIO]:[PROYECCION DE COSTO DEL SALDO]]) -> 21717444 | AG79: =+CATEGORIAS[[#This Row],[PRESUPUESTO FINAL PROYECTADO]]-CATEGORIAS[[#This Row],[COSTO REAL]]-CATEGORIAS[[#This Row],[PROYECCION TOTAL DE COSTO]] -> 0
A80: =+IFERROR(VLOOKUP(CATEGORIAS[[#This Row],[CATEGORIA2]],[1]HOMOLOGACION!$A$1:$I$571,9,FALSE),0) -> 0B02 | B80: =+IFERROR(VLOOKUP(CATEGORIAS[[#This Row],[CATEGORIA2]],[1]HOMOLOGACION!$A$1:$C$571,3,FALSE),0) -> 0B02 | C80: =+IFERROR(VLOOKUP(CATEGORIAS[[#This Row],[CATEGORIA2]],[1]HOMOLOGACION!$A$1:$D$571,4,FALSE),0) -> Estructura | D80: 21-0215-010G | E80: MAT CD - Estructura / Suministro Revestimiento / Todos (G) | F80: NO | G80: 0 | H80: 0 | I80: 0 | L80: =CATEGORIAS[[#This Row],[ADICIONALES]]+CATEGORIAS[[#This Row],[POM]] -> 0 | M80: 0 | N80: 0 | O80: =CATEGORIAS[[#This Row],[PRODUCCION PARTIDAS ORIGINALES ACTUAL]]+CATEGORIAS[[#This Row],[PRODUCCION ADICIONALES ACTUAL]] -> 0 | P80: 0 | Q80: 0 | R80: =CATEGORIAS[[#This Row],[PRODUCCION ANTERIOR]]+CATEGORIAS[[#This Row],[PRODUCCION ADICIONALES ANTERIOR]] -> 0 | S80: 0 | V80: =SUM(CATEGORIAS[[#This Row],[COSTO ACUMULADO AX]:[PROVISIONES]]) -> 0 | W80: 0 | Z80: =SUM(CATEGORIAS[[#This Row],[COSTO ACUMULADO ANTERIOR]:[PROVISIONES ANTERIOR]]) -> 0 | AA80: =CATEGORIAS[[#This Row],[PRESUPUESTO FINAL PROYECTADO]]-CATEGORIAS[[#This Row],[TOTAL PRODUCCION ACTUAL]] -> 0 | AB80: 0 | AE80: =SUM(CATEGORIAS[[#This Row],[INVENTARIO]:[PROYECCION DE COSTO DEL SALDO]]) -> 0 | AG80: =+CATEGORIAS[[#This Row],[PRESUPUESTO FINAL PROYECTADO]]-CATEGORIAS[[#This Row],[COSTO REAL]]-CATEGORIAS[[#This Row],[PROYECCION TOTAL DE COSTO]] -> 0
A81: =+IFERROR(VLOOKUP(CATEGORIAS[[#This Row],[CATEGORIA2]],[1]HOMOLOGACION!$A$1:$I$571,9,FALSE),0) -> 0B02 | B81: =+IFERROR(VLOOKUP(CATEGORIAS[[#This Row],[CATEGORIA2]],[1]HOMOLOGACION!$A$1:$C$571,3,FALSE),0) -> 0B02 | C81: =+IFERROR(VLOOKUP(CATEGORIAS[[#This Row],[CATEGORIA2]],[1]HOMOLOGACION!$A$1:$D$571,4,FALSE),0) -> Estructura | D81: 21-0299-010A | E81: MAT CD - Estructura / Otros / Todos (A) | F81: SI | G81: 7942962.8 | H81: 7942962.8 | I81: 31204.186 | L81: =CATEGORIAS[[#This Row],[ADICIONALES]]+CATEGORIAS[[#This Row],[POM]] -> 7974166.9 | M81: 3495612 | N81: 19435.156 | O81: =CATEGORIAS[[#This Row],[PRODUCCION PARTIDAS ORIGINALES ACTUAL]]+CATEGORIAS[[#This Row],[PRODUCCION ADICIONALES ACTUAL]] -> 3515047.1 | P81: 2409357.3 | Q81: 27279.987 | R81: =CATEGORIAS[[#This Row],[PRODUCCION ANTERIOR]]+CATEGORIAS[[#This Row],[PRODUCCION ADICIONALES ANTERIOR]] -> 2436637.3 | S81: 1398889 | T81: =430065+200000 -> 630065 | U81: 183926 | V81: =SUM(CATEGORIAS[[#This Row],[COSTO ACUMULADO AX]:[PROVISIONES]]) -> 2212880 | W81: 53800 | X81: 430065 | Y81: 200000 | Z81: =SUM(CATEGORIAS[[#This Row],[COSTO ACUMULADO ANTERIOR]:[PROVISIONES ANTERIOR]]) -> 683865 | AA81: =CATEGORIAS[[#This Row],[PRESUPUESTO FINAL PROYECTADO]]-CATEGORIAS[[#This Row],[TOTAL PRODUCCION ACTUAL]] -> 4459119.8 | AB81: 176182 | AD81: 5585104.9 | AE81: =SUM(CATEGORIAS[[#This Row],[INVENTARIO]:[PROYECCION DE COSTO DEL SALDO]]) -> 5761286.9 | AG81: =+CATEGORIAS[[#This Row],[PRESUPUESTO FINAL PROYECTADO]]-CATEGORIAS[[#This Row],[COSTO REAL]]-CATEGORIAS[[#This Row],[PROYECCION TOTAL DE COSTO]] -> 0
