Workbook
Name \0: #REF!
Name \1: #REF!
Name \a: #REF!
Name \b: #REF!
Name \c: #REF!
Name \d: #REF!
Name \f: #REF!
Name \g: #REF!
Name \h: #REF!
Name \L: #REF!
Name \n: #REF!
Name \p: #REF!
Name \q: #REF!
Name \r: #REF!
Name \s: #REF!
Name \t: #REF!
Name \w: #REF!
Name \x: #REF!
Name \y: #REF!
Name \z: #REF!
Name _______us96: #REF!
Name ______pg1: #REF!
Name ______pg15: #REF!
Name ______pg16: #REF!
Name ______pg17: #REF!
Name ______pg18: #REF!
Name ______pg24: #REF!
Name ______pg25: #REF!
Name ______pg26: #REF!
Name ______pg27: #REF!
Name ______pg28: #REF!
Name ______pg29: #REF!
Name ______pg33: #REF!
Name ______pg34: #REF!
Name ______pg35: #REF!
Name ______pg39: #REF!
Name ______pg40: #REF!
Name ______pg45: #REF!
Name ______pg49: #REF!
Name ______pg6: #REF!
Name ______us96: #REF!
Name _____us96: #REF!
Name ____com1: #REF!
Name ____dta1: #REF!
Name ____mpm1: #REF!
Name ____pg1: #REF!
Name ____pg15: #REF!
Name ____pg16: #REF!
Name ____pg17: #REF!
Name ____pg18: #REF!
Name ____pg24: #REF!
Name ____pg25: #REF!
Name ____pg26: #REF!
Name ____pg27: #REF!
Name ____pg28: #REF!
Name ____pg29: #REF!
Name ____pg3: #REF!
Name ____pg33: #REF!
Name ____pg34: #REF!
Name ____pg35: #REF!

Sheet EP
B2: ECHEVERRIA IZQUIERDO MONTAJES INDUSTRIALES S.A.
C8: EDP Facturados
B9: ITEM | C9: N° ESTADO DE PAGO | D9: PERIODO PRODUCCIÓN | E9: AVANCE | F9: PAGO ANTICIPO | G9: RETENCIONES | H9: REAJUSTE PERIODO | J9: TOTAL PRESENTE EDP NETO | K9: TOTAL FACTURADO NETO | L9: IVA | M9: TOTAL FACTURADO | N9: N° FACTURA | O9: FECHA FACTURACIÓN | P9: OBSERVACIÓN
B10: 1 | C10: Estado de Pago N°1 | D10: Noviembre | E10: 190035944 | G10: -9520801 | H10: 380072 | I10: =+H10/J10 -> 0.0021010617 | J10: =+E10+G10+H10 -> 180895215 | K10: =+J10 -> 180895215 | L10: =+K10*0.19 -> 34370091 | M10: =+K10+L10 -> 2.1526531e+08 | N10: 45277 | O10: 45656
B11: 2 | C11: Estado de Pago N°2 | D11: Diciembre | E11: 146331142 | G11: -7323874 | H11: 146331 | I11: =+H11/J11 -> 0.001051579 | J11: =+E11+F11+G11+H11 -> 139153599 | K11: =+J11 -> 139153599 | L11: =+K11*0.19 -> 26439184 | M11: =+K11+L11 -> 1.6559278e+08 | N11: 45305 | O11: 45687
B12: 3 | C12: Estado de Pago N°3 | D12: Enero | E12: 329194039 | G12: -16640759 | H12: 3621134 | I12: =+H12/J12 -> 0.011452963 | J12: =+E12+F12+G12+H12 -> 316174414 | K12: =+J12 -> 316174414 | L12: =+K12*0.19 -> 60073139 | M12: =+K12+L12 -> 3.7624755e+08 | N12: 45339 | O12: 45708
B13: 4 | C13: Estado de Pago N°4 | D13: Febrero | E13: 284749673 | G13: -14451046 | H13: 4271245.1 | I13: =+H13/J13 -> 0.015556132 | J13: =+E13+F13+G13+H13 -> 2.7456987e+08 | K13: =+J13 -> 2.7456987e+08 | L13: =+K13*0.19 -> 52168276 | M13: =+K13+L13 -> 3.2673815e+08 | N13: 45390 | O13: 45744
B14: 5 | C14: Estado de Pago N°5 | D14: Marzo | E14: 417332301 | G14: -21283947 | H14: 8346646 | I14: =+H14/J14 -> 0.020639835 | J14: =+E14+F14+G14+H14 -> 404395000 | K14: =+J14 -> 404395000 | L14: =+K14*0.19 -> 76835050 | M14: =+K14+L14 -> 481230050 | N14: 45502 | O14: 45777
B15: 6 | C15: Estado de Pago N°6 | D15: Abril | E15: =283585877+1155883 -> 284741760 | G15: -14550304 | H15: 6264319 | I15: =+H15/J15 -> 0.022659389 | J15: =+E15+F15+G15+H15 -> 276455775 | K15: =+J15 -> 276455775 | L15: =+K15*0.19 -> 52526597 | M15: =+K15+L15 -> 3.2898237e+08 | N15: 45567 | O15: 45824
B16: 7 | C16: Estado de Pago N°7 | D16: Mayo | E16: 630093992 | G16: -32260812 | H16: 15122256 | I16: =+H16/J16 -> 0.024671053 | J16: =+E16+F16+G16+H16 -> 612955436 | K16: =+J16 -> 612955436 | L16: =+K16*0.19 -> 1.1646153e+08 | M16: =+K16+L16 -> 7.2941697e+08 | N16: 45575 | O16: 45838
B17: 8 | C17: Estado de Pago N°8 | D17: Junio | E17: 464630398 | G17: -23696150 | H17: 9292608 | I17: =+H17/J17 -> 0.020639835 | J17: =+E17+F17+G17+H17 -> 450226856 | K17: =+J17 -> 450226856 | L17: =+K17*0.19 -> 85543103 | M17: =+K17+L17 -> 5.3576996e+08 | N17: 45610 | O17: 45861
B18: 9 | C18: Estado de Pago N°9 | D18: Julio | E18: =755255614+5353187 -> 760608801 | G18: -39133323 | H18: 22057655 | I18: =+H18/J18 -> 0.029666001 | J18: =+E18+F18+G18+H18 -> 743533133 | K18: =+J18 -> 743533133 | L18: =+K18*0.19 -> 1.412713e+08 | M18: =+K18+L18 -> 8.8480443e+08 | N18: 45656 | O18: 45890
B19: 10 | C19: Estado de Pago N°10 | D19: Agosto | E19: 644125917 | G19: -33140278 | H19: 18679651 | I19: =+H19/J19 -> 0.029666001 | J19: =+E19+F19+G19+H19 -> 629665290 | K19: =+J19 -> 629665290 | L19: =+K19*0.19 -> 1.1963641e+08 | M19: =+K19+L19 -> 7.493017e+08 | N19: 45677 | O19: 45915
B20: 11 | C20: Estado de Pago N°11 | D20: Septiembre | E20: 390436268 | G20: -20185555 | H20: 13274833 | I20: =+H20/J20 -> 0.034612644 | J20: =+E20+F20+G20+H20 -> 383525546 | K20: =+J20 -> 383525546 | L20: =+K20*0.19 -> 72869854 | M20: =+K20+L20 -> 4.563954e+08 | N20: 45712 | O20: 45952
B21: 12 | C21: Estado de Pago N°12 | D21: Octubre | E21: 385422972 | G21: -19926368 | H21: 13104381 | I21: =+H22/J22 -> 0.037557732 | J21: =+E21+F21+G21+H21 -> 3.7860099e+08 | K21: =+J21 -> 3.7860099e+08 | L21: =+K21*0.19 -> 71934187 | M21: =+K21+L21 -> 4.5053517e+08 | N21: 45771 | O21: 45980
B22: 13 | C22: Estado de Pago N°13 | D22: Noviembre | E22: 462264701 | G22: -23968425 | H22: 17103794 | I22: =+H22/J22 -> 0.037557732 | J22: =+E22+F22+G22+H22 -> 4.5540007e+08 | K22: =+J22 -> 4.5540007e+08 | L22: =+K22*0.19 -> 86526013 | M22: =+K22+L22 -> 5.4192608e+08 | N22: 45821 | O22: 46009
B23: 14 | C23: Estado de Pago N°14 | D23: Diciembre | E23: 198410088 | G23: -10267722 | H23: 6944353.1 | I23: =+H23/J23 -> 0.035596237 | J23: =+E23+F23+G23+H23 -> 1.9508672e+08 | K23: =+J23 -> 1.9508672e+08 | L23: =+K23*0.19 -> 37066477 | M23: =+K23+L23 -> 2.321532e+08 | N23: 45888 | O23: 46069
B24: 15
B25: 16 | C25: Estado de Pago N°1 (Caldera) | D25: Agosto | E25: 268988202 | J25: =+E25+F25+G25+H25 -> 268988202 | K25: =+J25 -> 268988202 | L25: =+K25*0.19 -> 51107758 | M25: =+K25+L25 -> 3.2009596e+08 | N25: 45667 | O25: 45904
B26: 17 | J26: =+E26+F26+G26+H26 -> 0 | K26: =+J26 -> 0 | L26: =+K26*0.19 -> 0 | M26: =+K26+L26 -> 0
B27: 18 | J27: =+E27+F27+G27+H27 -> 0 | K27: =+J27 -> 0 | L27: =+K27*0.19 -> 0 | M27: =+K27+L27 -> 0
B28: 19
E29: =+SUM(E10:E28) -> 5857366198 | F29: =+SUM(F10:F28) -> 0 | G29: =+SUM(G10:G28) -> -286349364 | H29: =+SUM(H10:H28) -> 1.3860928e+08 | J29: =+SUM(J10:J28) -> 5.7096261e+09 | K29: =+SUM(K10:K28) -> 5.7096261e+09 | L29: =+SUM(L10:L28) -> 1.084829e+09 | M29: =+SUM(M10:M28) -> 6.7944551e+09
C31: EDP | E31: =+E29+E39 -> 5.8753568e+09 | H31: =+H29+H39 -> 1.3860928e+08
B32: ITEM | C32: N° ESTADO DE PAGO | D32: PERIODO PRODUCCIÓN | E32: MONTO NETO | F32: PAGO ANTICIPO | G32: =+G9 -> RETENCIONES | H32: REAJUSTE PERIODO | J32: TOTAL PRESENTE EDP NETO | K32: TOTAL FACTURADO NETO | L32: IVA | M32: TOTAL FACTURADO | N32: N° FACTURA | O32: FECHA FACTURACIÓN | P32: OBSERVACIÓN
B33: 1 | C33: Ventas a 3eros | D33: Diciembre | E33: 17990642 | J33: =+E33+F33+G33+H33 -> 17990642 | K33: =+J33 -> 17990642 | L33: =+K33*0.19 -> 3418222 | M33: =+K33+L33 -> 21408864
B34: =+B33+1 -> 2
B35: =+B34+1 -> 3
B36: =+B35+1 -> 4
B37: 6
E39: =+SUM(E33:E38) -> 17990642 | F39: =+SUM(F33:F38) -> 0 | G39: =+SUM(G33:G38) -> 0 | H39: =+SUM(H33:H38) -> 0 | I39: =+SUM(I33:I38) -> 0 | J39: =+SUM(J33:J38) -> 17990642 | K39: =+SUM(K33:K38) -> 17990642 | L39: =+SUM(L33:L38) -> 3418222 | M39: =+SUM(M33:M38) -> 21408864
H42: =+H29+H39 -> 1.3860928e+08 | J42: =+J29+J39 -> 5.7276168e+09

Sheet EDP Detalle
B3: CC008 | E3: 44621 | F3: 44652 | G3: 44682 | H3: 44713 | I3: 44743 | J3: 44774 | K3: 44805 | L3: 44835 | M3: 44866 | N3: 44896 | O3: 44896 | P3: 44927 | Q3: 44958 | R3: 44986 | S3: 45017 | T3: 45047 | U3: 45047 | V3: 45078 | W3: 45108 | X3: 45139 | Y3: 45170 | Z3: 45200 | AA3: 45231 | AB3: 45261
B4: Detalle | C4: Total | D4: Anticipo | E4: EDP1 | F4: EDP2 | G4: EDP3 | H4: EDP4 | I4: EDP5 | J4: EDP6 | K4: EDP7 | L4: EDP8 | M4: EDP9 | N4: EDP10 | O4: EDP11 | P4: EDP12 | Q4: EDP13 | R4: EDP14 | S4: EDP15 | T4: EDP16 | U4: EDP17 | V4: EDP18 | W4: EDP19 | X4: EDP20 | Y4: EDP21 | Z4: EDP22 | AA4: EDP23 | AB4: EDP24
B5: Instalación de Faena | C5: =+SUM(D5:AB5) -> 9.611484e+08 | E5: 5.4785459e+08 | H5: 3.1717897e+08 | S5: 96114840 | V5: 0
B6: Movilización | C6: =+SUM(D6:AB6) -> 1.4417226e+08 | E6: 1.2975503e+08 | H6: 0 | K6: 14417226 | S6: 0 | V6: 0
B7: Desmovilización y Cierre Ambiental | C7: =+SUM(D7:AB7) -> 0 | E7: 0 | H7: 0 | S7: 0 | V7: 0
B8: Gastos Generales | C8: =+SUM(D8:AB8) -> 1.7665686e+10 | E8: 3.6771478e+08 | F8: 2.4583554e+08 | G8: 5.5826325e+08 | H8: 4.6229356e+08 | I8: 2.3007647e+08 | J8: 6.2363309e+08 | K8: 5.0806158e+08 | L8: 4.7126357e+09 | M8: 9.1057261e+08 | N8: 9.3314253e+08 | P8: 3.4584799e+08 | Q8: 1.131755e+09 | R8: 3.1799185e+09 | S8: 1.2654146e+09 | T8: 1.3426678e+09 | V8: 8.4785298e+08
B9: Utilidades | C9: =+SUM(D9:AB9) -> 1.9687236e+09 | E9: 68081615 | F9: 45515932 | G9: 1.0336126e+08 | H9: 85592677 | I9: 42598172 | J9: 1.1546435e+08 | K9: 94066529 | L9: 1.4408036e+08 | M9: 1.6610413e+08 | N9: 1.7445445e+08 | P9: 1.2806605e+08 | Q9: 4.190841e+08 | S9: 82427919 | T9: 2.0619276e+08 | V9: 93633323
B10: Bodega Internacional | C10: =+SUM(D10:AB10) -> 3.0920908e+09 | E10: 510647917 | F10: 1.8340517e+08 | G10: 1.9313477e+08 | H10: 2.2699464e+08 | I10: 1.9856142e+08 | J10: 90546661 | K10: 67924508 | L10: 9877207.9 | M10: 1147019.8 | N10: 6642897.9 | P10: 1.4627428e+08 | Q10: 1.4627428e+08 | R10: 6.968589e+08 | S10: 2.1188182e+08 | T10: 2.0792182e+08 | V10: 1.939975e+08
B11: Costo Directo | C11: =+SUM(D11:AB11) -> 3.5872716e+10 | E11: 9.0634509e+08 | F11: 1.3428885e+09 | G11: 1.6758695e+09 | H11: 2.0215029e+09 | I11: 2.7998407e+08 | J11: 9.8780552e+08 | K11: 1.6986357e+09 | L11: 1.3141572e+09 | M11: 2.0626347e+09 | N11: 1.2821538e+09 | P11: 3.3190402e+09 | Q11: 3.2867514e+09 | R11: 3.156655e+09 | S11: 4.4472907e+09 | T11: 5.1712815e+09 | V11: 2.91972e+09
B12: Adicionales | C12: =+SUM(D12:AB12) -> 2.573672e+10 | E12: 48935985 | F12: 142989465 | H12: 1.9931688e+08 | I12: 4.6493003e+09 | J12: 2.0635774e+08 | K12: 3.5388367e+08 | L12: 1.8175291e+09 | M12: 1.8123052e+09 | N12: 1.6671569e+08 | O12: 2617955666 | P12: 2.5495082e+09 | Q12: 1.0828851e+09 | R12: 7.5139506e+08 | S12: 1.9597098e+09 | T12: 2.7018243e+09 | U12: 2.8740615e+09 | V12: 1.8020466e+09
B13: Reajuste | C13: =+SUM(D13:AB13) -> 1.1604886e+10 | F13: 1.0003419e+08 | G13: 1.2911268e+08 | H13: 36199046 | I13: 1.2491615e+08 | J13: 2.5411531e+08 | K13: 3.4586899e+08 | L13: 8.117979e+08 | M13: 7.7609806e+08 | N13: 4.3047422e+08 | O13: 138088993 | P13: 1.098429e+09 | Q13: 1.0934662e+09 | R13: 1.4996882e+09 | S13: 1.5447884e+09 | T13: 1.8851914e+09 | U13: 1.7835604e+08 | V13: 1.1582612e+09
B14: Anticipo | C14: =+SUM(D14:AB14) -> -0.40000582 | D14: 9762647282 | E14: -1.9525295e+09 | H14: -2.6033726e+09 | I14: -2.6033726e+09 | L14: -2.6033726e+09
C15: =+SUM(C5:C14) -> 9.7046143e+10 | D15: =+SUM(D5:D14) -> 9762647282 | E15: =+SUM(E5:E14) -> 6.2680555e+08 | F15: =+SUM(F5:F14) -> 2.0606688e+09 | G15: =+SUM(G5:G14) -> 2.6597415e+09 | H15: =+SUM(H5:H14) -> 7.4570602e+08 | I15: =+SUM(I5:I14) -> 2.922064e+09 | J15: =+SUM(J5:J14) -> 2.2779227e+09 | ... V15: =+SUM(V5:V14) -> 7.0155115e+09
D16: =+D15-EP!#REF! -> #REF! | E16: =+E15-EP!J10 -> 4.4591034e+08 | F16: =+F15-EP!J11 -> 1.9215152e+09 | G16: =+G15-EP!J12 -> 2.3435671e+09 | H16: =+H15-EP!J13 -> 4.7113615e+08 | I16: =+I15-EP!J14 -> 2.517669e+09 | J16: =+J15-EP!J15 -> 2.0014669e+09 | K16: =+K15-EP!J16 -> 2.4699028e+09 | L16: =+L15-EP!J17 -> 5.7564781e+09 | M16: =+M15-EP!J18 -> 4.9853286e+09 | N16: =+N15-EP!J19 -> 2.3639183e+09 | O16: =+O15-EP!J20 -> 2372519113 | P16: =+P15-EP!J21 -> 7.2085646e+09 | Q16: =+Q15-EP!J22 -> 6.7048161e+09 | R16: =+R15-EP!J23 -> 9.0894289e+09 | S16: =+S15-EP!J24 -> 9.6076281e+09 | T16: =+T15-EP!#REF! -> #REF! | U16: =+U15-EP!#REF! -> #REF! | V16: =+V15-EP!#REF! -> #REF!
B20: CC017 | E20: 44713 | F20: 44774 | G20: 44805 | H20: 44835 | I20: 44866 | J20: 44896 | K20: 44927 | L20: 44958 | M20: 44986 | N20: 45017 | O20: 44682 | P20: 44713
B21: Detalle | C21: Total | D21: Anticipo | E21: EDP1 | F21: EDP2 | G21: EDP3 | H21: EDP4 | I21: EDP5 | J21: EDP6 | K21: EDP7 | L21: EDP8 | M21: EDP9 | N21: EDP10 | O21: EDP11 | P21: EDP12 | Q21: EDP13 | R21: EDP14 | S21: EDP15 | T21: EDP16 | U21: EDP17
B22: Instalación de Faena | C22: =+SUM(D22:U22) -> 3.166046e+08 | E22: 1.8996276e+08 | G22: 1.2664184e+08
B23: Movilización | C23: =+SUM(D23:U23) -> 0
B24: Desmovilización y Cierre Ambiental | C24: =+SUM(D24:U24) -> 0
B25: Gastos Generales | C25: =+SUM(D25:U25) -> 1.8323627e+09 | E25: 1.3980467e+08 | F25: 36419191 | G25: 1.0761482e+08 | H25: 1.4284221e+08 | I25: 1.0592891e+08 | J25: 1.2939595e+08 | K25: 1.0753633e+08 | L25: 89561107 | M25: 1.0147147e+08 | N25: 1.4623989e+08 | O25: 1.6151441e+08 | P25: 5.6403376e+08
B26: Utilidades | C26: =+SUM(D26:U26) -> 1.461134e+08 | E26: 15130946 | F26: 3941619.2 | G26: 11647063 | H26: 15459696 | I26: 11464599 | J26: 14004418 | K26: 11638569 | L26: 9693125.3 | M26: 10982174 | N26: 15827423 | O26: 17480572 | P26: 8843195.8
B27: Bodega Internacional | C27: =+SUM(D27:U27) -> 0
B28: Costo Directo | C28: =+SUM(D28:U28) -> 2.6102741e+09 | E28: 2.7098812e+08 | F28: 1.9232122e+08 | G28: 1.5323017e+08 | H28: 2.8702843e+08 | I28: 2.3011445e+08 | J28: 1.8082072e+08 | K28: 2.0918012e+08 | L28: 2.9315603e+08 | M28: 1.9622664e+08 | N28: 2.8360672e+08 | O28: 77732513 | P28: 2.3586899e+08
B29: Adicionales | C29: =+SUM(D29:U29) -> 1.810188e+08 | I29: 24185858 | J29: 0 | K29: 83815363 | M29: 73017580 | O29: 0
B30: Reajuste | C30: =+SUM(D30:U30) -> 7.2679501e+08 | E30: 31170016 | F30: 29064312 | G30: 49855814 | H30: 55626212 | I30: 46428275 | J30: 40498457 | K30: 63816570 | L30: 72584127 | M30: 58234283 | N30: 82436325 | O30: 47486884 | P30: 1.4959374e+08
B31: Anticipo | C31: =+SUM(D31:U31) -> 0
C32: =+SUM(C22:C31) -> 5.8131686e+09 | D32: =+SUM(D22:D31) -> 0 | E32: =+SUM(E22:E31) -> 6.4705651e+08 | F32: =+SUM(F22:F31) -> 2.6174634e+08 | G32: =+SUM(G22:G31) -> 4.489897e+08 | H32: =+SUM(H22:H31) -> 5.0095655e+08 | I32: =+SUM(I22:I31) -> 4.1812209e+08 | J32: =+SUM(J22:J31) -> 3.6471955e+08 | ... U32: =+SUM(U22:U31) -> 0
E33: =+E32-EP!#REF! -> #REF! | F33: =+F32-EP!#REF! -> #REF! | G33: =+G32-EP!#REF! -> #REF! | H33: =+H32-EP!#REF! -> #REF! | I33: =+I32-EP!#REF! -> #REF! | J33: =+J32-EP!#REF! -> #REF! | K33: =+K32-EP!#REF! -> #REF! | L33: =+L32-EP!J33 -> 4.4700375e+08 | M33: =+M32-EP!J34 -> 4.3993214e+08 | N33: =+N32-EP!J35 -> 5.2811035e+08 | O33: =+O32-EP!J36 -> 3.0421438e+08 | P33: =+P32-EP!J37 -> 9.5833968e+08
